[
  {
    "name": "Aetomylaeus bovinus",
    "sciname": "",
    "IUCN": "",
    "description": "Introducción Aetomylaeus bovinus conocida comúnmente como raya toro o pez obispo. Puede llegar a medir más de dos metros, lo que la convierte en una de las rayas de mayor tamaño que se conocen en el Mediterráneo. Esta especie ha sido documentada en las aguas tropicales y cálidas del Atlántico oriental. A día de hoy, sigue siendo poco conocida, y parece que podría encontrarse en vías de extinción en el Mediterráneo y el mar Negro. Habiendo ya desaparecido prácticamente del mar Egeo. Las poblaciones presentes en el océano Atlántico parecen gozar de una situación algo mejor. Sus principales amenazas son la sobrepesca y las capturas accidentales. ¿Quién es ella?  Aetomylaeus Las especies del género Aetomylaeus son comúnmente conocidas como rayas águila, a veces también como rayas toro. Pertenecen a la familia de los Myliobatidae. Al igual que ocurre con otras rayas, las aletas pectorales y el cuerpo se confunden. Sin embargo, las aletas pueden distinguirse por la posición de la cabeza que sobresale del resto del cuerpo. Estos peces de tamaño imponente poseen una pequeña aleta dorsal bien visible, y un aguijón en la base de la cola. Esta última es más larga que el resto del cuerpo. Las mandíbulas son poderosas con numerosas filas de grandes dientes. Los especímenes de mayor tamaño pueden llegar a sobrepasar los 2 metros. Estas rayas son parientes de los Myliobatis pero al contrario que ocurre en estos últimos, las Aetomylaeus poseen unas aletas pectorales separadas del lóbulo rostral que se juntan al nivel de los ojos. La espina de la cola está poco desarrollada. Las Aetomylaeus fueron durante mucho tiempo clasificadas con otras especies de rayas bajo el género Pteromylaeus. Su biología es aún en día poco conocida, y se trata de un animal inofensivo para el hombre. Frecuentan principalmente las aguas costeras pero pueden ser vistas en aguas abiertas, solas o formando pequeños grupos. Las rayas águila se alimentan de crustáceos y moluscos que habitan en el fondo. Son ovovivíparas y dan a luz a crías completamente formadas. Tan solo una especie está presente en el océano Atlántico y en el mar Mediterráneo, las otras 6 restantes se encuentran en el océano Pacífico. Apreciadas por su carne, han sido objeto importante de la pesca. El desconocimiento de su ciclo biológico y su baja tasa de crecimiento han provocado una escasez de sus poblaciones. En 2020, de 7 especies, 5 estaban consideradas como vulnerables por el IUCN, de las otras dos, de una no se tiene información y la otra es actualmente una preocupación menor.  Tipo raya Tamaño medio 150 cm Tamaño máximo 220 cm Mimetismo fondo arenoso Aetomylaeus bovinus, raya toro © Xavi Salvador Costa Tipo raya Tamaño medio 150 cm Tamaño máximo 220 cm Mimetismo fondo arenoso ¿Cómo reconocer a Este pez ? Esta especie es fácilmente reconocible frente a otras rayas. Su cuerpo es de un color marrón-beige con numerosas líneas azul pálido repartidas sobre el dorso. El vientre, sin embargo, es de color blanco. Posee una imponente cabeza, en la que resalta su hocico, alargado y plano, con forma de pico de pato. La boca contiene 7 filas de dientes planos. Diferencias entre machos y hembras Macho y hembra son muy similares, sin embargo los individuos de mayor tamaño son siempre hembras. Modo de vida y comportamiento dieta carnívoro Sociabilidad grupos o en solitario territorial No Modo de vida Diurno La raya toro vive tanto en grupo como en solitario. Generalmente, suele frecuentar las zonas costeras aunque ha sido también observada en aguas abiertas. Habitualmente suele encontrarse próxima al fondo, en busca de crustáceos y moluscos con los que alimentarse. En particular, mejillones, ostras y gasterópodos. También ha sido observada en aguas salobres. Se trata de una especie migratoria, las hembras se desplazan para dar a luz. Reproducción Modo de reproducción ovovivíparo Especie migratoria Sí Se trata de una especie ovovivípara. Los embriones son incubados en el interior de las hembras. Alimentándose inicialmente de la yema del huevo para después recibir un complemento alimenticio por parte de la madre, por absorción indirecta del líquido uterino enriquecido en grasa o proteínas. Esta forma de alimentación sigue una estructura compleja. La gestación dura en torno a 6 meses, y de ella nacerán entre 3 y 7 crías, totalmente formadas y con un tamaño cercano a los 45 cm. Riesgos para los humanos Venenoso No La especie parece inofensiva para el hombre. Sin embargo, conviene mantener una cierta prudencia en caso de encontrarse con individuos de gran tamaño. Origen y distribución Origen Mar Mediterráneo Mar Negro Océano Atlántico templado oriental Océano Atlántico tropical oriental Islas Islas Canarias Presencia geográfica y estado de la población Las poblaciones del Mediterráneo están actualmente en disminución. Siendo cada vez más difícil encontrar a esta especie en esta zona, podría llegar incluso a desaparecer si no se toman medidas pertinentes. Estado de conservación de las poblaciones (UICN) Mundo : CR ¿Cuál es su hábitat? Características del entorno natural Profundidad 10 - 150 m Presentación del biotopo Esta especie se encuentra principalmente en las proximidades de los fondos arenosos, fangosos o de algas. Comúnmente suele ser vista a profundidades entre los 10 y los 150 metros aunque, en ocasiones, asciende a la superficie. Especie del mismo biotopo reyezuelo Apogonidae pez jabalí Caproidae gobio negro Gobiidae cabrilla reina Serranidae rape común Lophiidae pez de san Pedro Zeidae Previous Next Para saber más Especie de la misma familia raya jaspeada Myliobatidae águila de mar Myliobatidae Previous Next Para leer en la web Fuentes y realización Participación y validación El equipo de Fishipedia y sus colaboradores especializados se comprometen a proporcionar contenido de alta calidad. Sin embargo, aunque la información proviene de fuentes científicas o testimonios de especialistas, los archivos pueden contener imprecisiones. Benoit Chartrer Traducción Traducción realizada con la valiosa contribución de nuestros traductores, quienes hacen que esta información esté disponible para un público más amplio. Silvia Gomez Referencias bibliográficas A revised generic arrangement for the eagle ray family Myliobatidae, with definitions for the valid genera - WILLIAM T. WHITE - ZOOTAXA - 2014. Bull ray, Aetomylaeus bovinus (Geoffroy Saint‐Hilaire, 1817) (Myliobatidae) in the Mediterranean Sea and captures of juveniles from Izmir Bay (Aegean Sea, Turkey) - O. Akyol - I. Aydın - O. El Kamel-Moutalibi - C. Capapé - WILEY - 2017. Interactúa con Fishipedia Para ponerse en contacto con nuestro equipo o participar en nuestro proyecto. Contribuya a esta página Plantilla y contenido © Fishipedia - Reproducción no autorizada sin solicitud previa - ISSN 2270-7247 - Última actualización el 12/11/2023 © Fishipedia.fr 2024",
    "genderDescription": "Myliobatidae",
    "type": "",
    "size": "150 cm",
    "maxSize": "220 cm",
    "mimetism": "fondo arenoso",
    "recognize": "",
    "fe/maleDifferences": "Macho y hembra son muy similares, sin embargo los individuos de mayor tamaño son siempre hembras.",
    "diet": "carnívoro",
    "territorial": "No",
    "social": "grupos o en solitario",
    "lifeMode": "dieta",
    "lifeDescription": "",
    "reproductionMode": "<  raya toro  Aetomylaeus bovinus  Geoffroy Saint-Hilaire  1271  (Mundo) CR  Myliobatidae  Aetomylaeus",
    "migration": "",
    "reproductionDescription": "",
    "poison": "No",
    "danger": "",
    "depth": "Enciclopedia Explorar Acuariofilia A propósito Prensa Peces Ballestas Barracudas Doradas y sargos Escorpenas Hipocampos Lábridos Morenas Peces cirujano Peces globo Peces payaso Rayas Tiburones Reptiles Cocodrilos Serpientes Tortugas Moluscos Caracoles Nudibranquios Calamares Pulpos Sepias Otros temas Anfibios Cnidarios Crustáceos Amazonas Anaconda gigante Anguila eléctrica Paiche Piraña roja Raya motoro / Raya de rio Tararira Mediterráneo Atún rojo Congrio Dorada real Manta raya Mero Sargo Islas Canarias Ángel de mar Caballito de mar Pez roca de Madeira Pez trompeta atlántico Tiburón Mako Vieja colorada Mar del Caribe Cirujano azul Gran barracuda / Picúa Pez ángel francés pez ángel reina Raya jaspeada Robalo blanco Mar Rojo Mero del Coral Morena gigante Pez león Pez Napoléon Raya de arrecife Vieja florida Especies comunes Betta Splendens Chupa algas Corydoras Discos Escalar Gamba Red Cherry Guppy Pez dorado Pez payaso Grupos temáticos Cíclidos enanos Killis Lochas Luchadores Peces gato Tetras Vivíparos Práctica Peces compatibles 20 L Peces compatibles 40 L Peces compatibles 60 L Peces compatibles 80 L Peces compatibles 100 L El proyecto Fishipedia Nuestra ética Proyecto Yaku Nawi Los fotógrafos colaboradores CONTÁCTANOS Enciclopedia Peces Ballestas Barracudas Doradas y sargos Escorpenas Hipocampos Lábridos Morenas Peces cirujano Peces globo Peces payaso Rayas Tiburones Reptiles Cocodrilos Serpientes Tortugas Moluscos Caracoles Nudibranquios Calamares Pulpos Sepias Otros temas Anfibios Cnidarios Crustáceos Explorar Amazonas Anaconda gigante Anguila eléctrica Paiche Piraña roja Raya motoro / Raya de rio Tararira Mediterráneo Atún rojo Congrio Dorada real Manta raya Mero Sargo Islas Canarias Ángel de mar Caballito de mar Pez roca de Madeira Pez trompeta atlántico Tiburón Mako Vieja colorada Mar del Caribe Cirujano azul Gran barracuda / Picúa Pez ángel francés pez ángel reina Raya jaspeada Robalo blanco Mar Rojo Mero del Coral Morena gigante Pez león Pez Napoléon Raya de arrecife Vieja florida Acuariofilia Especies comunes Betta Splendens Chupa algas Corydoras Discos Escalar Gamba Red Cherry Guppy Pez dorado Pez payaso Grupos temáticos Cíclidos enanos Killis Lochas Luchadores Peces gato Tetras Vivíparos Práctica Peces compatibles 20 L Peces compatibles 40 L Peces compatibles 60 L Peces compatibles 80 L Peces compatibles 100 L A propósito El proyecto Fishipedia Nuestra ética Proyecto Yaku Nawi Los fotógrafos colaboradores CONTÁCTANOS Prensa",
    "image": "",
    "mapImage": ""
  },
  {
    "name": "Anthias anthias",
    "sciname": "",
    "IUCN": "",
    "description": "Introducción Anthias anthias, más comúnmente denominado tres colas, es un pez que habita en agua de mar.  de realización. Los textos propuestos actualmente provienen de nuestro modelo de datos o están en proceso de redacción. Para solicitar prioridad para este contenido, puedes escribirnos AQUÍ. ¿Quién es él?  Tamaño medio 15 cm Tamaño máximo 27 cm Longevidad 7 años Forma Ovoide Anthias anthias, tres colas © Benoit Chartrer Anthias anthias, tres colas © Aquarium-Museum ULiege Previous Next Tamaño medio 15 cm Tamaño máximo 27 cm Longevidad 7 años Forma Ovoide ¿Cómo reconocer a Este pez ? El tres colas mide alrededor de 15 cm. Los machos dominantes pueden, sin embargo, llegar a alcanzar los 27 cm. Este pez presenta una coloración bicolor con un cuerpo mayoritariamente naranja y rosa. Diferencias entre machos y hembras El macho adulto presenta un mayor tamaño que la hembra. Modo de vida y comportamiento dieta carnívoro Sociabilidad bancos territorial Sí Modo de vida Nocturno El tres colas es un pez que vive en bancos a media profundidad y próximo al fondo. Los miembros de cada grupo se organizan en una jerarquía bien organizada. Es un animal carnívoro de temperamento tranquilo. Este pez vive principalmente de noche. Generalmente, abandona su escondite y comienza su actividad una vez que cae la noche. El tres colas es un animal territorial que no tolerará ninguna incursión en su territorio. Particularmente virulento con otras especies territoriales, no dudará en provocar numerosos enfrentamientos. Reproducción Modo de reproducción ovíparo Hermafrodita protógino El tres colas es un pez ovíparo. nace siempre siendo hembra. A medida que crecen, los ejemplares cambiarán de sexo para convertirse en machos, esto se conoce con el nombre de hermafroditismo sucesivo de tipo protógino. Especies inofensivas Esta especie no supone ningún peligro en particular para el ser humano cuando se encuentra en su entorno natural. Origen y distribución Origen Mar Mediterráneo Océano Atlántico templado oriental Océano Atlántico tropical oriental Islas Córcega Islas Canarias Cerdeña Sicilia Estado de conservación de las poblaciones (UICN) Mundo : LC ¿Dónde observar esta especie? ¿Cuál es su hábitat? Características del entorno natural Temperatura 14 - 25 °C Profundidad 30 - 300 m Corriente Lenta Presentación del biotopo Frecuentemente encontramos a el tres colas a una profundidad de entre 30m y 300m. Sin embargo, no resulta del todo imposible observar a esta especie a otras profundidades. Para saber más Especie de la misma familia Mirolabrichthys evansi Anthiadidae Anthias naranja Anthiadidae Pseudanthias hypselosoma Anthiadidae Pseudanthias pascalus Anthiadidae Pseudanthias ventralis Anthiadidae Pseudanthias pleurotaenia Anthiadidae Pseudanthias cooperi Anthiadidae Mirolabrichthys tuka Anthiadidae Previous Next Para leer en la web Fuentes y realización Participación y validación El equipo de Fishipedia y sus colaboradores especializados se comprometen a proporcionar contenido de alta calidad. Sin embargo, aunque la información proviene de fuentes científicas o testimonios de especialistas, los archivos pueden contener imprecisiones. Benoit Chartrer Théo Guillaume Adrien Falzon Traducción Traducción realizada con la valiosa contribución de nuestros traductores, quienes hacen que esta información esté disponible para un público más amplio. Silvia Gomez Referencias bibliográficas GUIDE DES POISSONS DE LA MEDITERRANEE - Harmelin-Vivien M. - Harmelin J.-G. - Delachaux et Niestlé - 1991. GUIDE D’IDENTIFICATION DES POISSONS MARINS, EUROPE ET MÉDITERRANÉE - LOUISY Patrick - Ulmer - 2002. Interactúa con Fishipedia Para ponerse en contacto con nuestro equipo o participar en nuestro proyecto. Contribuya a esta página Plantilla y contenido © Fishipedia - Reproducción no autorizada sin solicitud previa - ISSN 2270-7247 - Última actualización el 12/11/2023 © Fishipedia.fr 2024",
    "genderDescription": "Anthiadidae",
    "type": "",
    "size": "15 cm",
    "maxSize": "27 cm",
    "mimetism": "",
    "recognize": "",
    "fe/maleDifferences": "El macho adulto presenta un mayor tamaño que la hembra.",
    "diet": "carnívoro",
    "territorial": "Sí",
    "social": "bancos",
    "lifeMode": "dieta",
    "lifeDescription": "",
    "reproductionMode": "<  tres colas  Anthias anthias  Linnaeus  1758  (Mundo) LC  Anthiadidae  Anthias",
    "migration": "",
    "reproductionDescription": "",
    "poison": "",
    "danger": "de realización. Los textos propuestos actualmente provienen de nuestro modelo de datos o están en proceso de redacción. Para solicitar prioridad para este contenido, puedes escribirnos AQUÍ.",
    "depth": "jerarquía",
    "image": "",
    "mapImage": ""
  },
  {
    "name": "Apogon imberbis",
    "sciname": "",
    "IUCN": "",
    "description": "Introducción Apogon imberbis, más comúnmente denominado reyezuelo, es un pez que habita en agua de mar.  de realización. Los textos propuestos actualmente provienen de nuestro modelo de datos o están en proceso de redacción. Para solicitar prioridad para este contenido, puedes escribirnos AQUÍ. ¿Quién es él?  Tipo Pez cardenal Tamaño medio 12 cm Tamaño máximo 15 cm Forma Inclasificable Apogon imberbis, reyezuelo © François Libert Tipo Pez cardenal Tamaño medio 12 cm Tamaño máximo 15 cm Forma Inclasificable ¿Cómo reconocer a Este pez ? El reyezuelo mide entre 12 y 15 cm. Este pez presenta una coloración unicolor con un cuerpo mayoritariamente rojo. Modo de vida y comportamiento dieta carnívoro Sociabilidad grupos o en solitario territorial Sí Modo de vida Nocturno El reyezuelo es un pez que vive en grupos o en solitario próximo al fondo. Es un animal carnívoro de temperamento tranquilo. Este pez vive principalmente de noche. Generalmente, abandona su escondite y comienza su actividad una vez que cae la noche. Aunque algo territorial, el reyezuelo se trata de un animal bastante tranquilo que generalmente se comporta de manera pacífica frente al resto de especies. Cabe señalar que a veces se comporta de manera menos tolerante con sus congéneres. Algunas pequeñas luchas pueden producirse entre los diferentes miembros del grupo, hasta que se establece un equilibrio. Reproducción Modo de reproducción ovíparo incubador bucal paternal El reyezuelo es un pez ovíparo incubador bucal paternal. Especies inofensivas Esta especie no supone ningún peligro en particular para el ser humano cuando se encuentra en su entorno natural. Origen y distribución Origen Mar Mediterráneo Océano Atlántico templado oriental Islas Córcega Islas Canarias Cerdeña Sicilia Estado de conservación de las poblaciones (UICN) Mundo : LC ¿Dónde observar esta especie? ¿Cuál es su hábitat? Características del entorno natural Temperatura 25 - 28 °C Profundidad 3 - 200 m Corriente Moderada Presentación del biotopo Frecuentemente encontramos a el reyezuelo a una profundidad de entre 3m y 200m. Sin embargo, no resulta del todo imposible observar a esta especie a otras profundidades. Especie del mismo biotopo águila de mar Myliobatidae lubina Moronidae Previous Next Mantenimiento en acuarios Deontología Respeto por la vida salvaje Con el fin de preservar la vida salvaje, si usted adquiere este animal, tenga en cuenta que este no debe ser nunca liberado en la naturaleza. Ver también el mapa de Fishipedia. Fishipedia apoya la práctica de una acuariofilia responsable y respetuosa con el medio ambiente. Fomentamos esta práctica siempre que esté motivada por el deseo de comprender el funcionamiento biológico de los seres vivos y siempre que se lleve a cabo respetando la vida animal. Creemos que la acuariofilia supone una manera de facilitar el acceso al descubrimiento de los diferentes ecosistemas acuáticos, en particular el agua dulce, aprovechando este conocimiento para protegerlos y respetarlos. Lógicamente, estamos en contra de la compra compulsiva de animales, que deriva en un mantenimiento inadecuado con un espacio insuficiente en el acuario. Nuestras recomendaciones volumen mínimo 400 litros Población min 1 Temperatura 25 - 28 °C pH (acidez) 8.2 - 8.4 Características Dificultad cría moderada robustez robusto  pacífico Disponibilidad ocasional Consejos generales  Se recomienda encarecidamente leer la ficha dedicada completa así como informarse del mantenimiento del animal previamente, con el fin de evitar cualquier potencial conflicto, incluso la muerte del ejemplar (o de los demás habitantes del acuario). Es importante no sobrecargar su acuario, limitando así un posible caso de contaminación del agua. El mantenimiento resultará, además, más sencillo.  en agua de mar La preparación de un acuario de agua de mar requiere ciertos conocimientos previos. El agua de mar es generalmente sintética, constituida por agua de ósmosis inversa y sal sintética a un nivel de 33 g/litro. También es posible utilizar directamente agua de mar (asegurándose siempre de que el agua no esté contaminada). La puesta en marcha de un acuario de agua de mar se realizará en tres fases: la instalación de una decoración de piedra viva, la introducción de invertebrados un mes después y la introducción de peces 3 meses después. Es fundamental esperar el mayor tiempo posible antes de introducir a los animales, dejando así que la microfauna cuente con el tiempo suficiente para desarrollarse de manera correcta. El equilibrio y la estabilidad físico-química son fundamentales para lograr el éxito en este tipo de acuarios. Recordatorio general sobre datos de mantenimiento Configuración de su acuario Le démarrage d'un aquarium est une partie primordiale pour l'équilibre et le bien-être des poissons. Lorsque l'on met en eau un aquarium, l'eau passe naturellement par un cycle biologique : le cycle de l'azote. Celui-ci dure environ trois semaines. Tous les 2 jours, nous vous conseillons de tester votre eau jusqu'à ce que le taux de nitrite soit à zéro pendant plusieurs jours d'affilée. Pour accélérer ce cycle, vous pouvez utiliser un activateur de bactéries comme JBL Denitrol. Cette solution riche en bactéries vivantes et enzymes permet une mise en place rapide du cycle de l'azote. Les poissons peuvent alors être introduits plus rapidement. Pruebas de los parámetros del agua Il est important de tester l'eau de son aquarium régulièrement pour maintenir un environnement sain pour les poissons et les autres habitants. Les tests d'eau permettent de mesurer les niveaux de différents paramètres tels que le pH, la dureté totale, ainsi que les taux de nitrates, de nitrites et d'ammoniaque. Pour réaliser ces tests, vous pouvez utiliser des produits d'analyse spécialisés tels que JBL ProScan qui permet de réaliser un diagnostic de l'eau directement via un smartphone. Il existe également des coffrets de tests plus classiques de bandelettes, comme JBL PROAQUATEST. Cambios de agua En cas d’usage de l’eau du robinet, vous pouvez utiliser un conditionneur d’eau de type Biotopol de JBL pour éliminer les substances nocives comme le chlore, le cuivre, le plomb et le zinc. Les conditionneurs d'eau garantissent une meilleure santé aux poissons et une meilleure croissance des plantes. Precauciones a tener en cuenta con el cloro El cloro y la cloramina resultan peligrosos para la salud de los animales. Usados ​​para desinfectar el agua, estos agentes están presentes en cantidades significativas en el agua del grifo. Recomendamos utilizar anticloro en cada cambio de agua. Además del cloro, los tratamientos y medicamentos vendidos para el comercio de acuarios contienen, a veces, metales pesados que pueden resultar ​​peligrosos en altas dosis. Información específica para el reyezuelo El reyezuelo es una especie marina que habita de forma natural a una temperatura comprendida entre 25 °C y 28 °C. Para un buen mantenimiento, la temperatura no debe superar nunca los 31°C durante largos periodos. El contenido en nitrato debe permanecer por debajo de 50mg/L. Para mantener el agua limpia y sin contaminantes, te recomendamos planificar una renovación mensual del 20% al 30% del volumen de agua. En agua de mar, es también posible eliminar el contenido en nitrato mediante uno de los siguientes métodos: Jaubert, desnitrificante de azufre, biopeletts o el método vodka. Dificultad de mantenimiento La cría de esta especie es accesible siempre que exista una documentación previa sobre sus necesidades en acuario. Los eventuales cohabitantes del acuario deberán elegirse con cuidado para evitar posibles casos de depredación. Especie disponible ocasionalmente Esta especie generalmente se encuentra disponible en tiendas especializadas o en clubs dedicados a la acuariofilia. Los ejemplares provenientes de la selección artificial son un poco más fáciles de criar, pero aún así, será siempre necesario respetar los parámetros específicos del agua. Incompatibilidades formales Atención, el reyezuelo es incompatible con crustáceos. Convivencia y Medio Ambiente En el contexto de un acuario comunitario, esta especie debe mantenerse en un volumen mínimo de 400 litros. Tratándose de una especie con un carácter algo \"miedoso\", conviene no mezclar a el reyezuelo con otras especies territoriales de gran tamaño o con peces muy agresivos. Sin embargo, puede convivir fácilmente con otros vecinos territoriales con un temperamento pacífico o con otras especies no territoriales poco agresivas. Se recomienda preveer una disposición adecuada para cada especie territorial: cada especie debe poder beneficiarse de una superficie así como de una decoración que le permita yuxtaponer su territorio al de sus vecinos de acuario. Consejos de alimentación El reyezuelo es un animal carnívoro. Esta especie puede ser alimentada con alimentos secos (copos, gránulos), alimentos frescos y alimentos congelados. Para evitar deficiencias, se recomienda variar el tipo de alimento. Se recomienda no sobrealimentar a los animales evitando así contaminar el agua. Para la mayoría de las especies, es conveniente administrar varias porciones menores cada día en lugar de una única comida copiosa. Protocolo de reproducción Dificultad de mantenimiento accesible Protección de la puesta Sí Hibridación En general, no se recomienda mezclar varias especies del mismo género, o diferentes variedades de la misma especie, con el fin de evitar una posible hibridación. Otros animales que podrían interesarte doncella común Labridae Estas plantas podrían interesarte Las plantas desempeñan un papel esencial en la acuariofilia, tanto por su capacidad de filtrar el agua absorbiendo los nutrientes en exceso como por su valor estético. Proporcionan refugios naturales a los peces, pueden servir como lugar de reproducción y contribuyen, en general, al equilibrio y a las buenas condiciones de mantenimiento del acuario. La selección presentada aquí reúne especies procedentes de las mismas regiones que la especie descrita en esta ficha, aunque no necesariamente de su biotopo exacto de origen. posidonia Posidoniaceae Ejemplos de acuarios que contienen esta especie Para saber más Especie de la misma familia Sphaeramia nematoptera Apogonidae Ostorhinchus rubrimacula Apogonidae Pterapogon kauderni Apogonidae Pristicon trimaculatus Apogonidae Pristiapogon fraenatus Apogonidae Ostorhinchus doederleini Apogonidae Zoramia leptacantha Apogonidae Ostorhinchus capricornis Apogonidae Previous Next Para leer en la web Fuentes y realización Participación y validación El equipo de Fishipedia y sus colaboradores especializados se comprometen a proporcionar contenido de alta calidad. Sin embargo, aunque la información proviene de fuentes científicas o testimonios de especialistas, los archivos pueden contener imprecisiones. Benoit Chartrer Traducción Traducción realizada con la valiosa contribución de nuestros traductores, quienes hacen que esta información esté disponible para un público más amplio. Referencias bibliográficas MAJOR CORAL REEF FISH SPECIES OF THE SOUTH PACIFIC WITH BASIC INFORMATION ON THEIR BIOLOGY AND ECOLOGY - Kulbicki Michel - Labrosse Pierre - Letourneur Yves - Manaldo Esther - Moutham Gérard - Vigliola Laurent - Wantiez Laurent - - 2011. Nouméa Interactúa con Fishipedia Para ponerse en contacto con nuestro equipo o participar en nuestro proyecto. Contribuya a esta página Plantilla y contenido © Fishipedia - Reproducción no autorizada sin solicitud previa - ISSN 2270-7247 - Última actualización el 13/11/2023 © Fishipedia.fr 2024",
    "genderDescription": "Apogonidae",
    "type": "",
    "size": "12 cm",
    "maxSize": "15 cm",
    "mimetism": "",
    "recognize": "",
    "fe/maleDifferences": "",
    "diet": "carnívoro",
    "territorial": "Sí",
    "social": "grupos o en solitario",
    "lifeMode": "dieta",
    "lifeDescription": "",
    "reproductionMode": "<  reyezuelo  Apogon imberbis  Linnaeus  1758  (Mundo) LC  Apogonidae  Apogon",
    "migration": "",
    "reproductionDescription": "",
    "poison": "",
    "danger": "de realización. Los textos propuestos actualmente provienen de nuestro modelo de datos o están en proceso de redacción. Para solicitar prioridad para este contenido, puedes escribirnos AQUÍ.",
    "depth": "3 - 200 m",
    "image": "",
    "mapImage": ""
  },
  {
    "name": "Atherina boyeri",
    "sciname": "",
    "IUCN": "",
    "description": "Introducción Atherina boyeri, más conocido como pejerrey del Mediterráneo, un pez de agua salada, presente en el océano Atlántico Norte, en el mar Mediterráneo y el mar Negro. ¿Quién es él?  Tamaño medio 18 cm Tamaño máximo 20 cm Longevidad 4 años Atherina boyeri, pejerrey mediterráneo Atherina boyeri, pejerrey mediterráneo Atherina boyeri, pejerrey mediterráneo Previous Next Tamaño medio 18 cm Tamaño máximo 20 cm Longevidad 4 años ¿Cómo reconocer a Este pez ? Esta especie presenta un cuerpo mayoritariamente plateado y gris. El dorso varía del amarillo verdoso al azul con puntos negros, la zona del vientre es de color gris plateado. Una línea de color amarillo y azul divide su cuerpo en dos de forma horizontal. Esta banda característica de esta especie, se sitúa en lugar de la que debería ser la línea lateral del cuerpo. Las aletas son translúcidas, situándose las pectorales en la parte alta del cuerpo. Esta especie tiene un ojo de gran tamaño. Diferencias entre machos y hembras Esta especie no presenta dimorfismo entre machos y hembras. Modo de vida y comportamiento dieta carnívoro Sociabilidad bancos territorial No Modo de vida Diurno El pejerrey del mediterráneo es un pez que vive en bancos cerca de la superficie y siempre próximos a la costa. Es una especie de temperamento tranquilo con un nado vivo. Esta especie soporta bien las variaciones en la salinidad, por lo que no es extraño encontrarla en las desembocaduras de los estuarios, en agua casi dulce. Reproducción Modo de reproducción ovíparo El pejerrey es un pez gonocórico, ovíparo, que desova en aguas abiertas. Esta especie alcanza la madurez sexual con un tamaño de 4 centímetros. La reproducción tiene lugar entre las estaciones de invierno y otoño. Las puestas son más intensas durante la época de verano. Los huevos tienen la particularidad de tener una textura pegajosa, lo que les permite adherirse a rocas, vegetales u otros deshechos. La incubación puede durar en torno a un mes y las larvas miden entre 4 y 6 milímetros. En función de la temperatura del agua, el tamaño de las crías puede llegar a multiplicarse por diez durante el primer año. Especies inofensivas Esta especie no presenta ningún peligro para el hombre en caso de un encuentro en su medio natural. Origen y distribución Origen Mar Mediterráneo Mar Negro Océano Atlántico templado oriental Océano Atlántico Oriental Frío Islas Islas Canarias Presencia geográfica y estado de la población Esta especie está presente en gran parte de las costas del Atlántico Nororiental, en el mar Mediterráneo y en el mar Negro. La especie no se encuentra en peligro actualmente. Estado de conservación de las poblaciones (UICN) Mundo : LC Francia : LC ¿Cuál es su hábitat? Características del entorno natural Temperatura 8 - 26 °C Profundidad 0 - 50 m Presentación del biotopo Esta especie suele encontrarse a poca profundidad, entre 0 y 3 metros. Sin embargo, puede ser vista hasta los 50 metros. Esta especie eurihalina, capaz de vivir en aguas que poseen un amplio rango de concentración de sales, frecuenta las zonas costeras, las lagunas y la alta mar. Especie del mismo biotopo chopa Sparidae pargo común Sparidae águila de mar Myliobatidae aguja de mar Syngnathidae doncella común Labridae raya torpedo Torpedinidae Previous Next Para saber más Especie de la misma familia Atherinomorus lacunosus Atherinidae Para leer en la web Fuentes y realización Participación y validación El equipo de Fishipedia y sus colaboradores especializados se comprometen a proporcionar contenido de alta calidad. Sin embargo, aunque la información proviene de fuentes científicas o testimonios de especialistas, los archivos pueden contener imprecisiones. Adrien Falzon Traducción Traducción realizada con la valiosa contribución de nuestros traductores, quienes hacen que esta información esté disponible para un público más amplio. Referencias bibliográficas Ecology, age and growth of Atherina boyeri and Atherina presbyter in the Ria de Aveiro, Portugal - Lúcia POMBO - Mike ELLIOTT - José Eduardo REBELO - Cybium - 2005. Interactúa con Fishipedia Para ponerse en contacto con nuestro equipo o participar en nuestro proyecto. Contribuya a esta página Plantilla y contenido © Fishipedia - Reproducción no autorizada sin solicitud previa - ISSN 2270-7247 - Última actualización el 12/11/2023 © Fishipedia.fr 2024",
    "genderDescription": "Atherinidae",
    "type": "",
    "size": "18 cm",
    "maxSize": "20 cm",
    "mimetism": "",
    "recognize": "",
    "fe/maleDifferences": "Esta especie no presenta dimorfismo entre machos y hembras.",
    "diet": "carnívoro",
    "territorial": "No",
    "social": "bancos",
    "lifeMode": "dieta",
    "lifeDescription": "",
    "reproductionMode": "<  pejerrey mediterráneo  Atherina boyeri  Risso  1810  (Mundo) LC  Atherinidae  Atherina",
    "migration": "",
    "reproductionDescription": "",
    "poison": "",
    "danger": "",
    "depth": "Enciclopedia Explorar Acuariofilia A propósito Prensa Peces Ballestas Barracudas Doradas y sargos Escorpenas Hipocampos Lábridos Morenas Peces cirujano Peces globo Peces payaso Rayas Tiburones Reptiles Cocodrilos Serpientes Tortugas Moluscos Caracoles Nudibranquios Calamares Pulpos Sepias Otros temas Anfibios Cnidarios Crustáceos Amazonas Anaconda gigante Anguila eléctrica Paiche Piraña roja Raya motoro / Raya de rio Tararira Mediterráneo Atún rojo Congrio Dorada real Manta raya Mero Sargo Islas Canarias Ángel de mar Caballito de mar Pez roca de Madeira Pez trompeta atlántico Tiburón Mako Vieja colorada Mar del Caribe Cirujano azul Gran barracuda / Picúa Pez ángel francés pez ángel reina Raya jaspeada Robalo blanco Mar Rojo Mero del Coral Morena gigante Pez león Pez Napoléon Raya de arrecife Vieja florida Especies comunes Betta Splendens Chupa algas Corydoras Discos Escalar Gamba Red Cherry Guppy Pez dorado Pez payaso Grupos temáticos Cíclidos enanos Killis Lochas Luchadores Peces gato Tetras Vivíparos Práctica Peces compatibles 20 L Peces compatibles 40 L Peces compatibles 60 L Peces compatibles 80 L Peces compatibles 100 L El proyecto Fishipedia Nuestra ética Proyecto Yaku Nawi Los fotógrafos colaboradores CONTÁCTANOS Enciclopedia Peces Ballestas Barracudas Doradas y sargos Escorpenas Hipocampos Lábridos Morenas Peces cirujano Peces globo Peces payaso Rayas Tiburones Reptiles Cocodrilos Serpientes Tortugas Moluscos Caracoles Nudibranquios Calamares Pulpos Sepias Otros temas Anfibios Cnidarios Crustáceos Explorar Amazonas Anaconda gigante Anguila eléctrica Paiche Piraña roja Raya motoro / Raya de rio Tararira Mediterráneo Atún rojo Congrio Dorada real Manta raya Mero Sargo Islas Canarias Ángel de mar Caballito de mar Pez roca de Madeira Pez trompeta atlántico Tiburón Mako Vieja colorada Mar del Caribe Cirujano azul Gran barracuda / Picúa Pez ángel francés pez ángel reina Raya jaspeada Robalo blanco Mar Rojo Mero del Coral Morena gigante Pez león Pez Napoléon Raya de arrecife Vieja florida Acuariofilia Especies comunes Betta Splendens Chupa algas Corydoras Discos Escalar Gamba Red Cherry Guppy Pez dorado Pez payaso Grupos temáticos Cíclidos enanos Killis Lochas Luchadores Peces gato Tetras Vivíparos Práctica Peces compatibles 20 L Peces compatibles 40 L Peces compatibles 60 L Peces compatibles 80 L Peces compatibles 100 L A propósito El proyecto Fishipedia Nuestra ética Proyecto Yaku Nawi Los fotógrafos colaboradores CONTÁCTANOS Prensa",
    "image": "",
    "mapImage": ""
  },
  {
    "name": "Aulostomus strigosus",
    "sciname": "",
    "IUCN": "",
    "description": "Introducción Aulostomus strigosus, conocido comúnmente como \"pez trompeta del Atlántico\", es un pez marino de la familia Aulostomidae. Habita en aguas tropicales y subtropicales del Océano Atlántico oriental, desde Marruecos hasta Senegal. También es habitual en la mayoría de las islas oceánicas de estas regiones, incluidas las Islas Canarias, las Islas de Cabo Verde y Madeira. ¿Quién es él?  Aulostomus Aún poco conocido, el género Aulostomus incluía tres especies en 2021. Todas ellas comúnmente denominadas \"peces trompeta\", una designación que hace referencia a su forma alargada. Es el único género de la familia Aulostomidae. Estos peces son fácilmente reconocibles gracias a su cuerpo delgado y su característico hocico largo. Poseen dos aletas dorsales y unas pequeñas aletas pélvicas. Sus parientes más cercanos son los conocidos como peces pipa, Fistulariidae. Los trompetas se distinguen entre otras cosas por su cola gruesa y coloreada, aguas arriba de la aleta caudal. Capaces de cambiar de color según su entorno, son depredadores de tamaño mediano especializados en la caza de otros peces. Se les suele observar regularmente nadando en cardúmenes, especialmente en compañía de otros grandes peces herbívoros como el pez loro. Estos peces se mimetizan discretamente con el paisaje adoptando una postura característica: colgando boca abajo, inmóviles, listos para sorprender a sus presas. La reproducción tiene lugar en aguas abiertas, y los huevos son arrastrados directamente por las corrientes una vez que se ha producido la fecundación.  Tamaño medio 60 cm Tamaño máximo 75 cm Patrón puntuación Aulostomus strigosus, pez trompeta del atlántico oriental © Benoit Chartrer Tamaño medio 60 cm Tamaño máximo 75 cm Patrón puntuación ¿Cómo reconocer a Este pez ? En los adultos, la cola es de color oscuro y aparece cubierta de rayas verticales y puntos azulados. La coloración comienza detrás de las aletas dorsal y anal y termina justo antes de la aleta caudal. El cuerpo, que puede llegar a alcanzar los 75 centímetros, es de color plateado, en ocasiones con reflejos azulados o verdosos, y cubierto de pequeños puntos negros. Una mancha negra se encuentra presente en la parte frontal del hocico y en las aletas anal y dorsal. En la aleta caudal pueden observarse dos manchas del mismo color. Los ejemplares más jóvenes poseen una coloración más vistosa, pudiendo, en ocasiones, tener un color amarillento a verdoso, con una serie de puntos en los mismos tonos. Diferencias entre machos y hembras No hay diferencias morfológicas obvias entre macho y hembra. Modo de vida y comportamiento dieta carnívoro Sociabilidad grupos o en solitario territorial No Modo de vida Diurno Esta especie es de carácter solitario e independiente. Sin embargo, no es extraño observar algunos ejemplares formando grupos para cazar o descansando en la misma zona. Cuando no están al acecho, estos peces se infiltran entre otras especies activas en las claras aguas de los arrecifes. Así aprovechan para protegerse de depredadores más grandes y cazar otro tipos de presas. El modo de vida de esta especie no ha sido, a día de hoy, muy estudiado. El pez trompeta del Atlántico parece ser principalmente piscívoro, pero también puede cazar otras presas pequeñas cerca de las rocas. Reproducción Modo de reproducción ovíparo que desova en aguas abiertas El pez trompeta del Atlántico es un pez ovíparo que desova en aguas abiertas. La reproducción de esta especie es aún poco conocida. Especies inofensivas Esta especie no presenta ningún peligro particular para los humanos en caso de encuentro en su medio natural. El encuentro puede ser, en ocasiones, bastante sorprendente ya que se han dado casos en los que individuos de unos sesenta centímetros se mezclan entre los nadadores en aguas muy poco profundas. Origen y distribución Origen Océano Atlántico templado oriental Océano Atlántico tropical oriental Islas Islas Canarias Presencia geográfica y estado de la población La especie se pesca localmente, aunque la presión pesquera parece, en general, ser débil. Su carne es consumida ocasionalmente por la población local. En determinadas zonas, como Canarias, en ocasiones existen grandes diferencias de abundancia en función del estado de salud de los ecosistemas. Estado de conservación de las poblaciones (UICN) Mundo : LC ¿Cuál es su hábitat? Características del entorno natural Profundidad 3 - 25 m Corriente Fuerte, Moderada y Lenta Presentación del biotopo El pez trompeta del Atlántico frecuenta las aguas costeras claras y poco profundas. Pudiendo ser observado hasta los 25 metros de profundidad. Esta especie vive en zonas rocosas, zonas de arrecifes o en los fondos densos plagados de guijarros. Especie del mismo biotopo sargo común Sparidae mojarra Sparidae raspallón Sparidae dorada Sparidae pez de san Pedro Zeidae caballito de mar mediterráneo Syngnathidae Previous Next Para saber más Para leer en la web Fuentes y realización Participación y validación El equipo de Fishipedia y sus colaboradores especializados se comprometen a proporcionar contenido de alta calidad. Sin embargo, aunque la información proviene de fuentes científicas o testimonios de especialistas, los archivos pueden contener imprecisiones. Pauline Gély Benoit Chartrer Traducción Traducción realizada con la valiosa contribución de nuestros traductores, quienes hacen que esta información esté disponible para un público más amplio. Referencias bibliográficas PHYLOGEOGRAPHY OF THE TRUMPETFISHES (AULOSTOMUS): RING SPECIESCOMPLEX ON A GLOBAL SCALE - B. W. BOWEN - A. L. BASS - L.A. Rocha - W. S. GRANT - D. Ross Robertson - EVOLUTION - 2001. Interactúa con Fishipedia Para ponerse en contacto con nuestro equipo o participar en nuestro proyecto. Contribuya a esta página Plantilla y contenido © Fishipedia - Reproducción no autorizada sin solicitud previa - ISSN 2270-7247 - Última actualización el 12/11/2023 © Fishipedia.fr 2024",
    "genderDescription": "Aulostomidae",
    "type": "",
    "size": "60 cm",
    "maxSize": "75 cm",
    "mimetism": "",
    "recognize": "",
    "fe/maleDifferences": "No hay diferencias morfológicas obvias entre macho y hembra.",
    "diet": "carnívoro",
    "territorial": "No",
    "social": "grupos o en solitario",
    "lifeMode": "dieta",
    "lifeDescription": "",
    "reproductionMode": "<  pez trompeta del atlántico oriental  Aulostomus strigosus  Wheeler  1955  (Mundo) LC  Aulostomidae  Aulostomus",
    "migration": "",
    "reproductionDescription": "",
    "poison": "",
    "danger": "",
    "depth": "Enciclopedia Explorar Acuariofilia A propósito Prensa Peces Ballestas Barracudas Doradas y sargos Escorpenas Hipocampos Lábridos Morenas Peces cirujano Peces globo Peces payaso Rayas Tiburones Reptiles Cocodrilos Serpientes Tortugas Moluscos Caracoles Nudibranquios Calamares Pulpos Sepias Otros temas Anfibios Cnidarios Crustáceos Amazonas Anaconda gigante Anguila eléctrica Paiche Piraña roja Raya motoro / Raya de rio Tararira Mediterráneo Atún rojo Congrio Dorada real Manta raya Mero Sargo Islas Canarias Ángel de mar Caballito de mar Pez roca de Madeira Pez trompeta atlántico Tiburón Mako Vieja colorada Mar del Caribe Cirujano azul Gran barracuda / Picúa Pez ángel francés pez ángel reina Raya jaspeada Robalo blanco Mar Rojo Mero del Coral Morena gigante Pez león Pez Napoléon Raya de arrecife Vieja florida Especies comunes Betta Splendens Chupa algas Corydoras Discos Escalar Gamba Red Cherry Guppy Pez dorado Pez payaso Grupos temáticos Cíclidos enanos Killis Lochas Luchadores Peces gato Tetras Vivíparos Práctica Peces compatibles 20 L Peces compatibles 40 L Peces compatibles 60 L Peces compatibles 80 L Peces compatibles 100 L El proyecto Fishipedia Nuestra ética Proyecto Yaku Nawi Los fotógrafos colaboradores CONTÁCTANOS Enciclopedia Peces Ballestas Barracudas Doradas y sargos Escorpenas Hipocampos Lábridos Morenas Peces cirujano Peces globo Peces payaso Rayas Tiburones Reptiles Cocodrilos Serpientes Tortugas Moluscos Caracoles Nudibranquios Calamares Pulpos Sepias Otros temas Anfibios Cnidarios Crustáceos Explorar Amazonas Anaconda gigante Anguila eléctrica Paiche Piraña roja Raya motoro / Raya de rio Tararira Mediterráneo Atún rojo Congrio Dorada real Manta raya Mero Sargo Islas Canarias Ángel de mar Caballito de mar Pez roca de Madeira Pez trompeta atlántico Tiburón Mako Vieja colorada Mar del Caribe Cirujano azul Gran barracuda / Picúa Pez ángel francés pez ángel reina Raya jaspeada Robalo blanco Mar Rojo Mero del Coral Morena gigante Pez león Pez Napoléon Raya de arrecife Vieja florida Acuariofilia Especies comunes Betta Splendens Chupa algas Corydoras Discos Escalar Gamba Red Cherry Guppy Pez dorado Pez payaso Grupos temáticos Cíclidos enanos Killis Lochas Luchadores Peces gato Tetras Vivíparos Práctica Peces compatibles 20 L Peces compatibles 40 L Peces compatibles 60 L Peces compatibles 80 L Peces compatibles 100 L A propósito El proyecto Fishipedia Nuestra ética Proyecto Yaku Nawi Los fotógrafos colaboradores CONTÁCTANOS Prensa",
    "image": "",
    "mapImage": ""
  },
  {
    "name": "Balistes capriscus",
    "sciname": "",
    "IUCN": "",
    "description": "Introducción El pez ballesta, también conocido como « ballesta gris », « ballesta común » y de forma más ocasional como « cerdo de mar », es un pez que puede ser observado desde las aguas del mar Negro hasta el mar del Caribe. Habita también las costas desde el Sudeste de Brasil hasta Canadá, en la zona Oeste del océano Atlántico. En la cara Este, ha sido documentado desde Angola hasta Irlanda. Su presencia en zonas limítrofes es más esporádica. Forma parte de las especies con el área más grande de repartición en la zona Atlántica. Los ballesta son peces conocidos por su carne, hecho poco conocido en Europa. Es por ello, que han sido objeto de una pesca intensiva histórica al otro lado del Atlántico así como en las costas africanas. Varios estudios realizados sobre la población de este pez en México han demostrado que las tasas de captura inducidas por la pesca comercial y recreativa no son sostenibles. Después de un pico de capturas en el año 1990, las poblaciones no han dejado de disminuir. Desde 2015, el ballesta está considerado como una especie \"vulnerable\" por el IUCN, estos peces deben siempre ser liberados en caso de captura accidental. En el litoral francés, es posible encontrar esta especie a lo largo del mar Mediterráneo y en el golfo de Gascuña. Aunque poco común, puede ser observado en la zona de Bretaña donde ha sido objeto de numerosos artículos de prensa sensacionalistas. En ellos se narraba la llegada de un pez tropical a costas francesas. En verdad, ya había sido documentado en el siglo pasado antes de su casi total desaparición. Gracias al calentamiento de las aguas, esta especie puede ver aumentada su área de repartición. Aunque de afinidad tropical, forma parte junto al lábrido verde y al pez loro rojo, de las especies autóctonas del mar Mediterráneo. El calentamiento climático parece jugar a favor de este trío cuyas poblaciones estaban antes focalizadas en las zonas Sur y Este del Mediterráneo. El lábrido verde se encuentra a día de hoy presente en Córcega así como en el sur de la costa Azul. En julio de 2020, una serie de mordeduras en las costas francesas podrían ser atribuidas a peces ballesta que protegían sus nidos. ¿Quién es él?  Balistes Al igual que el resto de balístidos, el género Balistes se caracteriza por la presencia de dos espinas eréctiles, una sobre la aleta dorsal (primer radio) y la otra en la zona ventral, creada de la fusión de las aletas pélvicas. La espina dorsal posee un mecanismo de bloqueo que sirve como método disuasorio frente a posibles depredadores, y que permite además que el pez se ancle en pequeñas grietas o fisuras impidiendo así ser arrastrado por las corrientes.  Tipo ballesta Tamaño medio 44 cm Tamaño máximo 66 cm Forma Oval Patrón moteado Balistes capriscus, ballesta común © Benoit Chartrer Balistes capriscus, ballesta común © Kevin Bryant Balistes capriscus, ballesta común © Kevin Bryant Balistes capriscus, ballesta común © Kevin Bryant Balistes capriscus, ballesta común © Kevin Bryant Balistes capriscus, ballesta común © Kevin Bryant Previous Next Tipo ballesta Tamaño medio 44 cm Tamaño máximo 66 cm Forma Oval Patrón moteado ¿Cómo reconocer a Este pez ? El ballesta común posee un cuerpo de forma oval y mayoritariamente de color gris. A veces son visibles algunas manchas marrones con reflejos azules en los flancos. Los ojos son pequeños, independientes y situados en la zona alta de la cabeza. Las aletas pectorales son cortas y transparentes. La aleta caudal es larga y tiene forma de lira. Como en la mayor parte de los ballesta, la segunda aleta dorsal así como la aleta anal están bastante desarrolladas y le sirven para nadar. Diferencias entre machos y hembras Los machos son de mayor tamaño que las hembras. Modo de vida y comportamiento dieta carnívoro Sociabilidad grupos o en solitario territorial No Modo de vida Diurno Los adultos nada a lo largo del fondo marino, en solitario o formando pequeños grupos, mientras los especímenes más jóvenes suelen ser vistos en la superficie, próximos a la zona de algas Sargassum. El nado puede ser bastante enérgico pero estos peces en general tienen un temperamento tranquilo. Fuera del período de reproducción, son prácticamente nocturnos y recorren los arrecifes en busca de presas en forma de moluscos y crustáceos. Balistes capriscus se caracteriza por defender su territorio durante el período de reproducción, mostrando un comportamiento agresivo. Reproducción Modo de reproducción ovíparo que desova en sustrato descubierto Los peces ballesta son conocidos por proteger y cuidar los huevos. Primero, la hembra prepara el nido en la arena donde depositará sus huevos. Estos serán incubados entre 12 y 58 horas para ser después transportados por las corrientes. Las crías son pelágicas durante un tiempo prolongado. Pasan entre 4 y 7 meses en superficie, camuflados entres las algas marrones de tipo sargazo. Machos y hembras alcanzan la madurez sexual con el mismo tamaño: 25 cm. Sin embargo, los machos la alcanzan con un año, mientras las hembras deben esperar a tener 2 años. En el mar Mediterráneo y en el golfo de México, la temporada de reproducción tiene lugar entre mayo y agosto. En el Oeste de África se produce entre octubre y diciembre, mientras en Brasil tiene lugar entre noviembre y febrero. Riesgos para los humanos Venenoso No Mordedor Sí Los peces ballesta son peces de carácter, en particular durante el período de reproducción. No dudarán en atacar a los bañistas que se acerquen a su nido. Al contrario que los peces escorpión, las rayas y los escorpena, este pez no es venenoso y se limita a dar pequeñas mordeduras, como una gran piraña. Menos virulento que su pariente tropical, el ballesta titán. Las mordeduras y pequeños golpes son inofensivos para los nadadores, pero pueden llegar a ser problemáticos durante las inmersiones. De hecho, se han dado casos en los que los ballesta rompen las máscaras de algunos buceadores experimentados a grandes profundidades. Además, los peces ballesta defienden un territorio cónico de su nido, de forma vertical. Así, no es recomendable sobrepasar un nido por encima ya que el ballesta atacará. Sino que al contrario, es recomendable alejarse hacia un lado. Origen y distribución Origen Golfo de México Mar del Caribe Mar Mediterráneo Océano Atlántico: costa norte de Brasil Océano Atlántico templado oriental Océano Atlántico Oriental Frío Océano Atlántico noroeste templado frío Océano Atlántico templado cálido del noroeste Sudoeste del Océano Atlántico templado cálido Océano Atlántico tropical oriental Océano Atlántico tropical Sudoeste Islas Islas Canarias Presencia geográfica y estado de la población La especie está presente en casi la totalidad del océano Atlántico. Muy común anteriormente, los ballestas están a día de hoy amenazados por la sobrepesca en una gran parte de su área. En numerosas regiones son todavía capturados antes de haber tenido tiempo para reproducirse. Los científicos estiman una disminución del 63 al 68% de la población durante tres generaciones, en el 25 a 75% de su área de repartición (golfo de México, golfo de Guinea y Brasil). Golfo de México a Estados Unidos: Esta especie ha constituido un importante recurso pesquero durante los años 80 y 90 en los estados de Texas, Misisipi, Alabama, Luisiana y Florida. Desde 1990, y aún más en 1993, las poblaciones no han dejado de disminuir. Planes para la conservación han sido puestos en marcha pero ningún signo de recuperación fue observado en 2014. Sur del golfo de México: No existen muchas estadísticas sobre esta región. Los ballesta parecen menos numerosos, acosados por la pesca artesanal, en particular en el Caribe. Faltan estudios más extensos para poder evaluar el estado de la población. Costa Atlántica Noroeste: La especie no es objeto de la pesca industrial o semiindustrial en esta región. Sin embargo, la tasa de captura accidental se ha dividido por 5 desde los años 70, sugiriendo una disminución de las poblaciones. Brasil: La situación en la costa sudamericana es una de las más preocupantes. Explotado desde los años 60 a lo largo del estado de São Paulo. Comenzó a ser objeto de una pesca intensiva durante los años 90 y 2000, convirtiéndose en uno de los principales recursos pesqueros en el estado de Espírito Santo hasta que un colapso en las poblaciones provocó su desaparición del comercio marítimo. Las pesquerías con redes de enmalle, con un tamaño de malla inferior a la talla de reproducción son las responsables de esta catástrofe ecológica. Los científicos estiman que casi la mitad de los peces capturados no habían alcanzado aún la madurez. Costa del Atlántico Sureste y Mediterráneo : En el lado africano, después de haber sido la especie más pescada en el golfo de Guinea durante casi 20 años, las poblaciones se han desplomado. Después de una edad de oro durante los años 7o y 80, las capturas disminuyeron e incluso colapsaron en Ghana, Togo, Sierra Leona, Costa de Marfil y Cabo Verde. En Costa de Marfil, este pez que abundaba durante los años 80 desapareció prácticamente desde el año 1993. Una segunda especie, B. carolinensis, ha visto igualmente disminuir su número debido a la sobreexplotación. En Ghana, entre 1979 y 1980, el ballesta correspondía a un 62% de la biomasa total de peces demersales de aguas costeras. Durante el curso de los años 80, cerca de 8000 toneladas de ballestas fueron capturados por año en las costas ghanesas. En 1995, 2 toneladas de peces ballesta fueron pescados. Más recientemente, la especie podría comenzar a restablecerse en Ghana y en Sierra Leona, donde forma parte de las 20 especies más vistas frecuentemente. Costa del Atlántico Noreste: Túnez y Portugal fueron los países donde más capturas se realizaron en el período entre 1993 y 2009, con una media de 77 toneladas por año. En 2009, Libia pescó 432 toneladas de estos peces. En Irlanda, un aumento de las capturas fue registrada entre 1989 y 1991, fecha que podría coincidir con los años de observación de ballestas en las costas bretonas. Estado de conservación de las poblaciones (UICN) Mundo : VU ¿Dónde observar esta especie? ¿Cuál es su hábitat? Características del entorno natural Temperatura 18 - 24 °C Profundidad 1 - 100 m Presentación del biotopo Los peces ballestas son vistos a menudo entre 10 y 50 metros de profundidad. Los adultos frecuentan las zonas litorales poco profundas como las praderas marinas, los arrecifes coralinos o las bahías rocosas. A veces pueden ser avistados a las puertas de los estuarios. Sus numerosos y coloridos parientes son también frecuentes habitantes de los arrecifes de coral. Especie del mismo biotopo galán Labridae tapaculo Bothidae gallinita Tetraodontidae tordo Labridae pez víbora Trachinidae raya toro Myliobatidae Previous Next Para saber más Especie de la misma familia ballesta titán Balistidae ballesta de márgenes amarillos Balistidae pez ballesta azul Balistidae Rhinecanthus rectangulus Balistidae Sufflamen bursa Balistidae Rhinecanthus lunula Balistidae pez ballesta a manchas amarillas Balistidae ballesta picasso Balistidae Previous Next Para leer en la web Fuentes y realización Participación y validación El equipo de Fishipedia y sus colaboradores especializados se comprometen a proporcionar contenido de alta calidad. Sin embargo, aunque la información proviene de fuentes científicas o testimonios de especialistas, los archivos pueden contener imprecisiones. Benoit Chartrer Traducción Traducción realizada con la valiosa contribución de nuestros traductores, quienes hacen que esta información esté disponible para un público más amplio. Referencias bibliográficas A new maximum length for the grey triggerfish, Balistes capriscus Gmelin, 1789 (pisces: Balistidae) from the Adriatic Sea - Dulčić Jakov - Alen Soldo - INSTITUTE OF OCEANOGRAPHYAND FISHERIES - SPLIT CROATIA - 2005. Age, growth, and mortality of gray triggerfish (Balistes capriscus) from the southeastern United States - Michael L. Burton - Jennifer C. Potts - Daniel R. Carr - Michael Cooper - Jessica Lewis - NOAA - National Marine Fisheries Service - 2014. The reproductive biology of the grey triggerfish Balistes capriscus (Pisces: Balistidae) in the Gulf of Gabe` s (south-eastern Mediterranean Sea) - Hichem Kacem - Neifar Lassâd - Marine Biological Association of the United Kingdom - 2014. Interactúa con Fishipedia Para ponerse en contacto con nuestro equipo o participar en nuestro proyecto. Contribuya a esta página Plantilla y contenido © Fishipedia - Reproducción no autorizada sin solicitud previa - ISSN 2270-7247 - Última actualización el 12/11/2023 © Fishipedia.fr 2024",
    "genderDescription": "Balistidae",
    "type": "",
    "size": "44 cm",
    "maxSize": "66 cm",
    "mimetism": "",
    "recognize": "",
    "fe/maleDifferences": "Los machos son de mayor tamaño que las hembras.",
    "diet": "carnívoro",
    "territorial": "No",
    "social": "grupos o en solitario",
    "lifeMode": "dieta",
    "lifeDescription": "",
    "reproductionMode": "<  ballesta común  Balistes capriscus  Gmelin  1789  (Mundo) VU  Balistidae  Balistes",
    "migration": "",
    "reproductionDescription": "",
    "poison": "No",
    "danger": "",
    "depth": "Enciclopedia Explorar Acuariofilia A propósito Prensa Peces Ballestas Barracudas Doradas y sargos Escorpenas Hipocampos Lábridos Morenas Peces cirujano Peces globo Peces payaso Rayas Tiburones Reptiles Cocodrilos Serpientes Tortugas Moluscos Caracoles Nudibranquios Calamares Pulpos Sepias Otros temas Anfibios Cnidarios Crustáceos Amazonas Anaconda gigante Anguila eléctrica Paiche Piraña roja Raya motoro / Raya de rio Tararira Mediterráneo Atún rojo Congrio Dorada real Manta raya Mero Sargo Islas Canarias Ángel de mar Caballito de mar Pez roca de Madeira Pez trompeta atlántico Tiburón Mako Vieja colorada Mar del Caribe Cirujano azul Gran barracuda / Picúa Pez ángel francés pez ángel reina Raya jaspeada Robalo blanco Mar Rojo Mero del Coral Morena gigante Pez león Pez Napoléon Raya de arrecife Vieja florida Especies comunes Betta Splendens Chupa algas Corydoras Discos Escalar Gamba Red Cherry Guppy Pez dorado Pez payaso Grupos temáticos Cíclidos enanos Killis Lochas Luchadores Peces gato Tetras Vivíparos Práctica Peces compatibles 20 L Peces compatibles 40 L Peces compatibles 60 L Peces compatibles 80 L Peces compatibles 100 L El proyecto Fishipedia Nuestra ética Proyecto Yaku Nawi Los fotógrafos colaboradores CONTÁCTANOS Enciclopedia Peces Ballestas Barracudas Doradas y sargos Escorpenas Hipocampos Lábridos Morenas Peces cirujano Peces globo Peces payaso Rayas Tiburones Reptiles Cocodrilos Serpientes Tortugas Moluscos Caracoles Nudibranquios Calamares Pulpos Sepias Otros temas Anfibios Cnidarios Crustáceos Explorar Amazonas Anaconda gigante Anguila eléctrica Paiche Piraña roja Raya motoro / Raya de rio Tararira Mediterráneo Atún rojo Congrio Dorada real Manta raya Mero Sargo Islas Canarias Ángel de mar Caballito de mar Pez roca de Madeira Pez trompeta atlántico Tiburón Mako Vieja colorada Mar del Caribe Cirujano azul Gran barracuda / Picúa Pez ángel francés pez ángel reina Raya jaspeada Robalo blanco Mar Rojo Mero del Coral Morena gigante Pez león Pez Napoléon Raya de arrecife Vieja florida Acuariofilia Especies comunes Betta Splendens Chupa algas Corydoras Discos Escalar Gamba Red Cherry Guppy Pez dorado Pez payaso Grupos temáticos Cíclidos enanos Killis Lochas Luchadores Peces gato Tetras Vivíparos Práctica Peces compatibles 20 L Peces compatibles 40 L Peces compatibles 60 L Peces compatibles 80 L Peces compatibles 100 L A propósito El proyecto Fishipedia Nuestra ética Proyecto Yaku Nawi Los fotógrafos colaboradores CONTÁCTANOS Prensa",
    "image": "",
    "mapImage": ""
  },
  {
    "name": "Bodianus scrofa",
    "sciname": "",
    "IUCN": "",
    "description": "Introducción Bodianus scrofa, conocido como pez perro según recoge Fishbase, es un pez marino endémico de la Macaronesia. Este lábrido multicolor ha sido fruto de una pesca intensiva y está actualmente considerado como vulnerable desde 2008 por la IUCN. Las poblaciones alrededor de las Islas Canarias y Madeira son particularmente pequeñas, siendo su situación también complicada en Cabo Verde. ¿Quién es él?  Bodianus Según Fishbase, el género Bodianus contenía 45 especies en 2010. Según el análisis filogenético, se reconocen y diferencian 10 subgéneros según su área de distribución en el mundo. El nombre del género deriva del portugués “bodiano, pudiano” que significa pudor, ya que la parte anterior del cuerpo “enrojece” debido a una coloración vinosa. La mayoría de los peces de este género viven en arrecifes rocosos y de coral. Los adultos se observan generalmente entre la superficie y los 70 metros de profundidad. Sin embargo, algunas especies pueden encontrarse a profundidades de hasta 510 metros. El género Bodianus se distribuye en las zonas tropical, subtropical y templada cálida de los tres océanos principales. Está particularmente presente en el Océano Índico occidental, en el Océano Pacífico central como en Hawai, pero también en el Océano Atlántico occidental. Los peces del género son de tamaño relativamente grande. El pez más grande del género mide 80 cm (Bodianus perditio) mientras que el pez más pequeño mide 5,9 cm (Bodianus bimaculatus). El tamaño medio ronda los 30-40 cm. Como la mayoría de los lábridos, los peces del género Bodianus son reconocidos como hermafroditas protóginos, lo que significa que los peces nacen hembras y se vuelven machos a medida que crecen. También son ovíparos (huevos que eclosionan fuera del cuerpo de la hembra). El desove a menudo tiene lugar en un entorno pelágico. Entre las 45 especies que constituyen el género Bodianus, tan solo dos de ellas se encuentran amenazadas. Bodianus scrofa es la especie más amenazada y está catalogada con el estatus de \"vulnerable\". Bodianus frenchii está, a día de hoy, catalogado como \"casi amenazado\". El resto de especies se clasifican como \"de menor preocupación\".  Tipo Lábrido Tamaño medio 70 cm Tamaño máximo 80 cm Patrón líneas horizontales Bodianus scrofa, pez perro © Michael J Sealey Bodianus scrofa, pez perro © Xaime Beiro Previous Next Tipo Lábrido Tamaño medio 70 cm Tamaño máximo 80 cm Patrón líneas horizontales ¿Cómo reconocer a Este pez ? Este pez mide alrededor de 70 cm. Sin embargo, los machos dominantes pueden llegar a alcanzar los 80 cm. Esta especie presenta una coloración tricolor: rojo, amarillo y rosado. Posee también unas características rayas horizontales de color rojo y amarillo. Diferencias entre machos y hembras El macho adulto es de mayor tamaño que la hembra. Modo de vida y comportamiento dieta carnívoro Sociabilidad solitario territorial Sí Modo de vida Diurno Este pez de carácter solitario reside naturalmente cerca del fondo. Se trata de una especie carnívora de temperamento bastante tranquilo que se alimenta principalmente de invertebrados, en particular de erizos de mar y gasterópodos. Esta especie es territorial y no suele apreciar la presencia de intrusos, especialmente de otros animales con comportamiento similar. También puede mostrarse virulento contra sus congéneres. Sin embargo, apenas mostrará interés por otras especies no territoriales. Reproducción Modo de reproducción ovíparo que desova en aguas abiertas Poligamia Sí Hermafrodita protógino Se trata de un pez ovíparo que desova en aguas abiertas. En esta especie, los machos dominantes son polígamos y se reproducen cada temporada con entre una y tres hembras. Estas últimas residen en el territorio del macho. Todos los individuos nacen hembras. Al crecer, las hembras cambiarán de sexo para convertirse en machos, esto se denomina hermafroditismo sucesivo de tipo protógino. Este lábrido no hace nido y tampoco cuida su puesta. Después del desove, los huevos son llevados a aguas más profundas. Los juveniles se refugian en grietas y cavidades, por debajo de los 30 metros de profundidad. Especies inofensivas Esta especie no presenta ningún peligro en particular para los humanos en caso de encuentro en su medio natural. Origen y distribución Origen Océano Atlántico templado oriental Islas Islas Canarias Presencia geográfica y estado de la población Esta especie se encuentra en la Macaronesia. Las poblaciones en las Azores todavía son saludables, con individuos registrados en muchos arrecifes rocosos de 15 a 50 metros de profundidad. Sin embargo, las poblaciones de Madeira, Canarias y Cabo Verde aparecen de manera más dispersa. Apreciada por su carne, es objeto de la pesca artesanal y recreativa. Está presente en un área de ocupación estimada en menos de 2000 km², y a día de hoy, sigue siendo estando bajo la presión pesquera en toda su área de distribución en 2022. Estado de conservación de las poblaciones (UICN) Mundo : VU ¿Cuál es su hábitat? Características del entorno natural Temperatura 16 - 24 °C Profundidad 15 - 200 m Corriente Fuerte y Moderada Presentación del biotopo Este pez se encuentra con mayor frecuencia a una profundidad de entre 15 y 200 m. Sin embargo, no es imposible encontrarlo a otras profundidades. Frecuenta las áreas rocosas de las costas de las islas y los arrecifes en alta mar, así como los bancos poco profundos. Aprecia también las zonas de alto relieve con fuertes corrientes. Especie del mismo biotopo morena común Muraenidae reyezuelo Apogonidae abade Serranidae gobio de roca Gobiidae blenio del Atlántico Blenniidae pez trompeta del atlántico oriental Aulostomidae Previous Next Para saber más Especie de la misma familia Hologymnosus doliatus Labridae doncella común Labridae Macropharyngodon meleagris Labridae Symphodus doderleini Labridae tordo picudo Labridae Hemigymnus melapterus Labridae Centrolabrus exoletus Labridae Halichoeres argus Labridae Previous Next Para leer en la web Fuentes y realización Participación y validación El equipo de Fishipedia y sus colaboradores especializados se comprometen a proporcionar contenido de alta calidad. Sin embargo, aunque la información proviene de fuentes científicas o testimonios de especialistas, los archivos pueden contener imprecisiones. Traducción Traducción realizada con la valiosa contribución de nuestros traductores, quienes hacen que esta información esté disponible para un público más amplio. Interactúa con Fishipedia Para ponerse en contacto con nuestro equipo o participar en nuestro proyecto. Contribuya a esta página Plantilla y contenido © Fishipedia - Reproducción no autorizada sin solicitud previa - ISSN 2270-7247 - Última actualización el 11/11/2023 © Fishipedia.fr 2024",
    "genderDescription": "Labridae",
    "type": "",
    "size": "Tipo Lábrido Tamaño medio 70 cm Tamaño máximo 80 cm Patrón líneas horizontales Bodianus scrofa, pez perro © Michael J Sealey Bodianus scrofa, pez perro © Xaime Beiro Previous Next Tipo Lábrido Tamaño medio 70 cm Tamaño máximo 80 cm Patrón líneas horizontales",
    "maxSize": "80 cm",
    "mimetism": "",
    "recognize": "",
    "fe/maleDifferences": "El macho adulto es de mayor tamaño que la hembra.",
    "diet": "carnívoro",
    "territorial": "Sí",
    "social": "solitario",
    "lifeMode": "dieta",
    "lifeDescription": "",
    "reproductionMode": "<  pez perro  Bodianus scrofa  Valenciennes  1839  (Mundo) VU  Labridae  Bodianus",
    "migration": "",
    "reproductionDescription": "",
    "poison": "",
    "danger": "",
    "depth": "Enciclopedia Explorar Acuariofilia A propósito Prensa Peces Ballestas Barracudas Doradas y sargos Escorpenas Hipocampos Lábridos Morenas Peces cirujano Peces globo Peces payaso Rayas Tiburones Reptiles Cocodrilos Serpientes Tortugas Moluscos Caracoles Nudibranquios Calamares Pulpos Sepias Otros temas Anfibios Cnidarios Crustáceos Amazonas Anaconda gigante Anguila eléctrica Paiche Piraña roja Raya motoro / Raya de rio Tararira Mediterráneo Atún rojo Congrio Dorada real Manta raya Mero Sargo Islas Canarias Ángel de mar Caballito de mar Pez roca de Madeira Pez trompeta atlántico Tiburón Mako Vieja colorada Mar del Caribe Cirujano azul Gran barracuda / Picúa Pez ángel francés pez ángel reina Raya jaspeada Robalo blanco Mar Rojo Mero del Coral Morena gigante Pez león Pez Napoléon Raya de arrecife Vieja florida Especies comunes Betta Splendens Chupa algas Corydoras Discos Escalar Gamba Red Cherry Guppy Pez dorado Pez payaso Grupos temáticos Cíclidos enanos Killis Lochas Luchadores Peces gato Tetras Vivíparos Práctica Peces compatibles 20 L Peces compatibles 40 L Peces compatibles 60 L Peces compatibles 80 L Peces compatibles 100 L El proyecto Fishipedia Nuestra ética Proyecto Yaku Nawi Los fotógrafos colaboradores CONTÁCTANOS Enciclopedia Peces Ballestas Barracudas Doradas y sargos Escorpenas Hipocampos Lábridos Morenas Peces cirujano Peces globo Peces payaso Rayas Tiburones Reptiles Cocodrilos Serpientes Tortugas Moluscos Caracoles Nudibranquios Calamares Pulpos Sepias Otros temas Anfibios Cnidarios Crustáceos Explorar Amazonas Anaconda gigante Anguila eléctrica Paiche Piraña roja Raya motoro / Raya de rio Tararira Mediterráneo Atún rojo Congrio Dorada real Manta raya Mero Sargo Islas Canarias Ángel de mar Caballito de mar Pez roca de Madeira Pez trompeta atlántico Tiburón Mako Vieja colorada Mar del Caribe Cirujano azul Gran barracuda / Picúa Pez ángel francés pez ángel reina Raya jaspeada Robalo blanco Mar Rojo Mero del Coral Morena gigante Pez león Pez Napoléon Raya de arrecife Vieja florida Acuariofilia Especies comunes Betta Splendens Chupa algas Corydoras Discos Escalar Gamba Red Cherry Guppy Pez dorado Pez payaso Grupos temáticos Cíclidos enanos Killis Lochas Luchadores Peces gato Tetras Vivíparos Práctica Peces compatibles 20 L Peces compatibles 40 L Peces compatibles 60 L Peces compatibles 80 L Peces compatibles 100 L A propósito El proyecto Fishipedia Nuestra ética Proyecto Yaku Nawi Los fotógrafos colaboradores CONTÁCTANOS Prensa",
    "image": "",
    "mapImage": ""
  },
  {
    "name": "Boops boops",
    "sciname": "",
    "IUCN": "",
    "description": "Introducción Boops boops, más comúnmente denominada boga, es un pez que habita en agua de mar.  de realización. Los textos propuestos actualmente provienen de nuestro modelo de datos o están en proceso de redacción. Para solicitar prioridad para este contenido, puedes escribirnos AQUÍ. ¿Quién es ella?  Tamaño medio 20 cm Tamaño máximo 40 cm Longevidad 5 años Forma Oval Boops boops, boga © Thomas Menut Tamaño medio 20 cm Tamaño máximo 40 cm Longevidad 5 años Forma Oval ¿Cómo reconocer a Este pez ? La boga mide entre 20 y 40 cm. Este pez presenta una coloración unicolor con un cuerpo mayoritariamente plateado. Modo de vida y comportamiento dieta carnívoro Sociabilidad bancos territorial No Modo de vida Diurno La boga es un pez que vive en bancos a media profundidad y próximo a la superficie. Es un animal carnívoro de temperamento tranquilo. De manera general, esta especie no suele prestar demasiada atención al resto de especies que se cruzan en su camino. Reproducción Especies inofensivas Esta especie no supone ningún peligro en particular para el ser humano cuando se encuentra en su entorno natural. Origen y distribución Origen Mar Mediterráneo Océano Atlántico templado oriental Islas Islas Canarias Estado de conservación de las poblaciones (UICN) Mundo : LC ¿Dónde observar esta especie? ¿Cuál es su hábitat? Características del entorno natural Profundidad 0 - 350 m Presentación del biotopo Frecuentemente encontramos a la boga a una profundidad de entre 0m y 350m. Sin embargo, no resulta del todo imposible observar a esta especie a otras profundidades. Especie del mismo biotopo miracielo Uranoscopidae raya mosaico Rajidae rape común Lophiidae pez de san Pedro Zeidae raya mariposa Gymnuridae tapaculo Bothidae Previous Next Para saber más Especie de la misma familia sargo breado Sparidae pargo común Sparidae dentón común Sparidae mojarra Sparidae sargo común Sparidae breca Sparidae dorada Sparidae chopa Sparidae Previous Next Para leer en la web Fuentes y realización Participación y validación El equipo de Fishipedia y sus colaboradores especializados se comprometen a proporcionar contenido de alta calidad. Sin embargo, aunque la información proviene de fuentes científicas o testimonios de especialistas, los archivos pueden contener imprecisiones. Adrien Falzon Benoit Chartrer Traducción Traducción realizada con la valiosa contribución de nuestros traductores, quienes hacen que esta información esté disponible para un público más amplio. Interactúa con Fishipedia Para ponerse en contacto con nuestro equipo o participar en nuestro proyecto. Contribuya a esta página Plantilla y contenido © Fishipedia - Reproducción no autorizada sin solicitud previa - ISSN 2270-7247 - Última actualización el 13/11/2023 © Fishipedia.fr 2024",
    "genderDescription": "Sparidae",
    "type": "",
    "size": "20 cm",
    "maxSize": "40 cm",
    "mimetism": "",
    "recognize": "",
    "fe/maleDifferences": "",
    "diet": "carnívoro",
    "territorial": "No",
    "social": "bancos",
    "lifeMode": "dieta",
    "lifeDescription": "",
    "reproductionMode": "<  boga  Boops boops  Linnaeus  1758  (Mundo) LC  Sparidae  Boops",
    "migration": "",
    "reproductionDescription": "",
    "poison": "",
    "danger": "de realización. Los textos propuestos actualmente provienen de nuestro modelo de datos o están en proceso de redacción. Para solicitar prioridad para este contenido, puedes escribirnos AQUÍ.",
    "depth": "tranquilo",
    "image": "",
    "mapImage": ""
  },
  {
    "name": "Bothus podas",
    "sciname": "",
    "IUCN": "",
    "description": "Introducción Bothus podas, más comúnmente conocido como tapaculo, y a menudo mal denominado con el nombre de rodaballo debido a su parecido, nombre que en realidad pertenece a las especies Scophthalmus maximus y Scophthalmus rhombus. Bothus podas un pez plano que vive en el Mar Mediterráneo y en la costa oriental templada del Océano Atlántico. ¿Quién es él?  Bothus En 2019, el género Bothus incluía 16 especies según FishBase. Estas especies se encuentran ampliamente distribuidas por todo el planeta, especialmente en las zonas tropicales y templadas. Algunos de ellos se conocen comúnmente como \"platijas\". Como todos los peces planos del grupo pleuronectiforme, los dos ojos están colocados en un mismo flanco. Estos peces se caracterizan por el amplio espacio entre cada ojo, característica que se observa especialmente en los machos. Los ojos están presentes en el lado izquierdo, que también suele ser más colorido. Las aletas pélvicas son desiguales con una aleta situada cerca de los ojos de forma más alargada. Estas especies dividen su forma de vida en tres etapas: huevo, larva y adulto. Las larvas y los adultos difieren en coloración, simetría y forma del cuerpo. En este género, es el ojo derecho el que migra al ojo izquierdo. La migración del ojo puede ocurrir a través de una hendidura formada durante la separación de la aleta dorsal del cráneo o a través de un \"agujero\" en la cabeza que impulsa el proceso. Los cambios en la pigmentación también tienen lugar durante la metamorfosis. Al igual que en otros peces planos relacionados, las células pigmentarias (encargadas de aportar color) están presentes al nacer en ambos lados del cuerpo, pero en poca abundancia. Durante la metamorfosis, estos melanóforos desaparecen en el lado \"ciego\" (la parte inferior) y se sitúan únicamente en el lado de los ojos. Estos peces poseen la capacidad de cambiar de color para mimetizarse con el fondo marino, imitando especialmente las zonas arenosas. Este comportamiento está controlado por unos neurotransmisores encargados de enviar señales que intervienen en los cambios en los melanóforos. Los diferentes colores resultan de las concentraciones elegidas de gránulos de pigmento en las diferentes áreas. Estos cambios son siempre reversibles. Además de esta capacidad de mimetismo, todos los peces de este género pueden enterrarse en la arena para camuflarse. Además de su capacidad para camuflarse, estos animales poseen un órgano sensorial que detecta el movimiento y la vibración en el agua. Los ojos en la parte superior del cuerpo del adulto sirven como órganos visuales.  Tipo pez plano Tamaño medio 15 cm Tamaño máximo 45 cm Mimetismo fondo arenoso Patrón puntuación Bothus podas, tapaculo © Thomas Menut Tipo pez plano Tamaño medio 15 cm Tamaño máximo 45 cm Mimetismo fondo arenoso Patrón puntuación ¿Cómo reconocer a Este pez ? Pez plano El tapaculo es un siniestro pez óseo (con sus dos ojos en la misma cara: la izquierda). Las escamas del lado de los ojos son ctenoides y cicloides del lado ciego. Los radios superiores de la aleta pectoral no aparecen extendidos. El lado superior es de color marrón claro con manchas más oscuras. Existe una subespecie en las islas de Madeira y Canarias, que presenta un color que va del marrón oscuro al púrpura oscuro. Esta especie puede ser confundida con las especies del género Scophthalmus aunque se distingue de estas por su forma de diamante. Diferencias entre machos y hembras El macho adulto es de mayor tamaño que la hembra. El ancho interorbital también es mayor en este último. Modo de vida y comportamiento dieta omnívoro con tendencia carnívora Sociabilidad solitario territorial Sí Modo de vida Nocturno Los machos de esta especie son territoriales y no aceptan competidores en su zona de vida. Debido a ello pueden llegar a mostrar signos de agresividad, realizando incluso algunas exhibiciones de fuerza. Las hembras son más pacíficas, habitando en pequeños territorios que pueden integrar los de los machos. Los territorios cambian entre el día y la noche. Parecería que los machos se acercan a la orilla durante la noche mientras que las hembras alcanzan aguas más profundas. Estos peces son solitarios y pasan todo el tiempo descansando sobre el sustrato o enterrados, a la espera de presas, especialmente invertebrados y pequeños peces. Ellos mismos son cazados por rayas y tiburones. En caso de amenaza, se mimetizan con el fondo o se hunden instantáneamente en la arena hasta que desaparece el peligro. Se encuentran principalmente en fondos arenosos o mixtos del Mediterráneo, a menudo cerca de Posidonia. Reproducción Modo de reproducción ovíparo que desova en aguas abiertas Esta especie se trata de un pez ovíparo que desova en aguas abiertas. Los machos poseen un harén de varias hembras que residen en su territorio. Los compañeros potenciales se comunican mediante el tacto utilizando la aleta pectoral ocular. Después de un período de cortejo, macho y hembra se colocan en la columna de agua y ascienden juntos. Durante el ascenso, a unos 2 metros sobre el sustrato, se liberan simultáneamente los gametos. Después del proceso de apareamiento, los machos \"verifican\" que el apareamiento haya sido exitoso. Se envía algún tipo de señal entre los peces en este momento, aunque, a día de hoy, se desconoce si se trata de una señal visual o una señal química. Los huevos son después arrastrados por la corriente. La reproducción tiene lugar entre mayo y agosto, y parece tener lugar preferentemente al anochecer. Especies inofensivas Esta especie no presenta ningún peligro en particular para los humanos en caso de encuentro en su medio natural. Origen y distribución Origen Mar Mediterráneo Océano Atlántico templado oriental Islas Córcega Islas Canarias Cerdeña Sicilia Presencia geográfica y estado de la población El tapaculo vive en el Mar Mediterráneo y en la fachada oriental templada del Océano Atlántico. Estado de conservación de las poblaciones (UICN) Mundo : LC ¿Dónde observar esta especie? ¿Cuál es su hábitat? Características del entorno natural Temperatura 18 - 28 °C Profundidad 15 - 400 m Presentación del biotopo Esta especie bentónica, que se observa regularmente entre los 15 y los 20 metros, está presente a grandes profundidades. Especie del mismo biotopo gallinita Tetraodontidae raya redonda Dasyatidae águila de mar Myliobatidae pez jabalí Caproidae raya boca de rosa Rajidae ballesta común Balistidae Previous Next Mantenimiento en acuarios Deontología Respeto por la vida salvaje Con el fin de preservar la vida salvaje, si usted adquiere este animal, tenga en cuenta que este no debe ser nunca liberado en la naturaleza. Ver también el mapa de Fishipedia. Fishipedia apoya la práctica de una acuariofilia responsable y respetuosa con el medio ambiente. Fomentamos esta práctica siempre que esté motivada por el deseo de comprender el funcionamiento biológico de los seres vivos y siempre que se lleve a cabo respetando la vida animal. Creemos que la acuariofilia supone una manera de facilitar el acceso al descubrimiento de los diferentes ecosistemas acuáticos, en particular el agua dulce, aprovechando este conocimiento para protegerlos y respetarlos. Lógicamente, estamos en contra de la compra compulsiva de animales, que deriva en un mantenimiento inadecuado con un espacio insuficiente en el acuario. Nuestras recomendaciones volumen mínimo 1000 litros Población min 1 Temperatura 18 - 28 °C pH (acidez) 8.2 - 8.4 Características Dificultad cría moderada robustez robusto  poco agresivo Disponibilidad rare Consejos generales  Se recomienda encarecidamente leer la ficha dedicada completa así como informarse del mantenimiento del animal previamente, con el fin de evitar cualquier potencial conflicto, incluso la muerte del ejemplar (o de los demás habitantes del acuario). Es importante no sobrecargar su acuario, limitando así un posible caso de contaminación del agua. El mantenimiento resultará, además, más sencillo.  en agua de mar La preparación de un acuario de agua de mar requiere ciertos conocimientos previos. El agua de mar es generalmente sintética, constituida por agua de ósmosis inversa y sal sintética a un nivel de 33 g/litro. También es posible utilizar directamente agua de mar (asegurándose siempre de que el agua no esté contaminada). La puesta en marcha de un acuario de agua de mar se realizará en tres fases: la instalación de una decoración de piedra viva, la introducción de invertebrados un mes después y la introducción de peces 3 meses después. Es fundamental esperar el mayor tiempo posible antes de introducir a los animales, dejando así que la microfauna cuente con el tiempo suficiente para desarrollarse de manera correcta. El equilibrio y la estabilidad físico-química son fundamentales para lograr el éxito en este tipo de acuarios. Recordatorio general sobre datos de mantenimiento Configuración de su acuario Le démarrage d'un aquarium est une partie primordiale pour l'équilibre et le bien-être des poissons. Lorsque l'on met en eau un aquarium, l'eau passe naturellement par un cycle biologique : le cycle de l'azote. Celui-ci dure environ trois semaines. Tous les 2 jours, nous vous conseillons de tester votre eau jusqu'à ce que le taux de nitrite soit à zéro pendant plusieurs jours d'affilée. Pour accélérer ce cycle, vous pouvez utiliser un activateur de bactéries comme JBL Denitrol. Cette solution riche en bactéries vivantes et enzymes permet une mise en place rapide du cycle de l'azote. Les poissons peuvent alors être introduits plus rapidement. Pruebas de los parámetros del agua Il est important de tester l'eau de son aquarium régulièrement pour maintenir un environnement sain pour les poissons et les autres habitants. Les tests d'eau permettent de mesurer les niveaux de différents paramètres tels que le pH, la dureté totale, ainsi que les taux de nitrates, de nitrites et d'ammoniaque. Pour réaliser ces tests, vous pouvez utiliser des produits d'analyse spécialisés tels que JBL ProScan qui permet de réaliser un diagnostic de l'eau directement via un smartphone. Il existe également des coffrets de tests plus classiques de bandelettes, comme JBL PROAQUATEST. Cambios de agua En cas d’usage de l’eau du robinet, vous pouvez utiliser un conditionneur d’eau de type Biotopol de JBL pour éliminer les substances nocives comme le chlore, le cuivre, le plomb et le zinc. Les conditionneurs d'eau garantissent une meilleure santé aux poissons et une meilleure croissance des plantes. Precauciones a tener en cuenta con el cloro El cloro y la cloramina resultan peligrosos para la salud de los animales. Usados ​​para desinfectar el agua, estos agentes están presentes en cantidades significativas en el agua del grifo. Recomendamos utilizar anticloro en cada cambio de agua. Además del cloro, los tratamientos y medicamentos vendidos para el comercio de acuarios contienen, a veces, metales pesados que pueden resultar ​​peligrosos en altas dosis. Información específica para el tapaculo El tapaculo es una especie marina que habita de forma natural a una temperatura comprendida entre 18 °C y 28 °C. Para un buen mantenimiento, la temperatura no debe superar nunca los 31°C durante largos periodos. El contenido en nitrato debe permanecer por debajo de 50mg/L. Para mantener el agua limpia y sin contaminantes, te recomendamos planificar una renovación mensual del 20% al 30% del volumen de agua. En agua de mar, es también posible eliminar el contenido en nitrato mediante uno de los siguientes métodos: Jaubert, desnitrificante de azufre, biopeletts o el método vodka. Dificultad de mantenimiento La cría de esta especie es accesible siempre que exista una documentación previa sobre sus necesidades en acuario. Los eventuales cohabitantes del acuario deberán elegirse con cuidado para evitar posibles casos de depredación. Especie poco común Esta especie es poco habitual en el mercado acuariófilo. Sobretodo, suele ser mantenida por expertos que se dedican a criar y reproducir ejemplares derivados de algunas cepas de origen salvaje. Si deseas conseguir esta especie, te aconsejamos acercarte a clubs especializados. Los especímenes provenientes de la selección son algo más fáciles de criar aunque será siempre necesario respetar los parámetros específicos del agua. Incompatibilidades formales Atención, el tapaculo es incompatible con crustáceos. Convivencia y Medio Ambiente En el contexto de un acuario comunitario, esta especie debe mantenerse en un volumen mínimo de 1000 litros. El tapaculo puede mostrar signos de agresividad. De manera general, esta especie no debe mezclarse con especies territoriales de gran tamaño o otras demasiado agresivas con el fin de evitar un posible estrés e incluso alguna lesión indeseada. Sin embargo, puede convivir junto a otras especies de temperamento pacífico y con algunos vecinos ligeramente territoriales siempre que el volumen del acuario lo permita. Es importante evitar que dos especies territoriales compartan una misma zona de vida en un acuario de volumen insuficiente. Consejos de alimentación El tapaculo es un animal omnívoro con tendencia carnívora. Se recomienda no sobrealimentar a los animales evitando así contaminar el agua. Para la mayoría de las especies, es conveniente administrar varias porciones menores cada día en lugar de una única comida copiosa. Protocolo de reproducción Protección de la puesta No Hibridación En general, no se recomienda mezclar varias especies del mismo género, o diferentes variedades de la misma especie, con el fin de evitar una posible hibridación. Estas plantas podrían interesarte Las plantas desempeñan un papel esencial en la acuariofilia, tanto por su capacidad de filtrar el agua absorbiendo los nutrientes en exceso como por su valor estético. Proporcionan refugios naturales a los peces, pueden servir como lugar de reproducción y contribuyen, en general, al equilibrio y a las buenas condiciones de mantenimiento del acuario. La selección presentada aquí reúne especies procedentes de las mismas regiones que la especie descrita en esta ficha, aunque no necesariamente de su biotopo exacto de origen. posidonia Posidoniaceae Ejemplos de acuarios que contienen esta especie Para saber más Para leer en la web Fuentes y realización Participación y validación El equipo de Fishipedia y sus colaboradores especializados se comprometen a proporcionar contenido de alta calidad. Sin embargo, aunque la información proviene de fuentes científicas o testimonios de especialistas, los archivos pueden contener imprecisiones. Benoit Chartrer Traducción Traducción realizada con la valiosa contribución de nuestros traductores, quienes hacen que esta información esté disponible para un público más amplio. Interactúa con Fishipedia Para ponerse en contacto con nuestro equipo o participar en nuestro proyecto. Contribuya a esta página Plantilla y contenido © Fishipedia - Reproducción no autorizada sin solicitud previa - ISSN 2270-7247 - Última actualización el 12/11/2023 © Fishipedia.fr 2024",
    "genderDescription": "Bothidae",
    "type": "",
    "size": "15 cm",
    "maxSize": "45 cm",
    "mimetism": "Tipo pez plano Tamaño medio 15 cm Tamaño máximo 45 cm Mimetismo fondo arenoso Patrón puntuación Bothus podas, tapaculo © Thomas Menut Tipo pez plano Tamaño medio 15 cm Tamaño máximo 45 cm Mimetismo fondo arenoso Patrón puntuación",
    "recognize": "",
    "fe/maleDifferences": "El macho adulto es de mayor tamaño que la hembra. El ancho interorbital también es mayor en este último.",
    "diet": "omnívoro con tendencia carnívora",
    "territorial": "Sí",
    "social": "solitario",
    "lifeMode": "dieta",
    "lifeDescription": "",
    "reproductionMode": "<  tapaculo  Bothus podas  Delaroche  1809  (Mundo) LC  Bothidae  Bothus",
    "migration": "Tipo pez plano Tamaño medio 15 cm Tamaño máximo 45 cm Mimetismo fondo arenoso Patrón puntuación Bothus podas, tapaculo © Thomas Menut Tipo pez plano Tamaño medio 15 cm Tamaño máximo 45 cm Mimetismo fondo arenoso Patrón puntuación",
    "reproductionDescription": "",
    "poison": "",
    "danger": "",
    "depth": "Enciclopedia Explorar Acuariofilia A propósito Prensa Peces Ballestas Barracudas Doradas y sargos Escorpenas Hipocampos Lábridos Morenas Peces cirujano Peces globo Peces payaso Rayas Tiburones Reptiles Cocodrilos Serpientes Tortugas Moluscos Caracoles Nudibranquios Calamares Pulpos Sepias Otros temas Anfibios Cnidarios Crustáceos Amazonas Anaconda gigante Anguila eléctrica Paiche Piraña roja Raya motoro / Raya de rio Tararira Mediterráneo Atún rojo Congrio Dorada real Manta raya Mero Sargo Islas Canarias Ángel de mar Caballito de mar Pez roca de Madeira Pez trompeta atlántico Tiburón Mako Vieja colorada Mar del Caribe Cirujano azul Gran barracuda / Picúa Pez ángel francés pez ángel reina Raya jaspeada Robalo blanco Mar Rojo Mero del Coral Morena gigante Pez león Pez Napoléon Raya de arrecife Vieja florida Especies comunes Betta Splendens Chupa algas Corydoras Discos Escalar Gamba Red Cherry Guppy Pez dorado Pez payaso Grupos temáticos Cíclidos enanos Killis Lochas Luchadores Peces gato Tetras Vivíparos Práctica Peces compatibles 20 L Peces compatibles 40 L Peces compatibles 60 L Peces compatibles 80 L Peces compatibles 100 L El proyecto Fishipedia Nuestra ética Proyecto Yaku Nawi Los fotógrafos colaboradores CONTÁCTANOS Enciclopedia Peces Ballestas Barracudas Doradas y sargos Escorpenas Hipocampos Lábridos Morenas Peces cirujano Peces globo Peces payaso Rayas Tiburones Reptiles Cocodrilos Serpientes Tortugas Moluscos Caracoles Nudibranquios Calamares Pulpos Sepias Otros temas Anfibios Cnidarios Crustáceos Explorar Amazonas Anaconda gigante Anguila eléctrica Paiche Piraña roja Raya motoro / Raya de rio Tararira Mediterráneo Atún rojo Congrio Dorada real Manta raya Mero Sargo Islas Canarias Ángel de mar Caballito de mar Pez roca de Madeira Pez trompeta atlántico Tiburón Mako Vieja colorada Mar del Caribe Cirujano azul Gran barracuda / Picúa Pez ángel francés pez ángel reina Raya jaspeada Robalo blanco Mar Rojo Mero del Coral Morena gigante Pez león Pez Napoléon Raya de arrecife Vieja florida Acuariofilia Especies comunes Betta Splendens Chupa algas Corydoras Discos Escalar Gamba Red Cherry Guppy Pez dorado Pez payaso Grupos temáticos Cíclidos enanos Killis Lochas Luchadores Peces gato Tetras Vivíparos Práctica Peces compatibles 20 L Peces compatibles 40 L Peces compatibles 60 L Peces compatibles 80 L Peces compatibles 100 L A propósito El proyecto Fishipedia Nuestra ética Proyecto Yaku Nawi Los fotógrafos colaboradores CONTÁCTANOS Prensa",
    "image": "",
    "mapImage": ""
  },
  {
    "name": "Canthigaster capistrata",
    "sciname": "",
    "IUCN": "",
    "description": "Introducción Canthigaster capistrata es un pez de agua salada nativo del océano Atlántico templado, del este de las Azores a Cabo Verde. ¿Quién es ella?  Canthigaster Canthigaster es un género de pequeños peces marinos de la familia Tetraodontidae. El género agrupa a poco menos de 40 especies distribuidas en las áreas tropicales y subtropicales de los océanos Pacífico, Atlántico e Índico. Los peces de este género frecuentan áreas poco profundas de los arrecifes de coral. Estos peces se caracterizan por poseer un cuerpo comprimido, un hocico alargado y puntiagudo y la ausencia de aletas pélvicas. La boca es pequeña y está provista de dientes similares a los de los Tétraodon, encontrándose fusionados en dos dientes en cada mandíbula, formando una especie de pico. Gracias a la particular forma de su boca, el Canthigaster puede picotear fácilmente algas y otros organismos bénticos. Al igual que Tetraodon, los peces del género Canthigaster poseen tetrodotoxina. Son tóxicos cuando se comen. En las especies estudiadas, existe un ligero dimorfismo sexual, siendo los machos más grandes que las hembras. Durante la época de reproducción, los machos defienden un territorio habitado por varias hembras. Estas últimas construyen un nido de algas directamente en el sustrato, en el cual depositan sus huevos. Una vez realizada la fecundación, los padres abandonan el nido y no realizan ningún cuidado específico. Algunas especies como C. valentini y C. solendri son comunes en el mercado dedicado al mundo de los peces. En 2022, su población no se encuentra amenazada en su medio natural.  Tipo pez globo Tamaño medio 9 cm Tamaño máximo 11 cm Canthigaster capistrata, gallinita Tipo pez globo Tamaño medio 9 cm Tamaño máximo 11 cm ¿Cómo reconocer a Este pez ? Pez globo Esta especie pertenece al grupo de los peces globo. Estos peces se apodan así ya que tienen la capacidad de inflarse cuando se sienten amenazados. Para lograr esta hinchazón, tragan agua, llenando sus estómagos hasta alcanzar más del doble de su tamaño. Esto resulta posible gracias a la elasticidad de su piel. Este hecho los hace parecer mucho más impresionantes a los ojos de sus depredadores. Resultando además mucho más complicados de tragar. Sin embargo, este cambio en su forma se convierte también en una desventaja ya que, una vez inflados, apenas pueden desplazarse. Canthigaster capistrata presenta una coloración multicolor con un cuerpo predominantemente blanco y beige. La forma es característica del Canthigaster, con un cuerpo de forma elíptica, aerodinámico, en el que el vientre es más ligero que la espalda. Este aparece atravesado por una banda horizontal de color oscuro que va desde la zona situada debajo de la boca hasta la parte posterior de la aleta anal. Una banda longitudinal negra atraviesa el cuerpo desde detrás del ojo hasta el final de la parte superior de la aleta caudal. Los ojos son de un característico color amarillo, y la aleta caudal aparece bordeada de un margen negro en la parte superior e inferior. El cuerpo está cubierto de pequeñas manchas azules dispuestas al azar. Las aletas pélvicas están ausentes, mientras las aletas anal y dorsal se sitúan en la parte trasera del cuerpo. La aleta caudal sirve como timón y rara vez la utiliza para nadar. Esto se hace a través de las aletas pectorales dorsal y anal. Las aletas son translúcidas. Diferencias entre machos y hembras No existe dimorfismo aparente en esta especie. Modo de vida y comportamiento dieta carnívoro Sociabilidad solitario territorial Sí Modo de vida Diurno Canthigaster capistrata es un pez de carácter solitario que reside en la naturaleza a media profundidad y cerca del fondo. Diurno, se desplaza escudriñando las piedras y algas en busca de pequeños crustáceos. En ocasiones, pùeden observarse algunos grupos dispersos formados por varios individuos. Los machos de esta especie son territoriales y no aceptan la presencia de rivales. Reproducción Modo de reproducción ovíparo que desova en sustrato descubierto Poligamia Sí Canthigaster capistrata es un pez ovíparo. Aunque, a día de hoy, aún se desconoce su método de reproducción, se piensa que probablemente sea similar al de otros peces del mismo género. La hembra construiría un nido en el que pondría sus huevos, para ser después fertilizados por el macho, inmediatamente después de la puesta. La hembra defendería los huevos hasta su eclosión. Especies inofensivas Esta especie no supone ningún peligro particular para los humanos en caso de encuentro en su medio natural. Sin embargo, como todos sucede con todos los Tétraodon , contiene una neurotoxina llamada tetrodotoxina que puede llegar a ser mortal si se ingiere. Origen y distribución Origen Océano Atlántico templado oriental Islas Islas Canarias Presencia geográfica y estado de la población Las poblaciones salvajes de esta especie no parecen estar amenazadas. Estado de conservación de las poblaciones (UICN) Mundo : LC ¿Cuál es su hábitat? Características del entorno natural Temperatura 19 - 24 °C Profundidad 0 - 20 m Presentación del biotopo Canthigaster capistrata se encuentra con mayor frecuencia a menos de 20 metros de profundidad, cercano al fondo, entre rocas y algas. Especie del mismo biotopo raya látigo común Dasyatidae rape negro Lophiidae raya boca de rosa Rajidae lenguado Soleidae tiburón sedoso Carcharhinidae murión Muraenidae Previous Next Para saber más Especie de la misma familia Sphoeroides marmoratus Tetraodontidae Carinotetraodon irrubesco Tetraodontidae pez globo moteado Tetraodontidae pez globo enmascarado Tetraodontidae Tetraodon lineatus Tetraodontidae pez globo reticulado Tetraodontidae pez globo mapa Tetraodontidae pez globo estrellado Tetraodontidae Previous Next Para leer en la web Fuentes y realización Participación y validación El equipo de Fishipedia y sus colaboradores especializados se comprometen a proporcionar contenido de alta calidad. Sin embargo, aunque la información proviene de fuentes científicas o testimonios de especialistas, los archivos pueden contener imprecisiones. Adrien Falzon Traducción Traducción realizada con la valiosa contribución de nuestros traductores, quienes hacen que esta información esté disponible para un público más amplio. Interactúa con Fishipedia Para ponerse en contacto con nuestro equipo o participar en nuestro proyecto. Contribuya a esta página Plantilla y contenido © Fishipedia - Reproducción no autorizada sin solicitud previa - ISSN 2270-7247 - Última actualización el 11/11/2023 © Fishipedia.fr 2024",
    "genderDescription": "Tetraodontidae",
    "type": "",
    "size": "9 cm",
    "maxSize": "11 cm",
    "mimetism": "",
    "recognize": "",
    "fe/maleDifferences": "No existe dimorfismo aparente en esta especie.",
    "diet": "carnívoro",
    "territorial": "Sí",
    "social": "solitario",
    "lifeMode": "dieta",
    "lifeDescription": "",
    "reproductionMode": "<  gallinita  Canthigaster capistrata  Lowe  1839  (Mundo) LC  Tetraodontidae  Canthigaster",
    "migration": "",
    "reproductionDescription": "",
    "poison": "",
    "danger": "",
    "depth": "Enciclopedia Explorar Acuariofilia A propósito Prensa Peces Ballestas Barracudas Doradas y sargos Escorpenas Hipocampos Lábridos Morenas Peces cirujano Peces globo Peces payaso Rayas Tiburones Reptiles Cocodrilos Serpientes Tortugas Moluscos Caracoles Nudibranquios Calamares Pulpos Sepias Otros temas Anfibios Cnidarios Crustáceos Amazonas Anaconda gigante Anguila eléctrica Paiche Piraña roja Raya motoro / Raya de rio Tararira Mediterráneo Atún rojo Congrio Dorada real Manta raya Mero Sargo Islas Canarias Ángel de mar Caballito de mar Pez roca de Madeira Pez trompeta atlántico Tiburón Mako Vieja colorada Mar del Caribe Cirujano azul Gran barracuda / Picúa Pez ángel francés pez ángel reina Raya jaspeada Robalo blanco Mar Rojo Mero del Coral Morena gigante Pez león Pez Napoléon Raya de arrecife Vieja florida Especies comunes Betta Splendens Chupa algas Corydoras Discos Escalar Gamba Red Cherry Guppy Pez dorado Pez payaso Grupos temáticos Cíclidos enanos Killis Lochas Luchadores Peces gato Tetras Vivíparos Práctica Peces compatibles 20 L Peces compatibles 40 L Peces compatibles 60 L Peces compatibles 80 L Peces compatibles 100 L El proyecto Fishipedia Nuestra ética Proyecto Yaku Nawi Los fotógrafos colaboradores CONTÁCTANOS Enciclopedia Peces Ballestas Barracudas Doradas y sargos Escorpenas Hipocampos Lábridos Morenas Peces cirujano Peces globo Peces payaso Rayas Tiburones Reptiles Cocodrilos Serpientes Tortugas Moluscos Caracoles Nudibranquios Calamares Pulpos Sepias Otros temas Anfibios Cnidarios Crustáceos Explorar Amazonas Anaconda gigante Anguila eléctrica Paiche Piraña roja Raya motoro / Raya de rio Tararira Mediterráneo Atún rojo Congrio Dorada real Manta raya Mero Sargo Islas Canarias Ángel de mar Caballito de mar Pez roca de Madeira Pez trompeta atlántico Tiburón Mako Vieja colorada Mar del Caribe Cirujano azul Gran barracuda / Picúa Pez ángel francés pez ángel reina Raya jaspeada Robalo blanco Mar Rojo Mero del Coral Morena gigante Pez león Pez Napoléon Raya de arrecife Vieja florida Acuariofilia Especies comunes Betta Splendens Chupa algas Corydoras Discos Escalar Gamba Red Cherry Guppy Pez dorado Pez payaso Grupos temáticos Cíclidos enanos Killis Lochas Luchadores Peces gato Tetras Vivíparos Práctica Peces compatibles 20 L Peces compatibles 40 L Peces compatibles 60 L Peces compatibles 80 L Peces compatibles 100 L A propósito El proyecto Fishipedia Nuestra ética Proyecto Yaku Nawi Los fotógrafos colaboradores CONTÁCTANOS Prensa",
    "image": "",
    "mapImage": ""
  },
  {
    "name": "Capros aper",
    "sciname": "",
    "IUCN": "",
    "description": "Introducción Capros aper, conocido como pez jabalí, es un pez marino originario de la parte este del océano Atlántico y del mar Mediterráneo. Esta especie bentónica habita en zonas rocosas y corallígenas a profundidades intermedias, generalmente entre 30 y 700 metros de profundidad.  de realización. Los textos propuestos actualmente provienen de nuestro modelo de datos o están en proceso de redacción. Para solicitar prioridad para este contenido, puedes escribirnos AQUÍ. ¿Quién es él?  Tamaño medio 13 cm Tamaño máximo 25 cm Longevidad 26 años Patrón líneas verticales Capros aper, pez jabalí © Paul Moine Tamaño medio 13 cm Tamaño máximo 25 cm Longevidad 26 años Patrón líneas verticales ¿Cómo reconocer a Este pez ? El pez jabalí mide alrededor de 13 cm. Las hembras presentan un tamaño mayor, algunos ejemplares pueden llegar a alcanzar los 25 cm. Este pez presenta una coloración bicolor con un cuerpo mayoritariamente naranja y rosa. Posee también líneas verticales de color naranja. Diferencias entre machos y hembras La hembra presenta un tamaño mayor que el macho. Modo de vida y comportamiento dieta carnívoro Sociabilidad bancos territorial No Modo de vida Diurno El pez jabalí es un pez que vive en bancos próximo al fondo. Es un animal carnívoro de temperamento más bien tranquilo. De manera general, esta especie no suele prestar demasiada atención al resto de especies que se cruzan en su camino. Reproducción Modo de reproducción ovíparo que desova en aguas abiertas El pez jabalí es un pez ovíparo que desova en aguas abiertas. Especies inofensivas Esta especie no supone ningún peligro en particular para el ser humano cuando se encuentra en su entorno natural. Origen y distribución Origen Mar del Norte Mar Mediterráneo Océano Atlántico templado oriental Océano Atlántico Oriental Frío Islas Córcega Islas Canarias Cerdeña Sicilia Estado de conservación de las poblaciones (UICN) Mundo : LC ¿Dónde observar esta especie? ¿Cuál es su hábitat? Características del entorno natural Temperatura 7 - 15 °C Profundidad 30 - 700 m Presentación del biotopo Frecuentemente encontramos a el pez jabalí a una profundidad de entre 30m y 700m. Sin embargo, no resulta del todo imposible observar a esta especie a otras profundidades. Especie del mismo biotopo pez ángel Squatinidae dorada Sparidae chopa Sparidae raya toro Myliobatidae rocoso de la costa Gadidae salvariego Trachinidae Previous Next Para saber más Para leer en la web Fuentes y realización Participación y validación El equipo de Fishipedia y sus colaboradores especializados se comprometen a proporcionar contenido de alta calidad. Sin embargo, aunque la información proviene de fuentes científicas o testimonios de especialistas, los archivos pueden contener imprecisiones. Benoit Chartrer Traducción Traducción realizada con la valiosa contribución de nuestros traductores, quienes hacen que esta información esté disponible para un público más amplio. Silvia Gomez Interactúa con Fishipedia Para ponerse en contacto con nuestro equipo o participar en nuestro proyecto. Contribuya a esta página Plantilla y contenido © Fishipedia - Reproducción no autorizada sin solicitud previa - ISSN 2270-7247 - Última actualización el 21/11/2023 © Fishipedia.fr 2024",
    "genderDescription": "Caproidae",
    "type": "",
    "size": "13 cm",
    "maxSize": "25 cm",
    "mimetism": "",
    "recognize": "",
    "fe/maleDifferences": "La hembra presenta un tamaño mayor que el macho.",
    "diet": "carnívoro",
    "territorial": "No",
    "social": "bancos",
    "lifeMode": "dieta",
    "lifeDescription": "",
    "reproductionMode": "<  pez jabalí  Capros aper  Linné  1758  (Mundo) LC  Caproidae  Capros",
    "migration": "",
    "reproductionDescription": "",
    "poison": "",
    "danger": "de realización. Los textos propuestos actualmente provienen de nuestro modelo de datos o están en proceso de redacción. Para solicitar prioridad para este contenido, puedes escribirnos AQUÍ.",
    "depth": "",
    "image": "",
    "mapImage": ""
  },
  {
    "name": "Carcharhinus falciformis",
    "sciname": "",
    "IUCN": "",
    "description": "Introducción El tiburón sedoso, también conocido en ciertas regiones como tiburón jaquetón o tiburón piloto, se encuentra presente en todos los mares, océanos tropicales y subtropicales del planeta. Este tiburón forma parte del grupo de peces más afectados por la sobrepesca, clasificado por la IUCN como vulnerable. ¿Quién es él?  Carcharhinus El género Carcharhinus, del griego karcharos, es parte del orden Carcharhiniformes. Los Carchariformes incluyen los tipos más comunes de tiburones (englobando a más de 50 géneros) como el tiburón tigre, el tiburón martillo, el tiburón longimane o incluso el alitán. Las especies de este orden se caracterizan por la presencia de unas membranas nictitantes en el ojo, conocidas cómo \"párpados\", a diferencia de los Lamniformes que no las poseen.  Tipo tiburón Tamaño medio 200 cm Tamaño máximo 260 cm Longevidad 25 años Forma Oval Carcharhinus falciformis, tiburón sedoso © Fabrice Guérin Tipo tiburón Tamaño medio 200 cm Tamaño máximo 260 cm Longevidad 25 años Forma Oval ¿Cómo reconocer a Este pez ? Esta especie posee un cuerpo alargado y esbelto, en el que el dorso aparece coloreado en un tono gris mientras la zona del vientre es blanca. La cabeza de forma puntiaguda presenta una ancha nariz, los ojos son grandes y los dientes oblicuos tienen forma de sierra. Las aletas pectorales son largas y de forma triangular. La primera aleta dorsal es corta y se encuentra posicionada detrás de las aletas posteriores, algo característico de esta especie. Además es posible observar la presencia de una cresta inter dorsal. Su aleta caudal es heterocerca y presenta una muesca en su parte superior. Diferencias entre machos y hembras El macho posee un par de pterigopodios, órganos reproductores formados a partir de la modificación de las aletas pélvicas, que le permiten fecundar a la hembra. Modo de vida y comportamiento dieta carnívoro Sociabilidad solitario territorial No Modo de vida Diurno El tiburón sedoso es un pez de carácter solitario que forma parte de los principales depredadores de su biotopo, se alimenta de peces, moluscos y otros crustáceos. Se trata de una especie rápida, activa y de carácter agresivo. Reproducción Modo de reproducción ovíparo Especie migratoria Sí Vivíparo, puede reproducirse todos los años, sin estacionalidad. La hembra da a luz entre 2 y 15 crías que miden entre 55 y 72 cm. Riesgos para los humanos Venenoso No Mordedor Sí Este tiburón está provisto de una poderosa mandíbula y puede llegar a morder si se siente amenazado. Por ello recomendamos permanecer atento en su presencia, especialmente durante las inmersiones y las sesiones de pesca. Origen y distribución Origen Golfo de Bengala Golfo de México Golfo Pérsico Gran Barrera de Coral mar Arábigo Mar de Tasmania Mar del Caribe Mar de Filipinas Mar Rojo Mares del Sudeste Asiático Mares indonesios Océano Atlántico: costa norte de Brasil Océano Atlántico templado oriental Océano Atlántico templado cálido del noroeste Sudoeste del Océano Atlántico templado cálido Océano Atlántico tropical oriental Océano Atlántico tropical Sudoeste Océano Índico occidental Galápagos Océano Pacífico tropical oriental Océano Pacífico tropical occidental Oceanía Islas Islas Canarias Polinesia Francesa Estado de conservación de las poblaciones (UICN) Mundo : VU ¿Cuál es su hábitat? Características del entorno natural Temperatura 24 - 28 °C Profundidad 1 - 500 m  Pelágico activo Presentación del biotopo Esta especie es epipelágica, evoluciona tanto en aguas profundas como cerca de las vertientes oceánicas y de las costas. Siendo posible observarla de manera habitual entre los bancos de atunes. Especie del mismo biotopo ballesta común Balistidae tiburón blanco Lamnidae lubina Moronidae pez cirujano estriado Acanthuridae pez araña Trachinidae Sufflamen bursa Balistidae Previous Next Para saber más Especie de la misma familia tiburón limón Carcharhinidae tiburón toro Carcharhinidae tiburón tigre Carcharhinidae tiburón de arrecife de punta blanca Carcharhinidae tiburón martillo gigante Carcharhinidae tiburón martillo común Carcharhinidae tintorera Carcharhinidae Previous Next Para leer en la web Fuentes y realización Participación y validación El equipo de Fishipedia y sus colaboradores especializados se comprometen a proporcionar contenido de alta calidad. Sin embargo, aunque la información proviene de fuentes científicas o testimonios de especialistas, los archivos pueden contener imprecisiones. Adrien Falzon Benoit Chartrer Traducción Traducción realizada con la valiosa contribución de nuestros traductores, quienes hacen que esta información esté disponible para un público más amplio. Silvia Gomez Interactúa con Fishipedia Para ponerse en contacto con nuestro equipo o participar en nuestro proyecto. Contribuya a esta página Plantilla y contenido © Fishipedia - Reproducción no autorizada sin solicitud previa - ISSN 2270-7247 - Última actualización el 30/11/2023 © Fishipedia.fr 2024",
    "genderDescription": "Carcharhinidae",
    "type": "",
    "size": "200 cm",
    "maxSize": "260 cm",
    "mimetism": "",
    "recognize": "",
    "fe/maleDifferences": "El macho posee un par de pterigopodios, órganos reproductores formados a partir de la modificación de las aletas pélvicas, que le permiten fecundar a la hembra.",
    "diet": "carnívoro",
    "territorial": "No",
    "social": "solitario",
    "lifeMode": "dieta",
    "lifeDescription": "",
    "reproductionMode": "<  tiburón sedoso  Carcharhinus falciformis  Müller & Henle  1839  (Mundo) VU  Carcharhinidae  Carcharhinus",
    "migration": "",
    "reproductionDescription": "",
    "poison": "No",
    "danger": "",
    "depth": "1 - 500 m",
    "image": "",
    "mapImage": ""
  },
  {
    "name": "Carcharodon carcharias",
    "sciname": "",
    "IUCN": "",
    "description": "Introducción El famoso tiburón blanco se encuentra en las aguas costeras y oceánicas de la mayor parte de los océanos así como en los mares temperados y subtropicales del mundo. Descrito por primera vez en 1758 por Carl Linnaeus bajo el nombre Carcharodon carcharias, se volvió muy popular gracias al libro \"Tiburón\" de Peter Benchley y su adaptación al cine por Steven Spielberg. ¿Quién es él?  Carcharodon El género Carcharodon forma parte del orden de los Lamniformes (del griego lamna o lamnaes que significa \"tiburón\", seguido del término \"forma\" del latín forma). Las especies de este género no poseen párpados a diferencia de los Carcharhiniformes. El orden Lamniformes incluye las especies de tiburones más conocidas, entre las que se encuentra el gran tiburón blanco, y especies extremadamente raras como los tiburones de boca ancha.  Tipo tiburón Tamaño medio 450 cm Tamaño máximo 750 cm Longevidad 40 años Forma Rectangular Carcharodon carcharias, tiburón blanco © Fabrice Guérin Tipo tiburón Tamaño medio 450 cm Tamaño máximo 750 cm Longevidad 40 años Forma Rectangular ¿Cómo reconocer a Este pez ? En esta especie el dorso es de color gris mientras el vientre presenta un color blanco, de ahí su nombre. Los dientes son planos y de forma triangular, con forma de sierra y de una longitud en torno a los 5 cm en un ejemplar adulto. Posee una cola homocerca (la aleta es más o menos simétrica), lo que favorece su gran capacidad de propulsión. Modo de vida y comportamiento dieta carnívoro Sociabilidad solitario territorial No Modo de vida Diurno El tiburón blanco es un depredador solitario que se alimenta de peces teleósteos, de otros tiburones, rayas y mamíferos marinos. Es también un pez oportunista que suele aprovechar los cadáveres de ballenas que encuentra a la deriva en las aguas más frías. Se trata de una especie con un sentido de la vista muy desarrollado, que muestra un carácter observador y curioso frente a objetos y actividades. Reproducción Modo de reproducción ovovivíparo Especie migratoria Sí La madurez sexual de un gran tiburón blanco tiene lugar en torno a los 12-17 años en la hembra y entre los 7-9 años en el macho. La gestación es de tipo aplacental y vivípara, y dura en torno a 18 meses. Esta especie presenta oofagia (las crías se alimentan de los huevos no fecundados en el vientre de la madre). Una vez finalizado el proceso de gestación, la hembra dará a luz a una docena de crías de un tamaño que supera el metro, lo que evita el riesgo de depredación. Especies potencialmente mortales Venenoso No Mordedor Sí El tiburón blanco es un animal poderoso que puede provocar lesiones mortales en los humanos en caso de ataque. La mayor parte de estos ataques se dan a surfistas, ya que la tabla es a veces confundida con tortugas o focas. Aunque espectaculares, estos accidentes son poco habituales. Origen y distribución Origen Golfo de México Mar de Tasmania Mar de Japón Mar Mediterráneo Océano Atlántico templado oriental Océano Atlántico noroeste templado frío Océano Atlántico templado cálido del noroeste Océano Atlántico tropical oriental Océano Índico occidental Islas Islas Canarias Presencia geográfica y estado de la población La información sobre el estado de las poblaciones de tiburones y su explotación es poco precisa. Sin embargo, varios indicadores, como la disminución de las capturas, pintan un cuadro bastante sombrío, aunque las situaciones varían de una especie a otra. El tiburón blanco (Carcharodon carcharias) y el tiburón peregrino (Cetorhinus maximus) están incluidos en el Apéndice II de la CITES desde 2004 y 2003, respectivamente. Estado de conservación de las poblaciones (UICN) Mundo : VU ¿Cuál es su hábitat? Características del entorno natural Profundidad 0 - 1200 m  Pelágico activo Presentación del biotopo Esta especie de tiburón habita en aguas poco profundas, aunque está capacitado para alcanzar hasta los 1200 metros de profundidad. Suele ser observado a menudo en proximidad de las costas arenosas o rocosas. Aunque atraído por los estuarios donde acude en ocasiones a cazar, no suele frecuentar las aguas salobres y dulces, por lo que a diferencia de algunos de sus parientes, no es posible encontrarlo en los ríos costeros. Especie del mismo biotopo raya pelágica Dasyatidae tiburón mako Lamnidae chucla Sparidae aguja de mar Syngnathidae bonito del Atlántico Scombridae raya mariposa Gymnuridae Previous Next Mantenimiento en cautividad No recomendado Desaconsejamos el mantenimiento de esta especie en acuario. Debido a ciertas necesidades que si no se satisfacen correctamente podrían generar un estrés significativo que podría conducir a una disminución de la esperanza de vida, un retraso en el crecimiento o el desarrollo de patógenos. Para saber más Especie de la misma familia tiburón mako Lamnidae Para leer en la web Fuentes y realización Participación y validación El equipo de Fishipedia y sus colaboradores especializados se comprometen a proporcionar contenido de alta calidad. Sin embargo, aunque la información proviene de fuentes científicas o testimonios de especialistas, los archivos pueden contener imprecisiones. Adrien Falzon Benoit Chartrer Yuhei Nakata Silvia Gomez Traducción Traducción realizada con la valiosa contribución de nuestros traductores, quienes hacen que esta información esté disponible para un público más amplio. Silvia Gomez Interactúa con Fishipedia Para ponerse en contacto con nuestro equipo o participar en nuestro proyecto. Contribuya a esta página Plantilla y contenido © Fishipedia - Reproducción no autorizada sin solicitud previa - ISSN 2270-7247 - Última actualización el 20/11/2023 © Fishipedia.fr 2024",
    "genderDescription": "Lamnidae",
    "type": "",
    "size": "450 cm",
    "maxSize": "750 cm",
    "mimetism": "",
    "recognize": "",
    "fe/maleDifferences": "",
    "diet": "carnívoro",
    "territorial": "No",
    "social": "solitario",
    "lifeMode": "dieta",
    "lifeDescription": "",
    "reproductionMode": "<  tiburón blanco  Carcharodon carcharias  Carl von Linné  1758  (Mundo) VU  Lamnidae  Carcharodon",
    "migration": "",
    "reproductionDescription": "",
    "poison": "No",
    "danger": "",
    "depth": "Enciclopedia Explorar Acuariofilia A propósito Prensa Peces Ballestas Barracudas Doradas y sargos Escorpenas Hipocampos Lábridos Morenas Peces cirujano Peces globo Peces payaso Rayas Tiburones Reptiles Cocodrilos Serpientes Tortugas Moluscos Caracoles Nudibranquios Calamares Pulpos Sepias Otros temas Anfibios Cnidarios Crustáceos Amazonas Anaconda gigante Anguila eléctrica Paiche Piraña roja Raya motoro / Raya de rio Tararira Mediterráneo Atún rojo Congrio Dorada real Manta raya Mero Sargo Islas Canarias Ángel de mar Caballito de mar Pez roca de Madeira Pez trompeta atlántico Tiburón Mako Vieja colorada Mar del Caribe Cirujano azul Gran barracuda / Picúa Pez ángel francés pez ángel reina Raya jaspeada Robalo blanco Mar Rojo Mero del Coral Morena gigante Pez león Pez Napoléon Raya de arrecife Vieja florida Especies comunes Betta Splendens Chupa algas Corydoras Discos Escalar Gamba Red Cherry Guppy Pez dorado Pez payaso Grupos temáticos Cíclidos enanos Killis Lochas Luchadores Peces gato Tetras Vivíparos Práctica Peces compatibles 20 L Peces compatibles 40 L Peces compatibles 60 L Peces compatibles 80 L Peces compatibles 100 L El proyecto Fishipedia Nuestra ética Proyecto Yaku Nawi Los fotógrafos colaboradores CONTÁCTANOS Enciclopedia Peces Ballestas Barracudas Doradas y sargos Escorpenas Hipocampos Lábridos Morenas Peces cirujano Peces globo Peces payaso Rayas Tiburones Reptiles Cocodrilos Serpientes Tortugas Moluscos Caracoles Nudibranquios Calamares Pulpos Sepias Otros temas Anfibios Cnidarios Crustáceos Explorar Amazonas Anaconda gigante Anguila eléctrica Paiche Piraña roja Raya motoro / Raya de rio Tararira Mediterráneo Atún rojo Congrio Dorada real Manta raya Mero Sargo Islas Canarias Ángel de mar Caballito de mar Pez roca de Madeira Pez trompeta atlántico Tiburón Mako Vieja colorada Mar del Caribe Cirujano azul Gran barracuda / Picúa Pez ángel francés pez ángel reina Raya jaspeada Robalo blanco Mar Rojo Mero del Coral Morena gigante Pez león Pez Napoléon Raya de arrecife Vieja florida Acuariofilia Especies comunes Betta Splendens Chupa algas Corydoras Discos Escalar Gamba Red Cherry Guppy Pez dorado Pez payaso Grupos temáticos Cíclidos enanos Killis Lochas Luchadores Peces gato Tetras Vivíparos Práctica Peces compatibles 20 L Peces compatibles 40 L Peces compatibles 60 L Peces compatibles 80 L Peces compatibles 100 L A propósito El proyecto Fishipedia Nuestra ética Proyecto Yaku Nawi Los fotógrafos colaboradores CONTÁCTANOS Prensa",
    "image": "",
    "mapImage": ""
  },
  {
    "name": "Cetorhinus maximus",
    "sciname": "",
    "IUCN": "",
    "description": "Introducción Cetorhinus maximus, más comúnmente conocido como tiburón peregrino, es una especie marina que se encuentra en las aguas costeras y oceánicas de la mayor parte de los mares y océanos temperados. Descrito por primera vez en 1765 por Gunnerus. Debe su nombre a la forma en la que busca alimento. Se trata del segundo pez más grande después del tiburón ballena. ¿Quién es él?  Cetorhinus El género Cetorhinus forma parte del orden de los Lamniformes y fue descrito en 1816 por Blainville. El término Cetorhinus proviene del latín \"cetus\" que significa ballena, y \"rhinus\" que significa nariz, lo que hace referencia a su desarrollado sentido del olfato. Este género cuenta únicamente con una especie, el tiburón peregrino.  Tipo tiburón Tamaño medio 1000 cm Tamaño máximo 1200 cm Longevidad 50 años Forma Rectangular Cetorhinus maximus, tiburón peregrino © Fabrice Guérin Tipo tiburón Tamaño medio 1000 cm Tamaño máximo 1200 cm Longevidad 50 años Forma Rectangular ¿Cómo reconocer a Este pez ? El tiburón peregrino presenta un cuerpo unicolor, este puede variar desde un tono negruzco hasta un marrón grisáceo. Este tiburón posee unas mandíbulas especiales que le permiten abrir ampliamente su boca para alimentarse. Es fácilmente identificable gracias a su gran tamaño y sus amplias branquias. Su cola tiene una forma que recuerda a un croissant. Modo de vida y comportamiento dieta carnívoro Sociabilidad grupos o en solitario territorial No Modo de vida Diurno El tiburón peregrino habita a profundidad media e incluso cercano al fondo. Se alimenta cercano a la superficie, esencialmente de zooplancton y algunos pequeños peces gregarios. De temperamento tranquilo, resulta totalmente inofensivo para el hombre. Reproducción Modo de reproducción ovovivíparo Especie migratoria Sí Esta especie alcanza su madurez sexual en torno a los 16-20 años en el caso de las hembras y entre los 12-16 años en los machos. Vivíparo, la gestación es de tipo aplacental con una duración que puede ir desde los 2,5 a los 3,5 años. Tratándose del período de gestación más extenso en los vertebrados. Posteriormente, la hembra da a luz a media docena de crías, cada una con un tamaño que supera el metro. Especies inofensivas Esta especie no representa un peligro particular para los humanos en caso de encuentro en su entorno natural. Origen y distribución Origen Golfo de Alaska Mar de Ojotsk Mar Mediterráneo Océano Atlántico templado oriental Océano Atlántico Oriental Frío Océano Atlántico noroeste templado frío Océano Atlántico templado cálido del noroeste Islas Islas Canarias Presencia geográfica y estado de la población La información sobre el estado de las poblaciones de tiburones y su explotación es poco precisa. Sin embargo, existen ciertos indicadores como la disminución de las capturas y de los rendimientos, que ofrecen un panorama bastante sombrío (bien es cierto que el estado variará de una especie a otra). El gran tiburón blanco (Carcharodon carcharias) y el tiburón peregrino (Cetorhinus maximus) están incluidos en el Apéndice II de la CITES desde 2004 y 2003 respectivamente. Estado de conservación de las poblaciones (UICN) Mundo : EN Francia : VU ¿Cuál es su hábitat? Características del entorno natural Profundidad 0 - 2000 m  Pelágico activo Presentación del biotopo El tiburón peregrino se encuentra generalmente en las zonas ricas en zooplancton. Tratándose de zonas con fuertes mareas, en los alrededores de islas y en bahías. También es posible observarlo en zonas que superan los 1000 metros de profundidad. Especie del mismo biotopo tiburón sedoso Carcharhinidae pez piloto Carangidae pez limón Carangidae pez luna Molidae tintorera Carcharhinidae raya pelágica Dasyatidae Previous Next Mantenimiento en cautividad No recomendado Desaconsejamos el mantenimiento de esta especie en acuario. Debido a ciertas necesidades que si no se satisfacen correctamente podrían generar un estrés significativo que podría conducir a una disminución de la esperanza de vida, un retraso en el crecimiento o el desarrollo de patógenos. Para saber más Para leer en la web Fuentes y realización Participación y validación El equipo de Fishipedia y sus colaboradores especializados se comprometen a proporcionar contenido de alta calidad. Sin embargo, aunque la información proviene de fuentes científicas o testimonios de especialistas, los archivos pueden contener imprecisiones. Yuhei Nakata Benoit Chartrer Silvia Gomez Traducción Traducción realizada con la valiosa contribución de nuestros traductores, quienes hacen que esta información esté disponible para un público más amplio. Silvia Gomez Interactúa con Fishipedia Para ponerse en contacto con nuestro equipo o participar en nuestro proyecto. Contribuya a esta página Plantilla y contenido © Fishipedia - Reproducción no autorizada sin solicitud previa - ISSN 2270-7247 - Última actualización el 12/11/2023 © Fishipedia.fr 2024",
    "genderDescription": "Cetorhinidae",
    "type": "",
    "size": "1000 cm",
    "maxSize": "1200 cm",
    "mimetism": "",
    "recognize": "",
    "fe/maleDifferences": "",
    "diet": "carnívoro",
    "territorial": "No",
    "social": "grupos o en solitario",
    "lifeMode": "dieta",
    "lifeDescription": "",
    "reproductionMode": "<  tiburón peregrino  Cetorhinus maximus  Johan Ernst Gunnerus  1765  (Mundo) EN  Cetorhinidae  Cetorhinus",
    "migration": "",
    "reproductionDescription": "",
    "poison": "",
    "danger": "",
    "depth": "Enciclopedia Explorar Acuariofilia A propósito Prensa Peces Ballestas Barracudas Doradas y sargos Escorpenas Hipocampos Lábridos Morenas Peces cirujano Peces globo Peces payaso Rayas Tiburones Reptiles Cocodrilos Serpientes Tortugas Moluscos Caracoles Nudibranquios Calamares Pulpos Sepias Otros temas Anfibios Cnidarios Crustáceos Amazonas Anaconda gigante Anguila eléctrica Paiche Piraña roja Raya motoro / Raya de rio Tararira Mediterráneo Atún rojo Congrio Dorada real Manta raya Mero Sargo Islas Canarias Ángel de mar Caballito de mar Pez roca de Madeira Pez trompeta atlántico Tiburón Mako Vieja colorada Mar del Caribe Cirujano azul Gran barracuda / Picúa Pez ángel francés pez ángel reina Raya jaspeada Robalo blanco Mar Rojo Mero del Coral Morena gigante Pez león Pez Napoléon Raya de arrecife Vieja florida Especies comunes Betta Splendens Chupa algas Corydoras Discos Escalar Gamba Red Cherry Guppy Pez dorado Pez payaso Grupos temáticos Cíclidos enanos Killis Lochas Luchadores Peces gato Tetras Vivíparos Práctica Peces compatibles 20 L Peces compatibles 40 L Peces compatibles 60 L Peces compatibles 80 L Peces compatibles 100 L El proyecto Fishipedia Nuestra ética Proyecto Yaku Nawi Los fotógrafos colaboradores CONTÁCTANOS Enciclopedia Peces Ballestas Barracudas Doradas y sargos Escorpenas Hipocampos Lábridos Morenas Peces cirujano Peces globo Peces payaso Rayas Tiburones Reptiles Cocodrilos Serpientes Tortugas Moluscos Caracoles Nudibranquios Calamares Pulpos Sepias Otros temas Anfibios Cnidarios Crustáceos Explorar Amazonas Anaconda gigante Anguila eléctrica Paiche Piraña roja Raya motoro / Raya de rio Tararira Mediterráneo Atún rojo Congrio Dorada real Manta raya Mero Sargo Islas Canarias Ángel de mar Caballito de mar Pez roca de Madeira Pez trompeta atlántico Tiburón Mako Vieja colorada Mar del Caribe Cirujano azul Gran barracuda / Picúa Pez ángel francés pez ángel reina Raya jaspeada Robalo blanco Mar Rojo Mero del Coral Morena gigante Pez león Pez Napoléon Raya de arrecife Vieja florida Acuariofilia Especies comunes Betta Splendens Chupa algas Corydoras Discos Escalar Gamba Red Cherry Guppy Pez dorado Pez payaso Grupos temáticos Cíclidos enanos Killis Lochas Luchadores Peces gato Tetras Vivíparos Práctica Peces compatibles 20 L Peces compatibles 40 L Peces compatibles 60 L Peces compatibles 80 L Peces compatibles 100 L A propósito El proyecto Fishipedia Nuestra ética Proyecto Yaku Nawi Los fotógrafos colaboradores CONTÁCTANOS Prensa",
    "image": "",
    "mapImage": ""
  },
  {
    "name": "Chromis limbata",
    "sciname": "",
    "IUCN": "",
    "description": "Introducción Chromis limbata, más comúnmente denominada fula blanca, es un pez que habita en agua de mar, originario de Océano Atlántico templado oriental.  de realización. Los textos propuestos actualmente provienen de nuestro modelo de datos o están en proceso de redacción. Para solicitar prioridad para este contenido, puedes escribirnos AQUÍ. ¿Quién es ella?  Chromis El género Chromis pertenece a la familia Pomacentridae, y agrupa a algo menos de un centenar de especies distribuidas en la mayoría de los mares y océanos. A este género de peces se les conoce de manera común como damiselas. Gregarias, las especies del género se encuentran con mayor frecuencia formando grandes cardúmenes sobre montículos rocosos o arrecifes de coral. Al menor peligro, se sumergerán inmediatamente con el fin de esconderse. Algunas especies pueden ser hermafroditas. Los adultos protegen los huevos de los depredadores, generalmente hasta que nacen. Los peces del género son presa frecuente de los pescadores, con la intención de venderlos en el mercado destinado a la acuariofilia. Sin embargo, el impacto vinculado a esta pesca sigue siendo insignificante debido a la alta densidad de población. Numerosas especies costeras tropicales son muy resistentes a las variaciones en los parámetros fisicoquímicos y es probable que, en caso de desplazamiento de la población, lleguen a colonizar nuevos nichos ecológicos. Este es el caso, por ejemplo, de Chromis limbata originaria del Atlántico occidental que actualmente coloniza las costas de Brasil.  Tipo Damisela Tamaño medio 9 cm Tamaño máximo 12 cm Chromis limbata, fula blanca Tipo Damisela Tamaño medio 9 cm Tamaño máximo 12 cm ¿Cómo reconocer a Este pez ? La fula blanca mide alrededor de 9 cm. Los machos dominantes pueden, sin embargo, llegar a alcanzar los 12 cm. La fula blanca mide alrededor de 9 cm. Las hembras presentan un tamaño mayor, algunos ejemplares pueden llegar a alcanzar los 12 cm. Este pez presenta una coloración multicolor con un cuerpo mayoritariamente amarillo, azul, negro, morado y gris. Diferencias entre machos y hembras La hembra presenta un tamaño mayor que el macho. El macho adulto presenta un mayor tamaño que la hembra. Modo de vida y comportamiento dieta omnívoro con tendencia carnívora Sociabilidad bancos territorial Sí Modo de vida Diurno La fula blanca es un pez que vive en bancos próximo al fondo. Es un animal omnívoro con tendencia carnívora de temperamento . Reproducción Modo de reproducción ovíparo que desova en sustrato oculto Hermafrodita protógino La fula blanca es un pez ovíparo que desova en sustrato oculto. nace siempre siendo hembra. A medida que crecen, los ejemplares cambiarán de sexo para convertirse en machos, esto se conoce con el nombre de hermafroditismo sucesivo de tipo protógino. Este pez protege sus huevos de los depredadores circundantes. Especies inofensivas Esta especie no supone ningún peligro en particular para el ser humano cuando se encuentra en su entorno natural. Origen y distribución Origen Océano Atlántico templado oriental Islas Islas Canarias Estado de conservación de las poblaciones (UICN) Mundo : LC ¿Cuál es su hábitat? Características del entorno natural Temperatura 15 - 26 °C Profundidad 5 - 45 m Presentación del biotopo Frecuentemente encontramos a la fula blanca a una profundidad de entre 5m y 45m. Sin embargo, no resulta del todo imposible observar a esta especie a otras profundidades. Especie del mismo biotopo moma Blenniidae gallinita Tetraodontidae pez luna Molidae rascacio negro Scorpaenidae escórpora Scorpaenidae boga Sparidae Previous Next Para saber más Especie de la misma familia pez payaso de Mauricio Pomacentridae pez payaso común Pomacentridae Chrysiptera cyanea Pomacentridae Amphiprion allardi Pomacentridae Chrysiptera glauca Pomacentridae Dischistodus perspicillatus Pomacentridae sargento mayor del Pacífico Pomacentridae pez payaso ensillado Pomacentridae Previous Next Para leer en la web Fuentes y realización Participación y validación El equipo de Fishipedia y sus colaboradores especializados se comprometen a proporcionar contenido de alta calidad. Sin embargo, aunque la información proviene de fuentes científicas o testimonios de especialistas, los archivos pueden contener imprecisiones. Adrien Falzon Traducción Traducción realizada con la valiosa contribución de nuestros traductores, quienes hacen que esta información esté disponible para un público más amplio. Referencias bibliográficas The recent colonization of south Brazil by the Azores chromis Chromis limbata - A. B. Anderson - E. M. Salas - L.A. Rocha - S. R. Floeter - WILEY - 2017. Population expansion of the invasive Pomacentridae Chromis limbata (Valenciennes, 1833) in southern Brazilian coast: long-term monitoring, fundamental niche availability and new records - Antônio B. Anderson - Jodir Pereira da Silva - Raquel Sorvilo - Carlo Leopoldo B. Francini - SERGIO R. FLOETER - João P. Barreiros - WILEY - 2020. Reproductive synchrony in a temperate damselfish,Chromis limbata - Betty J.L. Laglbauer - Pedro Afonso - Anick Donnay - Ricardo S. Santos - acta ethologica - 2016. Interactúa con Fishipedia Para ponerse en contacto con nuestro equipo o participar en nuestro proyecto. Contribuya a esta página Plantilla y contenido © Fishipedia - Reproducción no autorizada sin solicitud previa - ISSN 2270-7247 - Última actualización el 13/11/2023 © Fishipedia.fr 2024",
    "genderDescription": "Pomacentridae",
    "type": "",
    "size": "9 cm",
    "maxSize": "12 cm",
    "mimetism": "",
    "recognize": "",
    "fe/maleDifferences": "La hembra presenta un tamaño mayor que el macho. El macho adulto presenta un mayor tamaño que la hembra.",
    "diet": "omnívoro con tendencia carnívora",
    "territorial": "Sí",
    "social": "bancos",
    "lifeMode": "dieta",
    "lifeDescription": "",
    "reproductionMode": "<  fula blanca  Chromis limbata  Valenciennes  1833  (Mundo) LC  Pomacentridae  Chromis",
    "migration": "",
    "reproductionDescription": "",
    "poison": "",
    "danger": "de realización. Los textos propuestos actualmente provienen de nuestro modelo de datos o están en proceso de redacción. Para solicitar prioridad para este contenido, puedes escribirnos AQUÍ.",
    "depth": "5 - 45 m",
    "image": "",
    "mapImage": ""
  },
  {
    "name": "Conger conger",
    "sciname": "",
    "IUCN": "",
    "description": "Introducción El congrio europeo, Conger conger, es un depredador común de las zonas rocosas del Mar Mediterráneo y la costa este del Océano Atlántico. Esta especie, apreciada por su carne, es capturada de manera regular y es posible encontrarla fácilmente en las pescaderías. De comportamiento más bien nocturno, rara vez se le observa durante el día en su entorno natural. Para poder avistarlo es necesario observar pacientemente el fondo de las cavidades rocosas o cuevas en las que puede asomar su característica cabeza. Generalmente se le atribuyen algunas leves mordeduras a bañistas y buceadores. Estos incidentes suelen tener lugar principalmente cuando las víctimas ponen sus manos o pies en las rocas. Los congrios protegen su espacio vital durante el día y no dudan en atacar a cualquier intruso que entre en su territorio.  de realización. Los textos propuestos actualmente provienen de nuestro modelo de datos o están en proceso de redacción. Para solicitar prioridad para este contenido, puedes escribirnos AQUÍ. ¿Quién es él?  Conger El género Conger pertenece a la familia Congridae y agrupa a anguilas de tamaño mediano y largo, hasta la fecha están incluidas en este género 17 especies. Las especies de Conger se encuentran en las zonas de la cuenca del Indo-Pacífico y el Océano Atlántico. Estos peces se alimentan principalmente de crustáceos bentónicos y peces pequeños. La búsqueda de alimento tiene lugar principalmente por la noche. Estas especies se encuentran cerca de sustratos rocosos y de grava, en aguas profundas o templadas. Los ejemplares más jóvenes son particularmente aficionados a los fondos arenosos considerados como áreas de cría. Algunas características morfológicas pueden diferenciar al género Conger de otros dentro de la familia Congridae. Algunas de las características que presentan estos peces son unos desarrollados labios inferiores y superiores. Los dientes maxilares y mandibulares se presentan en una o dos filas, teniendo los de la fila exterior extremos afilados. La reproducción implica la migración a alta mar, ya que el desove se realiza a profundidades abismales.  Tipo Congrio y anguila Tamaño medio 150 cm Tamaño máximo 300 cm Longevidad 15 años Forma Serpentiforme Conger conger, congrio común © Dennis Rabeling Conger conger, congrio común © Dennis Rabeling Conger conger, congrio común © Thomas Menut Conger conger, congrio común © Dennis Rabeling Conger conger, congrio común © Dennis Rabeling Previous Next Tipo Congrio y anguila Tamaño medio 150 cm Tamaño máximo 300 cm Longevidad 15 años Forma Serpentiforme ¿Cómo reconocer a Este pez ? El cuerpo es alargado y serpentiforme, de color gris oscuro. Esta especie no presenta aleta pélvica y las aletas pectorales son más imponentes que en el caso de la anguila. La aleta dorsal no está separada de la anal que comienza justo después del ano. La mandíbula es puntiaguda, provista de numerosos dientes y prominente en su parte superior. Diferencias entre machos y hembras No se observa un dimorfismo importante en esta especie, si bien la hembra presenta un tamaño ligeramente más grande. Modo de vida y comportamiento dieta carnívoro Sociabilidad solitario territorial Sí Modo de vida Nocturno El congrio es un poderoso cazador que actúa predominantemente en el crepúsculo y durante la noche. Es conocido por ser especialmente rápido. Durante el día, permanece escondido en agujeros, fallas y hendiduras, aunque se han registrado algunos avistamientos durante el día. Suele merodear al atardecer, en busca de peces, crustáceos y cefalópodos. Los congrios muestran canibalismo y son también carroñeros. Al igual que sucede con las morenas, los buceadores deben tener especial cuidado con las hendiduras donde se esconde esta especie. Las mordeduras de defensa pueden ser graves. Reproducción Modo de reproducción ovíparo que desova en aguas abiertas Especie migratoria Sí La forma de reproducción de este pez es todavía poco conocida. Parece que los congrios alcanzan la madurez sexual entre los 5 y los 15 años. Es un pez que realiza migraciones dentro del propio océano. La reproducción tiene lugar frente a las costas de Portugal y en el mar Mediterráneo. Varias fuentes indican que las islas Azores son también un importante caldo de cultivo. Los estudios son difíciles de realizar ya que esta especie desova a profundidades abismales, entre 3.000 y 4.000 metros. Las hembras ponen entre 3 y 8 millones de huevos. Como otros peces de su familia, solo se reproduce una vez en su vida. Riesgos para los humanos Venenoso No Mordedor Sí Esta especie puede atacar si se siente amenazada. Es importante permanecer especialmente atento durante las inmersiones o las sesiones de pesca. Origen y distribución Origen Mar Mediterráneo Océano Atlántico templado oriental Islas Islas Canarias Presencia geográfica y estado de la población La especie es común en las zonas templadas y se observa de forma menos común en zonas más frías como el Mar Negro, Islandia y Noruega. Se encuentra en abundancia en la zona marina costera del mar Mediterráneo. El estado de las poblaciones del congrio no es aún muy conocido. Esta especie, de escasa importancia comercial en Francia (el mercado español está más desarrollado), no ha sido objeto de estudios en profundidad. Se dice que la especie es frágil debido a su particular ciclo biológico: baja tasa de reproducción y madurez sexual tardía. Estado de conservación de las poblaciones (UICN) Mundo : LC ¿Cuál es su hábitat? Características del entorno natural Profundidad 5 - 500 m Presentación del biotopo El congrio europeo se encuentra con mayor frecuencia en áreas rocosas a una profundidad de menos de 500 metros. Sin embargo, es posible también encontrar este pez a otras profundidades. Las crías viven en las proximidades de la costa para trasladarse después a aguas a mayores profundidades, siempre sobre fondos rocosos. Especie del mismo biotopo moma Blenniidae pez roca de Madeira Scorpaenidae morena común Muraenidae rascacio negro Scorpaenidae barriguda cornuda Blenniidae escórpora Scorpaenidae Previous Next Para saber más Especie de la misma familia anguila de jardín de Hass Congridae Gorgasia preclara Congridae Previous Next Para leer en la web Fuentes y realización Participación y validación El equipo de Fishipedia y sus colaboradores especializados se comprometen a proporcionar contenido de alta calidad. Sin embargo, aunque la información proviene de fuentes científicas o testimonios de especialistas, los archivos pueden contener imprecisiones. Benoit Chartrer Adrien Falzon Traducción Traducción realizada con la valiosa contribución de nuestros traductores, quienes hacen que esta información esté disponible para un público más amplio. Interactúa con Fishipedia Para ponerse en contacto con nuestro equipo o participar en nuestro proyecto. Contribuya a esta página Plantilla y contenido © Fishipedia - Reproducción no autorizada sin solicitud previa - ISSN 2270-7247 - Última actualización el 12/11/2023 © Fishipedia.fr 2024",
    "genderDescription": "Congridae",
    "type": "",
    "size": "150 cm",
    "maxSize": "300 cm",
    "mimetism": "",
    "recognize": "",
    "fe/maleDifferences": "No se observa un dimorfismo importante en esta especie, si bien la hembra presenta un tamaño ligeramente más grande.",
    "diet": "carnívoro",
    "territorial": "Sí",
    "social": "solitario",
    "lifeMode": "dieta",
    "lifeDescription": "",
    "reproductionMode": "<  congrio común  Conger conger  Linnaeus  1758  (Mundo) LC  Congridae  Conger",
    "migration": "Tipo Congrio y anguila Tamaño medio 150 cm Tamaño máximo 300 cm Longevidad 15 años Forma Serpentiforme Conger conger, congrio común © Dennis Rabeling Conger conger, congrio común © Dennis Rabeling Conger conger, congrio común © Thomas Menut Conger conger, congrio común © Dennis Rabeling Conger conger, congrio común © Dennis Rabeling Previous Next Tipo Congrio y anguila Tamaño medio 150 cm Tamaño máximo 300 cm Longevidad 15 años Forma Serpentiforme",
    "reproductionDescription": "",
    "poison": "No",
    "danger": "de realización. Los textos propuestos actualmente provienen de nuestro modelo de datos o están en proceso de redacción. Para solicitar prioridad para este contenido, puedes escribirnos AQUÍ.",
    "depth": "Enciclopedia Explorar Acuariofilia A propósito Prensa Peces Ballestas Barracudas Doradas y sargos Escorpenas Hipocampos Lábridos Morenas Peces cirujano Peces globo Peces payaso Rayas Tiburones Reptiles Cocodrilos Serpientes Tortugas Moluscos Caracoles Nudibranquios Calamares Pulpos Sepias Otros temas Anfibios Cnidarios Crustáceos Amazonas Anaconda gigante Anguila eléctrica Paiche Piraña roja Raya motoro / Raya de rio Tararira Mediterráneo Atún rojo Congrio Dorada real Manta raya Mero Sargo Islas Canarias Ángel de mar Caballito de mar Pez roca de Madeira Pez trompeta atlántico Tiburón Mako Vieja colorada Mar del Caribe Cirujano azul Gran barracuda / Picúa Pez ángel francés pez ángel reina Raya jaspeada Robalo blanco Mar Rojo Mero del Coral Morena gigante Pez león Pez Napoléon Raya de arrecife Vieja florida Especies comunes Betta Splendens Chupa algas Corydoras Discos Escalar Gamba Red Cherry Guppy Pez dorado Pez payaso Grupos temáticos Cíclidos enanos Killis Lochas Luchadores Peces gato Tetras Vivíparos Práctica Peces compatibles 20 L Peces compatibles 40 L Peces compatibles 60 L Peces compatibles 80 L Peces compatibles 100 L El proyecto Fishipedia Nuestra ética Proyecto Yaku Nawi Los fotógrafos colaboradores CONTÁCTANOS Enciclopedia Peces Ballestas Barracudas Doradas y sargos Escorpenas Hipocampos Lábridos Morenas Peces cirujano Peces globo Peces payaso Rayas Tiburones Reptiles Cocodrilos Serpientes Tortugas Moluscos Caracoles Nudibranquios Calamares Pulpos Sepias Otros temas Anfibios Cnidarios Crustáceos Explorar Amazonas Anaconda gigante Anguila eléctrica Paiche Piraña roja Raya motoro / Raya de rio Tararira Mediterráneo Atún rojo Congrio Dorada real Manta raya Mero Sargo Islas Canarias Ángel de mar Caballito de mar Pez roca de Madeira Pez trompeta atlántico Tiburón Mako Vieja colorada Mar del Caribe Cirujano azul Gran barracuda / Picúa Pez ángel francés pez ángel reina Raya jaspeada Robalo blanco Mar Rojo Mero del Coral Morena gigante Pez león Pez Napoléon Raya de arrecife Vieja florida Acuariofilia Especies comunes Betta Splendens Chupa algas Corydoras Discos Escalar Gamba Red Cherry Guppy Pez dorado Pez payaso Grupos temáticos Cíclidos enanos Killis Lochas Luchadores Peces gato Tetras Vivíparos Práctica Peces compatibles 20 L Peces compatibles 40 L Peces compatibles 60 L Peces compatibles 80 L Peces compatibles 100 L A propósito El proyecto Fishipedia Nuestra ética Proyecto Yaku Nawi Los fotógrafos colaboradores CONTÁCTANOS Prensa",
    "image": "",
    "mapImage": ""
  },
  {
    "name": "Coris julis",
    "sciname": "",
    "IUCN": "",
    "description": "Introducción Coris julis, también conocida como doncella común, es un pez que puede observarse habitualmente en la costa este del océano Atlántico y en el mar Mediterráneo. Pertenece al grupo de peces conocido como doncellas. ¿Quién es ella?  Coris En 2022, el género Coris comprendía 27 especies según FishBase. Estos peces son comúnmente conocidos como \"doncellas\", aunque este término también puede referirse a especies alargadas de géneros cercanos como Thalasomma. En algunas regiones, estas especies también se llaman \"peces arcoíris\" y \"lábridos arcoíris\", nombres dados en referencia a su amplia variedad de colores. La mayoría de las especies de Coris se encuentran en la zona tropical del Indo-Pacífico. Una especie está presente en el Mediterráneo y otra en el océano Atlántico tropical, cerca de las costas africanas. Todas las especies son exclusivamente marinas. Los juveniles y los adultos a menudo frecuentan los mismos hábitats. Los hábitats costeros como los arrecifes rocosos y los praderas marinas proporcionan numerosos escondites. En 2022, de todas las especies del género Coris, tan solo Coris bulbifrons estaba clasificada como \"Vulnerable\" en la lista roja elaborada por la IUCN. Las demás especies del género no están amenazadas. Estos peces son particularmente objeto de la pesca recreativa y son capturados como \"captura incidental\" por los pescadores profesionales. Sufren de una gestión pesquera inexistente y la ausencia total de medidas de conservación.  Tipo Lábrido Tamaño medio 25 cm Tamaño máximo 30 cm Forma Rectangular Coris julis, doncella común Coris julis, doncella común © Benoit Chartrer Coris julis, doncella común © Thomas Menut Coris julis, doncella común © Benoit Chartrer Coris julis, doncella común © Benoit Chartrer Previous Next Tipo Lábrido Tamaño medio 25 cm Tamaño máximo 30 cm Forma Rectangular ¿Cómo reconocer a Este pez ? La doncella común presenta un cuerpo multicolor, mayoritariamente rojo, azul y verde. Este pez nace siempre siendo hembra, para a medida que crece, cambiar de sexo, transformándose en macho. A este hecho se le conoce como hermafroditismo sucesivo de tipo protógino. Diferencias entre machos y hembras En edad adulta, el macho presenta una coloración azul turquesa con una banda rojiza o anaranjada que atraviesa todo su cuerpo. Las hembras y los ejemplares más jóvenes poseen rayas naranjas, blancas y marrones. Modo de vida y comportamiento dieta omnívoro con tendencia carnívora Sociabilidad solitario territorial Sí Modo de vida Diurno Este pez de temperamento activo suele observarse con frecuencia formando pequeños grupos dispersos hasta que alcanza en torno a los 15 centímetros. Los machos adultos viven, sin embargo, en solitario a mayores profundidades. Se trata de una especie territorial, en particular los machos, que no suelen tolerar demasiado bien las incursiones en su hábitat. De manera general, puede decirse que se trata de un pez independiente que habita próximo a la zona de rocas o de las praderas marinas. Se nutre principalmente de pequeños gasterópodos, erizos de mar, camarones, lombrices, isópodos y anfípodos. Los adultos son capaces de elevar piedras, a veces de tamaño considerable, en busca de alimento. Cuando se siente en peligro, o durante la noche, esta especie no duda en enterrarse en la arena con el fin de camuflarse. Reproducción Modo de reproducción cuya forma de reproducción aún se desconoce Hermafrodita protógino El modo de reproducción de la doncella común sigue siendo a día de hoy poco conocido. Sin embargo, se sabe que todos los individuos nacen siendo hembras (protogenia), el cambio de sexo tiene lugar antes de alcanzar los 18 cm y no supera los 5 meses. Este pez puede considerarse sexualmente maduro a partir de un año de edad. Especies inofensivas Esta especie no representa un peligro particular para los seres humanos en caso de encuentro en su hábitat natural. Origen y distribución Origen Mar Mediterráneo Océano Atlántico templado oriental Océano Atlántico Oriental Frío Islas Islas Canarias Presencia geográfica y estado de la población Se trata de una especie muy común en la zona este del Océano Atlántico, con una distribución que va desde Suecia hasta el ecuador. Ubicua en el Mediterráneo, parece estar uniformemente distribuida. Algunos individuos del género Coris han sido observados en Cabo Verde y en Senegal. Sin embargo, no se trataría de Coris julis, sino de otra especie, Coris atlantica. Estado de conservación de las poblaciones (UICN) Mundo : LC Francia : LC ¿Dónde observar esta especie? ¿Cuál es su hábitat? Características del entorno natural Temperatura 12 - 26 °C Profundidad 1 - 120 m Corriente Moderada, Lenta y Estancada Presentación del biotopo La doncella común suele encontrarse con mayor frecuencia a una profundidad entre 1 y 60 metros. Sin embargo, en ocasiones es posible encontrar a este pez a otras profundidades diferentes. Suele habitar en las zonas rocosas y en los pastos marinos. Especie del mismo biotopo blenio del Atlántico Blenniidae miracielo Uranoscopidae pez verde Labridae dorada Sparidae pez de san Pedro Zeidae lubina Moronidae Previous Next Mantenimiento en cautividad No recomendado Desaconsejamos el mantenimiento de esta especie en acuario debido a su forma de vida, a su régimen alimentario y a su tamaño. Este pez presenta unas necesidades especiales, que de no ser cubiertas podrían generar un estrés importante pudiendo llegar a disminuir su esperanza de vida, deteniendo su crecimiento e incluso desarrollando una serie de patógenos. Es necesario tener en cuenta que existen, a menudo, diferencias notables de comportamiento entre los juveniles y los adultos que es necesario conocer antes de adquirir cualquier especie. Para saber más Especie de la misma familia Cheilinus fasciatus Labridae Cheilinus chlorourus Labridae lábrido de triple cola Labridae Oxycheilinus bimaculatus Labridae Halichoeres nebulosus Labridae Cheilio inermis Labridae lábrido de seis franjas Labridae Bodianus perditio Labridae Previous Next Para leer en la web Fuentes y realización Participación y validación El equipo de Fishipedia y sus colaboradores especializados se comprometen a proporcionar contenido de alta calidad. Sin embargo, aunque la información proviene de fuentes científicas o testimonios de especialistas, los archivos pueden contener imprecisiones. Benoit Chartrer Patrick Chartrer Garnier Julie Silvia Gomez Adrien Falzon Théo Guillaume Traducción Traducción realizada con la valiosa contribución de nuestros traductores, quienes hacen que esta información esté disponible para un público más amplio. Silvia Gomez Referencias bibliográficas The Use of Histological Techniques to Study the Reproductive Biology of the Hermaphroditic Mediterranean Fishes Coris julis, Serranus scriba, and Diplodus annularis - Alexandre Alonso-Fernandez - Josep Alós - Amalia Grau - Rosario Domínguez-Petit - Fran Saborido-Rey - Marine and Coastal Fisheries Dynamics Management and Ecosystem Science - 2011. Geographical and morphological variation within and between colour phases in Coris julis (L. 1758), a protogynous marine fish - CARMELO FRUCIANO - CONCETTA TIGANO - VENERA FERRITO - THE LINNEAN SOCIETY - 2011. Spacial distribution patterns of Coris julis and Thalassoma pavo (Pisces, Labridae) along the south-eastern Apulian coast (SE Italy) - Paolo Guidetti - Paolo D'Ambrosio - Editoria Scientifica Elettronica - 2004. Interactúa con Fishipedia Para ponerse en contacto con nuestro equipo o participar en nuestro proyecto. Contribuya a esta página Plantilla y contenido © Fishipedia - Reproducción no autorizada sin solicitud previa - ISSN 2270-7247 - Última actualización el 12/11/2023 © Fishipedia.fr 2024",
    "genderDescription": "Labridae",
    "type": "Enciclopedia Explorar Acuariofilia A propósito Prensa Peces Ballestas Barracudas Doradas y sargos Escorpenas Hipocampos Lábridos Morenas Peces cirujano Peces globo Peces payaso Rayas Tiburones Reptiles Cocodrilos Serpientes Tortugas Moluscos Caracoles Nudibranquios Calamares Pulpos Sepias Otros temas Anfibios Cnidarios Crustáceos Amazonas Anaconda gigante Anguila eléctrica Paiche Piraña roja Raya motoro / Raya de rio Tararira Mediterráneo Atún rojo Congrio Dorada real Manta raya Mero Sargo Islas Canarias Ángel de mar Caballito de mar Pez roca de Madeira Pez trompeta atlántico Tiburón Mako Vieja colorada Mar del Caribe Cirujano azul Gran barracuda / Picúa Pez ángel francés pez ángel reina Raya jaspeada Robalo blanco Mar Rojo Mero del Coral Morena gigante Pez león Pez Napoléon Raya de arrecife Vieja florida Especies comunes Betta Splendens Chupa algas Corydoras Discos Escalar Gamba Red Cherry Guppy Pez dorado Pez payaso Grupos temáticos Cíclidos enanos Killis Lochas Luchadores Peces gato Tetras Vivíparos Práctica Peces compatibles 20 L Peces compatibles 40 L Peces compatibles 60 L Peces compatibles 80 L Peces compatibles 100 L El proyecto Fishipedia Nuestra ética Proyecto Yaku Nawi Los fotógrafos colaboradores CONTÁCTANOS Enciclopedia Peces Ballestas Barracudas Doradas y sargos Escorpenas Hipocampos Lábridos Morenas Peces cirujano Peces globo Peces payaso Rayas Tiburones Reptiles Cocodrilos Serpientes Tortugas Moluscos Caracoles Nudibranquios Calamares Pulpos Sepias Otros temas Anfibios Cnidarios Crustáceos Explorar Amazonas Anaconda gigante Anguila eléctrica Paiche Piraña roja Raya motoro / Raya de rio Tararira Mediterráneo Atún rojo Congrio Dorada real Manta raya Mero Sargo Islas Canarias Ángel de mar Caballito de mar Pez roca de Madeira Pez trompeta atlántico Tiburón Mako Vieja colorada Mar del Caribe Cirujano azul Gran barracuda / Picúa Pez ángel francés pez ángel reina Raya jaspeada Robalo blanco Mar Rojo Mero del Coral Morena gigante Pez león Pez Napoléon Raya de arrecife Vieja florida Acuariofilia Especies comunes Betta Splendens Chupa algas Corydoras Discos Escalar Gamba Red Cherry Guppy Pez dorado Pez payaso Grupos temáticos Cíclidos enanos Killis Lochas Luchadores Peces gato Tetras Vivíparos Práctica Peces compatibles 20 L Peces compatibles 40 L Peces compatibles 60 L Peces compatibles 80 L Peces compatibles 100 L A propósito El proyecto Fishipedia Nuestra ética Proyecto Yaku Nawi Los fotógrafos colaboradores CONTÁCTANOS Prensa",
    "size": "25 cm",
    "maxSize": "30 cm",
    "mimetism": "",
    "recognize": "",
    "fe/maleDifferences": "En edad adulta, el macho presenta una coloración azul turquesa con una banda rojiza o anaranjada que atraviesa todo su cuerpo. Las hembras y los ejemplares más jóvenes poseen rayas naranjas, blancas y marrones.",
    "diet": "omnívoro con tendencia carnívora",
    "territorial": "Sí",
    "social": "solitario",
    "lifeMode": "dieta",
    "lifeDescription": "",
    "reproductionMode": "<  doncella común  Coris julis  Linnaeus  1758  (Mundo) LC  Labridae  Coris",
    "migration": "",
    "reproductionDescription": "",
    "poison": "",
    "danger": "",
    "depth": "Enciclopedia Explorar Acuariofilia A propósito Prensa Peces Ballestas Barracudas Doradas y sargos Escorpenas Hipocampos Lábridos Morenas Peces cirujano Peces globo Peces payaso Rayas Tiburones Reptiles Cocodrilos Serpientes Tortugas Moluscos Caracoles Nudibranquios Calamares Pulpos Sepias Otros temas Anfibios Cnidarios Crustáceos Amazonas Anaconda gigante Anguila eléctrica Paiche Piraña roja Raya motoro / Raya de rio Tararira Mediterráneo Atún rojo Congrio Dorada real Manta raya Mero Sargo Islas Canarias Ángel de mar Caballito de mar Pez roca de Madeira Pez trompeta atlántico Tiburón Mako Vieja colorada Mar del Caribe Cirujano azul Gran barracuda / Picúa Pez ángel francés pez ángel reina Raya jaspeada Robalo blanco Mar Rojo Mero del Coral Morena gigante Pez león Pez Napoléon Raya de arrecife Vieja florida Especies comunes Betta Splendens Chupa algas Corydoras Discos Escalar Gamba Red Cherry Guppy Pez dorado Pez payaso Grupos temáticos Cíclidos enanos Killis Lochas Luchadores Peces gato Tetras Vivíparos Práctica Peces compatibles 20 L Peces compatibles 40 L Peces compatibles 60 L Peces compatibles 80 L Peces compatibles 100 L El proyecto Fishipedia Nuestra ética Proyecto Yaku Nawi Los fotógrafos colaboradores CONTÁCTANOS Enciclopedia Peces Ballestas Barracudas Doradas y sargos Escorpenas Hipocampos Lábridos Morenas Peces cirujano Peces globo Peces payaso Rayas Tiburones Reptiles Cocodrilos Serpientes Tortugas Moluscos Caracoles Nudibranquios Calamares Pulpos Sepias Otros temas Anfibios Cnidarios Crustáceos Explorar Amazonas Anaconda gigante Anguila eléctrica Paiche Piraña roja Raya motoro / Raya de rio Tararira Mediterráneo Atún rojo Congrio Dorada real Manta raya Mero Sargo Islas Canarias Ángel de mar Caballito de mar Pez roca de Madeira Pez trompeta atlántico Tiburón Mako Vieja colorada Mar del Caribe Cirujano azul Gran barracuda / Picúa Pez ángel francés pez ángel reina Raya jaspeada Robalo blanco Mar Rojo Mero del Coral Morena gigante Pez león Pez Napoléon Raya de arrecife Vieja florida Acuariofilia Especies comunes Betta Splendens Chupa algas Corydoras Discos Escalar Gamba Red Cherry Guppy Pez dorado Pez payaso Grupos temáticos Cíclidos enanos Killis Lochas Luchadores Peces gato Tetras Vivíparos Práctica Peces compatibles 20 L Peces compatibles 40 L Peces compatibles 60 L Peces compatibles 80 L Peces compatibles 100 L A propósito El proyecto Fishipedia Nuestra ética Proyecto Yaku Nawi Los fotógrafos colaboradores CONTÁCTANOS Prensa",
    "image": "",
    "mapImage": ""
  },
  {
    "name": "Coryphaena hippurus",
    "sciname": "",
    "IUCN": "",
    "description": "Introducción Más conocido como dorado, llampuga o mahi-mahi en la Polinesia, es un pez marino de la familia Coryphaenidae. Se encuentra en las cálidas aguas de los océanos Atlántico, Índico y Pacífico. Se trata de una especie que pareciera estar aprovechando el calentamiento de los océanos, recientemente ha ingresado en el mar Mediterráneo. Como migrante, sus límites están determinados por la temperatura del agua, que debe superar siempre los 20 °C. Con una velocidad de carrera cercana a los 100 km/h, el dorado es uno de los animales acuáticos más rápidos del mundo.  de realización. Los textos propuestos actualmente provienen de nuestro modelo de datos o están en proceso de redacción. Para solicitar prioridad para este contenido, puedes escribirnos AQUÍ. ¿Quién es él?  Coryphaena En 2021, FishBase describe dos especies bajo el género Coryphaena. Estos peces oceánicos suelen vivir en grupos pequeños cerca de la superficie. Sus hábitos son similares a los del atún. Como depredadores oportunistas, los adultos cazan peces y cefalópodos siguiendo rutas migratorias. Estos depredadores desempeñan un papel importante en la cadena ecológica. También son conocidos por su velocidad, similar a los picudos o marlines. Su silueta esbelta, junto con una aleta dorsal distintiva y colores brillantes, permite una identificación rápida. Ampliamente distribuidos en la superficie del globo, estos peces son apreciados por los pescadores deportivos en el mar.  Tipo dorada y sargo Tamaño medio 100 cm Tamaño máximo 210 cm Longevidad 4 años Coryphaena hippurus, dorado © Cédric Pau Tipo dorada y sargo Tamaño medio 100 cm Tamaño máximo 210 cm Longevidad 4 años ¿Cómo reconocer a Este pez ? El cuerpo de este pez es esbelto, típico de los grandes nadadores. La cabeza es predominante, con los ojos situados muy cerca de la boca. Los peces de gran tamaño rara vez son muy coloridos. Sin embargo, con un lomo metálico azul-verde y un vientre dorado, el dorado es una excepción. Además, esta especie tiene la capacidad de cambiar de color de amarillo a azul en cuestión de minutos. Pueden observarse marcas cambiantes (rojas, azules, negras) en todo el cuerpo. Esta especie se caracteriza por la ausencia de espinas duras. Las aletas están formadas por radios blandos. La aleta dorsal es única y comienza sobre el ojo hasta alcanzar el pedúnculo caudal. La aleta anal comienza a la mitad del cuerpo. Las aletas pélvicas y caudales son delgadas y puntiagudas. Diferencias entre machos y hembras Esta especie presenta un importante dimorfismo sexual; los machos tienen un frente anguloso y muy desarrollado, mientras que las hembras presentan una cabeza redonda y un cuerpo más delgado Modo de vida y comportamiento dieta carnívoro Sociabilidad bancos territorial No Modo de vida Diurno El dorado es una especie pelágica activa que realiza grandes migraciones. Este depredador de aguas abiertas es capaz de atrapar presas muy rápidas, como los peces voladores de la familia Exocoetidae, que nadan a más de 60 km/h. Durante estas cazas espectaculares, persigue a los exocetos a velocidades asombrosas, provocándoles incluso salir del agua. Este pez suele vivir en pareja, aunque ocasionalmente puede formar grupos e incluso bancos. Reproducción Modo de reproducción ovíparo Especie migratoria Sí La madurez sexual se alcanza a una talla de 55,8 cm alrededor de los 4-5 meses de edad. La puesta en aguas abiertas, se cree que probablemente ocurre en aguas cálidas cerca de la costa. Los huevos y las larvas son pelágicos. Especies inofensivas Esta especie no representa un peligro particular para los humanos en caso de encuentro en su entorno natural. Origen y distribución Origen Golfo de México Golfo Pérsico Gran Barrera de Coral mar Arábigo mar de China oriental Mar del Caribe Mar de Filipinas Mar de Japón Mar Mediterráneo Mar Rojo Mares del Sudeste Asiático Mares indonesios Océano Atlántico: costa norte de Brasil Océano Atlántico templado oriental Océano Atlántico noroeste templado frío Océano Atlántico templado cálido del noroeste Sudoeste del Océano Atlántico templado cálido Océano Atlántico tropical oriental Océano Atlántico tropical Sudoeste Océano Índico occidental Islas Desventuradas Galápagos Océano Pacífico tropical oriental Océano Pacífico tropical occidental Islas Islas Canarias La Reunión Polinesia Francesa Presencia geográfica y estado de la población Gracias a su distribución global, la especie no parece estar amenazada por el momento. Sin embargo, esta especie tiene un alto valor comercial, lo que la convierte en una de las capturas preferidas por la industria pesquera. Su comportamiento pelágico generalmente solitario obliga a una pesca generalmente artesanal. Se utilizan técnicas de pesca que permiten la concentración de peces (DCP), especialmente en el Mediterráneo. El comportamiento agregativo de la especie alrededor de objetos flotantes la hace vulnerable a este tipo de captura. El aumento constante de las capturas sin regulación puede ser preocupante para el futuro de la especie. En 2005, por ejemplo, se pescaron mundialmente 58,076 toneladas. Estado de conservación de las poblaciones (UICN) Mundo : LC ¿Dónde observar esta especie? ¿Cuál es su hábitat? Características del entorno natural Temperatura 25 - 30 °C Profundidad 0 - 85 m Presentación del biotopo Estos peces pelágicos se mueven cerca de la superficie pero son capaces de descender a una profundidad de 85 m. Especie del mismo biotopo tiburón mako Lamnidae atún rojo del Atlántico Scombridae Echeneis naucrates Echeneidae pez piloto Carangidae mantarraya Mobulidae raya toro Myliobatidae Previous Next Para saber más Para leer en la web Fuentes y realización Participación y validación El equipo de Fishipedia y sus colaboradores especializados se comprometen a proporcionar contenido de alta calidad. Sin embargo, aunque la información proviene de fuentes científicas o testimonios de especialistas, los archivos pueden contener imprecisiones. Traducción Traducción realizada con la valiosa contribución de nuestros traductores, quienes hacen que esta información esté disponible para un público más amplio. Silvia Gomez Referencias bibliográficas Biology of the dolphinfish (Coryphaena hippurus) inthe western central Atlantic: a review - HAZEL A. OXENFORD - Scientia Marina - 1999. Feeding habits of the dolphinfish (Coryphaena hippurus) in the eastern Caribbean - HAZEL A. OXENFORD - WAYNE HUNTE - Scientia Marina - 1999. On the Identification, Distribution, and Biology of the Dolphins, Coryphaena Hippurus and C. Equiselis - Gibbs, Jr., Robert H. - Collette, Bruce B. - BULLETIN OF MARINE SCIENCE, - 1959. Interactúa con Fishipedia Para ponerse en contacto con nuestro equipo o participar en nuestro proyecto. Contribuya a esta página Plantilla y contenido © Fishipedia - Reproducción no autorizada sin solicitud previa - ISSN 2270-7247 - Última actualización el 12/11/2023 © Fishipedia.fr 2024",
    "genderDescription": "Coryphaenidae",
    "type": "",
    "size": "100 cm",
    "maxSize": "210 cm",
    "mimetism": "",
    "recognize": "",
    "fe/maleDifferences": "Esta especie presenta un importante dimorfismo sexual; los machos tienen un frente anguloso y muy desarrollado, mientras que las hembras presentan una cabeza redonda y un cuerpo más delgado",
    "diet": "carnívoro",
    "territorial": "No",
    "social": "bancos",
    "lifeMode": "dieta",
    "lifeDescription": "",
    "reproductionMode": "<  dorado  Coryphaena hippurus  Linnaeus  1758  (Mundo) LC  Coryphaenidae  Coryphaena",
    "migration": "",
    "reproductionDescription": "",
    "poison": "",
    "danger": "de realización. Los textos propuestos actualmente provienen de nuestro modelo de datos o están en proceso de redacción. Para solicitar prioridad para este contenido, puedes escribirnos AQUÍ.",
    "depth": "Enciclopedia Explorar Acuariofilia A propósito Prensa Peces Ballestas Barracudas Doradas y sargos Escorpenas Hipocampos Lábridos Morenas Peces cirujano Peces globo Peces payaso Rayas Tiburones Reptiles Cocodrilos Serpientes Tortugas Moluscos Caracoles Nudibranquios Calamares Pulpos Sepias Otros temas Anfibios Cnidarios Crustáceos Amazonas Anaconda gigante Anguila eléctrica Paiche Piraña roja Raya motoro / Raya de rio Tararira Mediterráneo Atún rojo Congrio Dorada real Manta raya Mero Sargo Islas Canarias Ángel de mar Caballito de mar Pez roca de Madeira Pez trompeta atlántico Tiburón Mako Vieja colorada Mar del Caribe Cirujano azul Gran barracuda / Picúa Pez ángel francés pez ángel reina Raya jaspeada Robalo blanco Mar Rojo Mero del Coral Morena gigante Pez león Pez Napoléon Raya de arrecife Vieja florida Especies comunes Betta Splendens Chupa algas Corydoras Discos Escalar Gamba Red Cherry Guppy Pez dorado Pez payaso Grupos temáticos Cíclidos enanos Killis Lochas Luchadores Peces gato Tetras Vivíparos Práctica Peces compatibles 20 L Peces compatibles 40 L Peces compatibles 60 L Peces compatibles 80 L Peces compatibles 100 L El proyecto Fishipedia Nuestra ética Proyecto Yaku Nawi Los fotógrafos colaboradores CONTÁCTANOS Enciclopedia Peces Ballestas Barracudas Doradas y sargos Escorpenas Hipocampos Lábridos Morenas Peces cirujano Peces globo Peces payaso Rayas Tiburones Reptiles Cocodrilos Serpientes Tortugas Moluscos Caracoles Nudibranquios Calamares Pulpos Sepias Otros temas Anfibios Cnidarios Crustáceos Explorar Amazonas Anaconda gigante Anguila eléctrica Paiche Piraña roja Raya motoro / Raya de rio Tararira Mediterráneo Atún rojo Congrio Dorada real Manta raya Mero Sargo Islas Canarias Ángel de mar Caballito de mar Pez roca de Madeira Pez trompeta atlántico Tiburón Mako Vieja colorada Mar del Caribe Cirujano azul Gran barracuda / Picúa Pez ángel francés pez ángel reina Raya jaspeada Robalo blanco Mar Rojo Mero del Coral Morena gigante Pez león Pez Napoléon Raya de arrecife Vieja florida Acuariofilia Especies comunes Betta Splendens Chupa algas Corydoras Discos Escalar Gamba Red Cherry Guppy Pez dorado Pez payaso Grupos temáticos Cíclidos enanos Killis Lochas Luchadores Peces gato Tetras Vivíparos Práctica Peces compatibles 20 L Peces compatibles 40 L Peces compatibles 60 L Peces compatibles 80 L Peces compatibles 100 L A propósito El proyecto Fishipedia Nuestra ética Proyecto Yaku Nawi Los fotógrafos colaboradores CONTÁCTANOS Prensa",
    "image": "",
    "mapImage": ""
  },
  {
    "name": "Dactylopterus volitans",
    "sciname": "",
    "IUCN": "",
    "description": "Introducción Dactylopterus volitans, es conocido por múltiples nombres dependiendo de la región, algunos de los más comunes son pez golondrina, alón volador o chicharra. Se trata de un pez marino originario del océano Atlántico. Se encuentra desde Canadá hasta Argentina en la costa oeste del Atlántico y desde el Canal de la Mancha hasta las Azores en la costa este. También está presente en el mar Mediterráneo, desde Gibraltar hasta Chipre. Al igual que otras especies de su familia, este pez realiza un movimiento característico que recuerda a la marcha terrestre utilizando sus aletas pélvicas. Estas aletas no son muy diferentes de las extremidades de los animales terrestres.  de realización. Los textos propuestos actualmente provienen de nuestro modelo de datos o están en proceso de redacción. Para solicitar prioridad para este contenido, puedes escribirnos AQUÍ. ¿Quién es él?  Dactylopterus El género Dactylopterus es monotípico, con una única especie Dactylopterus volitans. El nombre del género proviene del griego antiguo \"daktyleys\", que significa una especie de mújol, y \"pteron\", que significa alas. Literalmente traducido como mújol con alas. Comúnmente conocido como pez golondrina, esta especie comparte muchas características con los animales de los géneros Chelidonichthys, Aspiragla, Trigla, Eutrigla, Chelidonichthys y Dactyloptena. El género Dactylopterus se diferencia por el gran tamaño de las aletas pectorales, que llegan hasta la parte posterior de la aleta anal.  Tamaño medio 38 cm Tamaño máximo 50 cm Patrón moteado Dactylopterus volitans, pez golondrina © Benoit Chartrer Dactylopterus volitans, pez golondrina © Benoit Chartrer Dactylopterus volitans, pez golondrina © Kevin Bryant Dactylopterus volitans, pez golondrina © Kevin Bryant Previous Next Tamaño medio 38 cm Tamaño máximo 50 cm Patrón moteado ¿Cómo reconocer a Este pez ? Dactylopterus volitans presenta una longitud que oscila entre los 38 y 50 cm. Su cuerpo es ligeramente cónico desde la cabeza ancha hasta la aleta caudal. El color puede variar, con un vientre claro, a veces rojo, y un dorso marrón/beige. El cuerpo presenta matices de color marrón y manchas blancas azuladas. Las dos aletas dorsales son translúcidas, con radios marrones rayados de blanco. Las aletas pectorales son de gran tamaño y tienen puntos alineados en colores azul, blanco, beige y marrón, con predominio del azul en la parte exterior. La aleta caudal es beige rayada de marrón. La cabeza angular está compuesta por placas óseas, con ojos prominentes y una boca inferior que presenta una mandíbula superior más grande que la inferior. Se encuentran dos espinas dorsales aisladas antes de las dos aletas dorsales. Diferencias entre machos y hembras No existe dimorfismo sexual aparente en esta especie. Modo de vida y comportamiento dieta carnívoro Sociabilidad solitario territorial No Modo de vida Diurno Se trata de un pez que suele ser solitario, aunque se pueden observar individuos en pequeños grupos. Es un carnívoro que pasa su tiempo explorando el fondo marino con su boca y sus aletas pélvicas. La agitación en el lecho marino atrae a peces oportunistas como Carangoides bartholomaei y Cephalopholis fulva. En caso de peligro, despliega sus amplias aletas pectorales coloridas para impresionar a sus posibles depredadores. Estas posturas también podrían ser utilizadas como parte del cortejo de reproducción o para intimidar. Reproducción Modo de reproducción ovíparo Es un pez ovíparo que se reproduce en verano aprovechando el calentamiento del agua. Especies inofensivas Esta especie no representa un peligro particular para el ser humano en caso de encuentro en su entorno natural. Origen y distribución Origen Golfo de México Mar del Caribe Mar Mediterráneo Mar Negro Océano Atlántico: costa norte de Brasil Océano Atlántico templado oriental Océano Atlántico noroeste templado frío Océano Atlántico templado cálido del noroeste Sudoeste del Océano Atlántico templado cálido Océano Atlántico tropical oriental Océano Atlántico tropical Sudoeste Islas Islas Canarias Presencia geográfica y estado de la población La especie no parece estar oficialmente amenazada en su entorno natural. Sin embargo, los avistamientos parecen ser poco frecuentes en gran parte de su área de distribución, especialmente en el Mar Mediterráneo. Estado de conservación de las poblaciones (UICN) Mundo : LC ¿Dónde observar esta especie? ¿Cuál es su hábitat? Características del entorno natural Temperatura 13 - 28 °C Profundidad 1 - 100 m Presentación del biotopo Se encuentra con mayor frecuencia a esta especie a una profundidad de entre 1 y 100 metros. Sin embargo, no es imposible observarlo a otras profundidades. El sustrato suele estar compuesto por arena, rocas y barro. Especie del mismo biotopo jurel limón Carangidae pez de san Pedro Zeidae dorada Sparidae aguja de mar Syngnathidae pez escorpión Trachinidae lenguado Soleidae Previous Next Para saber más Especie de la misma familia Dactyloptena orientalis Dactylopteridae Para leer en la web Fuentes y realización Participación y validación El equipo de Fishipedia y sus colaboradores especializados se comprometen a proporcionar contenido de alta calidad. Sin embargo, aunque la información proviene de fuentes científicas o testimonios de especialistas, los archivos pueden contener imprecisiones. Adrien Falzon Benoit Chartrer Traducción Traducción realizada con la valiosa contribución de nuestros traductores, quienes hacen que esta información esté disponible para un público más amplio. Silvia Gomez Interactúa con Fishipedia Para ponerse en contacto con nuestro equipo o participar en nuestro proyecto. Contribuya a esta página Plantilla y contenido © Fishipedia - Reproducción no autorizada sin solicitud previa - ISSN 2270-7247 - Última actualización el 12/11/2023 © Fishipedia.fr 2024",
    "genderDescription": "Dactylopteridae",
    "type": "",
    "size": "38 cm",
    "maxSize": "50 cm",
    "mimetism": "",
    "recognize": "",
    "fe/maleDifferences": "No existe dimorfismo sexual aparente en esta especie.",
    "diet": "carnívoro",
    "territorial": "No",
    "social": "solitario",
    "lifeMode": "dieta",
    "lifeDescription": "",
    "reproductionMode": "<  pez golondrina  Dactylopterus volitans  Linnaeus  1758  (Mundo) LC  Dactylopteridae  Dactylopterus",
    "migration": "",
    "reproductionDescription": "",
    "poison": "",
    "danger": "de realización. Los textos propuestos actualmente provienen de nuestro modelo de datos o están en proceso de redacción. Para solicitar prioridad para este contenido, puedes escribirnos AQUÍ.",
    "depth": "Enciclopedia Explorar Acuariofilia A propósito Prensa Peces Ballestas Barracudas Doradas y sargos Escorpenas Hipocampos Lábridos Morenas Peces cirujano Peces globo Peces payaso Rayas Tiburones Reptiles Cocodrilos Serpientes Tortugas Moluscos Caracoles Nudibranquios Calamares Pulpos Sepias Otros temas Anfibios Cnidarios Crustáceos Amazonas Anaconda gigante Anguila eléctrica Paiche Piraña roja Raya motoro / Raya de rio Tararira Mediterráneo Atún rojo Congrio Dorada real Manta raya Mero Sargo Islas Canarias Ángel de mar Caballito de mar Pez roca de Madeira Pez trompeta atlántico Tiburón Mako Vieja colorada Mar del Caribe Cirujano azul Gran barracuda / Picúa Pez ángel francés pez ángel reina Raya jaspeada Robalo blanco Mar Rojo Mero del Coral Morena gigante Pez león Pez Napoléon Raya de arrecife Vieja florida Especies comunes Betta Splendens Chupa algas Corydoras Discos Escalar Gamba Red Cherry Guppy Pez dorado Pez payaso Grupos temáticos Cíclidos enanos Killis Lochas Luchadores Peces gato Tetras Vivíparos Práctica Peces compatibles 20 L Peces compatibles 40 L Peces compatibles 60 L Peces compatibles 80 L Peces compatibles 100 L El proyecto Fishipedia Nuestra ética Proyecto Yaku Nawi Los fotógrafos colaboradores CONTÁCTANOS Enciclopedia Peces Ballestas Barracudas Doradas y sargos Escorpenas Hipocampos Lábridos Morenas Peces cirujano Peces globo Peces payaso Rayas Tiburones Reptiles Cocodrilos Serpientes Tortugas Moluscos Caracoles Nudibranquios Calamares Pulpos Sepias Otros temas Anfibios Cnidarios Crustáceos Explorar Amazonas Anaconda gigante Anguila eléctrica Paiche Piraña roja Raya motoro / Raya de rio Tararira Mediterráneo Atún rojo Congrio Dorada real Manta raya Mero Sargo Islas Canarias Ángel de mar Caballito de mar Pez roca de Madeira Pez trompeta atlántico Tiburón Mako Vieja colorada Mar del Caribe Cirujano azul Gran barracuda / Picúa Pez ángel francés pez ángel reina Raya jaspeada Robalo blanco Mar Rojo Mero del Coral Morena gigante Pez león Pez Napoléon Raya de arrecife Vieja florida Acuariofilia Especies comunes Betta Splendens Chupa algas Corydoras Discos Escalar Gamba Red Cherry Guppy Pez dorado Pez payaso Grupos temáticos Cíclidos enanos Killis Lochas Luchadores Peces gato Tetras Vivíparos Práctica Peces compatibles 20 L Peces compatibles 40 L Peces compatibles 60 L Peces compatibles 80 L Peces compatibles 100 L A propósito El proyecto Fishipedia Nuestra ética Proyecto Yaku Nawi Los fotógrafos colaboradores CONTÁCTANOS Prensa",
    "image": "",
    "mapImage": ""
  },
  {
    "name": "Dasyatis pastinaca",
    "sciname": "",
    "IUCN": "",
    "description": "Introducción La raya látigo común o pastinaca es una especie emblemática del océano Atlántico y del mar Mediterráneo. Conocida también como chucho amarillo en las islas Canarias. Puede ser observada desde Senegal hasta el mar del Norte, tanto en las zonas costeras como en las lagunas marinas. Su cola está provista de un aguijón venenoso y su picadura puede ser peligrosa para el ser humano. ¿Quién es ella?  Dasyatis El género Dasyatis forma parte de la familia de los Dasiátidos, que engloba a la mayoría de las conocidas como rayas látigo o pastinacas. Al igual que los tiburones, las rayas pertenecen a la clase de los elasmobranquios, peces cartilaginosos. Las rayas se diferencian por poseer un cuerpo plano y la presencia de espiráculos en su parte dorsal. Se trata de un sistema de respiración especializado que les permite aspirar el agua y expulsarla por las hendiduras branquiales en la parte ventral, sin tomar arena. Todas las especies del género poseen una cola larga con un aguijón venenoso. En las rayas, el aguijón se reemplaza aproximadamente cada ocho a doce meses, dependiendo de la temperatura del agua y del desgaste del existente. En un acuario, suele ser habitual encontrar estos aguijones depositados en la arena. Se recomienda ser muy cuidadoso, ya que, aunque ya no sean venenosos, siguen siendo peligrosos. Con una forma afilada de unos diez centímetros de promedio, su aguijón puntiagudo rodeado de dentículos retrógrados (como un arpón) puede perforar fácilmente la piel. Cuando una de estas rayas se siente amenazada, levanta su aguijón y azota al intruso con su cola. El aguijón se clava en los tejidos de la víctima, rompiendo el tegumento que lo rodea y liberando el veneno. Este último es producido por dos glándulas venenosas situadas ventralmente en la base de la cola. En caso de picadura, será necesario sacar rápidamente a la persona del agua. Posteriormente, se debe enjuagar abundantemente la herida, retirar el aguijón o los restos si no han penetrado muy profundo y desinfectar. El veneno de las rayas es termolábil, es decir, se destruye con el calor.  Tipo raya Tamaño medio 60 cm Tamaño máximo 250 cm Forma Circular Dasyatis pastinaca, raya látigo común © Nicolas Descriaux Tipo raya Tamaño medio 60 cm Tamaño máximo 250 cm Forma Circular ¿Cómo reconocer a Este pez ? El término Dasyatis proviene del latín da sus que quiere decir \"rugoso\" y pastinaca que quiere decir \"mantarraya\". La raya pastinaca tiene forma de diamante con una cabeza ligeramente en punta. El dorso es de color beige mientras el vientre es blanco. Sus ojos se encuentran en la parte alta de la cabeza, lo que le permite tener un gran campo de visión. En la base de la cabeza, ligeramente hacia atrás, se encuentran tres grandes espiráculos, unos orificios que utiliza para respirar. La cola de esta especie tiene en general la misma talla que el cuerpo. El aguijón se encuentra en el centro de la cola. El ejemplar más grande documentado medía 2,5m, incluyendo la cola. Esta especie puede ser confundida con Dasyatis centroura, la pastinaca espinosa, cuyo nombre común hace referencia a una serie de protuberancias que luce sobre el dorso. A veces, puede ser también confundida con Dasyatis tortonesei, una especie muy similar pero de menor tamaño. Diferencias entre machos y hembras Al igual que ocurre con los tiburones, las rayas poseen dos pterigopodios, dos apéndices creados a partir de la modificación de las aletas pélvicas que permiten la transmisión del esperma hasta la cloaca de la hembra. Los machos pueden utilizar únicamente uno cada vez. Modo de vida y comportamiento dieta carnívoro Sociabilidad solitario territorial No Modo de vida Diurno Se trata de un animal solitario que se desplaza por el fondo marino. Donde pasa parte de su tiempo enterrada en la arena camuflada. Esta especie no se muestra temerosa frente a buceadores o bañistas, lo que la convierte en un animal especialmente peligroso ya que si se siente amenazada, o si por error es pisada, utilizará su aguijón, que puede llegar a medir 35cm de largo, para picar al intruso. La picadura puede llegar a ser mortal. Reproducción Modo de reproducción ovovivíparo Esta raya es un pez ovovivíparo que puede dar a luz de 5 a 7 crías por puesta, pasados 4 meses de gestación. Especies potencialmente mortales Venenoso Sí Se trata de una especie muy venenosa que puede llegar a causar lesiones graves en caso de contacto. En los casos más graves puede llegar a causar la muerte. ¿Qué hacer en caso de una picadura? En caso de mordedura, se deben seguir las siguientes reglas, manteniendo siempre el orden indicado: Aislar a la víctima del peligro y sacarla rápidamente del agua. Avisar a los servicios de emergencia. Colocar al sujeto en una posición semisentada para evitar que realice cualquier esfuerzo. Inmovilizar la extremidad afectada. Limpiar la herida. Dado que el veneno de esta especie es termolábil, puede neutralizarse si se somete a una temperatura cercana a los 45 ° C. Por tanto, será necesario calentar la herida. Esta popular técnica debe practicarse con mucho cuidado para no agravar el estado de la herida. Es recomendable sumergir la extremidad afectada en agua caliente. Si la mordedura es demasiado profunda, el procedimiento de calentar la herida resultará menos efectivo. En algunas ocasiones, la mordedura puede provocar molestias o incluso pérdida del conocimiento en la víctima. Origen y distribución Origen Mar Mediterráneo Mar Negro Océano Atlántico templado oriental Islas Córcega Islas Canarias Cerdeña Sicilia Estado de conservación de las poblaciones (UICN) Mundo : VU ¿Dónde observar esta especie? ¿Cuál es su hábitat? Características del entorno natural Temperatura 10 - 25 °C Profundidad 1 - 200 m Presentación del biotopo Esta raya se desplaza por el fondo arenoso en busca de crustáceos y gusanos enterrados en la arena. Rara vez suele verse a este animal haciendo incursiones en zonas rocosas. Generalmente, puede ser observada en la orilla del mar, hasta 200 m de profundidad, aunque también ha sido observada en estuarios en agua salobre. Especie del mismo biotopo trompetero Centriscidae rape común Lophiidae pez escorpión Trachinidae pez víbora Trachinidae raya redonda Dasyatidae miracielo Uranoscopidae Previous Next Para saber más Especie de la misma familia raya redonda Dasyatidae raya de cola corta Dasyatidae Pateobatis fai Dasyatidae raya sartén Dasyatidae raya látigo reticulada Dasyatidae raya pelágica Dasyatidae Hypanus americanus Dasyatidae raya látigo lija Dasyatidae Previous Next Para leer en la web Fuentes y realización Participación y validación El equipo de Fishipedia y sus colaboradores especializados se comprometen a proporcionar contenido de alta calidad. Sin embargo, aunque la información proviene de fuentes científicas o testimonios de especialistas, los archivos pueden contener imprecisiones. Adrien Falzon Benoit Chartrer Traducción Traducción realizada con la valiosa contribución de nuestros traductores, quienes hacen que esta información esté disponible para un público más amplio. Silvia Gomez Interactúa con Fishipedia Para ponerse en contacto con nuestro equipo o participar en nuestro proyecto. Contribuya a esta página Plantilla y contenido © Fishipedia - Reproducción no autorizada sin solicitud previa - ISSN 2270-7247 - Última actualización el 12/11/2023 © Fishipedia.fr 2024",
    "genderDescription": "Dasyatidae",
    "type": "",
    "size": "60 cm",
    "maxSize": "250 cm",
    "mimetism": "",
    "recognize": "",
    "fe/maleDifferences": "Al igual que ocurre con los tiburones, las rayas poseen dos pterigopodios, dos apéndices creados a partir de la modificación de las aletas pélvicas que permiten la transmisión del esperma hasta la cloaca de la hembra. Los machos pueden utilizar únicamente uno cada vez.",
    "diet": "carnívoro",
    "territorial": "No",
    "social": "solitario",
    "lifeMode": "dieta",
    "lifeDescription": "",
    "reproductionMode": "<  raya látigo común  Dasyatis pastinaca  Linnaeus  1758  (Mundo) VU  Dasyatidae  Dasyatis",
    "migration": "",
    "reproductionDescription": "",
    "poison": "",
    "danger": "",
    "depth": "Enciclopedia Explorar Acuariofilia A propósito Prensa Peces Ballestas Barracudas Doradas y sargos Escorpenas Hipocampos Lábridos Morenas Peces cirujano Peces globo Peces payaso Rayas Tiburones Reptiles Cocodrilos Serpientes Tortugas Moluscos Caracoles Nudibranquios Calamares Pulpos Sepias Otros temas Anfibios Cnidarios Crustáceos Amazonas Anaconda gigante Anguila eléctrica Paiche Piraña roja Raya motoro / Raya de rio Tararira Mediterráneo Atún rojo Congrio Dorada real Manta raya Mero Sargo Islas Canarias Ángel de mar Caballito de mar Pez roca de Madeira Pez trompeta atlántico Tiburón Mako Vieja colorada Mar del Caribe Cirujano azul Gran barracuda / Picúa Pez ángel francés pez ángel reina Raya jaspeada Robalo blanco Mar Rojo Mero del Coral Morena gigante Pez león Pez Napoléon Raya de arrecife Vieja florida Especies comunes Betta Splendens Chupa algas Corydoras Discos Escalar Gamba Red Cherry Guppy Pez dorado Pez payaso Grupos temáticos Cíclidos enanos Killis Lochas Luchadores Peces gato Tetras Vivíparos Práctica Peces compatibles 20 L Peces compatibles 40 L Peces compatibles 60 L Peces compatibles 80 L Peces compatibles 100 L El proyecto Fishipedia Nuestra ética Proyecto Yaku Nawi Los fotógrafos colaboradores CONTÁCTANOS Enciclopedia Peces Ballestas Barracudas Doradas y sargos Escorpenas Hipocampos Lábridos Morenas Peces cirujano Peces globo Peces payaso Rayas Tiburones Reptiles Cocodrilos Serpientes Tortugas Moluscos Caracoles Nudibranquios Calamares Pulpos Sepias Otros temas Anfibios Cnidarios Crustáceos Explorar Amazonas Anaconda gigante Anguila eléctrica Paiche Piraña roja Raya motoro / Raya de rio Tararira Mediterráneo Atún rojo Congrio Dorada real Manta raya Mero Sargo Islas Canarias Ángel de mar Caballito de mar Pez roca de Madeira Pez trompeta atlántico Tiburón Mako Vieja colorada Mar del Caribe Cirujano azul Gran barracuda / Picúa Pez ángel francés pez ángel reina Raya jaspeada Robalo blanco Mar Rojo Mero del Coral Morena gigante Pez león Pez Napoléon Raya de arrecife Vieja florida Acuariofilia Especies comunes Betta Splendens Chupa algas Corydoras Discos Escalar Gamba Red Cherry Guppy Pez dorado Pez payaso Grupos temáticos Cíclidos enanos Killis Lochas Luchadores Peces gato Tetras Vivíparos Práctica Peces compatibles 20 L Peces compatibles 40 L Peces compatibles 60 L Peces compatibles 80 L Peces compatibles 100 L A propósito El proyecto Fishipedia Nuestra ética Proyecto Yaku Nawi Los fotógrafos colaboradores CONTÁCTANOS Prensa",
    "image": "",
    "mapImage": ""
  },
  {
    "name": "Dicentrarchus labrax",
    "sciname": "",
    "IUCN": "",
    "description": "Introducción La lubina, también conocida como róbalo, es un pez emblemático de las costas europeas, presente desde el Mar del Norte hasta el Mediterráneo. Su abundancia varía según las regiones y la presión pesquera. Fácilmente observable desde la superficie, este pez resulta un buen indicador de la calidad de los ecosistemas marinos costeros. En Francia es uno de los pescados más consumidos: en 2019 se vendieron 4.204 toneladas, un mercado valorado en más de 58 millones de euros. Su cría en granjas acuícolas está aumentando en toda Europa. ¿Quién es ella?  Dicentrarchus Las especies del género Dicentrarchus pertenecen a la familia moronidae. Hoy en día, este género engloba a dos especies: Dicentrarchus labras (lubina común) y Dicentrarchus punctatus (baila). Los peces de este género presentan un tamaño mediano a grande (40 a 70 centímetros), con un cuerpo fusiforme, ligeramente comprimido en los costados. Los ejemplares más grandes pueden llegar a alcanzar 1 metro y 15 kilos. De color plateado o con manchas, siempre en tonos grises. A menudo se encuentran formando cardúmenes en las áreas rocosas de las aguas costeras poco profundas (menos de 100 metros). Son depredadores de cabeza grande y les gusta esconderse en las corrientes para sorprender a sus presas. Poseen dos aletas dorsales, la primera de ellas con espinas. Las pectorales son largas y puntiagudas. Tres espinas están presentes en la aleta anal. Estas especies son apreciadas por su carne. Debido a la pesca intensiva sus poblaciones está disminuyendo, a día de hoy.  Tamaño medio 50 cm Tamaño máximo 100 cm Longevidad 30 años Forma Oval Dicentrarchus labrax, lubina © Xaime Beiro Dicentrarchus labrax, lubina © Xaime Beiro Previous Next Tamaño medio 50 cm Tamaño máximo 100 cm Longevidad 30 años Forma Oval ¿Cómo reconocer a Este pez ? La lubina es un pez alargado de color plateado. El dorso y la cola tienden a ser de un gris más oscuro mientras que la zona de los flancos se aclara progresivamente al acercarse al vientre. Este pez posee dos aletas dorsales, la primera de ellas con unas diez espinas, mientras que la segunda presenta tan solo una. La aleta anal tiene tres espinas y unos diez radios blandos. El cuerpo aparece cubierto de escamas, con una línea que une la parte superior de las branquias con la aleta caudal, sin llegar a cubrirla. En algunos ejemplares pueden observarse una serie de reflejos de color azulado en la zona del dorso, mientras que el vientre puede ser ligeramente amarillo. Diferencias entre machos y hembras En esta especie no existe dimorfismo entre macho y hembra. Modo de vida y comportamiento dieta carnívoro Sociabilidad grupos o en solitario territorial No Modo de vida Diurno Las lubinas son peces rápidos y activos con una tendencia gregaria. Los juveniles habitan cerca de la costa, en las aguas poco profundas. A medida que crecen, comienzan a frecuentar los fondos irregulares, formados por rocas, guijarros y arena, alejándose de las costas. Estos entornos les proporcionan tanto zonas para esconderse como zonas de caza. Se trata de una especie carnívora, considerada como una gran cazadora. En mar abierto atacan a otros peces y cefalópodos mientras que cerca de la costa tienen como presas a pequeños crustáceos y otros organismos menores. Reproducción Gonocóricas, su fecundación es externa, la cría se da una vez al año. La temporada de reproducción comienza en agosto en las aguas más cálidas y puede extenderse durante varios meses cuando migra hacia aguas más frías. La puesta se realiza en invierno, entre los meses de diciembre y marzo, en el Atlántico y en los mares más fríos. La temperatura del agua debe estar entre 12 y 14°C. Especies inofensivas Esta especie no supone ningún peligro en particular para los humanos en caso de encuentro en su medio natural. Origen y distribución Origen Mar Mediterráneo Mar Negro Océano Atlántico templado oriental Islas Islas Canarias Cerdeña Sicilia Presencia geográfica y estado de la población La lubina se encuentra principalmente en el mar Mediterráneo y en las costas atlánticas europeas. Está presente también en el Mar del Norte y en el Canal de la Mancha. Las poblaciones más meridionales se han registrado en el Mar Rojo y el norte de África. Aunque no es una especie amenazada a corto plazo, si se observa una disminución en el tamaño de las capturas, lo que sugiere que se capturan cada vez más, ejemplares jóvenes que no han llegado a alcanzar su madurez sexual. Varios países europeos, incluidos Francia e Irlanda, han implementado políticas con el fin de salvaguardar esta especie, restringiendo el tamaño de las capturas y el período de pesca. Estas limitaciones son aún algo tímidas aunque marcan el inicio de un plan de conservación de la especie. La lubina tiene la capacidad de adaptarse tanto a las aguas frías del Canal de la Mancha como a las aguas más cálidas del Mediterráneo. Sin embargo, algunos estudios han demostrado que el aumento de CO2 en las aguas trastorna las capacidades olfativas de esta especie, aumentando su dificultad para alimentarse. Por lo tanto, una acidificación del Mediterráneo podría tener consecuencias significativas para las poblaciones de esta especie. Una lubina tenía un 100% de posibilidades de reproducirse cuando alcanzaba los 42 centímetros de tamaño, sin embargo la talla de captura autorizada para los pescadores profesionales en Europa se mantiene por debajo de este tamaño (en torno a los 36 centímetros). Por lo tanto, en algunas ocasiones los peces capturados no han tenido tiempo para reproducirse. Aunque sensible al estrés y a diferentes virus, la lubina es hoy en día una de las especies más estudiadas en el contexto de la acuicultura. El futuro de las poblaciones salvajes puede depender de estas nuevas granjas de reproducción. Estado de conservación de las poblaciones (UICN) Mundo : NT ¿Dónde observar esta especie? ¿Cuál es su hábitat? Características del entorno natural Profundidad 0 - 100 m Corriente Fuerte y Moderada Presentación del biotopo Esta especie es bentopelágica. Frecuenta las zonas costeras, especialmente los fondos rocosos cubiertos de arena. Prefiriendo las zonas donde el agua está en movimiento y oxigenada. Se encuentran principalmente en profundidades inferiores a 100 metros. Especie del mismo biotopo sargo común Sparidae blenio del Atlántico Blenniidae pez verde Labridae doncella común Labridae sargo picudo Sparidae chopa Sparidae Previous Next Para saber más Para leer en la web Fuentes y realización Participación y validación El equipo de Fishipedia y sus colaboradores especializados se comprometen a proporcionar contenido de alta calidad. Sin embargo, aunque la información proviene de fuentes científicas o testimonios de especialistas, los archivos pueden contener imprecisiones. Benoit Chartrer Marc Raggi Silvia Gomez Marine Kassel Traducción Traducción realizada con la valiosa contribución de nuestros traductores, quienes hacen que esta información esté disponible para un público más amplio. Silvia Gomez Referencias bibliográficas Cycle sexuel et fécondité du LoupDicentrarchus labrax - - 0. PRODUCTION DE JUVENILES DE BAR (Dicentrarchs labrax) EN MARAIS - O. Boussard - v. Buchet - H. Palvadeau - - 1995. Interactúa con Fishipedia Para ponerse en contacto con nuestro equipo o participar en nuestro proyecto. Contribuya a esta página Plantilla y contenido © Fishipedia - Reproducción no autorizada sin solicitud previa - ISSN 2270-7247 - Última actualización el 14/11/2023 © Fishipedia.fr 2024",
    "genderDescription": "Moronidae",
    "type": "",
    "size": "50 cm",
    "maxSize": "100 cm",
    "mimetism": "",
    "recognize": "",
    "fe/maleDifferences": "En esta especie no existe dimorfismo entre macho y hembra.",
    "diet": "carnívoro",
    "territorial": "No",
    "social": "grupos o en solitario",
    "lifeMode": "dieta",
    "lifeDescription": "",
    "reproductionMode": "<  lubina  Dicentrarchus labrax  Linnaeus  1758  (Mundo) NT  Moronidae  Dicentrarchus",
    "migration": "",
    "reproductionDescription": "",
    "poison": "",
    "danger": "",
    "depth": "Enciclopedia Explorar Acuariofilia A propósito Prensa Peces Ballestas Barracudas Doradas y sargos Escorpenas Hipocampos Lábridos Morenas Peces cirujano Peces globo Peces payaso Rayas Tiburones Reptiles Cocodrilos Serpientes Tortugas Moluscos Caracoles Nudibranquios Calamares Pulpos Sepias Otros temas Anfibios Cnidarios Crustáceos Amazonas Anaconda gigante Anguila eléctrica Paiche Piraña roja Raya motoro / Raya de rio Tararira Mediterráneo Atún rojo Congrio Dorada real Manta raya Mero Sargo Islas Canarias Ángel de mar Caballito de mar Pez roca de Madeira Pez trompeta atlántico Tiburón Mako Vieja colorada Mar del Caribe Cirujano azul Gran barracuda / Picúa Pez ángel francés pez ángel reina Raya jaspeada Robalo blanco Mar Rojo Mero del Coral Morena gigante Pez león Pez Napoléon Raya de arrecife Vieja florida Especies comunes Betta Splendens Chupa algas Corydoras Discos Escalar Gamba Red Cherry Guppy Pez dorado Pez payaso Grupos temáticos Cíclidos enanos Killis Lochas Luchadores Peces gato Tetras Vivíparos Práctica Peces compatibles 20 L Peces compatibles 40 L Peces compatibles 60 L Peces compatibles 80 L Peces compatibles 100 L El proyecto Fishipedia Nuestra ética Proyecto Yaku Nawi Los fotógrafos colaboradores CONTÁCTANOS Enciclopedia Peces Ballestas Barracudas Doradas y sargos Escorpenas Hipocampos Lábridos Morenas Peces cirujano Peces globo Peces payaso Rayas Tiburones Reptiles Cocodrilos Serpientes Tortugas Moluscos Caracoles Nudibranquios Calamares Pulpos Sepias Otros temas Anfibios Cnidarios Crustáceos Explorar Amazonas Anaconda gigante Anguila eléctrica Paiche Piraña roja Raya motoro / Raya de rio Tararira Mediterráneo Atún rojo Congrio Dorada real Manta raya Mero Sargo Islas Canarias Ángel de mar Caballito de mar Pez roca de Madeira Pez trompeta atlántico Tiburón Mako Vieja colorada Mar del Caribe Cirujano azul Gran barracuda / Picúa Pez ángel francés pez ángel reina Raya jaspeada Robalo blanco Mar Rojo Mero del Coral Morena gigante Pez león Pez Napoléon Raya de arrecife Vieja florida Acuariofilia Especies comunes Betta Splendens Chupa algas Corydoras Discos Escalar Gamba Red Cherry Guppy Pez dorado Pez payaso Grupos temáticos Cíclidos enanos Killis Lochas Luchadores Peces gato Tetras Vivíparos Práctica Peces compatibles 20 L Peces compatibles 40 L Peces compatibles 60 L Peces compatibles 80 L Peces compatibles 100 L A propósito El proyecto Fishipedia Nuestra ética Proyecto Yaku Nawi Los fotógrafos colaboradores CONTÁCTANOS Prensa",
    "image": "",
    "mapImage": ""
  },
  {
    "name": "Dicentrarchus punctatus",
    "sciname": "",
    "IUCN": "",
    "description": "Introducción Dicentrarchus punctatus, comúnmente conocido como baila o lubina de puntos, es una especie de la familia Moronidae. Se encuentra principalmente en las costas del Atlántico y en el mar Mediterráneo, aunque también se han registrado poblaciones en el golfo de Suez. Esta especie, poco conocida, se encuentra sujeta a ciertas regulaciones de pesca, especialmente en cuanto al tamaño mínimo de las capturas. La lubina no es directamente sensible al calor y se adapta tanto a las aguas frías del Canal de la Mancha como a las aguas más cálidas del Mediterráneo. Sin embargo, algunos estudios han demostrado que el aumento de CO2 en el agua perturba sus habilidades olfativas, aumentando su dificultad para alimentarse. Por lo tanto, la acidificación del Mediterráneo podría tener consecuencias importantes en el estado de sus poblaciones. ¿Quién es ella?  Dicentrarchus Las especies del género Dicentrarchus pertenecen a la familia moronidae. Hoy en día, este género engloba a dos especies: Dicentrarchus labras (lubina común) y Dicentrarchus punctatus (baila). Los peces de este género presentan un tamaño mediano a grande (40 a 70 centímetros), con un cuerpo fusiforme, ligeramente comprimido en los costados. Los ejemplares más grandes pueden llegar a alcanzar 1 metro y 15 kilos. De color plateado o con manchas, siempre en tonos grises. A menudo se encuentran formando cardúmenes en las áreas rocosas de las aguas costeras poco profundas (menos de 100 metros). Son depredadores de cabeza grande y les gusta esconderse en las corrientes para sorprender a sus presas. Poseen dos aletas dorsales, la primera de ellas con espinas. Las pectorales son largas y puntiagudas. Tres espinas están presentes en la aleta anal. Estas especies son apreciadas por su carne. Debido a la pesca intensiva sus poblaciones está disminuyendo, a día de hoy.  Tamaño medio 30 cm Tamaño máximo 70 cm Forma Oval Patrón manchas Dicentrarchus punctatus, baila © Benoit Chartrer Dicentrarchus punctatus, baila © Thomas Menut Previous Next Tamaño medio 30 cm Tamaño máximo 70 cm Forma Oval Patrón manchas ¿Cómo reconocer a Este pez ? Se trata de un pez alargado de color plateado. El dorso y la cola tienden hacia un gris más pronunciado, mientras que los flancos se aclaran a medida que se acercan al vientre. Se distingue fácilmente de la lubina común ya que su cuerpo está cubierto de manchas oscuras en el dorso y los flancos. También posee una mancha negra en la zona del opérculo. Al igual que su congénere, este pez posee dos aletas dorsales, la primera con una decena de espinas, mientras que la segunda solo tiene una. La aleta anal cuenta con tres espinas y una decena de radios blandos. Diferencias entre machos y hembras En esta especie el macho y la hembra no son fácilmente distinguibles. Modo de vida y comportamiento dieta carnívoro Sociabilidad grupos o en solitario territorial No Modo de vida Diurno Se trata de peces rápidos y activos, con una tendencia a ser gregarios. Las crías viven cerca de la costa, en aguas poco profundas. A medida que crecen, se alejan de la costa y se acercan a fondos compuestos principalmente por rocas, guijarros y arena, que proporcionan escondites y áreas de caza propicias. Estos peces son exclusivamente carnívoros. En alta mar, se alimentan de peces y cefalópodos, mientras que en las cercanías de la costa, se centran en pequeños camarones, moluscos y otros peces de menor tamaño. Reproducción Gonocóricos, su fecundación es externa. Estos peces se reproducen una vez al año. La temporada comienza en agosto en aguas más cálidas y puede extenderse durante varios meses a medida que se desplazan hacia aguas más frías. La puesta de huevos tiene lugar en invierno, desde diciembre hasta marzo, aunque se encuentra desfasada en el Atlántico y en mares más fríos. La temperatura del agua debe estar comprendida entre 12 y 14°C. Especies inofensivas Esta especie no representa un peligro particular para los humanos en caso de encuentro en su entorno natural. Origen y distribución Origen Mar Mediterráneo Océano Atlántico templado oriental Océano Atlántico tropical oriental Islas Islas Canarias Cerdeña Sicilia Presencia geográfica y estado de la población Dicentrarchus punctatus se encuentra principalmente en las aguas del Atlántico Este, desde el Canal de la Mancha hasta Senegal. También está registrado en las Islas Canaria y puede encontrarse en las costas del Mar Mediterráneo y en el golfo de Suez. Esta especie se agrupa para desovar frente a las costas y en aguas más profundas, de enero a marzo en el golfo de Vizcaya, de abril a junio en el sur del Mar del Norte y de marzo a mayo en las zonas intermedias. Durante este período, debido a estas concentraciones, se convierte en objetivo principal de los pescadores. Estado de conservación de las poblaciones (UICN) Mundo : LC ¿Cuál es su hábitat? Características del entorno natural Profundidad 0 - 30 m Presentación del biotopo Esta especie es pelágica y suele frecuentar las zonas costeras, especialmente las áreas rocosas con fondos arenosos. Prefiere las áreas donde el agua es rápida y bien oxigenada. Por lo general, se encuentra a profundidades inferiores a 100 metros y en algunas ocasiones ha sido avistado en estuarios. Especie del mismo biotopo pez verde Labridae pez pipa de rayas negras Syngnathidae raya mosaico Rajidae aguja de mar Syngnathidae vieja colorada Scaridae gorrión Labridae Previous Next Para saber más Para leer en la web Fuentes y realización Participación y validación El equipo de Fishipedia y sus colaboradores especializados se comprometen a proporcionar contenido de alta calidad. Sin embargo, aunque la información proviene de fuentes científicas o testimonios de especialistas, los archivos pueden contener imprecisiones. Silvia Gomez Benoit Chartrer Traducción Traducción realizada con la valiosa contribución de nuestros traductores, quienes hacen que esta información esté disponible para un público más amplio. Silvia Gomez Interactúa con Fishipedia Para ponerse en contacto con nuestro equipo o participar en nuestro proyecto. Contribuya a esta página Plantilla y contenido © Fishipedia - Reproducción no autorizada sin solicitud previa - ISSN 2270-7247 - Última actualización el 18/11/2023 © Fishipedia.fr 2024",
    "genderDescription": "Moronidae",
    "type": "",
    "size": "30 cm",
    "maxSize": "70 cm",
    "mimetism": "",
    "recognize": "",
    "fe/maleDifferences": "En esta especie el macho y la hembra no son fácilmente distinguibles.",
    "diet": "carnívoro",
    "territorial": "No",
    "social": "grupos o en solitario",
    "lifeMode": "dieta",
    "lifeDescription": "",
    "reproductionMode": "<  baila  Dicentrarchus punctatus  Bloch  1792  (Mundo) LC  Moronidae  Dicentrarchus",
    "migration": "",
    "reproductionDescription": "",
    "poison": "",
    "danger": "",
    "depth": "Enciclopedia Explorar Acuariofilia A propósito Prensa Peces Ballestas Barracudas Doradas y sargos Escorpenas Hipocampos Lábridos Morenas Peces cirujano Peces globo Peces payaso Rayas Tiburones Reptiles Cocodrilos Serpientes Tortugas Moluscos Caracoles Nudibranquios Calamares Pulpos Sepias Otros temas Anfibios Cnidarios Crustáceos Amazonas Anaconda gigante Anguila eléctrica Paiche Piraña roja Raya motoro / Raya de rio Tararira Mediterráneo Atún rojo Congrio Dorada real Manta raya Mero Sargo Islas Canarias Ángel de mar Caballito de mar Pez roca de Madeira Pez trompeta atlántico Tiburón Mako Vieja colorada Mar del Caribe Cirujano azul Gran barracuda / Picúa Pez ángel francés pez ángel reina Raya jaspeada Robalo blanco Mar Rojo Mero del Coral Morena gigante Pez león Pez Napoléon Raya de arrecife Vieja florida Especies comunes Betta Splendens Chupa algas Corydoras Discos Escalar Gamba Red Cherry Guppy Pez dorado Pez payaso Grupos temáticos Cíclidos enanos Killis Lochas Luchadores Peces gato Tetras Vivíparos Práctica Peces compatibles 20 L Peces compatibles 40 L Peces compatibles 60 L Peces compatibles 80 L Peces compatibles 100 L El proyecto Fishipedia Nuestra ética Proyecto Yaku Nawi Los fotógrafos colaboradores CONTÁCTANOS Enciclopedia Peces Ballestas Barracudas Doradas y sargos Escorpenas Hipocampos Lábridos Morenas Peces cirujano Peces globo Peces payaso Rayas Tiburones Reptiles Cocodrilos Serpientes Tortugas Moluscos Caracoles Nudibranquios Calamares Pulpos Sepias Otros temas Anfibios Cnidarios Crustáceos Explorar Amazonas Anaconda gigante Anguila eléctrica Paiche Piraña roja Raya motoro / Raya de rio Tararira Mediterráneo Atún rojo Congrio Dorada real Manta raya Mero Sargo Islas Canarias Ángel de mar Caballito de mar Pez roca de Madeira Pez trompeta atlántico Tiburón Mako Vieja colorada Mar del Caribe Cirujano azul Gran barracuda / Picúa Pez ángel francés pez ángel reina Raya jaspeada Robalo blanco Mar Rojo Mero del Coral Morena gigante Pez león Pez Napoléon Raya de arrecife Vieja florida Acuariofilia Especies comunes Betta Splendens Chupa algas Corydoras Discos Escalar Gamba Red Cherry Guppy Pez dorado Pez payaso Grupos temáticos Cíclidos enanos Killis Lochas Luchadores Peces gato Tetras Vivíparos Práctica Peces compatibles 20 L Peces compatibles 40 L Peces compatibles 60 L Peces compatibles 80 L Peces compatibles 100 L A propósito El proyecto Fishipedia Nuestra ética Proyecto Yaku Nawi Los fotógrafos colaboradores CONTÁCTANOS Prensa",
    "image": "",
    "mapImage": ""
  },
  {
    "name": "Diplodus annularis",
    "sciname": "",
    "IUCN": "",
    "description": "Introducción Diplodus annularis, se encuentra presente en la costa este del océano Atlántico, desde Mauritania hasta Bretaña. Aunque también es posible observarlo en el mar Negro y en el Mediterráneo. Su abundancia varía según la región y la presión pesquera. Fácilmente observable desde la superficie, esta especie es un buen indicador de la calidad de los ecosistemas marinos costeros. ¿Quién es él?  Diplodus Las especies del género Diplodus son conocidas comúnmente como « sargos ». Pertenecen a la familia de los espáridos (Sparidae) que incluye también a las obladas y las doradas. Los sargos son peces de tamaño pequeño o mediano, con un cuerpo ovalado y comprimido lateralmente. Los especímenes más grandes pueden alcanzar los 50 cm. La mayoría presenta una coloración que va del amarillo al azulado, con reflejos plateados. Algunas especies pueden mostrar marcas, líneas o manchas oscuras sobre su cuerpo. Estos pequeños depredadores poseen una gran cabeza con una pequeña boca ligeramente protráctil que le permite capturar rápidamente a sus presas. El nombre dado a este género hace referencia a la doble fila de dientes que poseen estos peces (del griego diploos, que significa \"doble\", y odous que significa \"dientes\"). La dentadura está bien desarrollada y está constituida de caninos y molares. La aleta dorsal de estos peces posee una docena de espinas afiladas, contando con tres espinas más en la aleta anal. Las pectorales son largas y puntiagudas. En 2020, 23 especies de este género fueron censadas en todo el mundo, principalmente en los océanos Atlántico e Índico. Dos especies son endémicas del Mediterráneo: D. bellottii y D. levantinus. La mayor parte de esos peces son explotados con fines comerciales, en particular por las pequeñas pesquerías. Numerosas especies frecuentan las zonas del litoral. Pudiendo ser vistas formando bancos o pequeños grupos en las praderas marinas y zonas rocosas.  Tipo dorada y sargo Tamaño medio 13 cm Tamaño máximo 28 cm Forma Ovoide Patrón puntuación Diplodus annularis, raspallón © Thomas Menut Tipo dorada y sargo Tamaño medio 13 cm Tamaño máximo 28 cm Forma Ovoide Patrón puntuación ¿Cómo reconocer a Este pez ? Esta especie posee un cuerpo plano y de forma ovalada. Su tamaño oscila entre los 12 y 27,5 centímetros. La coloración es principalmente de un tono gris claro con algunos reflejos plateados y verdosos, la parte superior de la cabeza y la base de la aleta caudal son ligeramente amarillentas. Las aletas pélvicas son amarillas, al igual que los primeros radios de la aleta anal. Una mancha negra es observable a nivel del pedúnculo caudal. Los juveniles suelen ser de color amarillo y se transforman en gris plateado a medida que crecen (desde la cola hacia la cabeza). Diferencias entre machos y hembras El macho y la hembra no son fácilmente distinguibles. Aunque los sexos aparecen separados, se han reportado casos de hermafroditismo protándrico. Modo de vida y comportamiento dieta carnívoro Sociabilidad grupos o en solitario territorial No Modo de vida Diurno Este pez suele vivir en pequeños grupos, aunque en ocasiones se le observa también en solitario. Es un pez de carácter territorial y no resulta extraño presenciar ciertos enfrentamientos entre dos especímenes. En la naturaleza, este pequeño depredador se alimenta de mejillones y otros invertebrados en zonas rocosas. Su potente dentición le permite romper conchas y erizos de mar. Reproducción La madurez sexual en esta especie se alcanza aproximadamente a los 2 años, con un tamaño de alrededor de 10 centímetros. El desove depende de la temperatura del agua. Se extiende entre los meses de abril y junio en las poblaciones del Atlántico y hasta julio - septiembre para las poblaciones del mar Negro. Las larvas son planctónicas y los juveniles se pueden observar hasta a 15 metros de profundidad. Especies inofensivas Esta especie no representa un peligro particular para los humanos en caso de encuentro en su entorno natural. Origen y distribución Origen Mar Mediterráneo Mar Negro Océano Atlántico templado oriental Islas Islas Canarias Cerdeña Sicilia Presencia geográfica y estado de la población No hay ningún texto que especifique la distribución y la conservación de la especie. Estado de conservación de las poblaciones (UICN) Mundo : LC ¿Dónde observar esta especie? ¿Cuál es su hábitat? Características del entorno natural Profundidad 0 - 90 m Corriente Fuerte Presentación del biotopo De forma más común se le suele observar a una profundidad inferior a 90 metros. Más frecuentemente a poca profundidad (10-15 metros) y, en ocasiones, cerca de la superficie. Esta especie vive cerca de las zonas rocosas y sobre los prados de hierbas marinas. También se puede observar al raspallón en lagunas y puertos. Especie del mismo biotopo pez verde Labridae mojarra Sparidae blenio del Atlántico Blenniidae pez trompeta del atlántico oriental Aulostomidae sargo común Sparidae lubina Moronidae Previous Next Para saber más Especie de la misma familia dorada Sparidae pargo común Sparidae breca Sparidae salpa Sparidae oblada Sparidae chucla Sparidae chopa Sparidae Pagrus auriga Sparidae Previous Next Para leer en la web Fuentes y realización Participación y validación El equipo de Fishipedia y sus colaboradores especializados se comprometen a proporcionar contenido de alta calidad. Sin embargo, aunque la información proviene de fuentes científicas o testimonios de especialistas, los archivos pueden contener imprecisiones. Adrien Falzon Benoit Chartrer Julie Magnus Traducción Traducción realizada con la valiosa contribución de nuestros traductores, quienes hacen que esta información esté disponible para un público más amplio. Silvia Gomez Referencias bibliográficas Reproductive biology of four Diplodusspecies Diplodus vulgaris, D. annularis,D. sargus sargus and D. puntazzo (Sparidae)in the Gulf of Tunis (central Mediterranean) - N. Mouine - P. Francour - M.H. Ktari - N. Chakroun-Marzouk - Marine Biological Association of the United Kingdom - 2012. SPARIDAE - K.E. Carpenter - FAO Fisheries Synopsis - 0. Interactúa con Fishipedia Para ponerse en contacto con nuestro equipo o participar en nuestro proyecto. Contribuya a esta página Plantilla y contenido © Fishipedia - Reproducción no autorizada sin solicitud previa - ISSN 2270-7247 - Última actualización el 12/11/2023 © Fishipedia.fr 2024",
    "genderDescription": "Sparidae",
    "type": "",
    "size": "13 cm",
    "maxSize": "28 cm",
    "mimetism": "",
    "recognize": "",
    "fe/maleDifferences": "El macho y la hembra no son fácilmente distinguibles. Aunque los sexos aparecen separados, se han reportado casos de hermafroditismo protándrico.",
    "diet": "carnívoro",
    "territorial": "No",
    "social": "grupos o en solitario",
    "lifeMode": "dieta",
    "lifeDescription": "",
    "reproductionMode": "<  raspallón  Diplodus annularis  Linnaeus  1758  (Mundo) LC  Sparidae  Diplodus",
    "migration": "",
    "reproductionDescription": "",
    "poison": "",
    "danger": "",
    "depth": "Enciclopedia Explorar Acuariofilia A propósito Prensa Peces Ballestas Barracudas Doradas y sargos Escorpenas Hipocampos Lábridos Morenas Peces cirujano Peces globo Peces payaso Rayas Tiburones Reptiles Cocodrilos Serpientes Tortugas Moluscos Caracoles Nudibranquios Calamares Pulpos Sepias Otros temas Anfibios Cnidarios Crustáceos Amazonas Anaconda gigante Anguila eléctrica Paiche Piraña roja Raya motoro / Raya de rio Tararira Mediterráneo Atún rojo Congrio Dorada real Manta raya Mero Sargo Islas Canarias Ángel de mar Caballito de mar Pez roca de Madeira Pez trompeta atlántico Tiburón Mako Vieja colorada Mar del Caribe Cirujano azul Gran barracuda / Picúa Pez ángel francés pez ángel reina Raya jaspeada Robalo blanco Mar Rojo Mero del Coral Morena gigante Pez león Pez Napoléon Raya de arrecife Vieja florida Especies comunes Betta Splendens Chupa algas Corydoras Discos Escalar Gamba Red Cherry Guppy Pez dorado Pez payaso Grupos temáticos Cíclidos enanos Killis Lochas Luchadores Peces gato Tetras Vivíparos Práctica Peces compatibles 20 L Peces compatibles 40 L Peces compatibles 60 L Peces compatibles 80 L Peces compatibles 100 L El proyecto Fishipedia Nuestra ética Proyecto Yaku Nawi Los fotógrafos colaboradores CONTÁCTANOS Enciclopedia Peces Ballestas Barracudas Doradas y sargos Escorpenas Hipocampos Lábridos Morenas Peces cirujano Peces globo Peces payaso Rayas Tiburones Reptiles Cocodrilos Serpientes Tortugas Moluscos Caracoles Nudibranquios Calamares Pulpos Sepias Otros temas Anfibios Cnidarios Crustáceos Explorar Amazonas Anaconda gigante Anguila eléctrica Paiche Piraña roja Raya motoro / Raya de rio Tararira Mediterráneo Atún rojo Congrio Dorada real Manta raya Mero Sargo Islas Canarias Ángel de mar Caballito de mar Pez roca de Madeira Pez trompeta atlántico Tiburón Mako Vieja colorada Mar del Caribe Cirujano azul Gran barracuda / Picúa Pez ángel francés pez ángel reina Raya jaspeada Robalo blanco Mar Rojo Mero del Coral Morena gigante Pez león Pez Napoléon Raya de arrecife Vieja florida Acuariofilia Especies comunes Betta Splendens Chupa algas Corydoras Discos Escalar Gamba Red Cherry Guppy Pez dorado Pez payaso Grupos temáticos Cíclidos enanos Killis Lochas Luchadores Peces gato Tetras Vivíparos Práctica Peces compatibles 20 L Peces compatibles 40 L Peces compatibles 60 L Peces compatibles 80 L Peces compatibles 100 L A propósito El proyecto Fishipedia Nuestra ética Proyecto Yaku Nawi Los fotógrafos colaboradores CONTÁCTANOS Prensa",
    "image": "",
    "mapImage": ""
  },
  {
    "name": "Diplodus cervinus",
    "sciname": "",
    "IUCN": "",
    "description": "Introducción Diplodus cervinus, comúnmente conocido como sargo real o sargo breado. Existen tres subespecies: hottentotus (océano Índico), omanensis (desde Sudáfrica hasta el mar de Arabia) y cervinus (mar del Norte, mar Mediterráneo y océano Atlántico Este). Apreciado por su carne, este pez parece estar bajo una fuerte presión presquera. Su rápido crecimiento lo hace interesante para la acuicultura. Sin embargo, es una especie bastante sensible al estrés, lo que dificulta su cría a gran escala. ¿Quién es él?  Diplodus Las especies del género Diplodus son conocidas comúnmente como « sargos ». Pertenecen a la familia de los espáridos (Sparidae) que incluye también a las obladas y las doradas. Los sargos son peces de tamaño pequeño o mediano, con un cuerpo ovalado y comprimido lateralmente. Los especímenes más grandes pueden alcanzar los 50 cm. La mayoría presenta una coloración que va del amarillo al azulado, con reflejos plateados. Algunas especies pueden mostrar marcas, líneas o manchas oscuras sobre su cuerpo. Estos pequeños depredadores poseen una gran cabeza con una pequeña boca ligeramente protráctil que le permite capturar rápidamente a sus presas. El nombre dado a este género hace referencia a la doble fila de dientes que poseen estos peces (del griego diploos, que significa \"doble\", y odous que significa \"dientes\"). La dentadura está bien desarrollada y está constituida de caninos y molares. La aleta dorsal de estos peces posee una docena de espinas afiladas, contando con tres espinas más en la aleta anal. Las pectorales son largas y puntiagudas. En 2020, 23 especies de este género fueron censadas en todo el mundo, principalmente en los océanos Atlántico e Índico. Dos especies son endémicas del Mediterráneo: D. bellottii y D. levantinus. La mayor parte de esos peces son explotados con fines comerciales, en particular por las pequeñas pesquerías. Numerosas especies frecuentan las zonas del litoral. Pudiendo ser vistas formando bancos o pequeños grupos en las praderas marinas y zonas rocosas.  Tipo dorada y sargo Tamaño medio 35 cm Tamaño máximo 55 cm Forma Ovoide Patrón líneas verticales Diplodus cervinus, sargo breado © Thomas Menut Diplodus cervinus, sargo breado © Xaime Beiro Previous Next Tipo dorada y sargo Tamaño medio 35 cm Tamaño máximo 55 cm Forma Ovoide Patrón líneas verticales ¿Cómo reconocer a Este pez ? Como sucede con otros sargos, el cuerpo es plano y con forma de ovoide. El tamaño promedio es de 35 cm, aunque algunos especímenes pueden superan los 55 cm. Es menos probable encontrar peces de estos tamaños debido a la presión pesquera. El cuerpo es de color gris claro con reflejos plateados y dorados. Cinco bandas verticales oscuras atraviesan el cuerpo. La primera está ubicada en la parte delantera de la aleta dorsal y la última en el pedúnculo caudal. La cabeza también está marcada por una banda negra vertical que pasa por el ojo. Durante el período de reproducción, es observable una mancha amarilla subocular. Esta especie tiene numerosas espinas puntiagudas: 11 o 12 en la aleta dorsal y 3 en la caudal. Estas últimas son grisáceas y las pélvicas son más oscuras. El hocico es puntiagudo y termina en un color más oscuro. La boca es ligeramente protráctil y se caracteriza por la presencia de unos gruesos labios. Diferencias entre machos y hembras Al igual que en otros sargos, la diferenciación sexual es difícil. Modo de vida y comportamiento dieta carnívoro Sociabilidad grupos o en solitario territorial No Modo de vida Diurno Este pez suele vivir en pequeños grupos de menos de diez ejemplares. Aunque son relativamente raros en el Mediterráneo, a veces se observan con otros sargos (D. vulgaris y D. sargus sargus). Los juveniles son omnívoros, se alimentan de algas, mejillones y otros invertebrados, mientras que los adultos son principalmente carnívoros. En aguas poco profundas, este pez se halla en áreas rocosas, mientras que en aguas más profundas tiende a habitar zonas de lodo. Reproducción Hermafrodita Protándrico La madurez sexual en esta especie se alcanza a los 2 años, con un tamaño cercano a los 25 cm. El cambio de sexo tiene lugar a los 5 años, y algunos estudios han demostrado que al menos parte de los individuos experimentan este cambio durante su crecimiento. En el Mediterráneo, la reproducción tiene lugar durante la primavera y el verano. El periodo de desove varía según la temperatura del agua. Las larvas son pelágicas y regresan posteriormente a las costas. Especies inofensivas Esta especie no supone ningún peligro en particular para el ser humano cuando se encuentra en su entorno natural. Origen y distribución Origen Mar Mediterráneo Océano Atlántico templado oriental Océano Atlántico Oriental Frío Islas Córcega Islas Canarias Cerdeña Sicilia Presencia geográfica y estado de la población Aunque esta especie se encuentra ampliamente distribuida, es poco común en gran parte de su área. A menudo se encuentra ausente en los registros de peces del Mediterráneo y no se dispone de datos suficientes para evaluar el estado de las poblaciones. Estado de conservación de las poblaciones (UICN) Mundo : LC ¿Dónde observar esta especie? ¿Cuál es su hábitat? Características del entorno natural Profundidad 25 - 300 m Presentación del biotopo Aunque esta especie ha sido registrada hasta a 300 metros de profundidad, generalmente se encuentra en fondos rocosos en zonas de 30 metros de profundidad. Benti-pelágico, este pez también puede encontrarse en solitario en fondos fangosos o arenosos. Especie del mismo biotopo boga Sparidae aguja de mar Syngnathidae tordo verde Labridae sargo picudo Sparidae serrano Serranidae pez herrera Sparidae Previous Next Para saber más Especie de la misma familia Pagrus auriga Sparidae sargo chopa Sparidae Pagellus acarne Sparidae chopa Sparidae boga Sparidae Spicara smaris Sparidae pez herrera Sparidae oblada Sparidae Previous Next Para leer en la web Fuentes y realización Participación y validación El equipo de Fishipedia y sus colaboradores especializados se comprometen a proporcionar contenido de alta calidad. Sin embargo, aunque la información proviene de fuentes científicas o testimonios de especialistas, los archivos pueden contener imprecisiones. Adrien Falzon Benoit Chartrer Julie Magnus Traducción Traducción realizada con la valiosa contribución de nuestros traductores, quienes hacen que esta información esté disponible para un público más amplio. Silvia Gomez Referencias bibliográficas Âge, croissance et reproduction du sar tambour Diplodus cervinus cervinus (Sparidae) des côtes de l’Est algérien - Farid Derbal - M. Hichem Kara - sfi-cybium - 2013. Editor: G. Duhame SPARIDAE - K.E. Carpenter - FAO Fisheries Synopsis - 0. Editor: G. Duhame Interactúa con Fishipedia Para ponerse en contacto con nuestro equipo o participar en nuestro proyecto. Contribuya a esta página Plantilla y contenido © Fishipedia - Reproducción no autorizada sin solicitud previa - ISSN 2270-7247 - Última actualización el 23/11/2023 © Fishipedia.fr 2024",
    "genderDescription": "Sparidae",
    "type": "",
    "size": "35 cm",
    "maxSize": "55 cm",
    "mimetism": "",
    "recognize": "",
    "fe/maleDifferences": "Al igual que en otros sargos, la diferenciación sexual es difícil.",
    "diet": "carnívoro",
    "territorial": "No",
    "social": "grupos o en solitario",
    "lifeMode": "dieta",
    "lifeDescription": "",
    "reproductionMode": "Enciclopedia Explorar Acuariofilia A propósito Prensa Peces Ballestas Barracudas Doradas y sargos Escorpenas Hipocampos Lábridos Morenas Peces cirujano Peces globo Peces payaso Rayas Tiburones Reptiles Cocodrilos Serpientes Tortugas Moluscos Caracoles Nudibranquios Calamares Pulpos Sepias Otros temas Anfibios Cnidarios Crustáceos Amazonas Anaconda gigante Anguila eléctrica Paiche Piraña roja Raya motoro / Raya de rio Tararira Mediterráneo Atún rojo Congrio Dorada real Manta raya Mero Sargo Islas Canarias Ángel de mar Caballito de mar Pez roca de Madeira Pez trompeta atlántico Tiburón Mako Vieja colorada Mar del Caribe Cirujano azul Gran barracuda / Picúa Pez ángel francés pez ángel reina Raya jaspeada Robalo blanco Mar Rojo Mero del Coral Morena gigante Pez león Pez Napoléon Raya de arrecife Vieja florida Especies comunes Betta Splendens Chupa algas Corydoras Discos Escalar Gamba Red Cherry Guppy Pez dorado Pez payaso Grupos temáticos Cíclidos enanos Killis Lochas Luchadores Peces gato Tetras Vivíparos Práctica Peces compatibles 20 L Peces compatibles 40 L Peces compatibles 60 L Peces compatibles 80 L Peces compatibles 100 L El proyecto Fishipedia Nuestra ética Proyecto Yaku Nawi Los fotógrafos colaboradores CONTÁCTANOS Enciclopedia Peces Ballestas Barracudas Doradas y sargos Escorpenas Hipocampos Lábridos Morenas Peces cirujano Peces globo Peces payaso Rayas Tiburones Reptiles Cocodrilos Serpientes Tortugas Moluscos Caracoles Nudibranquios Calamares Pulpos Sepias Otros temas Anfibios Cnidarios Crustáceos Explorar Amazonas Anaconda gigante Anguila eléctrica Paiche Piraña roja Raya motoro / Raya de rio Tararira Mediterráneo Atún rojo Congrio Dorada real Manta raya Mero Sargo Islas Canarias Ángel de mar Caballito de mar Pez roca de Madeira Pez trompeta atlántico Tiburón Mako Vieja colorada Mar del Caribe Cirujano azul Gran barracuda / Picúa Pez ángel francés pez ángel reina Raya jaspeada Robalo blanco Mar Rojo Mero del Coral Morena gigante Pez león Pez Napoléon Raya de arrecife Vieja florida Acuariofilia Especies comunes Betta Splendens Chupa algas Corydoras Discos Escalar Gamba Red Cherry Guppy Pez dorado Pez payaso Grupos temáticos Cíclidos enanos Killis Lochas Luchadores Peces gato Tetras Vivíparos Práctica Peces compatibles 20 L Peces compatibles 40 L Peces compatibles 60 L Peces compatibles 80 L Peces compatibles 100 L A propósito El proyecto Fishipedia Nuestra ética Proyecto Yaku Nawi Los fotógrafos colaboradores CONTÁCTANOS Prensa",
    "migration": "",
    "reproductionDescription": "",
    "poison": "",
    "danger": "",
    "depth": "Enciclopedia Explorar Acuariofilia A propósito Prensa Peces Ballestas Barracudas Doradas y sargos Escorpenas Hipocampos Lábridos Morenas Peces cirujano Peces globo Peces payaso Rayas Tiburones Reptiles Cocodrilos Serpientes Tortugas Moluscos Caracoles Nudibranquios Calamares Pulpos Sepias Otros temas Anfibios Cnidarios Crustáceos Amazonas Anaconda gigante Anguila eléctrica Paiche Piraña roja Raya motoro / Raya de rio Tararira Mediterráneo Atún rojo Congrio Dorada real Manta raya Mero Sargo Islas Canarias Ángel de mar Caballito de mar Pez roca de Madeira Pez trompeta atlántico Tiburón Mako Vieja colorada Mar del Caribe Cirujano azul Gran barracuda / Picúa Pez ángel francés pez ángel reina Raya jaspeada Robalo blanco Mar Rojo Mero del Coral Morena gigante Pez león Pez Napoléon Raya de arrecife Vieja florida Especies comunes Betta Splendens Chupa algas Corydoras Discos Escalar Gamba Red Cherry Guppy Pez dorado Pez payaso Grupos temáticos Cíclidos enanos Killis Lochas Luchadores Peces gato Tetras Vivíparos Práctica Peces compatibles 20 L Peces compatibles 40 L Peces compatibles 60 L Peces compatibles 80 L Peces compatibles 100 L El proyecto Fishipedia Nuestra ética Proyecto Yaku Nawi Los fotógrafos colaboradores CONTÁCTANOS Enciclopedia Peces Ballestas Barracudas Doradas y sargos Escorpenas Hipocampos Lábridos Morenas Peces cirujano Peces globo Peces payaso Rayas Tiburones Reptiles Cocodrilos Serpientes Tortugas Moluscos Caracoles Nudibranquios Calamares Pulpos Sepias Otros temas Anfibios Cnidarios Crustáceos Explorar Amazonas Anaconda gigante Anguila eléctrica Paiche Piraña roja Raya motoro / Raya de rio Tararira Mediterráneo Atún rojo Congrio Dorada real Manta raya Mero Sargo Islas Canarias Ángel de mar Caballito de mar Pez roca de Madeira Pez trompeta atlántico Tiburón Mako Vieja colorada Mar del Caribe Cirujano azul Gran barracuda / Picúa Pez ángel francés pez ángel reina Raya jaspeada Robalo blanco Mar Rojo Mero del Coral Morena gigante Pez león Pez Napoléon Raya de arrecife Vieja florida Acuariofilia Especies comunes Betta Splendens Chupa algas Corydoras Discos Escalar Gamba Red Cherry Guppy Pez dorado Pez payaso Grupos temáticos Cíclidos enanos Killis Lochas Luchadores Peces gato Tetras Vivíparos Práctica Peces compatibles 20 L Peces compatibles 40 L Peces compatibles 60 L Peces compatibles 80 L Peces compatibles 100 L A propósito El proyecto Fishipedia Nuestra ética Proyecto Yaku Nawi Los fotógrafos colaboradores CONTÁCTANOS Prensa",
    "image": "",
    "mapImage": ""
  },
  {
    "name": "Diplodus puntazzo",
    "sciname": "",
    "IUCN": "",
    "description": "Introducción El sargo picudo es un pez marino común del mar Mediterráneo. También está presente en el océano Atlántico, desde el estrecho de Gibraltar hasta la punta de África del Sur. Es objeto de numerosas pesquerías que utilizan todo tipo de técnicas: redes de enmalle, redes de arrastre, pesca con palangre y redes. En numerosas zonas también es pescado con línea. Debido a esta actividad pesquera es cada vez más difícil de observar en numerosos países, como Francia, pero aún sigue siendo frecuente en otras zonas como en el sur de Italia. Este pez está protegido desde 2006 por la Unión Europea. Toda captura de individuos de menos de 18 cm está prohibida, independientemente del tipo de pesca. Según algunos estudios científicos, la madurez sexual se alcanza a los 21 cm por lo que esta especie no debería ser capturada antes de alcanzar este tamaño. ¿Quién es él?  Diplodus Las especies del género Diplodus son conocidas comúnmente como « sargos ». Pertenecen a la familia de los espáridos (Sparidae) que incluye también a las obladas y las doradas. Los sargos son peces de tamaño pequeño o mediano, con un cuerpo ovalado y comprimido lateralmente. Los especímenes más grandes pueden alcanzar los 50 cm. La mayoría presenta una coloración que va del amarillo al azulado, con reflejos plateados. Algunas especies pueden mostrar marcas, líneas o manchas oscuras sobre su cuerpo. Estos pequeños depredadores poseen una gran cabeza con una pequeña boca ligeramente protráctil que le permite capturar rápidamente a sus presas. El nombre dado a este género hace referencia a la doble fila de dientes que poseen estos peces (del griego diploos, que significa \"doble\", y odous que significa \"dientes\"). La dentadura está bien desarrollada y está constituida de caninos y molares. La aleta dorsal de estos peces posee una docena de espinas afiladas, contando con tres espinas más en la aleta anal. Las pectorales son largas y puntiagudas. En 2020, 23 especies de este género fueron censadas en todo el mundo, principalmente en los océanos Atlántico e Índico. Dos especies son endémicas del Mediterráneo: D. bellottii y D. levantinus. La mayor parte de esos peces son explotados con fines comerciales, en particular por las pequeñas pesquerías. Numerosas especies frecuentan las zonas del litoral. Pudiendo ser vistas formando bancos o pequeños grupos en las praderas marinas y zonas rocosas.  Tipo dorada y sargo Tamaño medio 30 cm Tamaño máximo 60 cm Forma Ovoide Patrón líneas verticales Diplodus puntazzo, sargo picudo © Benoit Chartrer Diplodus puntazzo, sargo picudo © Thomas Menut Previous Next Tipo dorada y sargo Tamaño medio 30 cm Tamaño máximo 60 cm Forma Ovoide Patrón líneas verticales ¿Cómo reconocer a Este pez ? La mayoría de los individuos observados miden entre 20 y 30 cm, aunque los ejemplarees más grandes podrían llegar a alcanzar los 60 cm. Sin embargo, cada vez resulta más difícil encontrar peces de estos tamaños debido principalmente a la sobrepesca. El sargo picudo se asemeja al sargo breado, pero sus labios son delgados y sus rayas no presentan un color uniforme. El cuerpo es de color gris plateado, posee entre 6 y 7 rayas oscuras y entre 5 y 7 rayas claras. Sobre el pedúnculo caudal se observa una gran banda que desaparece con la edad. La cola aparece bordeada por un margen de negro. Al igual que en el sargo común, el resto de aletas son grisáceas. El cuerpo es de forma oval y está comprimido. Las aletas poseen espinas punzantes, 11 sobre la aleta dorsal y 3 sobre la anal. Diferencias entre machos y hembras No existe dimorfismo a simple vista en esta especie, sin embargo, los individuos de mayor tamaño son generalmente hembras. Modo de vida y comportamiento dieta carnívoro Sociabilidad grupos o en solitario territorial No Modo de vida Diurno Como ocurre con el resto de sargos, esta especie es de tendencia gregaria. Viviendo a veces asociado a otros sargos y doradas. Los ejemplares más jóvenes viven cerca de los pastos marinos y pueden remontar a veces a los estuarios. Los adultos frecuentan las zonas donde rompen las grandes olas antes de llegar a las primeras rocas. Permanecen al acecho cerca de las barreras rocosas donde cazan moluscos y crustáceos. Estos peces son omnívoros y complementan su régimen con diferentes tipos de plantas. Reproducción Hermafrodita Protándrico La mayoría de los individuos son hermafroditas, sin embargo, no todos los individuos cambian de sexo. La reproducción tiene lugar en los meses de julio a septiembre. Las larvas son al principio pelágicas, para volver después a los litorales. Los individuos alcanzan la madurez sexual después de los 3 años, con un tamaño superior a los 21 cm. Varios estudios demuestran que las recomendaciones de pesca para esta especie deberían ser revisadas para evitar la captura de los animales que no han alcanzado la madurez sexual, dejando así a todos los individuos la oportunidad de reproducirse. Especies inofensivas Esta especie no representa un peligro particular para los humanos en caso de encuentro en su entorno natural. Origen y distribución Origen Mar Mediterráneo Océano Atlántico templado oriental Islas Islas Canarias Cerdeña Sicilia Presencia geográfica y estado de la población Muy apreciado por su carne, este pez está protegido desde 2006 por la Unión Europea, toda captura de individuos de menos de 18 cm está prohibida, independientemente del tipo de pesca. Estado de conservación de las poblaciones (UICN) Mundo : LC ¿Dónde observar esta especie? ¿Cuál es su hábitat? Características del entorno natural Profundidad 0 - 150 m  Pelágico activo Corriente Fuerte Presentación del biotopo El sargo picudo puede ser observado hasta los 150 metros de profundidad. Sin embargo, es más frecuente encontrar a esta especie en los 50 primeros metros e incluso en superficie. Generalmente vive cerca de las zonas rocosas y sobre los pastos marinos. Aunque es un pez de carácter algo tímido, en las zonas de reserva, se muestra menos cuidadoso y puede ser abordado fácilmente. Especie del mismo biotopo pez verde Labridae pez trompeta del atlántico oriental Aulostomidae lubina Moronidae sargo común Sparidae mojarra Sparidae blenio del Atlántico Blenniidae Previous Next Para saber más Especie de la misma familia dentón común Sparidae dorada Sparidae Pagellus acarne Sparidae Pagrus auriga Sparidae Spicara smaris Sparidae chucla Sparidae pargo común Sparidae pez herrera Sparidae Previous Next Para leer en la web Fuentes y realización Participación y validación El equipo de Fishipedia y sus colaboradores especializados se comprometen a proporcionar contenido de alta calidad. Sin embargo, aunque la información proviene de fuentes científicas o testimonios de especialistas, los archivos pueden contener imprecisiones. Adrien Falzon Benoit Chartrer Julie Magnus Traducción Traducción realizada con la valiosa contribución de nuestros traductores, quienes hacen que esta información esté disponible para un público más amplio. Silvia Gomez Referencias bibliográficas Reproductive biology of four Diplodusspecies Diplodus vulgaris, D. annularis,D. sargus sargus and D. puntazzo (Sparidae)in the Gulf of Tunis (central Mediterranean) - N. Mouine - P. Francour - M.H. Ktari - N. Chakroun-Marzouk - Marine Biological Association of the United Kingdom - 2012. SPARIDAE - K.E. Carpenter - FAO Fisheries Synopsis - 0. Interactúa con Fishipedia Para ponerse en contacto con nuestro equipo o participar en nuestro proyecto. Contribuya a esta página Plantilla y contenido © Fishipedia - Reproducción no autorizada sin solicitud previa - ISSN 2270-7247 - Última actualización el 12/11/2023 © Fishipedia.fr 2024",
    "genderDescription": "Sparidae",
    "type": "",
    "size": "30 cm",
    "maxSize": "60 cm",
    "mimetism": "",
    "recognize": "",
    "fe/maleDifferences": "No existe dimorfismo a simple vista en esta especie, sin embargo, los individuos de mayor tamaño son generalmente hembras.",
    "diet": "carnívoro",
    "territorial": "No",
    "social": "grupos o en solitario",
    "lifeMode": "dieta",
    "lifeDescription": "",
    "reproductionMode": "<  sargo picudo  Diplodus puntazzo  Walbaum  1792  (Mundo) LC  Sparidae  Diplodus",
    "migration": "",
    "reproductionDescription": "",
    "poison": "",
    "danger": "",
    "depth": "Enciclopedia Explorar Acuariofilia A propósito Prensa Peces Ballestas Barracudas Doradas y sargos Escorpenas Hipocampos Lábridos Morenas Peces cirujano Peces globo Peces payaso Rayas Tiburones Reptiles Cocodrilos Serpientes Tortugas Moluscos Caracoles Nudibranquios Calamares Pulpos Sepias Otros temas Anfibios Cnidarios Crustáceos Amazonas Anaconda gigante Anguila eléctrica Paiche Piraña roja Raya motoro / Raya de rio Tararira Mediterráneo Atún rojo Congrio Dorada real Manta raya Mero Sargo Islas Canarias Ángel de mar Caballito de mar Pez roca de Madeira Pez trompeta atlántico Tiburón Mako Vieja colorada Mar del Caribe Cirujano azul Gran barracuda / Picúa Pez ángel francés pez ángel reina Raya jaspeada Robalo blanco Mar Rojo Mero del Coral Morena gigante Pez león Pez Napoléon Raya de arrecife Vieja florida Especies comunes Betta Splendens Chupa algas Corydoras Discos Escalar Gamba Red Cherry Guppy Pez dorado Pez payaso Grupos temáticos Cíclidos enanos Killis Lochas Luchadores Peces gato Tetras Vivíparos Práctica Peces compatibles 20 L Peces compatibles 40 L Peces compatibles 60 L Peces compatibles 80 L Peces compatibles 100 L El proyecto Fishipedia Nuestra ética Proyecto Yaku Nawi Los fotógrafos colaboradores CONTÁCTANOS Enciclopedia Peces Ballestas Barracudas Doradas y sargos Escorpenas Hipocampos Lábridos Morenas Peces cirujano Peces globo Peces payaso Rayas Tiburones Reptiles Cocodrilos Serpientes Tortugas Moluscos Caracoles Nudibranquios Calamares Pulpos Sepias Otros temas Anfibios Cnidarios Crustáceos Explorar Amazonas Anaconda gigante Anguila eléctrica Paiche Piraña roja Raya motoro / Raya de rio Tararira Mediterráneo Atún rojo Congrio Dorada real Manta raya Mero Sargo Islas Canarias Ángel de mar Caballito de mar Pez roca de Madeira Pez trompeta atlántico Tiburón Mako Vieja colorada Mar del Caribe Cirujano azul Gran barracuda / Picúa Pez ángel francés pez ángel reina Raya jaspeada Robalo blanco Mar Rojo Mero del Coral Morena gigante Pez león Pez Napoléon Raya de arrecife Vieja florida Acuariofilia Especies comunes Betta Splendens Chupa algas Corydoras Discos Escalar Gamba Red Cherry Guppy Pez dorado Pez payaso Grupos temáticos Cíclidos enanos Killis Lochas Luchadores Peces gato Tetras Vivíparos Práctica Peces compatibles 20 L Peces compatibles 40 L Peces compatibles 60 L Peces compatibles 80 L Peces compatibles 100 L A propósito El proyecto Fishipedia Nuestra ética Proyecto Yaku Nawi Los fotógrafos colaboradores CONTÁCTANOS Prensa",
    "image": "",
    "mapImage": ""
  },
  {
    "name": "Diplodus sargus",
    "sciname": "",
    "IUCN": "",
    "description": "Introducción El sargo común, Diplodus sargus, es uno de los peces emblemáticos de las costas europeas. Se encuentra presente desde el mar del Norte hasta el mar Mediterráneo. Su abundancia varía en función de la región y de la actividad pesquera. Esta especie es fácilmente observable desde la superficie y su presencia es un buen indicador de la calidad de los ecosistemas marinos costeros. ¿Quién es él?  Diplodus Las especies del género Diplodus son conocidas comúnmente como « sargos ». Pertenecen a la familia de los espáridos (Sparidae) que incluye también a las obladas y las doradas. Los sargos son peces de tamaño pequeño o mediano, con un cuerpo ovalado y comprimido lateralmente. Los especímenes más grandes pueden alcanzar los 50 cm. La mayoría presenta una coloración que va del amarillo al azulado, con reflejos plateados. Algunas especies pueden mostrar marcas, líneas o manchas oscuras sobre su cuerpo. Estos pequeños depredadores poseen una gran cabeza con una pequeña boca ligeramente protráctil que le permite capturar rápidamente a sus presas. El nombre dado a este género hace referencia a la doble fila de dientes que poseen estos peces (del griego diploos, que significa \"doble\", y odous que significa \"dientes\"). La dentadura está bien desarrollada y está constituida de caninos y molares. La aleta dorsal de estos peces posee una docena de espinas afiladas, contando con tres espinas más en la aleta anal. Las pectorales son largas y puntiagudas. En 2020, 23 especies de este género fueron censadas en todo el mundo, principalmente en los océanos Atlántico e Índico. Dos especies son endémicas del Mediterráneo: D. bellottii y D. levantinus. La mayor parte de esos peces son explotados con fines comerciales, en particular por las pequeñas pesquerías. Numerosas especies frecuentan las zonas del litoral. Pudiendo ser vistas formando bancos o pequeños grupos en las praderas marinas y zonas rocosas.  Tipo dorada y sargo Tamaño medio 15 cm Tamaño máximo 30 cm Forma Ovoide Patrón líneas verticales Diplodus sargus, sargo común © Benoit Chartrer Diplodus sargus, sargo común © Benoit Chartrer Diplodus sargus, sargo común © Thomas Menut Previous Next Tipo dorada y sargo Tamaño medio 15 cm Tamaño máximo 30 cm Forma Ovoide Patrón líneas verticales ¿Cómo reconocer a Este pez ? Al igual que ocurre con el resto de sargos, el cuerpo es plano y está comprimido. Este pez es de un color gris claro y presenta diversos reflejos plateados y verdosos. Las crías y los adultos más jóvenes se distinguen del resto de ejemplares por la presencia de nueve bandas verticales de color oscuro. La aleta caudal está bordeada por un margen de color negro y tiene una característica mancha en su base. El tamaño de esta especie suele oscilar entre 15 y 30 cm. Sin embargo, cada vez resulta más difícil encontrar ejemplares que sobrepasen los 40 cm. En la actualidad, se cuentan siete subespecies de sargo común: D. sargus ascencionis (Valenciennes, 1830), D. sargus cadenati (de la Paz, Bauchot & Daget, 1974), D. sargus capensis (Smith, 1844), D. sargus helenae (Sauvage, 1879), D. sargus kotschyi (Steindachner, 1876), D. sargus lineatus (Valenciennes, 1830) y D. sargus sargus (Linnaeus, 1758). Diferencias entre machos y hembras No se observa dimorfismo en esta especie. Modo de vida y comportamiento dieta carnívoro Sociabilidad grupos o en solitario territorial No Modo de vida Diurno Los sargos son peces rápidos y activos, de tendencia gregaria en general. Existe la teoría que defiende que este pez podría servirse de los reflejos plateados de su cuerpo para molestar a sus posibles depredadores. Las crías suelen habitar las aguas cercanas a las costas, siempre a poca profundidad En el Mediterráneo, utilizan la posidonia (Posidonia oceanica) y la zostera marina (Zostera marina) como viveros. Los adultos frecuentan los fondos irregulares, constituidos por rocas, guijarros y arena. Este tipo de entornos les proporciona escondites y áreas de caza a estos peces situados en el medio de la cadena alimenticia. Los sargos son peces omnívoros aunque la mayor parte de su alimentación se basa en moluscos (gasterópodos, bivalvos, poliplacóforos). Completan su régimen alimenticio con crustáceos (cangrejos, camarones y anfípodos) y plantas acuáticas (macrófitas). Se trata de una especie de fuerte temperamento, siendo frecuente observar luchas entre ejemplares. Reproducción Podría decirse que la mayoría de los individuos de esta especie son protándricos, es decir, nacen siendo machos para después cambiar de sexo cuando crecen. Sin embargo, no todos siguen esta regla. Algunos machos utilizan esta capacidad para cambiar de sexo únicamente cuando es necesario equilibrar los géneros dentro de una población. La madurez sexual tiene lugar a los 2 años, con un tamaño aproximado de 17 cm. El desove se observa en los meses de enero a marzo, a veces incluso más tarde. Especies inofensivas Esta especie no representa un peligro particular para los humanos en caso de encuentro en su entorno natural. Origen y distribución Origen Mar Mediterráneo Mar Negro Océano Atlántico templado oriental Islas Islas Canarias Cerdeña Sicilia Presencia geográfica y estado de la población La subespecie oceánica Diplodus sargus cenedati está presente desde Angola hasta Bretaña (Francia). En el mar Mediterráneo, podemos encontrar la subespecie Diplodus sargus sargus. Estado de conservación de las poblaciones (UICN) Mundo : LC ¿Dónde observar esta especie? ¿Cuál es su hábitat? Características del entorno natural Profundidad 0 - 50 m Corriente Fuerte Presentación del biotopo Esta especie es bentopelágica. Frecuenta las zonas costeras, en particular los fondos rocosos recubiertos de arena y los pastos marinos. Habitualmente, se encuentra a profundidades inferiores a 50 metros, aunque algunos individuos han sido observados a más de 150 metros. Especie del mismo biotopo pez trompeta del atlántico oriental Aulostomidae lubina Moronidae mojarra Sparidae raspallón Sparidae blenio del Atlántico Blenniidae pez verde Labridae Previous Next Para saber más Especie de la misma familia boga Sparidae dorada Sparidae dentón común Sparidae breca Sparidae pargo común Sparidae Pagrus auriga Sparidae chucla Sparidae oblada Sparidae Previous Next Para leer en la web Fuentes y realización Participación y validación El equipo de Fishipedia y sus colaboradores especializados se comprometen a proporcionar contenido de alta calidad. Sin embargo, aunque la información proviene de fuentes científicas o testimonios de especialistas, los archivos pueden contener imprecisiones. Benoit Chartrer Julie Magnus Silvia Gomez Traducción Traducción realizada con la valiosa contribución de nuestros traductores, quienes hacen que esta información esté disponible para un público más amplio. Silvia Gomez Interactúa con Fishipedia Para ponerse en contacto con nuestro equipo o participar en nuestro proyecto. Contribuya a esta página Plantilla y contenido © Fishipedia - Reproducción no autorizada sin solicitud previa - ISSN 2270-7247 - Última actualización el 18/02/2024 © Fishipedia.fr 2024",
    "genderDescription": "Sparidae",
    "type": "",
    "size": "15 cm",
    "maxSize": "30 cm",
    "mimetism": "",
    "recognize": "",
    "fe/maleDifferences": "No se observa dimorfismo en esta especie.",
    "diet": "carnívoro",
    "territorial": "No",
    "social": "grupos o en solitario",
    "lifeMode": "dieta",
    "lifeDescription": "",
    "reproductionMode": "<  sargo común  Diplodus sargus  Linnaeus  1758  (Mundo) LC  Sparidae  Diplodus",
    "migration": "",
    "reproductionDescription": "",
    "poison": "",
    "danger": "",
    "depth": "Enciclopedia Explorar Acuariofilia A propósito Prensa Peces Ballestas Barracudas Doradas y sargos Escorpenas Hipocampos Lábridos Morenas Peces cirujano Peces globo Peces payaso Rayas Tiburones Reptiles Cocodrilos Serpientes Tortugas Moluscos Caracoles Nudibranquios Calamares Pulpos Sepias Otros temas Anfibios Cnidarios Crustáceos Amazonas Anaconda gigante Anguila eléctrica Paiche Piraña roja Raya motoro / Raya de rio Tararira Mediterráneo Atún rojo Congrio Dorada real Manta raya Mero Sargo Islas Canarias Ángel de mar Caballito de mar Pez roca de Madeira Pez trompeta atlántico Tiburón Mako Vieja colorada Mar del Caribe Cirujano azul Gran barracuda / Picúa Pez ángel francés pez ángel reina Raya jaspeada Robalo blanco Mar Rojo Mero del Coral Morena gigante Pez león Pez Napoléon Raya de arrecife Vieja florida Especies comunes Betta Splendens Chupa algas Corydoras Discos Escalar Gamba Red Cherry Guppy Pez dorado Pez payaso Grupos temáticos Cíclidos enanos Killis Lochas Luchadores Peces gato Tetras Vivíparos Práctica Peces compatibles 20 L Peces compatibles 40 L Peces compatibles 60 L Peces compatibles 80 L Peces compatibles 100 L El proyecto Fishipedia Nuestra ética Proyecto Yaku Nawi Los fotógrafos colaboradores CONTÁCTANOS Enciclopedia Peces Ballestas Barracudas Doradas y sargos Escorpenas Hipocampos Lábridos Morenas Peces cirujano Peces globo Peces payaso Rayas Tiburones Reptiles Cocodrilos Serpientes Tortugas Moluscos Caracoles Nudibranquios Calamares Pulpos Sepias Otros temas Anfibios Cnidarios Crustáceos Explorar Amazonas Anaconda gigante Anguila eléctrica Paiche Piraña roja Raya motoro / Raya de rio Tararira Mediterráneo Atún rojo Congrio Dorada real Manta raya Mero Sargo Islas Canarias Ángel de mar Caballito de mar Pez roca de Madeira Pez trompeta atlántico Tiburón Mako Vieja colorada Mar del Caribe Cirujano azul Gran barracuda / Picúa Pez ángel francés pez ángel reina Raya jaspeada Robalo blanco Mar Rojo Mero del Coral Morena gigante Pez león Pez Napoléon Raya de arrecife Vieja florida Acuariofilia Especies comunes Betta Splendens Chupa algas Corydoras Discos Escalar Gamba Red Cherry Guppy Pez dorado Pez payaso Grupos temáticos Cíclidos enanos Killis Lochas Luchadores Peces gato Tetras Vivíparos Práctica Peces compatibles 20 L Peces compatibles 40 L Peces compatibles 60 L Peces compatibles 80 L Peces compatibles 100 L A propósito El proyecto Fishipedia Nuestra ética Proyecto Yaku Nawi Los fotógrafos colaboradores CONTÁCTANOS Prensa",
    "image": "",
    "mapImage": ""
  },
  {
    "name": "Diplodus vulgaris",
    "sciname": "",
    "IUCN": "",
    "description": "Introducción El sargo o mojarra, Diplodus vulgaris, también conocido en algunas zonas como seifia, es un pez común de las zonas rocosas costeras europeas. Puede observarse en una amplia zona, desde la Bahía de Biscarrose (Sudoeste de Francia) hasta Cabo Verde, el mar Mediterráneo y las costas de Sudáfrica. ¿Quién es ella?  Diplodus Las especies del género Diplodus son conocidas comúnmente como « sargos ». Pertenecen a la familia de los espáridos (Sparidae) que incluye también a las obladas y las doradas. Los sargos son peces de tamaño pequeño o mediano, con un cuerpo ovalado y comprimido lateralmente. Los especímenes más grandes pueden alcanzar los 50 cm. La mayoría presenta una coloración que va del amarillo al azulado, con reflejos plateados. Algunas especies pueden mostrar marcas, líneas o manchas oscuras sobre su cuerpo. Estos pequeños depredadores poseen una gran cabeza con una pequeña boca ligeramente protráctil que le permite capturar rápidamente a sus presas. El nombre dado a este género hace referencia a la doble fila de dientes que poseen estos peces (del griego diploos, que significa \"doble\", y odous que significa \"dientes\"). La dentadura está bien desarrollada y está constituida de caninos y molares. La aleta dorsal de estos peces posee una docena de espinas afiladas, contando con tres espinas más en la aleta anal. Las pectorales son largas y puntiagudas. En 2020, 23 especies de este género fueron censadas en todo el mundo, principalmente en los océanos Atlántico e Índico. Dos especies son endémicas del Mediterráneo: D. bellottii y D. levantinus. La mayor parte de esos peces son explotados con fines comerciales, en particular por las pequeñas pesquerías. Numerosas especies frecuentan las zonas del litoral. Pudiendo ser vistas formando bancos o pequeños grupos en las praderas marinas y zonas rocosas.  Tipo dorada y sargo Tamaño medio 22 cm Tamaño máximo 45 cm Forma Ovoide Patrón líneas verticales Diplodus vulgaris, mojarra © Benoit Chartrer Diplodus vulgaris, mojarra © Benoit Chartrer Previous Next Tipo dorada y sargo Tamaño medio 22 cm Tamaño máximo 45 cm Forma Ovoide Patrón líneas verticales ¿Cómo reconocer a Este pez ? Esta especie es fácilmente reconocible gracias a la característica mancha negra que posee encima de las aletas pectorales. De color gris claro, presenta diversos reflejos de color plateado y amarillo. Su cuerpo aparece recubierto de finas rayas horizontales de un color que puede variar del marrón al negro. Posee un cuerpo plano bordeado de un margen negro alrededor de la aleta caudal. Puede llegar a medir entre 22 y 45 cm en edad adulta aunque no es habitual encontrar especímenes de más de 30 cm. Esto podría ser debido a la sobrepesca. Diferencias entre machos y hembras No se observa dimorfismo en esta especie. Modo de vida y comportamiento dieta carnívoro Sociabilidad grupos o en solitario territorial No Modo de vida Diurno La mojarra suele vivir formando bancos o pequeños grupos. De manera ocasional, algunos individuos pueden ser observados también en solitario. Este pez presenta un temperamento menos violento hacia sus congéneres que el sargo común. En la naturaleza, estos adultos se alimentan de crustáceos, gusanos y moluscos. Las crías encuentran todo tipo de alimentos carnosos en los pastos marinos donde se refugian. Reproducción Se trata de una especie hermafrodita. La madurez sexual se alcanza con un tamaño cercano a los 17 cm, aproximadamente con 4 años de edad. El período de reproducción se extiende entre los meses de octubre a febrero. Especies inofensivas Esta especie no representa un peligro particular para los humanos en caso de encuentro en su entorno natural. Origen y distribución Origen Mar Mediterráneo Océano Atlántico templado oriental Islas Islas Canarias Cerdeña Sicilia Presencia geográfica y estado de la población No hay ningún texto en la actualidad que especifique la distribución y su conservación. Estado de conservación de las poblaciones (UICN) Mundo : LC ¿Dónde observar esta especie? ¿Cuál es su hábitat? Características del entorno natural Profundidad 1 - 100 m Corriente Fuerte Presentación del biotopo Esta especie habita generalmente a una profundidad inferior a 50 metros. Las crías y los juveniles viven próximos a los pastos marinos y las zonas rocosas de poca profundidad. Especie del mismo biotopo pez verde Labridae raspallón Sparidae sargo picudo Sparidae pez trompeta del atlántico oriental Aulostomidae sargo común Sparidae lubina Moronidae Previous Next Mantenimiento en cautividad No recomendado Desaconsejamos el mantenimiento de esta especie en acuario, debido a su forma de vida. Este pez presenta unas necesidades imponderables, que de no ser satisfechas podrían generar un estrés importante en el animal, disminuyendo así su esperanza de vida, limitando su crecimiento e incluso desarrollando ciertos patógenos. Para saber más Especie de la misma familia dentón común Sparidae breca Sparidae Pagrus auriga Sparidae Pagellus acarne Sparidae sargo chopa Sparidae pez herrera Sparidae pargo común Sparidae Spicara smaris Sparidae Previous Next Para leer en la web Fuentes y realización Participación y validación El equipo de Fishipedia y sus colaboradores especializados se comprometen a proporcionar contenido de alta calidad. Sin embargo, aunque la información proviene de fuentes científicas o testimonios de especialistas, los archivos pueden contener imprecisiones. Benoit Chartrer Julie Magnus Silvia Gomez Traducción Traducción realizada con la valiosa contribución de nuestros traductores, quienes hacen que esta información esté disponible para un público más amplio. Silvia Gomez Referencias bibliográficas Reproductive biology of four Diplodusspecies Diplodus vulgaris, D. annularis,D. sargus sargus and D. puntazzo (Sparidae)in the Gulf of Tunis (central Mediterranean) - N. Mouine - P. Francour - M.H. Ktari - N. Chakroun-Marzouk - Marine Biological Association of the United Kingdom - 2012. SPARIDAE - K.E. Carpenter - FAO Fisheries Synopsis - 0. Interactúa con Fishipedia Para ponerse en contacto con nuestro equipo o participar en nuestro proyecto. Contribuya a esta página Plantilla y contenido © Fishipedia - Reproducción no autorizada sin solicitud previa - ISSN 2270-7247 - Última actualización el 12/11/2023 © Fishipedia.fr 2024",
    "genderDescription": "Sparidae",
    "type": "",
    "size": "22 cm",
    "maxSize": "45 cm",
    "mimetism": "",
    "recognize": "",
    "fe/maleDifferences": "No se observa dimorfismo en esta especie.",
    "diet": "carnívoro",
    "territorial": "No",
    "social": "grupos o en solitario",
    "lifeMode": "dieta",
    "lifeDescription": "",
    "reproductionMode": "<  mojarra  Diplodus vulgaris  Geoffroy Saint-Hilaire  1817  (Mundo) LC  Sparidae  Diplodus",
    "migration": "",
    "reproductionDescription": "",
    "poison": "",
    "danger": "",
    "depth": "Enciclopedia Explorar Acuariofilia A propósito Prensa Peces Ballestas Barracudas Doradas y sargos Escorpenas Hipocampos Lábridos Morenas Peces cirujano Peces globo Peces payaso Rayas Tiburones Reptiles Cocodrilos Serpientes Tortugas Moluscos Caracoles Nudibranquios Calamares Pulpos Sepias Otros temas Anfibios Cnidarios Crustáceos Amazonas Anaconda gigante Anguila eléctrica Paiche Piraña roja Raya motoro / Raya de rio Tararira Mediterráneo Atún rojo Congrio Dorada real Manta raya Mero Sargo Islas Canarias Ángel de mar Caballito de mar Pez roca de Madeira Pez trompeta atlántico Tiburón Mako Vieja colorada Mar del Caribe Cirujano azul Gran barracuda / Picúa Pez ángel francés pez ángel reina Raya jaspeada Robalo blanco Mar Rojo Mero del Coral Morena gigante Pez león Pez Napoléon Raya de arrecife Vieja florida Especies comunes Betta Splendens Chupa algas Corydoras Discos Escalar Gamba Red Cherry Guppy Pez dorado Pez payaso Grupos temáticos Cíclidos enanos Killis Lochas Luchadores Peces gato Tetras Vivíparos Práctica Peces compatibles 20 L Peces compatibles 40 L Peces compatibles 60 L Peces compatibles 80 L Peces compatibles 100 L El proyecto Fishipedia Nuestra ética Proyecto Yaku Nawi Los fotógrafos colaboradores CONTÁCTANOS Enciclopedia Peces Ballestas Barracudas Doradas y sargos Escorpenas Hipocampos Lábridos Morenas Peces cirujano Peces globo Peces payaso Rayas Tiburones Reptiles Cocodrilos Serpientes Tortugas Moluscos Caracoles Nudibranquios Calamares Pulpos Sepias Otros temas Anfibios Cnidarios Crustáceos Explorar Amazonas Anaconda gigante Anguila eléctrica Paiche Piraña roja Raya motoro / Raya de rio Tararira Mediterráneo Atún rojo Congrio Dorada real Manta raya Mero Sargo Islas Canarias Ángel de mar Caballito de mar Pez roca de Madeira Pez trompeta atlántico Tiburón Mako Vieja colorada Mar del Caribe Cirujano azul Gran barracuda / Picúa Pez ángel francés pez ángel reina Raya jaspeada Robalo blanco Mar Rojo Mero del Coral Morena gigante Pez león Pez Napoléon Raya de arrecife Vieja florida Acuariofilia Especies comunes Betta Splendens Chupa algas Corydoras Discos Escalar Gamba Red Cherry Guppy Pez dorado Pez payaso Grupos temáticos Cíclidos enanos Killis Lochas Luchadores Peces gato Tetras Vivíparos Práctica Peces compatibles 20 L Peces compatibles 40 L Peces compatibles 60 L Peces compatibles 80 L Peces compatibles 100 L A propósito El proyecto Fishipedia Nuestra ética Proyecto Yaku Nawi Los fotógrafos colaboradores CONTÁCTANOS Prensa",
    "image": "",
    "mapImage": ""
  },
  {
    "name": "Echiichthys vipera",
    "sciname": "",
    "IUCN": "",
    "description": "Introducción Echiichthys Vipera, conocido comúnmente como « salvariego » es un pez marino originario de la zona Atlántica. Este pequeño depredador bentónico frecuenta los substratos arenosos de aguas poco profundas. Su área de repartición se extiende desde el norte de las islas Británicas hasta la cuenca del Mediterráneo, pasando por el mar del Norte y la costa Atlántica francesa, española y marroquí. Dotado con unas espinas venenosas, esta especie experta en camuflaje es temida por pescadores y bañistas. En la mayoría de casos, la víctima posa accidentalmente su pie sobre el animal enterrado en la arena. Discreto, este pequeño pez frecuenta las aguas cercanas a la costa durante los meses más cálidos, de ahí su habitual presencia en las zonas de baño durante el período estival. ¿Quién es él?  Echiichthys El género Echiichthys pertenece a la familia de los Trachinidae, contiene una única especie, Echiichthys Vipera. Sin embargo, el comportamiento y la forma de vida de este es muy similar a las especies del género Trachinus. La separación de ambos géneros está basado en algunas diferencias morfológicas mínimas.  Tamaño medio 10 cm Tamaño máximo 16 cm Longevidad 13 años Mimetismo fondo arenoso Patrón manchas Echiichthys vipera, salvariego © Xavi Salvador Costa Tamaño medio 10 cm Tamaño máximo 16 cm Longevidad 13 años Mimetismo fondo arenoso Patrón manchas ¿Cómo reconocer a Este pez ? El cuerpo de esta pequeña especie es alargado. El dorso es de color marrón y amarillo, moteado con manchas marrones o negras. Generalmente tiene una coloración más pálida que su pariente el Trachinus Draco. Los laterales son lisos y de color blanco plateado. La cabeza está comprimida y los ojos se encuentran muy próximos entre sí, provisto de una gran boca orientada hacia arriba. La primera aleta dorsal es corta, de color negro y venenosa mientras la segunda es más alargada. Otra espina, no venenosa, está orientada hacia la parte trasera, situada al nivel del opérculo branquial. A diferencia del Trachinus draco, esta especie no posee espinas sobre los ojos. Los adultos rara vez superan los 16 cm. Aunque algunos ejemplares de más de 20 cm han sido documentados en el mar del Norte, en las costas de Suffolk en Inglaterra. Diferencias entre machos y hembras Es difícil distinguir a machos y hembras en esta especie. Modo de vida y comportamiento dieta carnívoro Sociabilidad solitario territorial Sí Modo de vida Diurno Este pequeño animal frecuenta las aguas cálidas y poco profundas, realizando migraciones estacionales a pequeña escala, regidas por el calentamiento de las aguas. Se trata de un pez territorial y solitario que habita en el fondo del mar. Utilizando su arma venenosa como defensa, en caso de peligro se camufla enterrándose en la arena, dejando únicamente al descubierto sus ojos y la primera espina dorsal. Este pequeño depredador bentónico utiliza dos métodos diferentes de caza. De manera habitual, opera en forma de emboscada enterrado en la arena, de forma menos común, lo hace directamente en la columna de agua. Según diversos estudios, esta especie puede cazar tanto de día como de noche. Su régimen alimenticio está compuesto principalmente por pequeños crustáceos móviles y peces como los gobios, su manjar favorito en el mar del Norte. Algunas poblaciones se contentan también con pequeño cefalópodos. Reproducción Modo de reproducción ovíparo que desova en aguas abiertas Se trata de una especie ovovivípara que desova en aguas abiertas. Riesgos para los humanos Venenoso Sí Se trata de una especie muy venenosa que puede causar graves lesiones en caso de contacto. La picadura de su espina dorsal provoca un gran dolor pudiendo incluso causar nauseas y la formación de un edema localizado. El veneno es termolábil, la aplicación rápida de agua caliente (en torno a 45ºC) es altamente recomendable para evitar posibles complicaciones. El veneno está considerado como no mortal. ¿Qué hacer en caso de una picadura? En caso de mordedura, se deben seguir las siguientes reglas, manteniendo siempre el orden indicado: Aislar a la víctima del peligro y sacarla rápidamente del agua. Avisar a los servicios de emergencia. Colocar al sujeto en una posición semisentada para evitar que realice cualquier esfuerzo. Inmovilizar la extremidad afectada. Limpiar la herida. Dado que el veneno de esta especie es termolábil, puede neutralizarse si se somete a una temperatura cercana a los 45 ° C. Por tanto, será necesario calentar la herida. Esta popular técnica debe practicarse con mucho cuidado para no agravar el estado de la herida. Es recomendable sumergir la extremidad afectada en agua caliente. Si la mordedura es demasiado profunda, el procedimiento de calentar la herida resultará menos efectivo. En algunas ocasiones, la mordedura puede provocar molestias o incluso pérdida del conocimiento en la víctima. Origen y distribución Origen Mar Mediterráneo Océano Atlántico templado oriental Islas Islas Canarias Cerdeña Sicilia Presencia geográfica y estado de la población Su área de repartición geográfica se extiende desde el norte de las islas Británicas hasta la cuenca del Mediterráneo, pasando por el mar del Norte, la costa Atlántica francesa, española y marroquí. También es posible encontrarlo en las islas Canarias. Estado de conservación de las poblaciones (UICN) Mundo : NE ¿Cuál es su hábitat? Características del entorno natural Profundidad 0 - 150 m Corriente Moderada y Lenta Presentación del biotopo Este pez suele encontrarse a profundidades inferiores a 150 m en las zonas de aguas cálidas. Frecuenta de manera regular los estuarios, oculto en los sustratos arenosos o de pequeños guijarros. Especie del mismo biotopo águila de mar Myliobatidae pez verde Labridae Gobius cobitis Gobiidae chopa Sparidae lubina Moronidae miracielo Uranoscopidae Previous Next Para saber más Especie de la misma familia pez araña Trachinidae pez escorpión Trachinidae pez víbora Trachinidae Previous Next Para leer en la web Fuentes y realización Participación y validación El equipo de Fishipedia y sus colaboradores especializados se comprometen a proporcionar contenido de alta calidad. Sin embargo, aunque la información proviene de fuentes científicas o testimonios de especialistas, los archivos pueden contener imprecisiones. Aurélien Calas Benoit Chartrer Traducción Traducción realizada con la valiosa contribución de nuestros traductores, quienes hacen que esta información esté disponible para un público más amplio. Silvia Gomez Referencias bibliográficas The venoms of the lesser (Echiichthys vipera) and greater (Trachinus draco) weever fish– A review - Myriam Fezai - Mohamed Jemaà - Lucy M. Gorman - Sarah J. Judge - John B. Harris - Gary S. Caldwel - Elsevier Ltd - 2020. Le règne animal - Georges Cuvier - Organisation Cuvier - 1816. Seasonal and age-related migrations in the unexpectedly long-lived benthic fish the lesser weever, Echiichthys vipera (Cuvier, 1829) - Scott, A L - Henderson, P A. - Journal of the Marine Biological Association of the UK - 2016. Interactúa con Fishipedia Para ponerse en contacto con nuestro equipo o participar en nuestro proyecto. Contribuya a esta página Plantilla y contenido © Fishipedia - Reproducción no autorizada sin solicitud previa - ISSN 2270-7247 - Última actualización el 12/11/2023 © Fishipedia.fr 2024",
    "genderDescription": "Trachinidae",
    "type": "",
    "size": "10 cm",
    "maxSize": "16 cm",
    "mimetism": "fondo arenoso",
    "recognize": "",
    "fe/maleDifferences": "Es difícil distinguir a machos y hembras en esta especie.",
    "diet": "carnívoro",
    "territorial": "Sí",
    "social": "solitario",
    "lifeMode": "dieta",
    "lifeDescription": "",
    "reproductionMode": "<  salvariego  Echiichthys vipera  Cuvier  1829  (Mundo) NE  Trachinidae  Echiichthys",
    "migration": "",
    "reproductionDescription": "",
    "poison": "Enciclopedia Explorar Acuariofilia A propósito Prensa Peces Ballestas Barracudas Doradas y sargos Escorpenas Hipocampos Lábridos Morenas Peces cirujano Peces globo Peces payaso Rayas Tiburones Reptiles Cocodrilos Serpientes Tortugas Moluscos Caracoles Nudibranquios Calamares Pulpos Sepias Otros temas Anfibios Cnidarios Crustáceos Amazonas Anaconda gigante Anguila eléctrica Paiche Piraña roja Raya motoro / Raya de rio Tararira Mediterráneo Atún rojo Congrio Dorada real Manta raya Mero Sargo Islas Canarias Ángel de mar Caballito de mar Pez roca de Madeira Pez trompeta atlántico Tiburón Mako Vieja colorada Mar del Caribe Cirujano azul Gran barracuda / Picúa Pez ángel francés pez ángel reina Raya jaspeada Robalo blanco Mar Rojo Mero del Coral Morena gigante Pez león Pez Napoléon Raya de arrecife Vieja florida Especies comunes Betta Splendens Chupa algas Corydoras Discos Escalar Gamba Red Cherry Guppy Pez dorado Pez payaso Grupos temáticos Cíclidos enanos Killis Lochas Luchadores Peces gato Tetras Vivíparos Práctica Peces compatibles 20 L Peces compatibles 40 L Peces compatibles 60 L Peces compatibles 80 L Peces compatibles 100 L El proyecto Fishipedia Nuestra ética Proyecto Yaku Nawi Los fotógrafos colaboradores CONTÁCTANOS Enciclopedia Peces Ballestas Barracudas Doradas y sargos Escorpenas Hipocampos Lábridos Morenas Peces cirujano Peces globo Peces payaso Rayas Tiburones Reptiles Cocodrilos Serpientes Tortugas Moluscos Caracoles Nudibranquios Calamares Pulpos Sepias Otros temas Anfibios Cnidarios Crustáceos Explorar Amazonas Anaconda gigante Anguila eléctrica Paiche Piraña roja Raya motoro / Raya de rio Tararira Mediterráneo Atún rojo Congrio Dorada real Manta raya Mero Sargo Islas Canarias Ángel de mar Caballito de mar Pez roca de Madeira Pez trompeta atlántico Tiburón Mako Vieja colorada Mar del Caribe Cirujano azul Gran barracuda / Picúa Pez ángel francés pez ángel reina Raya jaspeada Robalo blanco Mar Rojo Mero del Coral Morena gigante Pez león Pez Napoléon Raya de arrecife Vieja florida Acuariofilia Especies comunes Betta Splendens Chupa algas Corydoras Discos Escalar Gamba Red Cherry Guppy Pez dorado Pez payaso Grupos temáticos Cíclidos enanos Killis Lochas Luchadores Peces gato Tetras Vivíparos Práctica Peces compatibles 20 L Peces compatibles 40 L Peces compatibles 60 L Peces compatibles 80 L Peces compatibles 100 L A propósito El proyecto Fishipedia Nuestra ética Proyecto Yaku Nawi Los fotógrafos colaboradores CONTÁCTANOS Prensa",
    "danger": "",
    "depth": "Enciclopedia Explorar Acuariofilia A propósito Prensa Peces Ballestas Barracudas Doradas y sargos Escorpenas Hipocampos Lábridos Morenas Peces cirujano Peces globo Peces payaso Rayas Tiburones Reptiles Cocodrilos Serpientes Tortugas Moluscos Caracoles Nudibranquios Calamares Pulpos Sepias Otros temas Anfibios Cnidarios Crustáceos Amazonas Anaconda gigante Anguila eléctrica Paiche Piraña roja Raya motoro / Raya de rio Tararira Mediterráneo Atún rojo Congrio Dorada real Manta raya Mero Sargo Islas Canarias Ángel de mar Caballito de mar Pez roca de Madeira Pez trompeta atlántico Tiburón Mako Vieja colorada Mar del Caribe Cirujano azul Gran barracuda / Picúa Pez ángel francés pez ángel reina Raya jaspeada Robalo blanco Mar Rojo Mero del Coral Morena gigante Pez león Pez Napoléon Raya de arrecife Vieja florida Especies comunes Betta Splendens Chupa algas Corydoras Discos Escalar Gamba Red Cherry Guppy Pez dorado Pez payaso Grupos temáticos Cíclidos enanos Killis Lochas Luchadores Peces gato Tetras Vivíparos Práctica Peces compatibles 20 L Peces compatibles 40 L Peces compatibles 60 L Peces compatibles 80 L Peces compatibles 100 L El proyecto Fishipedia Nuestra ética Proyecto Yaku Nawi Los fotógrafos colaboradores CONTÁCTANOS Enciclopedia Peces Ballestas Barracudas Doradas y sargos Escorpenas Hipocampos Lábridos Morenas Peces cirujano Peces globo Peces payaso Rayas Tiburones Reptiles Cocodrilos Serpientes Tortugas Moluscos Caracoles Nudibranquios Calamares Pulpos Sepias Otros temas Anfibios Cnidarios Crustáceos Explorar Amazonas Anaconda gigante Anguila eléctrica Paiche Piraña roja Raya motoro / Raya de rio Tararira Mediterráneo Atún rojo Congrio Dorada real Manta raya Mero Sargo Islas Canarias Ángel de mar Caballito de mar Pez roca de Madeira Pez trompeta atlántico Tiburón Mako Vieja colorada Mar del Caribe Cirujano azul Gran barracuda / Picúa Pez ángel francés pez ángel reina Raya jaspeada Robalo blanco Mar Rojo Mero del Coral Morena gigante Pez león Pez Napoléon Raya de arrecife Vieja florida Acuariofilia Especies comunes Betta Splendens Chupa algas Corydoras Discos Escalar Gamba Red Cherry Guppy Pez dorado Pez payaso Grupos temáticos Cíclidos enanos Killis Lochas Luchadores Peces gato Tetras Vivíparos Práctica Peces compatibles 20 L Peces compatibles 40 L Peces compatibles 60 L Peces compatibles 80 L Peces compatibles 100 L A propósito El proyecto Fishipedia Nuestra ética Proyecto Yaku Nawi Los fotógrafos colaboradores CONTÁCTANOS Prensa",
    "image": "",
    "mapImage": ""
  },
  {
    "name": "Enchelycore anatina",
    "sciname": "",
    "IUCN": "",
    "description": "Introducción Enchelycore anatina, más comúnmente denominada morena picopato, es un pez que habita en agua de mar.  de realización. Los textos propuestos actualmente provienen de nuestro modelo de datos o están en proceso de redacción. Para solicitar prioridad para este contenido, puedes escribirnos AQUÍ. ¿Quién es ella?  Tipo morena Tamaño medio 100 cm Tamaño máximo 120 cm Forma Serpentiforme Patrón manchas Enchelycore anatina, morena picopato © Xavi Salvador Costa Tipo morena Tamaño medio 100 cm Tamaño máximo 120 cm Forma Serpentiforme Patrón manchas ¿Cómo reconocer a Este pez ? La morena picopato mide entre 100 y 120 cm. Este pez presenta una coloración bicolor con un cuerpo mayoritariamente amarillo y marrón. Posee también manchas de color amarillo. Modo de vida y comportamiento dieta carnívoro Sociabilidad solitario territorial Sí Modo de vida Nocturno La morena picopato es un pez que vive en solitario entre las rocas. Es un animal carnívoro de temperamento más bien tranquilo. Este pez vive principalmente de noche. Generalmente, abandona su escondite y comienza su actividad una vez que cae la noche. La morena picopato es un animal territorial que no tolerará ninguna incursión en su territorio. Particularmente virulento con otras especies territoriales, no dudará en provocar numerosos enfrentamientos. Reproducción Modo de reproducción ovíparo La morena picopato es un pez ovíparo. Especies inofensivas Esta especie no supone ningún peligro en particular para el ser humano cuando se encuentra en su entorno natural. Origen y distribución Origen Mar Mediterráneo Islas Islas Canarias Estado de conservación de las poblaciones (UICN) Mundo : LC ¿Cuál es su hábitat? Características del entorno natural Temperatura 18 - 25 °C Profundidad 3 - 60 m Presentación del biotopo Frecuentemente encontramos a la morena picopato a una profundidad de entre 3m y 60m. Sin embargo, no resulta del todo imposible observar a esta especie a otras profundidades. Especie del mismo biotopo tordo rojo Labridae falso abadejo Serranidae blenio del Atlántico Blenniidae cherna Polyprionidae mero Serranidae pez verde Labridae Previous Next Para saber más Especie de la misma familia morena común Muraenidae anguila listón azul Muraenidae morena de boca blanca Muraenidae Gymnothorax undulatus Muraenidae morena de borde amarillo Muraenidae Gymnomuraena zebra Muraenidae morena verde Muraenidae morena leopardo Muraenidae Previous Next Para leer en la web Fuentes y realización Participación y validación El equipo de Fishipedia y sus colaboradores especializados se comprometen a proporcionar contenido de alta calidad. Sin embargo, aunque la información proviene de fuentes científicas o testimonios de especialistas, los archivos pueden contener imprecisiones. Benoit Chartrer Traducción Traducción realizada con la valiosa contribución de nuestros traductores, quienes hacen que esta información esté disponible para un público más amplio. Silvia Gomez Interactúa con Fishipedia Para ponerse en contacto con nuestro equipo o participar en nuestro proyecto. Contribuya a esta página Plantilla y contenido © Fishipedia - Reproducción no autorizada sin solicitud previa - ISSN 2270-7247 - Última actualización el 10/11/2023 © Fishipedia.fr 2024",
    "genderDescription": "Muraenidae",
    "type": "",
    "size": "100 cm",
    "maxSize": "120 cm",
    "mimetism": "",
    "recognize": "",
    "fe/maleDifferences": "",
    "diet": "carnívoro",
    "territorial": "Sí",
    "social": "solitario",
    "lifeMode": "dieta",
    "lifeDescription": "",
    "reproductionMode": "<  morena picopato  Enchelycore anatina  Lowe  1838  (Mundo) LC  Muraenidae  Enchelycore",
    "migration": "",
    "reproductionDescription": "",
    "poison": "",
    "danger": "de realización. Los textos propuestos actualmente provienen de nuestro modelo de datos o están en proceso de redacción. Para solicitar prioridad para este contenido, puedes escribirnos AQUÍ.",
    "depth": "3 - 60 m",
    "image": "",
    "mapImage": ""
  },
  {
    "name": "Epinephelus costae",
    "sciname": "",
    "IUCN": "",
    "description": "Introducción Epinephelus costae, conocido también como mero dorado. Sus poblaciones parecen dispersas y poco abundantes, aunque sigue presente en toda la zona del Atlántico Este y el mar Mediterráneo. Este depredador, apreciado por su carne, ha sido objeto de una intensa pesca a lo largo del siglo XX. ¿Quién es él?  Epinephelus En 2019, el género Epinephelus agrupaba 87 especies según Fishbase. Estos peces, denominados comúnmente \"meros\" pertenecen al \"grupo\" de los serránidos (Serranidae). Estos depredadores de carácter territorial poseen un cuerpo alargado y robusto. Con una cabeza imponente y una boca protráctil, posee una mandíbula que contiene en su parte delantera unos poderosos caninos. Todas las especies poseen 10 o 11 espinas dorsales. La mayor parte de estas especies se encuentran en los arrecifes de coral o en las zonas rocosas a excepción de E. aeneus, E. bruneus y E. areolatus que habitan en los fondos arenosos, limosos o fangosos. Los adultos suelen ser avistados a profundidades de entre 10 y 200 metros. La mayoría de los Epinephelus son animales hermafroditas protóginos, es decir, nacen hembras transformándose después en machos a medida que crecen. Sin embargo, es posible que no todas las hembras cambien de sexo y que algunos machos no desarrollen este estado comúnmente aceptado. Estos peces son muy valorados comercialmente para la alimentación y la pesca recreativa, pero son vulnerables a la sobrepesca debido a su crecimiento lento, madurez tardía y formación de agregaciones de reproducción. La sobrepesca, especialmente dirigida a los individuos maduros, puede causar desequilibrios en la proporción de sexos y afectar a la reproducción. Varias especies de meros ahora son objeto de cultivo en granjas acuícolas (especialmente E. coioides y E. malabaricus). Según la UICN, la sobrepesca y la contaminación ya han causado una disminución significativa de las poblaciones de muchos meros y varias especies están en peligro de extinción.  Tamaño medio 80 cm Tamaño máximo 140 cm Longevidad 30 años Mimetismo piedra Patrón líneas horizontales Epinephelus costae, falso abadejo © Thomas Menut Tamaño medio 80 cm Tamaño máximo 140 cm Longevidad 30 años Mimetismo piedra Patrón líneas horizontales ¿Cómo reconocer a Este pez ? Generalmente mide alrededor de un metro en edad adulta. La cabeza y el cuerpo son de un color marrón grisáceo, y este aparece cubierto de bandas horizontales marrón oscuro. Las escamas laterales del cuerpo son ctenoides, lo que hace que la piel sea rugosa. Los adultos presentan una característica mancha amarilla bajo la aleta dorsal. Las aletas son de un color más oscuro. Posee 11 espinas dorsales. Dos líneas negras delgadas se encuentran presentes en el morro, una parte del borde inferior del ojo y la otra es visible justo por encima de la mandíbula superior. Es un pez menos robusto que el mero común y difiere en su coloración. Sin embargo, a veces se puede confundir con el abadejo. Siendo este último más oscuro en edad adulta y con unas bandas horizontales más pronunciadas en los juveniles. Diferencias entre machos y hembras Las líneas en el cuerpo de los machos dominantes son menos visibles. La cabeza presenta reflejos violeta-marrón más o menos marcados dependiendo del estado de ánimo y de la presencia de hembras/machos competidores. La mancha amarilla debajo de la aleta dorsal es más evidente. Modo de vida y comportamiento dieta carnívoro Sociabilidad solitario territorial Sí Modo de vida Diurno Se trata de un depredador especializado en la caza de crustáceos, moluscos y peces. Los machos adultos son muy territoriales, y se desplazan entre las rocas, las zonas arenosas y las zonas mixtas, no toleran ninguna intrusión intraspecífica en su territorio. Los juveniles viven en pequeños grupos en aguas poco profundas, en ocasiones cerca de praderas de hierbas marinas y zonas mixtas. Reproducción Modo de reproducción ovíparo que desova en aguas abiertas Hermafrodita protógino Al igual que sucede con otros meros, en esta especie todos los peces nacen siendo hembras y, pasado un tiempo, algunos individuos se convierten en machos. Especies inofensivas Esta especie no representa un peligro particular para los humanos en caso de encuentro en su hábitat natural. Origen y distribución Origen Mar Mediterráneo Mar Negro Océano Atlántico templado oriental Islas Córcega Islas Canarias Cerdeña Sicilia Presencia geográfica y estado de la población La información sobre el estado de salud de las poblaciones de esta especie es escasa. Al igual que sucede con el mero común, se trata de una especie relativamente fácil de capturar. La debilidad de las poblaciones en las costas francesas podría indicar un nivel general de conservación deficiente. Estado de conservación de las poblaciones (UICN) Mundo : DD Francia : DD ¿Cuál es su hábitat? Características del entorno natural Temperatura 10 - 26 °C Profundidad 4 - 160 m Presentación del biotopo Este pez habita en zonas rocosas y arenosas. Los adultos son relativamente comunes alrededor de los 30 metros de profundidad. Para saber más Especie de la misma familia merlo del coral Serranidae cabrilla reina Serranidae Mycteroperca bonaci Serranidae serrano imperial Serranidae Serranus subligarius Serranidae abade Serranidae Serranocirrhitus latus Serranidae Serranus hepatus Serranidae Previous Next Para leer en la web Fuentes y realización Participación y validación El equipo de Fishipedia y sus colaboradores especializados se comprometen a proporcionar contenido de alta calidad. Sin embargo, aunque la información proviene de fuentes científicas o testimonios de especialistas, los archivos pueden contener imprecisiones. Benoit Chartrer Adrien Falzon Traducción Traducción realizada con la valiosa contribución de nuestros traductores, quienes hacen que esta información esté disponible para un público más amplio. Silvia Gomez Referencias bibliográficas FAO Species Catalogue. Vol. 16. Groupers of the world (family Serranidae, subfamily Epinephelinae). - Heemstra, P.C - J.E. Randall - FAO Fisheries Synopsis - 1993. Interactúa con Fishipedia Para ponerse en contacto con nuestro equipo o participar en nuestro proyecto. Contribuya a esta página Plantilla y contenido © Fishipedia - Reproducción no autorizada sin solicitud previa - ISSN 2270-7247 - Última actualización el 12/11/2023 © Fishipedia.fr 2024",
    "genderDescription": "Serranidae",
    "type": "",
    "size": "80 cm",
    "maxSize": "140 cm",
    "mimetism": "piedra",
    "recognize": "",
    "fe/maleDifferences": "Las líneas en el cuerpo de los machos dominantes son menos visibles. La cabeza presenta reflejos violeta-marrón más o menos marcados dependiendo del estado de ánimo y de la presencia de hembras/machos competidores. La mancha amarilla debajo de la aleta dorsal es más evidente.",
    "diet": "carnívoro",
    "territorial": "Tamaño medio 80 cm Tamaño máximo 140 cm Longevidad 30 años Mimetismo piedra Patrón líneas horizontales Epinephelus costae, falso abadejo © Thomas Menut Tamaño medio 80 cm Tamaño máximo 140 cm Longevidad 30 años Mimetismo piedra Patrón líneas horizontales",
    "social": "solitario",
    "lifeMode": "dieta",
    "lifeDescription": "",
    "reproductionMode": "<  falso abadejo  Epinephelus costae  Steindachner  1878  (Mundo) DD  Serranidae  Epinephelus",
    "migration": "",
    "reproductionDescription": "",
    "poison": "",
    "danger": "",
    "depth": "Enciclopedia Explorar Acuariofilia A propósito Prensa Peces Ballestas Barracudas Doradas y sargos Escorpenas Hipocampos Lábridos Morenas Peces cirujano Peces globo Peces payaso Rayas Tiburones Reptiles Cocodrilos Serpientes Tortugas Moluscos Caracoles Nudibranquios Calamares Pulpos Sepias Otros temas Anfibios Cnidarios Crustáceos Amazonas Anaconda gigante Anguila eléctrica Paiche Piraña roja Raya motoro / Raya de rio Tararira Mediterráneo Atún rojo Congrio Dorada real Manta raya Mero Sargo Islas Canarias Ángel de mar Caballito de mar Pez roca de Madeira Pez trompeta atlántico Tiburón Mako Vieja colorada Mar del Caribe Cirujano azul Gran barracuda / Picúa Pez ángel francés pez ángel reina Raya jaspeada Robalo blanco Mar Rojo Mero del Coral Morena gigante Pez león Pez Napoléon Raya de arrecife Vieja florida Especies comunes Betta Splendens Chupa algas Corydoras Discos Escalar Gamba Red Cherry Guppy Pez dorado Pez payaso Grupos temáticos Cíclidos enanos Killis Lochas Luchadores Peces gato Tetras Vivíparos Práctica Peces compatibles 20 L Peces compatibles 40 L Peces compatibles 60 L Peces compatibles 80 L Peces compatibles 100 L El proyecto Fishipedia Nuestra ética Proyecto Yaku Nawi Los fotógrafos colaboradores CONTÁCTANOS Enciclopedia Peces Ballestas Barracudas Doradas y sargos Escorpenas Hipocampos Lábridos Morenas Peces cirujano Peces globo Peces payaso Rayas Tiburones Reptiles Cocodrilos Serpientes Tortugas Moluscos Caracoles Nudibranquios Calamares Pulpos Sepias Otros temas Anfibios Cnidarios Crustáceos Explorar Amazonas Anaconda gigante Anguila eléctrica Paiche Piraña roja Raya motoro / Raya de rio Tararira Mediterráneo Atún rojo Congrio Dorada real Manta raya Mero Sargo Islas Canarias Ángel de mar Caballito de mar Pez roca de Madeira Pez trompeta atlántico Tiburón Mako Vieja colorada Mar del Caribe Cirujano azul Gran barracuda / Picúa Pez ángel francés pez ángel reina Raya jaspeada Robalo blanco Mar Rojo Mero del Coral Morena gigante Pez león Pez Napoléon Raya de arrecife Vieja florida Acuariofilia Especies comunes Betta Splendens Chupa algas Corydoras Discos Escalar Gamba Red Cherry Guppy Pez dorado Pez payaso Grupos temáticos Cíclidos enanos Killis Lochas Luchadores Peces gato Tetras Vivíparos Práctica Peces compatibles 20 L Peces compatibles 40 L Peces compatibles 60 L Peces compatibles 80 L Peces compatibles 100 L A propósito El proyecto Fishipedia Nuestra ética Proyecto Yaku Nawi Los fotógrafos colaboradores CONTÁCTANOS Prensa",
    "image": "",
    "mapImage": ""
  },
  {
    "name": "Epinephelus itajara",
    "sciname": "",
    "IUCN": "",
    "description": "Introducción Epinephelus itajara, también conocido como mero guasa o mero goliath es una especie marina que habita en aguas marinas tropicales y subtropicales. Ha sido observado en el Océano Atlántico occidental, incluido el Mar Caribe. Algunas poblaciones dispersas se encuentran también en las islas de Macronesia (Azores, Islas Canarias, Cabo Verde). Una de las especies relacionadas con Epinephelus itajara se encuentra presente en el Pacífico oriental, Epinephelus quinquefasciatus. Junto con este último, así como el mero gigante Epinephelus lanceolatus y el mero malabar Epinephelus malabaricus, se encuentra entre los peces óseos más grandes documentados. Situados en la parte alta de la cadena alimenticia, estos meros son consideran como los principales depredadores de sus ecosistemas, lo que los convierte en especies centinela. El mero guasa resulta una especie de particular interés para los aficionados a la pesca deportiva. Estos peces normalmente se liberan después de ser capturados y a día de hoy, aún son considerados como vulnerables según la IUCN. Al ser unos animales sedentarios que no huyen en presencia de los seres humanos, resultan un blanco fácil para los pescadores con arpón. Además de las frecuentes capturas de animales adultos, los juveniles encuentran diversas dificultades en sus ecosistemas favoritos: los manglares, debido a que estos se ven globalmente afectados por diversas contaminaciones, cuando no son simplemente destruidos por la urbanización de las costas. Aunque generalmente resultan inofensivos, se han dado casos en los que algunos individuos han seguido a los buzos, llegando en ocasiones a morder, aunque únicamente con el fin de defender su territorio. ¿Quién es él?  Epinephelus En 2019, el género Epinephelus agrupaba 87 especies según Fishbase. Estos peces, denominados comúnmente \"meros\" pertenecen al \"grupo\" de los serránidos (Serranidae). Estos depredadores de carácter territorial poseen un cuerpo alargado y robusto. Con una cabeza imponente y una boca protráctil, posee una mandíbula que contiene en su parte delantera unos poderosos caninos. Todas las especies poseen 10 o 11 espinas dorsales. La mayor parte de estas especies se encuentran en los arrecifes de coral o en las zonas rocosas a excepción de E. aeneus, E. bruneus y E. areolatus que habitan en los fondos arenosos, limosos o fangosos. Los adultos suelen ser avistados a profundidades de entre 10 y 200 metros. La mayoría de los Epinephelus son animales hermafroditas protóginos, es decir, nacen hembras transformándose después en machos a medida que crecen. Sin embargo, es posible que no todas las hembras cambien de sexo y que algunos machos no desarrollen este estado comúnmente aceptado. Estos peces son muy valorados comercialmente para la alimentación y la pesca recreativa, pero son vulnerables a la sobrepesca debido a su crecimiento lento, madurez tardía y formación de agregaciones de reproducción. La sobrepesca, especialmente dirigida a los individuos maduros, puede causar desequilibrios en la proporción de sexos y afectar a la reproducción. Varias especies de meros ahora son objeto de cultivo en granjas acuícolas (especialmente E. coioides y E. malabaricus). Según la UICN, la sobrepesca y la contaminación ya han causado una disminución significativa de las poblaciones de muchos meros y varias especies están en peligro de extinción.  Tamaño medio 150 cm Tamaño máximo 250 cm Longevidad 37 años Patrón moteado Epinephelus itajara, mero guasa © Xaime Beiro Epinephelus itajara, mero guasa © Xaime Beiro Previous Next Tamaño medio 150 cm Tamaño máximo 250 cm Longevidad 37 años Patrón moteado ¿Cómo reconocer a Este pez ? Epinephelus itajara mide alrededor de 150 cm. El ejemplar más grande capturado medía 250 cm con un peso de 320 kg. Este pez es bicolor con un cuerpo predominantemente marrón/gris o blanco/beige, ovalado y macizo. La cabeza aparece salpicada de pequeños puntos negros y en ella se distingue una boca ancha y protráctil. Las dos aletas dorsales se encuentran pegadas y se extienden desde la cabeza hasta el pedúnculo caudal. Los primeros 11 a 12 radios son pequeños y les siguen radios más alargados que forman una aleta redondeada. Las aletas pectoral, pélvica, anal y caudal son redondas y del mismo color que el cuerpo. Diferencias entre machos y hembras Parece que por debajo de los 80 cm, todos los meros goliath son hembras. Por encima de este tamaño, son machos o hembras sin dimorfismo aparente. Modo de vida y comportamiento dieta carnívoro Sociabilidad solitario territorial Sí Modo de vida Diurno El mero goliath caza al acecho y se trata de uno de los principales depredadores en su hábitat. Oportunista, no duda en atacar a cualquier animal más pequeño que se ponga a su alcance. Esta especie no es muy activa y se alimenta principalmente de presas de nado lento. Este pez de carácter solitario en su edad adulta habita sobre los fondos rocosos y en las zonas coralinas, pero también en zonas fangosas y cerca de estuarios. En realidad, tiene poco impacto en la vida salvaje, ya que es un depredador lento con poblaciones muy dispersas. Se alimenta principalmente de crustáceos, especialmente langostas, aunque en ocasiones también caza tortugas y peces, incluidas rayas. Se sabe que el mero goliath es un animal territorial sedentario. Generalmente se coloca cerca de una cueva, un refugio o un naufragio. En caso de intrusión, adoptará una actitud amenazadora abriendo la boca y haciendo temblar su cuerpo. Las relaciones entre congéneres son también turbulentas, ya que cada ejemplar busca asegurar su área de vida. Reproducción Modo de reproducción ovíparo Hermafrodita protógino Epinephelus itajara es un pez ovíparo. Aunque la especie es probablemente protógina, algunos datos parecen inconsistentes con respecto a esta teoría. Un estudio realizado en 481 individuos muestra una distribución de tallas entre 80 y 206 cm para los machos y entre 34 y 216 cm para las hembras. Por lo tanto, parece que los individuos de menos de 80 cm son siempre hembras y que tan solo algunos individuos cambian de sexo. La madurez sexual se alcanza alrededor de los 5-6 años para un tamaño de 110 cm. Un estudio demuestra que la madurez sexual para los machos se alcanza a los 115 cm en promedio por 122 cm para las hembras. Esto nuevamente socava la teoría del hermafroditismo protógino. Riesgos para los humanos Venenoso No Mordedor Sí Los individuos más grandes protegen cuidadosamente sus territorios. En algunas ocasiones, se han observado meros guasa siguiendo a buzos, adoptando posturas amenazantes y abriendo mucho la boca. Es recomendable evitar acercarse demasiado a estos peces y permanecer alerta en caso de encuentro. Del mismo modo, estos meros pueden causar lesiones graves a los pescadores que no están preparados o morder a los pescadores submarinos que mantienen su captura cerca del cuerpo. Origen y distribución Origen Golfo de México Mar del Caribe Océano Atlántico: costa norte de Brasil Océano Atlántico templado cálido del noroeste Océano Atlántico tropical Sudoeste Islas Islas Canarias Presencia geográfica y estado de la población Esta especie se encuentra bajo una importante presión por parte de la pesca recreativa e intensiva, su población, considerada vulnerable según la IUCN, se encuentra en constante declive. Sin una acción internacional colectiva, esta especie podría encontrarse rápidamente en peligro crítico. Observaciones locales recientes muestran que esta especie ya no se pesca ni se observa en África Occidental o en la isla de Guadalupe. Tratándose de un superdepredador, su rol de regulador es fundamental en los ecosistemas que frecuenta. La desaparición o rarefacción de esta especie probablemente provocaría una degradación de la biodiversidad debido a un efecto dominó. Esta especie es considerada un bioindicador en su entorno, y su sola presencia da una idea positiva de la riqueza de su entorno. Este pez también ayuda a regular especies invasoras como el Pterois volitans (pez león). El motivo de su declive está esencialmente ligado a la actividad pesquera, ya sea deportiva o industrial. La disminución en el número de individuos parece haber comenzado en la década de 1950. En la década de 1970, esta especie comenzó a ser menos habitual en las costas de Belice y Brasil. En la década de 1990, la población del Golfo de México ya había disminuido en más del 90%. Al ser una especie no muy tímida, su captura es muy fácil en pesca submarina, pudiéndose vaciar una zona de todos sus individuos en muy poco tiempo. Este factor, combinado con un crecimiento lento, una baja tasa de renovación de la población y un fuerte interés comercial, la convierten en una especie particularmente vulnerable. Otra razón del declive de la especie es la destrucción de su hábitat y en particular de las áreas de manglares, que son esenciales para los juveniles de esta especie. Las causas son múltiples, incluida la contaminación del agua vinculada a actividades humanas como el mercurio o los combustibles fósiles. Más anecdóticamente, esta especie es, en ocasiones, señalada como responsable de la mala pesca de peces y marisco, llegando a organizarse reducciones de población. A veces se ponen en marcha acciones locales, como la regulación de los tamaños de pesca, pero estas iniciativas todavía están mal conectadas y aún no permiten revertir la tendencia actual. Estado de conservación de las poblaciones (UICN) Mundo : VU ¿Dónde observar esta especie? ¿Cuál es su hábitat? Características del entorno natural Temperatura 23 - 28 °C Profundidad 0 - 100 m Presentación del biotopo Epinephelus itajara se encuentra con mayor frecuencia a una profundidad de entre 0 y 100 m. Sin embargo, no es imposible encontrar esta especie a otras profundidades. Esta especie frecuenta diferentes tipos de ambientes, rocosos, arenales, arrecifes, manglares, estuarios. Las larvas son pelágicas durante un promedio de 50 días, para después migrar a las zonas costeras y particularmente a los manglares, incluyendo áreas de mangle rojo (Rhizophora mangle). Los juveniles son eurihalinos y resistentes a salinidades muy bajas. Solo cuando maduran se trasladan a aguas más profundas. Los adultos prefieren las áreas de coral y especialmente los grandes relieves como naufragios o desniveles. Sedentarios, los adultos gustan de espacios ricos en cavidades y relieves variados que les permitan cazar, esconderse y dormir. Especie del mismo biotopo pez jabalí Caproidae raya mariposa Gymnuridae chopa Kyphosidae vieja colorada Scaridae ballesta común Balistidae raya redonda Dasyatidae Previous Next Para saber más Especie de la misma familia mero moteado Serranidae Serranocirrhitus latus Serranidae merlo del coral Serranidae serrano imperial Serranidae abade Serranidae serrano Serranidae Serranus subligarius Serranidae cabrilla reina Serranidae Previous Next Para leer en la web Fuentes y realización Participación y validación El equipo de Fishipedia y sus colaboradores especializados se comprometen a proporcionar contenido de alta calidad. Sin embargo, aunque la información proviene de fuentes científicas o testimonios de especialistas, los archivos pueden contener imprecisiones. Adrien Falzon Benoit Chartrer Traducción Traducción realizada con la valiosa contribución de nuestros traductores, quienes hacen que esta información esté disponible para un público más amplio. Silvia Gomez Referencias bibliográficas Mercury and histopathology of the vulnerable goliath grouper, Epinephelus itajara, in U.S. waters: a multi-tissue approach - Douglas H Adams - Christian Sonne - Elsevier Ltd - 2013. The influence of spear fishing on species composition and size of groupers on patch reefs in the upper Florida keys - Sluka RD - Sullivan KM - department of biology, University of Miami - 1998. The Effects of Fishing, Climate Change, and Other Anthropogenic Disturbances on Red Grouper and Other Reef Fishes in the Gulf of Mexico - Felicia C Coleman - Christopher C Koenig - Oxford University press - 2010. Le mérou géant (Epinephelus itajara) Synthèse bibliographique - David Fransolet - Université des Antilles et de la Guyane - 2014. Preliminary investigations of reproductive activity of the Jewfish, Epinephelus itajara (Pisces: Serranidae) - Patrick L. Colin - Caribbean Marine Research Center - 1990. Historical declines of goliath grouper populations in South Florida, USA. - Loren McClenachan - Inter-Research Science Publisher - 2009. FAO Species Catalogue. Vol. 16. Groupers of the world (family Serranidae, subfamily Epinephelinae). - Heemstra, P.C - J.E. Randall - FAO Fisheries Synopsis - 1993. Interactúa con Fishipedia Para ponerse en contacto con nuestro equipo o participar en nuestro proyecto. Contribuya a esta página Plantilla y contenido © Fishipedia - Reproducción no autorizada sin solicitud previa - ISSN 2270-7247 - Última actualización el 12/11/2023 © Fishipedia.fr 2024",
    "genderDescription": "Serranidae",
    "type": "Enciclopedia Explorar Acuariofilia A propósito Prensa Peces Ballestas Barracudas Doradas y sargos Escorpenas Hipocampos Lábridos Morenas Peces cirujano Peces globo Peces payaso Rayas Tiburones Reptiles Cocodrilos Serpientes Tortugas Moluscos Caracoles Nudibranquios Calamares Pulpos Sepias Otros temas Anfibios Cnidarios Crustáceos Amazonas Anaconda gigante Anguila eléctrica Paiche Piraña roja Raya motoro / Raya de rio Tararira Mediterráneo Atún rojo Congrio Dorada real Manta raya Mero Sargo Islas Canarias Ángel de mar Caballito de mar Pez roca de Madeira Pez trompeta atlántico Tiburón Mako Vieja colorada Mar del Caribe Cirujano azul Gran barracuda / Picúa Pez ángel francés pez ángel reina Raya jaspeada Robalo blanco Mar Rojo Mero del Coral Morena gigante Pez león Pez Napoléon Raya de arrecife Vieja florida Especies comunes Betta Splendens Chupa algas Corydoras Discos Escalar Gamba Red Cherry Guppy Pez dorado Pez payaso Grupos temáticos Cíclidos enanos Killis Lochas Luchadores Peces gato Tetras Vivíparos Práctica Peces compatibles 20 L Peces compatibles 40 L Peces compatibles 60 L Peces compatibles 80 L Peces compatibles 100 L El proyecto Fishipedia Nuestra ética Proyecto Yaku Nawi Los fotógrafos colaboradores CONTÁCTANOS Enciclopedia Peces Ballestas Barracudas Doradas y sargos Escorpenas Hipocampos Lábridos Morenas Peces cirujano Peces globo Peces payaso Rayas Tiburones Reptiles Cocodrilos Serpientes Tortugas Moluscos Caracoles Nudibranquios Calamares Pulpos Sepias Otros temas Anfibios Cnidarios Crustáceos Explorar Amazonas Anaconda gigante Anguila eléctrica Paiche Piraña roja Raya motoro / Raya de rio Tararira Mediterráneo Atún rojo Congrio Dorada real Manta raya Mero Sargo Islas Canarias Ángel de mar Caballito de mar Pez roca de Madeira Pez trompeta atlántico Tiburón Mako Vieja colorada Mar del Caribe Cirujano azul Gran barracuda / Picúa Pez ángel francés pez ángel reina Raya jaspeada Robalo blanco Mar Rojo Mero del Coral Morena gigante Pez león Pez Napoléon Raya de arrecife Vieja florida Acuariofilia Especies comunes Betta Splendens Chupa algas Corydoras Discos Escalar Gamba Red Cherry Guppy Pez dorado Pez payaso Grupos temáticos Cíclidos enanos Killis Lochas Luchadores Peces gato Tetras Vivíparos Práctica Peces compatibles 20 L Peces compatibles 40 L Peces compatibles 60 L Peces compatibles 80 L Peces compatibles 100 L A propósito El proyecto Fishipedia Nuestra ética Proyecto Yaku Nawi Los fotógrafos colaboradores CONTÁCTANOS Prensa",
    "size": "150 cm",
    "maxSize": "250 cm",
    "mimetism": "",
    "recognize": "",
    "fe/maleDifferences": "Parece que por debajo de los 80 cm, todos los meros goliath son hembras. Por encima de este tamaño, son machos o hembras sin dimorfismo aparente.",
    "diet": "carnívoro",
    "territorial": "Tamaño medio 150 cm Tamaño máximo 250 cm Longevidad 37 años Patrón moteado Epinephelus itajara, mero guasa © Xaime Beiro Epinephelus itajara, mero guasa © Xaime Beiro Previous Next Tamaño medio 150 cm Tamaño máximo 250 cm Longevidad 37 años Patrón moteado",
    "social": "solitario",
    "lifeMode": "dieta",
    "lifeDescription": "",
    "reproductionMode": "<  mero guasa  Epinephelus itajara  Lichtenstein  1822  (Mundo) VU  Serranidae  Epinephelus",
    "migration": "",
    "reproductionDescription": "",
    "poison": "No",
    "danger": "",
    "depth": "Enciclopedia Explorar Acuariofilia A propósito Prensa Peces Ballestas Barracudas Doradas y sargos Escorpenas Hipocampos Lábridos Morenas Peces cirujano Peces globo Peces payaso Rayas Tiburones Reptiles Cocodrilos Serpientes Tortugas Moluscos Caracoles Nudibranquios Calamares Pulpos Sepias Otros temas Anfibios Cnidarios Crustáceos Amazonas Anaconda gigante Anguila eléctrica Paiche Piraña roja Raya motoro / Raya de rio Tararira Mediterráneo Atún rojo Congrio Dorada real Manta raya Mero Sargo Islas Canarias Ángel de mar Caballito de mar Pez roca de Madeira Pez trompeta atlántico Tiburón Mako Vieja colorada Mar del Caribe Cirujano azul Gran barracuda / Picúa Pez ángel francés pez ángel reina Raya jaspeada Robalo blanco Mar Rojo Mero del Coral Morena gigante Pez león Pez Napoléon Raya de arrecife Vieja florida Especies comunes Betta Splendens Chupa algas Corydoras Discos Escalar Gamba Red Cherry Guppy Pez dorado Pez payaso Grupos temáticos Cíclidos enanos Killis Lochas Luchadores Peces gato Tetras Vivíparos Práctica Peces compatibles 20 L Peces compatibles 40 L Peces compatibles 60 L Peces compatibles 80 L Peces compatibles 100 L El proyecto Fishipedia Nuestra ética Proyecto Yaku Nawi Los fotógrafos colaboradores CONTÁCTANOS Enciclopedia Peces Ballestas Barracudas Doradas y sargos Escorpenas Hipocampos Lábridos Morenas Peces cirujano Peces globo Peces payaso Rayas Tiburones Reptiles Cocodrilos Serpientes Tortugas Moluscos Caracoles Nudibranquios Calamares Pulpos Sepias Otros temas Anfibios Cnidarios Crustáceos Explorar Amazonas Anaconda gigante Anguila eléctrica Paiche Piraña roja Raya motoro / Raya de rio Tararira Mediterráneo Atún rojo Congrio Dorada real Manta raya Mero Sargo Islas Canarias Ángel de mar Caballito de mar Pez roca de Madeira Pez trompeta atlántico Tiburón Mako Vieja colorada Mar del Caribe Cirujano azul Gran barracuda / Picúa Pez ángel francés pez ángel reina Raya jaspeada Robalo blanco Mar Rojo Mero del Coral Morena gigante Pez león Pez Napoléon Raya de arrecife Vieja florida Acuariofilia Especies comunes Betta Splendens Chupa algas Corydoras Discos Escalar Gamba Red Cherry Guppy Pez dorado Pez payaso Grupos temáticos Cíclidos enanos Killis Lochas Luchadores Peces gato Tetras Vivíparos Práctica Peces compatibles 20 L Peces compatibles 40 L Peces compatibles 60 L Peces compatibles 80 L Peces compatibles 100 L A propósito El proyecto Fishipedia Nuestra ética Proyecto Yaku Nawi Los fotógrafos colaboradores CONTÁCTANOS Prensa",
    "image": "",
    "mapImage": ""
  },
  {
    "name": "Epinephelus marginatus",
    "sciname": "",
    "IUCN": "",
    "description": "Introducción Epinephelus marginatus conocido también como \"mero común\" en el Mediterráneo. Este discreto depredador forma parte del grupo de los grandes cazadores de las zonas rocosas poco profundas. Muy apreciado por su carne, esta especie fue durante mucho tiempo la presa preferida de muchos pescadores. Denominado de muy diversas maneras según la región geográfica, como \"garoupa\" en Brasil, \"cernia bruna\" en Italia, \"mero\" en España y Portugal o \"mérou rouge\" en Túnez. A día de hoy, esta especie se encuentra considerada como amenazada por el IUCN, principalmente debido a la sobrepesca de la que ha sido objeto a lo largo de todo el siglo XX. En Córcega, donde se trata de una especie protegida, las poblaciones continúan desarrollándose a buen ritmo. ¿Quién es él?  Epinephelus En 2019, el género Epinephelus agrupaba 87 especies según Fishbase. Estos peces, denominados comúnmente \"meros\" pertenecen al \"grupo\" de los serránidos (Serranidae). Estos depredadores de carácter territorial poseen un cuerpo alargado y robusto. Con una cabeza imponente y una boca protráctil, posee una mandíbula que contiene en su parte delantera unos poderosos caninos. Todas las especies poseen 10 o 11 espinas dorsales. La mayor parte de estas especies se encuentran en los arrecifes de coral o en las zonas rocosas a excepción de E. aeneus, E. bruneus y E. areolatus que habitan en los fondos arenosos, limosos o fangosos. Los adultos suelen ser avistados a profundidades de entre 10 y 200 metros. La mayoría de los Epinephelus son animales hermafroditas protóginos, es decir, nacen hembras transformándose después en machos a medida que crecen. Sin embargo, es posible que no todas las hembras cambien de sexo y que algunos machos no desarrollen este estado comúnmente aceptado. Estos peces son muy valorados comercialmente para la alimentación y la pesca recreativa, pero son vulnerables a la sobrepesca debido a su crecimiento lento, madurez tardía y formación de agregaciones de reproducción. La sobrepesca, especialmente dirigida a los individuos maduros, puede causar desequilibrios en la proporción de sexos y afectar a la reproducción. Varias especies de meros ahora son objeto de cultivo en granjas acuícolas (especialmente E. coioides y E. malabaricus). Según la UICN, la sobrepesca y la contaminación ya han causado una disminución significativa de las poblaciones de muchos meros y varias especies están en peligro de extinción.  Tamaño medio 80 cm Tamaño máximo 140 cm Longevidad 50 años Mimetismo piedra Patrón moteado Epinephelus marginatus, mero © Xaime Beiro Epinephelus marginatus, mero © Xaime Beiro Epinephelus marginatus, mero © Xaime Beiro Previous Next Tamaño medio 80 cm Tamaño máximo 140 cm Longevidad 50 años Mimetismo piedra Patrón moteado ¿Cómo reconocer a Este pez ? El mero común tiene una cabeza y un cuerpo de color rojizo oscuro o grisáceo en la parte superior. El vientre es de un color claro, amarillento incluso, a veces. Numerosas manchas blancas o beiges son visibles en el cuerpo y a nivel de la cabeza. Las aletas impares presentan una coloración marrón oscuro, a menudo bordeadas de un margen blanco en la punta. Las aletas pélvicas y pectorales son oscuras, a menudo con un color amarillento en la base. Al igual que el resto de meros, esta especie posee numerosas espinas sobre las aletas, 11 sobre la dorsal y 3 sobre la aleta anal. Las simulaciones realizadas estiman una edad máxima en torno a los 35 años para un ejemplar de una longitud común de 120 cm. Diferencias entre machos y hembras La diferencia entre macho y hembra es claramente visible en esta especie. Los machos adultos presentan un mayor tamaño que las hembras. Modo de vida y comportamiento dieta carnívoro Sociabilidad solitario territorial Sí Modo de vida Diurno El mero común adulto vive en solitario, fuera de los períodos de reproducción. Habitual de las zonas rocosas, se trata de una especie territorial. Este hábil cazador, forma parte de los grandes depredadores de su biotopo, siendo los pulpos y los peces asociados a los arrecifes, sus principales presas. Generalmente, presenta un carácter tranquilo frente a los peces no territoriales, siempre que no se traten de presas potenciales. Al contrario, se mostrará agresivo frente a otras especies \"con carácter\" que se encuentren en su territorio. También puede mostrarse virulento frente a sus congéneres, en particular esto puede suceder entre machos. Reproducción Modo de reproducción ovíparo que desova en aguas abiertas Hermafrodita protógino Todos los individuos cambian de sexo. Esta especie de mero nace hembra para después modificar su sexo durante su desarrollo. La madurez sexual de las hembras se alcanza con 5 años. La transformación suele tener lugar entre los 10 y 15 años. Especies inofensivas Esta especie no supone ningún peligro en particular para el ser humano cuando se encuentra en su entorno natural. Origen y distribución Origen Mar Mediterráneo Océano Atlántico: costa norte de Brasil Océano Atlántico templado oriental Sudoeste del Océano Atlántico templado cálido Océano Atlántico tropical oriental Océano Atlántico tropical Sudoeste Islas Córcega Islas Canarias Cerdeña Sicilia Presencia geográfica y estado de la población El mero común es una de las especies más extendidas por el mundo. Siendo posible encontrarla a ambos lados del océano Atlántico, en todo el mar Mediterráneo y a lo largo de la punta sur de Sudáfrica. Ha sido documentado también en las aguas costeras de Mozambique y Madagascar, en la costa Este de Brasil, Uruguay y Argentina. En la zona del Mediterráneo ha sido visto (entre otros) en España, Francia, Italia, Grecia, Líbano, Israel, Algeria y Madeira, siendo objeto a día de hoy, de algunos planes de conservación debido a que las poblaciones han prácticamente desaparecido a lo largo del siglo XX. Estado de conservación de las poblaciones (UICN) Mundo : VU Francia : EN ¿Dónde observar esta especie? ¿Cuál es su hábitat? Características del entorno natural Temperatura 10 - 26 °C Profundidad 5 - 100 m Corriente Moderada y Lenta Presentación del biotopo Este pez suele ser observado a menudo a una profundidad inferior a los 100 metros. Sin embargo, es también posible avistarlo a otras profundidades. Habita las zonas rocosas, generalmente cerca de grandes cavidades. Especie del mismo biotopo blenio del Atlántico Blenniidae abade Serranidae pez verde Labridae mero moteado Serranidae Previous Next Para saber más Especie de la misma familia Mycteroperca bonaci Serranidae cabrilla reina Serranidae merlo del coral Serranidae abade Serranidae Plectropomus leopardus Serranidae Serranus subligarius Serranidae Cromileptes altivelis Serranidae mero moteado Serranidae Previous Next Para leer en la web Fuentes y realización Participación y validación El equipo de Fishipedia y sus colaboradores especializados se comprometen a proporcionar contenido de alta calidad. Sin embargo, aunque la información proviene de fuentes científicas o testimonios de especialistas, los archivos pueden contener imprecisiones. Benoit Chartrer Julie Magnus Silvia Gomez Traducción Traducción realizada con la valiosa contribución de nuestros traductores, quienes hacen que esta información esté disponible para un público más amplio. Silvia Gomez Referencias bibliográficas FAO Species Catalogue. Vol. 16. Groupers of the world (family Serranidae, subfamily Epinephelinae). - Heemstra, P.C - J.E. Randall - FAO Fisheries Synopsis - 1993. Induction of Female-to–male Sex Change in the Honeycomb Grouper (Epinephelus merra) by 11-ketotestosterone Treatments - Ramji Kumar Bhandari - Mohammad Ashraful Alam - Kiyoshi Soyano - Masaru Nakamura - Zoological Science - 2006. Interactúa con Fishipedia Para ponerse en contacto con nuestro equipo o participar en nuestro proyecto. Contribuya a esta página Plantilla y contenido © Fishipedia - Reproducción no autorizada sin solicitud previa - ISSN 2270-7247 - Última actualización el 14/11/2023 © Fishipedia.fr 2024",
    "genderDescription": "Serranidae",
    "type": "",
    "size": "80 cm",
    "maxSize": "140 cm",
    "mimetism": "piedra",
    "recognize": "",
    "fe/maleDifferences": "La diferencia entre macho y hembra es claramente visible en esta especie. Los machos adultos presentan un mayor tamaño que las hembras.",
    "diet": "carnívoro",
    "territorial": "Tamaño medio 80 cm Tamaño máximo 140 cm Longevidad 50 años Mimetismo piedra Patrón moteado Epinephelus marginatus, mero © Xaime Beiro Epinephelus marginatus, mero © Xaime Beiro Epinephelus marginatus, mero © Xaime Beiro Previous Next Tamaño medio 80 cm Tamaño máximo 140 cm Longevidad 50 años Mimetismo piedra Patrón moteado",
    "social": "solitario",
    "lifeMode": "dieta",
    "lifeDescription": "",
    "reproductionMode": "<  mero  Epinephelus marginatus  Lowe  1834  (Mundo) VU  Serranidae  Epinephelus",
    "migration": "",
    "reproductionDescription": "",
    "poison": "",
    "danger": "",
    "depth": "Enciclopedia Explorar Acuariofilia A propósito Prensa Peces Ballestas Barracudas Doradas y sargos Escorpenas Hipocampos Lábridos Morenas Peces cirujano Peces globo Peces payaso Rayas Tiburones Reptiles Cocodrilos Serpientes Tortugas Moluscos Caracoles Nudibranquios Calamares Pulpos Sepias Otros temas Anfibios Cnidarios Crustáceos Amazonas Anaconda gigante Anguila eléctrica Paiche Piraña roja Raya motoro / Raya de rio Tararira Mediterráneo Atún rojo Congrio Dorada real Manta raya Mero Sargo Islas Canarias Ángel de mar Caballito de mar Pez roca de Madeira Pez trompeta atlántico Tiburón Mako Vieja colorada Mar del Caribe Cirujano azul Gran barracuda / Picúa Pez ángel francés pez ángel reina Raya jaspeada Robalo blanco Mar Rojo Mero del Coral Morena gigante Pez león Pez Napoléon Raya de arrecife Vieja florida Especies comunes Betta Splendens Chupa algas Corydoras Discos Escalar Gamba Red Cherry Guppy Pez dorado Pez payaso Grupos temáticos Cíclidos enanos Killis Lochas Luchadores Peces gato Tetras Vivíparos Práctica Peces compatibles 20 L Peces compatibles 40 L Peces compatibles 60 L Peces compatibles 80 L Peces compatibles 100 L El proyecto Fishipedia Nuestra ética Proyecto Yaku Nawi Los fotógrafos colaboradores CONTÁCTANOS Enciclopedia Peces Ballestas Barracudas Doradas y sargos Escorpenas Hipocampos Lábridos Morenas Peces cirujano Peces globo Peces payaso Rayas Tiburones Reptiles Cocodrilos Serpientes Tortugas Moluscos Caracoles Nudibranquios Calamares Pulpos Sepias Otros temas Anfibios Cnidarios Crustáceos Explorar Amazonas Anaconda gigante Anguila eléctrica Paiche Piraña roja Raya motoro / Raya de rio Tararira Mediterráneo Atún rojo Congrio Dorada real Manta raya Mero Sargo Islas Canarias Ángel de mar Caballito de mar Pez roca de Madeira Pez trompeta atlántico Tiburón Mako Vieja colorada Mar del Caribe Cirujano azul Gran barracuda / Picúa Pez ángel francés pez ángel reina Raya jaspeada Robalo blanco Mar Rojo Mero del Coral Morena gigante Pez león Pez Napoléon Raya de arrecife Vieja florida Acuariofilia Especies comunes Betta Splendens Chupa algas Corydoras Discos Escalar Gamba Red Cherry Guppy Pez dorado Pez payaso Grupos temáticos Cíclidos enanos Killis Lochas Luchadores Peces gato Tetras Vivíparos Práctica Peces compatibles 20 L Peces compatibles 40 L Peces compatibles 60 L Peces compatibles 80 L Peces compatibles 100 L A propósito El proyecto Fishipedia Nuestra ética Proyecto Yaku Nawi Los fotógrafos colaboradores CONTÁCTANOS Prensa",
    "image": "",
    "mapImage": ""
  },
  {
    "name": "euthynnus alletteratus",
    "sciname": "",
    "IUCN": "",
    "description": "Introducción Euthynnus alletteratus, comúnmente conocido como la bacoreta, es un pez de agua salada tropical y templada presente en todo el océano Atlántico, el mar Mediterráneo, el mar Negro, el Canal de la Mancha y la zona del Caribe.  de realización. Los textos propuestos actualmente provienen de nuestro modelo de datos o están en proceso de redacción. Para solicitar prioridad para este contenido, puedes escribirnos AQUÍ. ¿Quién es ella?  Euthynnus El género Euthynnus es un género de peces que forma parte de la familia Scombridae. Esta familia incluye principalmente a los túnidos, bonitos y caballas. Este género abarca tres especies: E. affinis, E. alletteratus, E. lineatus, distribuidas en todas las zonas tropicales y templadas. Son peces pelágicos que viven en bancos cerca de la superficie. Se trata de depredadores activos que se alimentan de peces, crustáceos y moluscos. Son oportunistas y a veces se les observa cazando en compañía de delfines. Tienen un tamaño promedio de 80 centímetros. La reproducción ocurre en aguas abiertas y las larvas son pelágicas.  Tamaño medio 80 cm Tamaño máximo 122 cm Longevidad 10 años euthynnus alletteratus, bacoreta © Xavi Salvador Costa Tamaño medio 80 cm Tamaño máximo 122 cm Longevidad 10 años ¿Cómo reconocer a Este pez ? Presenta una forma ovalada, robusta y lateralmente comprimida. El vientre es de un tono plateado con la presencia de entre 3 y 7 manchas negras en la zona delantera, debajo de las aletas pectorales. La parte dorsal presenta matices azulados característicos de su especie. La aleta dorsal aparece reducida, ubicada al mismo nivel que la aleta anal. La aleta caudal tiene forma de creciente homocerca. Esta especie presenta ocho pinnas (aletas pequeñas) entre las aletas dorsal/anal y la aleta caudal en posición dorsal y ventral. Diferencias entre machos y hembras No hay dimorfismo aparente en esta especie. Modo de vida y comportamiento dieta carnívoro Sociabilidad bancos territorial No Modo de vida Diurno Es una especie pelágica que vive en bancos cerca de la superficie. Es un pez activo y oportunista que caza en aguas abiertas. A menudo se le observa aprovechando las estrategias de caza de otros depredadores como los atunes y los delfines. Esta especie es presa de el dorado, la melva, el pez espada y el tiburón. Reproducción Modo de reproducción ovíparo que desova en aguas abiertas Es una especie ovípara y la reproducción tiene lugar en aguas abiertas. La madurez sexual se alcanza con un tamaño de 34 centímetros. El desove se produce durante el calentamiento del agua en el Mar Mediterráneo, en los meses entre mayo y septiembre. El rango de temperatura para la reproducción se extiende de 24°C a 28°C. La hembra pone alrededor de 1,75 millones de huevos por año, y las larvas son posteriormente pelágicas. Especies inofensivas Esta especie no representa un peligro particular para los humanos en caso de encuentro en su entorno natural. Origen y distribución Origen Golfo de México Mar del Caribe Mar Mediterráneo Mar Negro Océano Atlántico: costa norte de Brasil Océano Atlántico templado oriental Océano Atlántico Oriental Frío Océano Atlántico noroeste templado frío Océano Atlántico templado cálido del noroeste Océano Atlántico tropical oriental Océano Atlántico tropical Sudoeste Islas Islas Canarias Cerdeña Sicilia Presencia geográfica y estado de la población Se encuentra presente en todo el océano Atlántico (desde el este del Skagerrak hasta Sudáfrica), así como en el Mar Mediterráneo, el Mar Negro, el Canal de la Mancha y la zona del Caribe. Estado de conservación de las poblaciones (UICN) Mundo : LC ¿Cuál es su hábitat? Características del entorno natural Temperatura 12 - 26 °C Profundidad 1 - 150 m  Pelágico activo Presentación del biotopo Euthynnus alletteratus se encuentra habitualmente cerca de la superficie, pero también ha sido registrado a profundidades de hasta 150 metros. Especie del mismo biotopo tiburón sedoso Carcharhinidae pez volador común Exocoetidae pez limón Carangidae tiburón blanco Lamnidae cazón Triakidae pez luna Molidae Previous Next Para saber más Especie de la misma familia caballa Scombridae caballa del Atlántico Scombridae Thunnus albacares Scombridae atún rojo del Atlántico Scombridae bonito del Atlántico Scombridae Previous Next Para leer en la web Fuentes y realización Participación y validación El equipo de Fishipedia y sus colaboradores especializados se comprometen a proporcionar contenido de alta calidad. Sin embargo, aunque la información proviene de fuentes científicas o testimonios de especialistas, los archivos pueden contener imprecisiones. Nans Gourgousse Adrien Falzon Traducción Traducción realizada con la valiosa contribución de nuestros traductores, quienes hacen que esta información esté disponible para un público más amplio. Silvia Gomez Referencias bibliográficas Estimating Age and Growth of Little Tunny, Euthynnus alletteratus, off the Coast of Senegal, Using Dorsal Fin Spine Sections - PATRICE M. CAYRE - TAIB DIOUP - NOAA - National Marine Fisheries Service - 1983. Reproductive biology of little tunny, Euthynnus alletteratus (Rafinesque), from the north-eastern Mediterranean Sea - A. E. Kahraman - T. Z. Alicli - T. Akayli - I. K. Oray - WILEY - 2008. Interactúa con Fishipedia Para ponerse en contacto con nuestro equipo o participar en nuestro proyecto. Contribuya a esta página Plantilla y contenido © Fishipedia - Reproducción no autorizada sin solicitud previa - ISSN 2270-7247 - Última actualización el 12/11/2023 © Fishipedia.fr 2024",
    "genderDescription": "Scombridae",
    "type": "",
    "size": "80 cm",
    "maxSize": "122 cm",
    "mimetism": "",
    "recognize": "",
    "fe/maleDifferences": "No hay dimorfismo aparente en esta especie.",
    "diet": "carnívoro",
    "territorial": "No",
    "social": "bancos",
    "lifeMode": "dieta",
    "lifeDescription": "",
    "reproductionMode": "<  bacoreta  euthynnus alletteratus  Rafinesque  1810  (Mundo) LC  Scombridae  Euthynnus",
    "migration": "",
    "reproductionDescription": "",
    "poison": "",
    "danger": "de realización. Los textos propuestos actualmente provienen de nuestro modelo de datos o están en proceso de redacción. Para solicitar prioridad para este contenido, puedes escribirnos AQUÍ.",
    "depth": "Enciclopedia Explorar Acuariofilia A propósito Prensa Peces Ballestas Barracudas Doradas y sargos Escorpenas Hipocampos Lábridos Morenas Peces cirujano Peces globo Peces payaso Rayas Tiburones Reptiles Cocodrilos Serpientes Tortugas Moluscos Caracoles Nudibranquios Calamares Pulpos Sepias Otros temas Anfibios Cnidarios Crustáceos Amazonas Anaconda gigante Anguila eléctrica Paiche Piraña roja Raya motoro / Raya de rio Tararira Mediterráneo Atún rojo Congrio Dorada real Manta raya Mero Sargo Islas Canarias Ángel de mar Caballito de mar Pez roca de Madeira Pez trompeta atlántico Tiburón Mako Vieja colorada Mar del Caribe Cirujano azul Gran barracuda / Picúa Pez ángel francés pez ángel reina Raya jaspeada Robalo blanco Mar Rojo Mero del Coral Morena gigante Pez león Pez Napoléon Raya de arrecife Vieja florida Especies comunes Betta Splendens Chupa algas Corydoras Discos Escalar Gamba Red Cherry Guppy Pez dorado Pez payaso Grupos temáticos Cíclidos enanos Killis Lochas Luchadores Peces gato Tetras Vivíparos Práctica Peces compatibles 20 L Peces compatibles 40 L Peces compatibles 60 L Peces compatibles 80 L Peces compatibles 100 L El proyecto Fishipedia Nuestra ética Proyecto Yaku Nawi Los fotógrafos colaboradores CONTÁCTANOS Enciclopedia Peces Ballestas Barracudas Doradas y sargos Escorpenas Hipocampos Lábridos Morenas Peces cirujano Peces globo Peces payaso Rayas Tiburones Reptiles Cocodrilos Serpientes Tortugas Moluscos Caracoles Nudibranquios Calamares Pulpos Sepias Otros temas Anfibios Cnidarios Crustáceos Explorar Amazonas Anaconda gigante Anguila eléctrica Paiche Piraña roja Raya motoro / Raya de rio Tararira Mediterráneo Atún rojo Congrio Dorada real Manta raya Mero Sargo Islas Canarias Ángel de mar Caballito de mar Pez roca de Madeira Pez trompeta atlántico Tiburón Mako Vieja colorada Mar del Caribe Cirujano azul Gran barracuda / Picúa Pez ángel francés pez ángel reina Raya jaspeada Robalo blanco Mar Rojo Mero del Coral Morena gigante Pez león Pez Napoléon Raya de arrecife Vieja florida Acuariofilia Especies comunes Betta Splendens Chupa algas Corydoras Discos Escalar Gamba Red Cherry Guppy Pez dorado Pez payaso Grupos temáticos Cíclidos enanos Killis Lochas Luchadores Peces gato Tetras Vivíparos Práctica Peces compatibles 20 L Peces compatibles 40 L Peces compatibles 60 L Peces compatibles 80 L Peces compatibles 100 L A propósito El proyecto Fishipedia Nuestra ética Proyecto Yaku Nawi Los fotógrafos colaboradores CONTÁCTANOS Prensa",
    "image": "",
    "mapImage": ""
  },
  {
    "name": "Exocoetus volitans",
    "sciname": "",
    "IUCN": "",
    "description": "Introducción Exocoetus volitans o pez volador es uno de los peces más curiosos del mundo marino. Se encuentra principalmente en las zonas tropicales y subtropicales, en todos los océanos del mundo. Esta especie es conocida por su capacidad para sobrevolar las aguas durante cientos de metros. Se cree que estos peces han evolucionado hasta adquirir esta característica con el fin de escapar de sus depredadores, como los verdeles, los atunes y otros grandes peces pelágicos. ¿Quién es él?  Exocoetus El género Exocoetus pertenece a la familia Exocoetidae que agrupa cerca de 70 especies. La mayor parte de estos peces son conocidos comúnmente como peces voladores. Las aletas pectorales son excepcionalmente grandes en estos peces, lo que les permite planear sobre el agua durante largas distancias. Estos peces se asemejan a los Cypselurus, sin embargo estos últimos tienen unas aletas pélvicas más alargadas por lo que parece que poseen cuatro alas. Estos peces pelágicos viven formando grandes bancos y se alimentan de plancton y crustáceos.  Tamaño medio 20 cm Tamaño máximo 30 cm Exocoetus volitans, pez volador común © Cédric Pau Tamaño medio 20 cm Tamaño máximo 30 cm ¿Cómo reconocer a Este pez ? El cuerpo, con forma de torpedo aerodinámico, permite a esta especie alcanzar altas velocidades. Este pez se sirve de sus grandes aletas pectorales, así como de las aletas pélvicas, para salir del agua y volar durante un período de tiempo relativamente largo. Las aletas no presentan espinas, y el lóbulo superior de la aleta caudal es más pequeño que el inferior. Normalmente esta especie mide cerca de 20 cm. El cuerpo y la cabeza están recubiertos de unas escamas grandes y blandas. Su coloración azul oscuro iridiscente en la parte de arriba y plateado en la parte de abajo le permite camuflarse con el cielo cuando el pez salta fuera del agua. Las aletas pectorales y caudal son de color gris, mientras el resto de aletas son transparentes. Al igual que sus congéneres, esta especie posee unos ojos planos. Lo que les permite ver fuera del agua. Diferencias entre machos y hembras Esta especie no presenta dimorfismo. No es posible diferencia machos y hembras a simple vista. Modo de vida y comportamiento dieta carnívoro Sociabilidad bancos territorial No Modo de vida Diurno En realidad, los peces voladores no vuelan, sino que planean en el aire. Varios estudios científicos se basan en la teoría de que estos peces han desarrollado esta característica para escapar de sus depredadores. Sin embargo, al salir del agua, se convierten también en presas de numerosas aves marinas. Para poder volar, estos peces deben alcanzar una gran velocidad dentro del agua, cerca de 50 km/h. Para alcanzar esta velocidad, utilizan principalmente su cola, que pueden llegar a batir hasta 50 veces por segundo. Una vez la velocidad ha sido alcanzada, se dirigen a la superficie donde despliegan sus aletas pectorales, permaneciendo con la cola sumergida en el agua hasta el último momento. Esta última será utilizada para propulsarse, lo que les permitirá alcanzar una altura de varios metros, planeando sobre el agua hasta un centenar de metros. Aunque el empuje viene producido por la acción de la cola, son sus largas aletas pectorales las que les ayudan a mantener la estabilidad durante el vuelo. El vuelo puede consistir a veces en numerosos deslizamientos, durante los cuales recuperar impulso. Este movimiento suele observarse a menudo en sincronización en todo el banco. Al igual que estos congéneres, esta especie se alimenta principalmente de plancton y pequeños crustáceos. Reproducción Modo de reproducción ovovivíparo Exocoetus volitans es un pez ovíparo, los huevos de esta especie son planctónicos. Las hembras ponen sus huevos en las algas e incluso a veces los liberan directamente en el agua. Estos huevos son muy cotizados en países como Japón, donde se utilizan para preparar sushi. Especies inofensivas Esta especie no supone ningún peligro en particular para el ser humano cuando se encuentra en su entorno natural. Origen y distribución Origen Golfo de Bengala Golfo de México Golfo Pérsico Gran Barrera de Coral mar Arábigo mar de China oriental Mar del Caribe Mar de Filipinas Mar de Japón Mar Mediterráneo Mares del Sudeste Asiático Mares indonesios Océano Atlántico: costa norte de Brasil Océano Atlántico templado oriental Océano Atlántico templado cálido del noroeste Sudoeste del Océano Atlántico templado cálido Océano Atlántico tropical oriental Océano Atlántico tropical Sudoeste Océano Índico occidental Galápagos Océano Pacífico tropical oriental Océano Pacífico tropical occidental Oceanía Islas Islas Canarias La Reunión Cerdeña Sicilia Presencia geográfica y estado de la población El pez volador se encuentra en las zonas tropicales y subtropicales de todos los océanos, en el mar Mediterráneo occidental y en algunas zonas del mar del Caribe. Ausente en los mares interiores del Sudeste asiático. En el océano Pacífico es posible encontrarlo desde México hasta el centro de Chile, documentado también en Galápagos, Hawaii, en las aguas de Japón, Filipinas, Australia y Tahití. Estos peces son pescados durante las épocas de primavera y verano con fines comerciales, siendo también utilizados como cebo en la pesca del pez espada y el atún. Estado de conservación de las poblaciones (UICN) Mundo : LC ¿Cuál es su hábitat? Características del entorno natural Temperatura 23 - 29 °C Profundidad 0 - 20 m  Pelágico activo Presentación del biotopo Esta especie vive normalmente a poca profundidad, tanto en aguas cercanas a la costa como en aguas abiertas. Especie del mismo biotopo tiburón peregrino Cetorhinidae bacoreta Scombridae tiburón ballena Rhincodontidae pez piloto Carangidae tiburón sarda Carcharhinidae Platax teira Ephippidae Previous Next Para saber más Para leer en la web Fuentes y realización Participación y validación El equipo de Fishipedia y sus colaboradores especializados se comprometen a proporcionar contenido de alta calidad. Sin embargo, aunque la información proviene de fuentes científicas o testimonios de especialistas, los archivos pueden contener imprecisiones. Silvia Gomez Benoit Chartrer Traducción Traducción realizada con la valiosa contribución de nuestros traductores, quienes hacen que esta información esté disponible para un público más amplio. Silvia Gomez Interactúa con Fishipedia Para ponerse en contacto con nuestro equipo o participar en nuestro proyecto. Contribuya a esta página Plantilla y contenido © Fishipedia - Reproducción no autorizada sin solicitud previa - ISSN 2270-7247 - Última actualización el 16/11/2023 © Fishipedia.fr 2024",
    "genderDescription": "Exocoetidae",
    "type": "",
    "size": "20 cm",
    "maxSize": "30 cm",
    "mimetism": "",
    "recognize": "",
    "fe/maleDifferences": "Esta especie no presenta dimorfismo. No es posible diferencia machos y hembras a simple vista.",
    "diet": "carnívoro",
    "territorial": "No",
    "social": "bancos",
    "lifeMode": "dieta",
    "lifeDescription": "",
    "reproductionMode": "<  pez volador común  Exocoetus volitans  Linnaeus  1758  (Mundo) LC  Exocoetidae  Exocoetus",
    "migration": "",
    "reproductionDescription": "",
    "poison": "",
    "danger": "",
    "depth": "Enciclopedia Explorar Acuariofilia A propósito Prensa Peces Ballestas Barracudas Doradas y sargos Escorpenas Hipocampos Lábridos Morenas Peces cirujano Peces globo Peces payaso Rayas Tiburones Reptiles Cocodrilos Serpientes Tortugas Moluscos Caracoles Nudibranquios Calamares Pulpos Sepias Otros temas Anfibios Cnidarios Crustáceos Amazonas Anaconda gigante Anguila eléctrica Paiche Piraña roja Raya motoro / Raya de rio Tararira Mediterráneo Atún rojo Congrio Dorada real Manta raya Mero Sargo Islas Canarias Ángel de mar Caballito de mar Pez roca de Madeira Pez trompeta atlántico Tiburón Mako Vieja colorada Mar del Caribe Cirujano azul Gran barracuda / Picúa Pez ángel francés pez ángel reina Raya jaspeada Robalo blanco Mar Rojo Mero del Coral Morena gigante Pez león Pez Napoléon Raya de arrecife Vieja florida Especies comunes Betta Splendens Chupa algas Corydoras Discos Escalar Gamba Red Cherry Guppy Pez dorado Pez payaso Grupos temáticos Cíclidos enanos Killis Lochas Luchadores Peces gato Tetras Vivíparos Práctica Peces compatibles 20 L Peces compatibles 40 L Peces compatibles 60 L Peces compatibles 80 L Peces compatibles 100 L El proyecto Fishipedia Nuestra ética Proyecto Yaku Nawi Los fotógrafos colaboradores CONTÁCTANOS Enciclopedia Peces Ballestas Barracudas Doradas y sargos Escorpenas Hipocampos Lábridos Morenas Peces cirujano Peces globo Peces payaso Rayas Tiburones Reptiles Cocodrilos Serpientes Tortugas Moluscos Caracoles Nudibranquios Calamares Pulpos Sepias Otros temas Anfibios Cnidarios Crustáceos Explorar Amazonas Anaconda gigante Anguila eléctrica Paiche Piraña roja Raya motoro / Raya de rio Tararira Mediterráneo Atún rojo Congrio Dorada real Manta raya Mero Sargo Islas Canarias Ángel de mar Caballito de mar Pez roca de Madeira Pez trompeta atlántico Tiburón Mako Vieja colorada Mar del Caribe Cirujano azul Gran barracuda / Picúa Pez ángel francés pez ángel reina Raya jaspeada Robalo blanco Mar Rojo Mero del Coral Morena gigante Pez león Pez Napoléon Raya de arrecife Vieja florida Acuariofilia Especies comunes Betta Splendens Chupa algas Corydoras Discos Escalar Gamba Red Cherry Guppy Pez dorado Pez payaso Grupos temáticos Cíclidos enanos Killis Lochas Luchadores Peces gato Tetras Vivíparos Práctica Peces compatibles 20 L Peces compatibles 40 L Peces compatibles 60 L Peces compatibles 80 L Peces compatibles 100 L A propósito El proyecto Fishipedia Nuestra ética Proyecto Yaku Nawi Los fotógrafos colaboradores CONTÁCTANOS Prensa",
    "image": "",
    "mapImage": ""
  },
  {
    "name": "Ginglymostoma cirratum",
    "sciname": "",
    "IUCN": "",
    "description": "Introducción Ginglymostoma cirratum, más conocido como tiburón nodriza o tiburón gata, es un pez tropical que se encuentra en el océano Atlántico. Ha sido observado en el golfo de México, en el mar del Caribe y hasta la parte sur de Brasil. ¿Quién es él?  Ginglymostoma El género Ginglymostoma pertenece a la familia Ginglymostomatidae, que incluye a la mayoría de los tiburones nodriza. Este nombre hace referencia al sonido de succión que producen estos peces con sus bocas, similar al de un bebé durante la lactancia. También son conocidos como tiburones dormilones. Inmóviles en el fondo, duermen cerca de 20 horas al día. A diferencia de la mayoría de los tiburones, no necesitan nadar para respirar. Tienen una respiración activa. La apertura y cierre de la boca, asociada a la contracción del faringe, permite que el agua circule desde la boca hasta las branquias.  Tipo tiburón Tamaño medio 240 cm Tamaño máximo 430 cm Longevidad 25 años Forma Rectangular Ginglymostoma cirratum, tiburón nodriza © Xaime Beiro Ginglymostoma cirratum, tiburón nodriza © Kevin Bryant Ginglymostoma cirratum, tiburón nodriza © Kevin Bryant Ginglymostoma cirratum, tiburón nodriza © Kevin Bryant Ginglymostoma cirratum, tiburón nodriza © Kevin Bryant Previous Next Tipo tiburón Tamaño medio 240 cm Tamaño máximo 430 cm Longevidad 25 años Forma Rectangular ¿Cómo reconocer a Este pez ? El tiburón nodriza, de color grisaceo o marrón, se caracteriza principalmente por tener un cuerpo alargado, un hocico de forma redondeada y unos ojos pequeños. La boca aparece en posición ventral coronada por dos fosas nasales y dos barbillas. La primera aleta dorsal está situada en la parte trasera del dorso, al nivel de las aletas pélvicas. Estas últimas son largas y cortas. La segunda aleta dorsal, más pequeña, está situada al mismo nivel que la aleta anal y muy cercana a la primera aleta dorsal. La aleta caudal tiene un único lóbulo y mide cerca de un cuarto del total del cuerpo, mientras las aletas pectorales son alargadas y con forma de triángulo. Tan sólo cuatro de las cinco hendiduras branquiales son visibles. Diferencias entre machos y hembras Al igual que ocurre en las rayas, los tiburones macho poseen un par de pterigopodios. Se trata de unos apéndices que se producen por la modificación de las aletas pélvicas y que permiten la transmisión del esperma hasta la cloaca de la hembra. Los machos pueden utilizar sólo uno a la vez. Modo de vida y comportamiento dieta carnívoro Sociabilidad solitario territorial No Modo de vida Nocturno De carácter solitario, el tiburón nodriza pasa la mayor parte del día durmiendo, escondido bajo rocas o en grietas. Esta especie nocturna se nutre principalmente de crustáceos, erizos, moluscos y algunos peces. Reproducción Modo de reproducción ovovivíparo El tiburón nodriza es ovíparo y alcanza la madurez sexual con un tamaño cercano a los 220 cm. Durante el acoplamiento, uno o dos machos rodean a la hembra, a veces incluso sujetando una de sus aletas con la boca. Seguidamente la hembra se pondrá boca arriba permitiendo así a uno de los machos fecundarla con uno de sus pterigopodios, mientras se gira sobre su espalda. Pasados unos 5 o 6 meses, la hembra dará a luz un gran número de crías, de 21 a 30, cada una de las cuales puede medir hasta 30 cm. Riesgos para los humanos Venenoso No Aunque esta especie no se caracteriza por su agresividad, podría llegar a morder a algún buceador demasiado intrusivo. Origen y distribución Origen Golfo de México Mar del Caribe Océano Atlántico: costa norte de Brasil Océano Atlántico templado cálido del noroeste Sudoeste del Océano Atlántico templado cálido Océano Atlántico tropical Sudoeste Islas Islas Canarias Estado de conservación de las poblaciones (UICN) Mundo : VU ¿Dónde observar esta especie? ¿Cuál es su hábitat? Características del entorno natural Profundidad 0 - 130 m  Pelágico activo Presentación del biotopo Este especie puede observarse hasta los 200 metros aunque en general es más probable encontrarla entre 15 y 25 metros de profundidad. Frecuenta las aguas cercanas a la costa, desde las zonas de surf a las bahías poco profundas. Así mismo está presente en la zona situada sobre las placas continentales exteriores. Este tiburón pasa la mayor parte del tiempo en el fondo del agua aunque, ocasionalmente, puede ser visto en aguas intermedias e incluso cercanas a la superficie. Especie del mismo biotopo pez limón Carangidae moma Blenniidae caballito de mar común Syngnathidae bonito del Atlántico Scombridae palometa Carangidae galán Labridae Previous Next Mantenimiento en cautividad No recomendado Fuera de acuarios públicos muy grandes, este pez no tiene lugar en cautiverio. Es uno de los tiburones más comúnmente exhibidos y estudiados en grandes instalaciones. Para saber más Especie de la misma familia Nebrius ferrugineus Ginglymostomatidae tiburón nodriza de cola corta Ginglymostomatidae Previous Next Para leer en la web Fuentes y realización Participación y validación El equipo de Fishipedia y sus colaboradores especializados se comprometen a proporcionar contenido de alta calidad. Sin embargo, aunque la información proviene de fuentes científicas o testimonios de especialistas, los archivos pueden contener imprecisiones. Adrien Falzon Benoit Chartrer Traducción Traducción realizada con la valiosa contribución de nuestros traductores, quienes hacen que esta información esté disponible para un público más amplio. Silvia Gomez Interactúa con Fishipedia Para ponerse en contacto con nuestro equipo o participar en nuestro proyecto. Contribuya a esta página Plantilla y contenido © Fishipedia - Reproducción no autorizada sin solicitud previa - ISSN 2270-7247 - Última actualización el 16/11/2023 © Fishipedia.fr 2024",
    "genderDescription": "Ginglymostomatidae",
    "type": "",
    "size": "240 cm",
    "maxSize": "430 cm",
    "mimetism": "",
    "recognize": "",
    "fe/maleDifferences": "Al igual que ocurre en las rayas, los tiburones macho poseen un par de pterigopodios. Se trata de unos apéndices que se producen por la modificación de las aletas pélvicas y que permiten la transmisión del esperma hasta la cloaca de la hembra. Los machos pueden utilizar sólo uno a la vez.",
    "diet": "carnívoro",
    "territorial": "No",
    "social": "solitario",
    "lifeMode": "dieta",
    "lifeDescription": "",
    "reproductionMode": "<  tiburón nodriza  Ginglymostoma cirratum  Bonnaterre  1788  (Mundo) VU  Ginglymostomatidae  Ginglymostoma",
    "migration": "",
    "reproductionDescription": "",
    "poison": "No",
    "danger": "",
    "depth": "Enciclopedia Explorar Acuariofilia A propósito Prensa Peces Ballestas Barracudas Doradas y sargos Escorpenas Hipocampos Lábridos Morenas Peces cirujano Peces globo Peces payaso Rayas Tiburones Reptiles Cocodrilos Serpientes Tortugas Moluscos Caracoles Nudibranquios Calamares Pulpos Sepias Otros temas Anfibios Cnidarios Crustáceos Amazonas Anaconda gigante Anguila eléctrica Paiche Piraña roja Raya motoro / Raya de rio Tararira Mediterráneo Atún rojo Congrio Dorada real Manta raya Mero Sargo Islas Canarias Ángel de mar Caballito de mar Pez roca de Madeira Pez trompeta atlántico Tiburón Mako Vieja colorada Mar del Caribe Cirujano azul Gran barracuda / Picúa Pez ángel francés pez ángel reina Raya jaspeada Robalo blanco Mar Rojo Mero del Coral Morena gigante Pez león Pez Napoléon Raya de arrecife Vieja florida Especies comunes Betta Splendens Chupa algas Corydoras Discos Escalar Gamba Red Cherry Guppy Pez dorado Pez payaso Grupos temáticos Cíclidos enanos Killis Lochas Luchadores Peces gato Tetras Vivíparos Práctica Peces compatibles 20 L Peces compatibles 40 L Peces compatibles 60 L Peces compatibles 80 L Peces compatibles 100 L El proyecto Fishipedia Nuestra ética Proyecto Yaku Nawi Los fotógrafos colaboradores CONTÁCTANOS Enciclopedia Peces Ballestas Barracudas Doradas y sargos Escorpenas Hipocampos Lábridos Morenas Peces cirujano Peces globo Peces payaso Rayas Tiburones Reptiles Cocodrilos Serpientes Tortugas Moluscos Caracoles Nudibranquios Calamares Pulpos Sepias Otros temas Anfibios Cnidarios Crustáceos Explorar Amazonas Anaconda gigante Anguila eléctrica Paiche Piraña roja Raya motoro / Raya de rio Tararira Mediterráneo Atún rojo Congrio Dorada real Manta raya Mero Sargo Islas Canarias Ángel de mar Caballito de mar Pez roca de Madeira Pez trompeta atlántico Tiburón Mako Vieja colorada Mar del Caribe Cirujano azul Gran barracuda / Picúa Pez ángel francés pez ángel reina Raya jaspeada Robalo blanco Mar Rojo Mero del Coral Morena gigante Pez león Pez Napoléon Raya de arrecife Vieja florida Acuariofilia Especies comunes Betta Splendens Chupa algas Corydoras Discos Escalar Gamba Red Cherry Guppy Pez dorado Pez payaso Grupos temáticos Cíclidos enanos Killis Lochas Luchadores Peces gato Tetras Vivíparos Práctica Peces compatibles 20 L Peces compatibles 40 L Peces compatibles 60 L Peces compatibles 80 L Peces compatibles 100 L A propósito El proyecto Fishipedia Nuestra ética Proyecto Yaku Nawi Los fotógrafos colaboradores CONTÁCTANOS Prensa",
    "image": "",
    "mapImage": ""
  },
  {
    "name": "Gobius niger",
    "sciname": "",
    "IUCN": "",
    "description": "Introducción Gobius niger, comúnmente denominado gobio negro o chaparrudo, se encuentra desde la costa del Atlántico Este hasta el mar Negro. Esta especie litoral se encuentra a poca profundidad, en zonas rocosas o limosas. También ha sido registrada en aguas salobres, en estuarios.  de realización. Los textos propuestos actualmente provienen de nuestro modelo de datos o están en proceso de redacción. Para solicitar prioridad para este contenido, puedes escribirnos AQUÍ. ¿Quién es él?  Gobius \"Gobius\" proviene del griego \"kobios\", que significa \"pez pequeño\". En 2023, el género Gobius comprende 30 especies según Fishbase. Estos peces son depredadores de pequeño tamaño que se mantienen inmóviles en el fondo. Se mimetizan con su entorno para sorprender a sus presas. La boca es protractil, y la presa es directamente engullida, de ahí el término común de gobio.  Tamaño medio 16 cm Tamaño máximo 18 cm Longevidad 5 años Forma Rectangular Mimetismo fondo rocoso Patrón moteado Gobius niger, gobio negro © Thomas Menut Tamaño medio 16 cm Tamaño máximo 18 cm Longevidad 5 años Forma Rectangular Mimetismo fondo rocoso Patrón moteado ¿Cómo reconocer a Este pez ? Se trata de una de las especies de gobios más grandes que habitan en la zona del Mediterráneo. El cuerpo tiene una tonalidad oscura en los adultos y presenta una característica mancha negra sobre la primera aleta dorsal. Diferencias entre machos y hembras La dimorfismo es bastante evidente en esta especie. La hembra tiene un cuerpo moteado gris/marrón, mientras que el macho es más oscuro, a veces incluso negro. La primera aleta aparece más desarrollada y los segundos y terceros radios son más largos. Los machos no dominantes son miméticos de las hembras. Adoptan un comportamiento parasitario durante la reproducción. Modo de vida y comportamiento dieta carnívoro Sociabilidad solitario territorial No Modo de vida Diurno Se trata de un pez solitario y territorial. Los machos presentan un comportamiento muy agresivo durante los períodos de reproducción, protegiendo un área de aproximadamente un metro de diámetro. Este pequeño depredador frecuenta las orillas del mar y los ambientes salobres, se encuentra en fondos arenosos o en praderas marinas. Discreto, se mimetiza con el entorno para capturar a sus presas. Se alimenta de crustáceos, pequeños peces, bivalvos, gasterópodos y gusanos poliquetos. Reproducción Modo de reproducción ovíparo que desova en sustrato oculto El período de reproducción tiene lugar en los meses entre marzo y septiembre. El macho emite una especie de gruñidos con el fin de atraer a las hembras a un nido que construye debajo de una piedra o un objeto artificial (bloque de hormigón, botella de vidrio, etc.). La puesta, que contiene entre 4,000 y 35,000 huevos, se deposita en el techo del nido, y los machos cuidan la puesta durante 5 a 6 días hasta que eclosiona. Las larvas son pelágicas. Especies inofensivas Este pez no representa un peligro particular para los humanos en caso de encuentro en su entorno natural. Origen y distribución Origen Mar Mediterráneo Mar Negro Océano Atlántico templado oriental Océano Atlántico Oriental Frío Islas Córcega Islas Canarias Cerdeña Sicilia Presencia geográfica y estado de la población En la fachada atlántica, esta especie se encuentra desde las aguas noruegas hasta las Islas Canarias. También está presente en el mar Mediterráneo y en el mar Negro. Estado de conservación de las poblaciones (UICN) Mundo : LC ¿Dónde observar esta especie? ¿Cuál es su hábitat? Características del entorno natural Temperatura 8 - 24 °C Profundidad 1 - 50 m Presentación del biotopo Este pez se encuentra con mayor frecuencia a profundidades inferiores a 40 metros. Más comúnmente, suele ser avistado en zonas menores a 15 metros, especialmente en lagunas y estuarios. Especie del mismo biotopo gobio de roca Gobiidae Chelon saliens Mugilidae merlo Labridae pez pipa de rayas negras Syngnathidae tordo verde Labridae Salaria pavo Blenniidae Previous Next Para saber más Especie de la misma familia Stiphodon imperiorientis Gobiidae Elacatinus evelynae Gobiidae Gobiodon okinawae Gobiidae Sicyopus auxilimentus Gobiidae Neogobius melanostomus Gobiidae Sicyopterus lagocephalus Gobiidae Stiphodon alcedo Gobiidae pez dragón de aleta negra Gobiidae Previous Next Para leer en la web Fuentes y realización Participación y validación El equipo de Fishipedia y sus colaboradores especializados se comprometen a proporcionar contenido de alta calidad. Sin embargo, aunque la información proviene de fuentes científicas o testimonios de especialistas, los archivos pueden contener imprecisiones. Adrien Falzon Benoit Chartrer Traducción Traducción realizada con la valiosa contribución de nuestros traductores, quienes hacen que esta información esté disponible para un público más amplio. Silvia Gomez Interactúa con Fishipedia Para ponerse en contacto con nuestro equipo o participar en nuestro proyecto. Contribuya a esta página Plantilla y contenido © Fishipedia - Reproducción no autorizada sin solicitud previa - ISSN 2270-7247 - Última actualización el 12/11/2023 © Fishipedia.fr 2024",
    "genderDescription": "Gobiidae",
    "type": "",
    "size": "16 cm",
    "maxSize": "18 cm",
    "mimetism": "fondo rocoso",
    "recognize": "",
    "fe/maleDifferences": "La dimorfismo es bastante evidente en esta especie. La hembra tiene un cuerpo moteado gris/marrón, mientras que el macho es más oscuro, a veces incluso negro. La primera aleta aparece más desarrollada y los segundos y terceros radios son más largos. Los machos no dominantes son miméticos de las hembras. Adoptan un comportamiento parasitario durante la reproducción.",
    "diet": "carnívoro",
    "territorial": "No",
    "social": "solitario",
    "lifeMode": "dieta",
    "lifeDescription": "",
    "reproductionMode": "<  gobio negro  Gobius niger  Linnaeus  1758  (Mundo) LC  Gobiidae  Gobius",
    "migration": "",
    "reproductionDescription": "",
    "poison": "",
    "danger": "de realización. Los textos propuestos actualmente provienen de nuestro modelo de datos o están en proceso de redacción. Para solicitar prioridad para este contenido, puedes escribirnos AQUÍ.",
    "depth": "Enciclopedia Explorar Acuariofilia A propósito Prensa Peces Ballestas Barracudas Doradas y sargos Escorpenas Hipocampos Lábridos Morenas Peces cirujano Peces globo Peces payaso Rayas Tiburones Reptiles Cocodrilos Serpientes Tortugas Moluscos Caracoles Nudibranquios Calamares Pulpos Sepias Otros temas Anfibios Cnidarios Crustáceos Amazonas Anaconda gigante Anguila eléctrica Paiche Piraña roja Raya motoro / Raya de rio Tararira Mediterráneo Atún rojo Congrio Dorada real Manta raya Mero Sargo Islas Canarias Ángel de mar Caballito de mar Pez roca de Madeira Pez trompeta atlántico Tiburón Mako Vieja colorada Mar del Caribe Cirujano azul Gran barracuda / Picúa Pez ángel francés pez ángel reina Raya jaspeada Robalo blanco Mar Rojo Mero del Coral Morena gigante Pez león Pez Napoléon Raya de arrecife Vieja florida Especies comunes Betta Splendens Chupa algas Corydoras Discos Escalar Gamba Red Cherry Guppy Pez dorado Pez payaso Grupos temáticos Cíclidos enanos Killis Lochas Luchadores Peces gato Tetras Vivíparos Práctica Peces compatibles 20 L Peces compatibles 40 L Peces compatibles 60 L Peces compatibles 80 L Peces compatibles 100 L El proyecto Fishipedia Nuestra ética Proyecto Yaku Nawi Los fotógrafos colaboradores CONTÁCTANOS Enciclopedia Peces Ballestas Barracudas Doradas y sargos Escorpenas Hipocampos Lábridos Morenas Peces cirujano Peces globo Peces payaso Rayas Tiburones Reptiles Cocodrilos Serpientes Tortugas Moluscos Caracoles Nudibranquios Calamares Pulpos Sepias Otros temas Anfibios Cnidarios Crustáceos Explorar Amazonas Anaconda gigante Anguila eléctrica Paiche Piraña roja Raya motoro / Raya de rio Tararira Mediterráneo Atún rojo Congrio Dorada real Manta raya Mero Sargo Islas Canarias Ángel de mar Caballito de mar Pez roca de Madeira Pez trompeta atlántico Tiburón Mako Vieja colorada Mar del Caribe Cirujano azul Gran barracuda / Picúa Pez ángel francés pez ángel reina Raya jaspeada Robalo blanco Mar Rojo Mero del Coral Morena gigante Pez león Pez Napoléon Raya de arrecife Vieja florida Acuariofilia Especies comunes Betta Splendens Chupa algas Corydoras Discos Escalar Gamba Red Cherry Guppy Pez dorado Pez payaso Grupos temáticos Cíclidos enanos Killis Lochas Luchadores Peces gato Tetras Vivíparos Práctica Peces compatibles 20 L Peces compatibles 40 L Peces compatibles 60 L Peces compatibles 80 L Peces compatibles 100 L A propósito El proyecto Fishipedia Nuestra ética Proyecto Yaku Nawi Los fotógrafos colaboradores CONTÁCTANOS Prensa",
    "image": "",
    "mapImage": ""
  },
  {
    "name": "Gobius paganellus",
    "sciname": "",
    "IUCN": "",
    "description": "Introducción Gobius paganellus, más comúnmente denominado gobio de roca, es un pez que habita en agua dulce, agua salobre y agua de mar.  de realización. Los textos propuestos actualmente provienen de nuestro modelo de datos o están en proceso de redacción. Para solicitar prioridad para este contenido, puedes escribirnos AQUÍ. ¿Quién es él?  Gobius \"Gobius\" proviene del griego \"kobios\", que significa \"pez pequeño\". En 2023, el género Gobius comprende 30 especies según Fishbase. Estos peces son depredadores de pequeño tamaño que se mantienen inmóviles en el fondo. Se mimetizan con su entorno para sorprender a sus presas. La boca es protractil, y la presa es directamente engullida, de ahí el término común de gobio.  Tamaño medio 7 cm Tamaño máximo 13 cm Forma Rectangular Mimetismo plantas Gobius paganellus, gobio de roca © Brenton Prigge Gobius paganellus, gobio de roca © Dennis Rabeling Previous Next Tamaño medio 7 cm Tamaño máximo 13 cm Forma Rectangular Mimetismo plantas ¿Cómo reconocer a Este pez ? El gobio de roca mide alrededor de 7 cm. Los machos dominantes pueden, sin embargo, llegar a alcanzar los 13 cm. Este pez presenta una coloración multicolor con un cuerpo mayoritariamente rojo, marrón y beige. Diferencias entre machos y hembras El macho adulto presenta un mayor tamaño que la hembra. Modo de vida y comportamiento dieta carnívoro Sociabilidad solitario territorial No Modo de vida Diurno El gobio de roca es un pez que vive en solitario. Es un animal carnívoro de temperamento tranquilo. Aunque se supone que el gobio de roca es una especie no territorial, puede mostrar signos de agresividad frente a otras especies . Reproducción Modo de reproducción ovíparo que desova en sustrato oculto El gobio de roca es un pez ovíparo que desova en sustrato oculto. Este pez protege sus huevos de los depredadores circundantes. Especies inofensivas Esta especie no supone ningún peligro en particular para el ser humano cuando se encuentra en su entorno natural. Origen y distribución Origen Mar Mediterráneo Océano Atlántico templado oriental Islas Córcega Islas Canarias Cerdeña Sicilia Estado de conservación de las poblaciones (UICN) Mundo : LC ¿Dónde observar esta especie? ¿Cuál es su hábitat? Características del entorno natural Temperatura 8 - 24 °C Profundidad 0 - 15 m Corriente Moderada, Lenta y Estancada Presentación del biotopo Frecuentemente encontramos a el gobio de roca a una profundidad de entre 0m y 15m. Sin embargo, no resulta del todo imposible observar a esta especie a otras profundidades. Especie del mismo biotopo Chelon saliens Mugilidae Salaria pavo Blenniidae Previous Next Para saber más Especie de la misma familia saltarín del fango rayado Gobiidae Sicyopus zosterophorus Gobiidae Stiphodon surrufus Gobiidae Rhinogobius formosanus Gobiidae Neogobius melanostomus Gobiidae Mugilogobius tigrinus Gobiidae Gobiodon histrio Gobiidae Sicyopus auxilimentus Gobiidae Previous Next Para leer en la web Fuentes y realización Participación y validación El equipo de Fishipedia y sus colaboradores especializados se comprometen a proporcionar contenido de alta calidad. Sin embargo, aunque la información proviene de fuentes científicas o testimonios de especialistas, los archivos pueden contener imprecisiones. Benoit Chartrer Traducción Traducción realizada con la valiosa contribución de nuestros traductores, quienes hacen que esta información esté disponible para un público más amplio. Silvia Gomez Interactúa con Fishipedia Para ponerse en contacto con nuestro equipo o participar en nuestro proyecto. Contribuya a esta página Plantilla y contenido © Fishipedia - Reproducción no autorizada sin solicitud previa - ISSN 2270-7247 - Última actualización el 08/11/2023 © Fishipedia.fr 2024",
    "genderDescription": "Gobiidae",
    "type": "",
    "size": "7 cm",
    "maxSize": "13 cm",
    "mimetism": "plantas",
    "recognize": "",
    "fe/maleDifferences": "El macho adulto presenta un mayor tamaño que la hembra.",
    "diet": "carnívoro",
    "territorial": "No",
    "social": "solitario",
    "lifeMode": "dieta",
    "lifeDescription": "",
    "reproductionMode": "<  gobio de roca  Gobius paganellus  Linné  1758  (Mundo) LC  Gobiidae  Gobius",
    "migration": "",
    "reproductionDescription": "",
    "poison": "",
    "danger": "de realización. Los textos propuestos actualmente provienen de nuestro modelo de datos o están en proceso de redacción. Para solicitar prioridad para este contenido, puedes escribirnos AQUÍ.",
    "depth": "0 - 15 m",
    "image": "",
    "mapImage": ""
  },
  {
    "name": "Gymnothorax unicolor",
    "sciname": "",
    "IUCN": "",
    "description": "Introducción El murión, Gymnothorax unicolor, o morena chocolate, es una especie marina originaria del océano Atlántico Este. Esta pequeña morena se encuentra presente en el mar Mediterráneo. ¿Quién es él?  Gymnothorax Las Gymnothorax son comúnmente conocidas como morenas. Con 127 especies descritas en 2021, es el género más diversificado dentro de la familia Muraenidae. Se describen especialmente las representantes más grandes de la familia, que pueden alcanzar los tres metros de longitud. La biología y morfología de muchas morenas aún están poco documentadas debido al gran número de especies y sus hábitos secretos. Parte de las especies fueron anteriormente clasificadas en los géneros Lycodontis y Muraena. Las morenas de este género están presentes en todos los mares tropicales y subtropicales del mundo, donde generalmente residen en áreas de arrecifes y fondos rocosos. Algunas especies se adaptan a las aguas salobres (manglares...) e incluso pueden remontar algunos ríos. Aunque generalmente se encuentran ocultas en las grietas, algunas Gymnothorax habitan en los fondos fangosos en algunas regiones particulares. Al igual que el resto de morenas, estos peces se caracterizan por poseer un cuerpo fuertemente comprimido y alargado. Algunas especies presentan patrones de color brillantes, aunque la mayoría son más bien de colores apagados. La mayoría de las Gymnothorax tienen un cuerpo cubierto de puntos oscuros en la zona de los costados. En comparación con la mayoría de las especies de peces, la boca es grande. La mandíbula está equipada con numerosos dientes y colmillos afilados. Algunas especies, quizás incluso podría decirse que todas, poseen una doble dentición. Además de estas características, las Gymnothorax se caracterizan por la falta de escamas, aletas pectorales y aletas pélvicas. También tienen la particularidad de tener las aletas dorsal, caudal y anal fusionadas. Todas las especies son nocturnas y carnívoras. Durante el día, generalmente se esconden en las rocas, dejando asomar tan solo la cabeza. Son territoriales y no comparten su área de vida con otros congéneres. Sorprendidas, pueden llegar a morder a cualquier intruso que las moleste. En sesiones de buceo o incluso durante el baño, es importante ser cauteloso y nunca introducir la mano profundamente en los agujeros de las rocas. Los ejemplares grandes pueden causar lesiones profundas e incluso cortar un dedo, por ejemplo. Aparte de estos casos particulares, que corresponden a una postura defensiva, las morenas son perfectamente inofensivas y tienden a huir en presencia de los humanos. Algunos individuos pueden mostrarse curiosos y aventurarse en algunos contactos pacíficos con buceadores. Al igual que con los pulpos, se producen interacciones amistosas entre buceadores y morenas cuando estas últimas están acostumbradas a los humanos. Aunque poco estudiadas, las poblaciones de morenas parecen ser abundantes en la mayoría de las regiones. Rara vez son consumidas por los humanos, ya que los especímenes más grandes son propensos a la ciguatera, una toxina que causa intoxicación alimentaria y puede ser mortal.  Tipo morena Tamaño medio 80 cm Tamaño máximo 100 cm Longevidad 20 años Gymnothorax unicolor, murión © Xavi Salvador Costa Tipo morena Tamaño medio 80 cm Tamaño máximo 100 cm Longevidad 20 años ¿Cómo reconocer a Este pez ? Esta morena mide entre 80 y 100 cm. Anguiliforme, su cuerpo presenta una coloración mayoritariamente marrón o ocre. Posee una cabeza grande y robusta, en la que aparecen dos narinas tubulares. La mandíbula se extiende hacia la parte trasera del ojo y su boca está equipada con dientes finos y afilados. Las aletas pélvicas y pectorales son inexistentes en esta especie. Las aletas dorsal, anal y caudal forman una aleta continua bordeada por un ribete de color claro. Diferencias entre machos y hembras No existe dimorfismo aparente en esta especie. Modo de vida y comportamiento dieta carnívoro Sociabilidad solitario territorial Sí Modo de vida Diurno Esta especie de morena caza al acecho y forma parte de los depredadores de su biotopo. Oportunista, no duda en atacar a cualquier animal de tamaño más pequeño que esté a su alcance. Es una especie solitaria que reside naturalmente en las rocas y grietas. Territorial, esta morena no aprecia la presencia de intrusos cercanos, especialmente los animales con comportamientos similares. No obstante, suele coexistir de manera pacífica con otras especies no territoriales que no representan presas potenciales. Reproducción Modo de reproducción ovíparo Se trata de una especie ovípara. Riesgos para los humanos Venenoso No Mordedor Sí En raras ocasiones, esta especie puede llegar a morder si se siente amenazada. Es importante permanecer especialmente atento, durante las inmersiones o sesiones de pesca. Origen y distribución Origen Mar Mediterráneo Océano Atlántico templado oriental Islas Islas Canarias Presencia geográfica y estado de la población Las poblaciones salvajes no parecen estar amenazadas, por el momento. Estado de conservación de las poblaciones (UICN) Mundo : LC ¿Cuál es su hábitat? Características del entorno natural Temperatura 17 - 22 °C Profundidad 4 - 20 m Presentación del biotopo Esta especie suele encontrarse de forma más habitual a una profundidad de entre 4 y 20 metros. Sin embargo, no es imposible observarla a otras profundidades. Este pez prefiere las grietas y las zonas rocosas para esconderse. Especie del mismo biotopo gallinita Tetraodontidae gobio de roca Gobiidae Previous Next Para saber más Especie de la misma familia Gymnomuraena zebra Muraenidae Echidna nebulosa Muraenidae morena picopato Muraenidae anguila listón azul Muraenidae morena común Muraenidae Previous Next Para leer en la web Fuentes y realización Participación y validación El equipo de Fishipedia y sus colaboradores especializados se comprometen a proporcionar contenido de alta calidad. Sin embargo, aunque la información proviene de fuentes científicas o testimonios de especialistas, los archivos pueden contener imprecisiones. Adrien Falzon Traducción Traducción realizada con la valiosa contribución de nuestros traductores, quienes hacen que esta información esté disponible para un público más amplio. Silvia Gomez Interactúa con Fishipedia Para ponerse en contacto con nuestro equipo o participar en nuestro proyecto. Contribuya a esta página Plantilla y contenido © Fishipedia - Reproducción no autorizada sin solicitud previa - ISSN 2270-7247 - Última actualización el 13/11/2023 © Fishipedia.fr 2024",
    "genderDescription": "Muraenidae",
    "type": "",
    "size": "80 cm",
    "maxSize": "100 cm",
    "mimetism": "",
    "recognize": "",
    "fe/maleDifferences": "No existe dimorfismo aparente en esta especie.",
    "diet": "carnívoro",
    "territorial": "Tipo morena Tamaño medio 80 cm Tamaño máximo 100 cm Longevidad 20 años Gymnothorax unicolor, murión © Xavi Salvador Costa Tipo morena Tamaño medio 80 cm Tamaño máximo 100 cm Longevidad 20 años",
    "social": "solitario",
    "lifeMode": "dieta",
    "lifeDescription": "",
    "reproductionMode": "<  murión  Gymnothorax unicolor  Delaroche  1809  (Mundo) LC  Muraenidae  Gymnothorax",
    "migration": "",
    "reproductionDescription": "",
    "poison": "No",
    "danger": "",
    "depth": "Enciclopedia Explorar Acuariofilia A propósito Prensa Peces Ballestas Barracudas Doradas y sargos Escorpenas Hipocampos Lábridos Morenas Peces cirujano Peces globo Peces payaso Rayas Tiburones Reptiles Cocodrilos Serpientes Tortugas Moluscos Caracoles Nudibranquios Calamares Pulpos Sepias Otros temas Anfibios Cnidarios Crustáceos Amazonas Anaconda gigante Anguila eléctrica Paiche Piraña roja Raya motoro / Raya de rio Tararira Mediterráneo Atún rojo Congrio Dorada real Manta raya Mero Sargo Islas Canarias Ángel de mar Caballito de mar Pez roca de Madeira Pez trompeta atlántico Tiburón Mako Vieja colorada Mar del Caribe Cirujano azul Gran barracuda / Picúa Pez ángel francés pez ángel reina Raya jaspeada Robalo blanco Mar Rojo Mero del Coral Morena gigante Pez león Pez Napoléon Raya de arrecife Vieja florida Especies comunes Betta Splendens Chupa algas Corydoras Discos Escalar Gamba Red Cherry Guppy Pez dorado Pez payaso Grupos temáticos Cíclidos enanos Killis Lochas Luchadores Peces gato Tetras Vivíparos Práctica Peces compatibles 20 L Peces compatibles 40 L Peces compatibles 60 L Peces compatibles 80 L Peces compatibles 100 L El proyecto Fishipedia Nuestra ética Proyecto Yaku Nawi Los fotógrafos colaboradores CONTÁCTANOS Enciclopedia Peces Ballestas Barracudas Doradas y sargos Escorpenas Hipocampos Lábridos Morenas Peces cirujano Peces globo Peces payaso Rayas Tiburones Reptiles Cocodrilos Serpientes Tortugas Moluscos Caracoles Nudibranquios Calamares Pulpos Sepias Otros temas Anfibios Cnidarios Crustáceos Explorar Amazonas Anaconda gigante Anguila eléctrica Paiche Piraña roja Raya motoro / Raya de rio Tararira Mediterráneo Atún rojo Congrio Dorada real Manta raya Mero Sargo Islas Canarias Ángel de mar Caballito de mar Pez roca de Madeira Pez trompeta atlántico Tiburón Mako Vieja colorada Mar del Caribe Cirujano azul Gran barracuda / Picúa Pez ángel francés pez ángel reina Raya jaspeada Robalo blanco Mar Rojo Mero del Coral Morena gigante Pez león Pez Napoléon Raya de arrecife Vieja florida Acuariofilia Especies comunes Betta Splendens Chupa algas Corydoras Discos Escalar Gamba Red Cherry Guppy Pez dorado Pez payaso Grupos temáticos Cíclidos enanos Killis Lochas Luchadores Peces gato Tetras Vivíparos Práctica Peces compatibles 20 L Peces compatibles 40 L Peces compatibles 60 L Peces compatibles 80 L Peces compatibles 100 L A propósito El proyecto Fishipedia Nuestra ética Proyecto Yaku Nawi Los fotógrafos colaboradores CONTÁCTANOS Prensa",
    "image": "",
    "mapImage": ""
  },
  {
    "name": "Gymnura altavela",
    "sciname": "",
    "IUCN": "",
    "description": "Introducción Gymnura altavela, es comúnmente conocida como \"raya mariposa\" o \"raya alada\", en Canarias se le denomina también con el sobrenombre de \"raya mantelina\". Se trata de un elasmobranquio bentónico que se encuentra en aguas subtropicales marinas y salobres a lo largo de las costas del Atlántico oriental y occidental, en el mar Mediterráneo y en el mar Negro. La raya mariposa posee una pequeña espina venenosa al final de su cola delgada y corta. Esta especie se encuentra actualmente categorizada como \"en peligro de extinción\", víctima de la captura accidental asociada a la pesca de arrastre. ¿Quién es ella?  Gymnura El género Gymnura pertenece a la familia Gymnuridae y engloba un total de 16 especies que se encuentran repartidas en las aguas de todo el mundo, ocasionalmente en estuarios. La mayoría de estas especies se encuentran, a día de hoy, en peligro de extinción. Algunas de ellas son consideradas como un verdadero manjar en ciertos países, y son también, víctimas de la captura accidental asociada a la pesca de arrastre. Son especies marinas presentes en aguas tropicales y templadas cálidas que migran a aguas templadas durante las estaciones cálidas. Los ejemplares del género Gymnura son carnívoros y se alimentan de peces y todo tipo de pequeños organismos. Se encuentran en zonas costeras, cerca del fondo en áreas arenosas y fangosas, a menudo expuestas. El cuerpo es plano, las aletas pectorales forman una especie de disco muy ancho alrededor del cuerpo y hasta el extremo anterior de la cabeza. La cola es muy corta y delgada. Algunas especies poseen una espina venenosa en la cola, pero son mucho menos peligrosas que las rayas del género Dasyatis. Son peces vivíparos, en los que la fecundación es interna y la reproducción es estacional.  Tipo raya Tamaño medio 200 cm Tamaño máximo 400 cm Longevidad 18 años Mimetismo fondo arenoso Patrón manchas Gymnura altavela, raya mariposa Tipo raya Tamaño medio 200 cm Tamaño máximo 400 cm Longevidad 18 años Mimetismo fondo arenoso Patrón manchas ¿Cómo reconocer a Este pez ? El cuerpo de esta especie es muy ancho en forma de disco sub-rómbico, siendo más ancho que largo. Su parte posterior es generalmente de color marrón oscuro y se caracteriza por la presencia de pequeñas manchas oculares de un color gris claro. La superficie inferior del disco y las aletas pélvicas son blancas con tintes marrones, lo que le da una apariencia \"oxidada\". El hocico es corto y redondeado, poseeyendo unos ojos ovalados. La boca, branquias y nariz (fosas nasales) son ventrales. Los ojos y los espiráculos son dorsales. La cola es corta, de color blanco o rosado y está provista de un aguijón. Diferencias entre machos y hembras No existen diferencias morfológicas aparentes entre machos y hembras. Modo de vida y comportamiento dieta carnívoro Sociabilidad solitario territorial No Modo de vida Diurno Gymnura altavela es un depredador carnívoro que se alimenta de peces, crustáceos, moluscos y plancton. Caza principalmente en áreas abiertas de arena y barro cercanas a la costa. La raya mariposa generalmente no es agresiva, sin embargo, podría llegar a utilizar su aguijón para defenderse si fuese necesario. Por ello recomendamos tener especial cuidado en su presencia, evitando pisarla. Reproducción Se trata de un pez vivíparo, siendo su reproducción aplacentaria. Especies inofensivas Esta especie no presenta mayor peligro para los humanos, sin embargo, la picadura de Gymnura Altavela podría llegar a causar fuertes dolores. Origen y distribución Origen Mar Mediterráneo Mar Negro Océano Atlántico templado oriental Océano Atlántico noroeste templado frío Océano Atlántico templado cálido del noroeste Sudoeste del Océano Atlántico templado cálido Islas Islas Canarias Cerdeña Sicilia Presencia geográfica y estado de la población Esta especie se encuentra a lo largo de las costas del Atlántico este y oeste, en el mar Mediterráneo y en el mar Negro. Estado de conservación de las poblaciones (UICN) Mundo : EN ¿Cuál es su hábitat? Características del entorno natural Temperatura 15 - 28 °C Profundidad 5 - 100 m  Bentónico libre Presentación del biotopo Gymnura altavela puede ser observada con mayor frecuencia a una profundidad de menos de 100 metros. Este pez bentónico frecuenta los fondos abiertos de arena y barro, así como los estuarios y las lagunas. Especie del mismo biotopo boga Sparidae pez de san Pedro Zeidae pez ángel Squatinidae ballesta común Balistidae tiburón blanco Lamnidae pez golondrina Dactylopteridae Previous Next Para saber más Para leer en la web Fuentes y realización Participación y validación El equipo de Fishipedia y sus colaboradores especializados se comprometen a proporcionar contenido de alta calidad. Sin embargo, aunque la información proviene de fuentes científicas o testimonios de especialistas, los archivos pueden contener imprecisiones. Aurélien Calas Traducción Traducción realizada con la valiosa contribución de nuestros traductores, quienes hacen que esta información esté disponible para un público más amplio. Silvia Gomez Referencias bibliográficas Nouvelle description de Gymnura altavela (Linnaeus, 1758) (Pisces, Rajiformes, Gymnuridae). - Christian CAPAPE - Bulletin de l'Institut National Scientifique et Technique d'Océanographie et de Pêche de Salammbo - 1981. Age and growth assessment of western North Atlantic spiny butterfly ray Gymnura altavela (L. 1758) using computed tomography of vertebral centra - K.T. Parsons - Environmental Biology of Fishes - 2017. Captive husbandry and bioenergetics of the spiny butterfly ray,Gymnura altavela (Linnaeus) - Alan Henningsen - Bulletin de l'Institut National Scientifique et Technique d'Océanographie et de Pêche de Salammbo - 1996. Interactúa con Fishipedia Para ponerse en contacto con nuestro equipo o participar en nuestro proyecto. Contribuya a esta página Plantilla y contenido © Fishipedia - Reproducción no autorizada sin solicitud previa - ISSN 2270-7247 - Última actualización el 12/11/2023 © Fishipedia.fr 2024",
    "genderDescription": "Gymnuridae",
    "type": "",
    "size": "200 cm",
    "maxSize": "400 cm",
    "mimetism": "fondo arenoso",
    "recognize": "",
    "fe/maleDifferences": "No existen diferencias morfológicas aparentes entre machos y hembras.",
    "diet": "carnívoro",
    "territorial": "No",
    "social": "solitario",
    "lifeMode": "dieta",
    "lifeDescription": "",
    "reproductionMode": "<  raya mariposa  Gymnura altavela  Linnaeus  1758  (Mundo) EN  Gymnuridae  Gymnura",
    "migration": "",
    "reproductionDescription": "",
    "poison": "",
    "danger": "",
    "depth": "Enciclopedia Explorar Acuariofilia A propósito Prensa Peces Ballestas Barracudas Doradas y sargos Escorpenas Hipocampos Lábridos Morenas Peces cirujano Peces globo Peces payaso Rayas Tiburones Reptiles Cocodrilos Serpientes Tortugas Moluscos Caracoles Nudibranquios Calamares Pulpos Sepias Otros temas Anfibios Cnidarios Crustáceos Amazonas Anaconda gigante Anguila eléctrica Paiche Piraña roja Raya motoro / Raya de rio Tararira Mediterráneo Atún rojo Congrio Dorada real Manta raya Mero Sargo Islas Canarias Ángel de mar Caballito de mar Pez roca de Madeira Pez trompeta atlántico Tiburón Mako Vieja colorada Mar del Caribe Cirujano azul Gran barracuda / Picúa Pez ángel francés pez ángel reina Raya jaspeada Robalo blanco Mar Rojo Mero del Coral Morena gigante Pez león Pez Napoléon Raya de arrecife Vieja florida Especies comunes Betta Splendens Chupa algas Corydoras Discos Escalar Gamba Red Cherry Guppy Pez dorado Pez payaso Grupos temáticos Cíclidos enanos Killis Lochas Luchadores Peces gato Tetras Vivíparos Práctica Peces compatibles 20 L Peces compatibles 40 L Peces compatibles 60 L Peces compatibles 80 L Peces compatibles 100 L El proyecto Fishipedia Nuestra ética Proyecto Yaku Nawi Los fotógrafos colaboradores CONTÁCTANOS Enciclopedia Peces Ballestas Barracudas Doradas y sargos Escorpenas Hipocampos Lábridos Morenas Peces cirujano Peces globo Peces payaso Rayas Tiburones Reptiles Cocodrilos Serpientes Tortugas Moluscos Caracoles Nudibranquios Calamares Pulpos Sepias Otros temas Anfibios Cnidarios Crustáceos Explorar Amazonas Anaconda gigante Anguila eléctrica Paiche Piraña roja Raya motoro / Raya de rio Tararira Mediterráneo Atún rojo Congrio Dorada real Manta raya Mero Sargo Islas Canarias Ángel de mar Caballito de mar Pez roca de Madeira Pez trompeta atlántico Tiburón Mako Vieja colorada Mar del Caribe Cirujano azul Gran barracuda / Picúa Pez ángel francés pez ángel reina Raya jaspeada Robalo blanco Mar Rojo Mero del Coral Morena gigante Pez león Pez Napoléon Raya de arrecife Vieja florida Acuariofilia Especies comunes Betta Splendens Chupa algas Corydoras Discos Escalar Gamba Red Cherry Guppy Pez dorado Pez payaso Grupos temáticos Cíclidos enanos Killis Lochas Luchadores Peces gato Tetras Vivíparos Práctica Peces compatibles 20 L Peces compatibles 40 L Peces compatibles 60 L Peces compatibles 80 L Peces compatibles 100 L A propósito El proyecto Fishipedia Nuestra ética Proyecto Yaku Nawi Los fotógrafos colaboradores CONTÁCTANOS Prensa",
    "image": "",
    "mapImage": ""
  },
  {
    "name": "Hippocampus guttulatus",
    "sciname": "",
    "IUCN": "",
    "description": "Introducción Hippocampus guttulatus es un pez de pequeño tamaño que se encuentra presente en las aguas costeras poco profundas del océano Atlántico y del mar Mediterráneo. Hace tiempo, el Mar Menor en España era un lugar privilegiado para su observación, pero a día de hoy, sus poblaciones han desaparecido en casi toda la laguna y apenas se observan ejemplares. Es posible encontrarlo en las zonas de pastos marinos, rocas e incluso en los fondos recubiertos de grava. Según el IUCN no existen actualmente datos para valorar el estado de sus poblaciones. Esta especie está inscrita en el anexo II de CITES. Al igual que ocurre con otras especies de hipocampos, también conocidos como caballitos de mar, se encuentran amenazados debido a la degradación de su hábitat, causado principalmente por el desarrollo en las zonas de costa, así como por la pesca intensiva. Estos animales son capturados a menudo para venderlos en el mercado acuariófilo, y en algunas zonas de Asia son utilizados también en la medicina tradicional. Durante mucho tiempo fueron secados y utilizados como amuletos o souvenirs, aunque esta práctica está en disminución hoy en día. ¿Quién es él?  Hippocampus En 2019, el género Hippocampus agrupaba a más de 57 especies censadas. Estos peces son conocidos como \"caballitos de mar\" en referencia a la forma de su cabeza, que recuerda a la cabeza de un caballo. Se desplazan en posición vertical, propulsándose con su aleta dorsal y sus aletas pectorales. La aleta anal es rudimentaria y se encuentra prácticamente ausente. La cola de estos peces ha evolucionado poco a poco, hasta convertirse en un órgano prensil con el cual estos animales se adhieren a la vegetación. La reproducción de los hipocampos es atípica, siendo la hembra quien introduce los huevos en la bolsa ventral del macho. Su alimentación está constituida por microorganismos marinos (crustáceos enanos, larvas, zooplancton, huevos de otros peces...). Para tragarlos, utilizan su boca, situada en el extremo de su hocico, a veces denominado tubo. Cada aspiración produce un ruido seco. La presa es tragada entera ya que estos peces no poseen dientes.  Tipo Hipocampo Tamaño medio 18 cm Tamaño máximo 21 cm Hippocampus guttulatus, caballito de mar mediterráneo © Xaime Beiro Hippocampus guttulatus, caballito de mar mediterráneo © Théo Guillaume Previous Next Tipo Hipocampo Tamaño medio 18 cm Tamaño máximo 21 cm ¿Cómo reconocer a Este pez ? Esta especie de hipocampo mide entre 8 y 18 cm, aunque han sido observados algunos ejemplares que alcanzaban los 21,5 cm. El cuerpo mide más de un tercio de la longitud de su cabeza y está recubierto de espinas con las puntas desafiladas. Esta especie es fácilmente reconocible debido a la forma alargada de su hocico. No presenta espina caudal, ya que esta ha sido modificada en forma de una cola prensil que el animal utiliza para adherirse a plantas y esponjas. Su coloración varía del verde oscuro al marrón, siendo en ocasiones de color amarillento aunque esto es poco habitual. Esta coloración le permite camuflarse con el entorno. El cuerpo presenta unas prominentes manchas blancas que tienen a fundirse formando líneas horizontales. Algunos individuos pueden presentar unas pálidas marcas en forma de sillas de montar. Diferencias entre machos y hembras Los machos presentan un vientre más voluminoso con una forma redondeada, mientras que en las hembras el vientre termina formando un ángulo de 90º. Modo de vida y comportamiento dieta carnívoro Sociabilidad pareja o en solitario territorial No Modo de vida Diurno Este hipocampo no es una especie migratoria pero al igual que ocurre con otras especies de estos animales, la dispersión de ejemplares adultos en grandes distancias puede deberse posiblemente a la acción de las olas y las fuertes corrientes durante tempestades, o debido a que estos animales se adhieren a veces a deshechos flotantes. En invierno, se acerca a las zonas más profundas. Debido a sus minúsculas aletas, se trata de un pez muy lento, que utiliza su coloración para camuflarse con el medio, sorprendiendo así a sus presas y protegiéndose de los depredadores. Estos animales son pequeños pero voraces. Esta especie se nutre principalmente de pequeños crustáceos, larvas, huevos de peces y otros organismos planctónicos. Se estima que pueden llegar a vivir entre 4 y 7 años. Reproducción Modo de reproducción ovovivíparo Esta especie es monógama y ovovivípara. Durante la época de apareamiento, machos y hembras cambian de color volviéndose más brillantes, en particular durante el cortejo y el apareamiento. Como ocurre en otras especies de caballitos de mar, es la hembra la que deposita los huevos en la bolsa del macho. El período de gestación dura 21 días. Las crías miden 1,5 cm después de 3 semanas de incubación. Se estima que los recién nacidos tienen un estado planctónico que dura al menos 8 semanas. Especies inofensivas Esta especie no representa un peligro particular para los seres humanos en caso de encuentro en su entorno natural. Origen y distribución Origen Mar Mediterráneo Océano Atlántico templado oriental Islas Islas Canarias Cerdeña Sicilia Presencia geográfica y estado de la población Presente en las aguas templadas del océano Atlántico oriental, desde las costas del sur de Reino Unido a los Países Bajos, hasta Marruecos, incluyendo las islas Canarias, las Azores y Madeira, así como el mar Mediterráneo. Recientes estudios han confirmado que algunos ejemplares de esta especie se encuentran presentes en el mar Negro. Estado de conservación de las poblaciones (UICN) Mundo : DD ¿Cuál es su hábitat? Características del entorno natural Temperatura 18 - 24 °C Profundidad 1 - 20 m Corriente Lenta y Estancada Presentación del biotopo Estos peces habitan las aguas costeras poco profundas (entre 1 y 20 metros), siendo posible encontrarlos en las lagunas litorales camuflados entre las algas, las rocas y los fondos de grava. A veces, es posible observarlos también en zonas de agua salobre, en lagos y marismas junto al mar. Especie del mismo biotopo doncella común Labridae caballito de mar común Syngnathidae pez de san Pedro Zeidae dorada Sparidae pez trompeta del atlántico oriental Aulostomidae Previous Next Mantenimiento en cautividad No recomendado Este caballito de mar puede ser mantenido en acuarios, pero las condiciones para lograrlo son particularmente complicadas. Su cuidado solo debe considerarse con una gran experiencia en acuarofilia. Para saber más Especie de la misma familia aguja mula Syngnathidae Dunckerocampus dactyliophorus Syngnathidae aguja de mar Syngnathidae Syngnathus tenuirostris Syngnathidae Dunckerocampus chapmani Syngnathidae Doryrhamphus excisus Syngnathidae Entelurus aequoreus Syngnathidae Microphis retzii Syngnathidae Previous Next Para leer en la web Fuentes y realización Participación y validación El equipo de Fishipedia y sus colaboradores especializados se comprometen a proporcionar contenido de alta calidad. Sin embargo, aunque la información proviene de fuentes científicas o testimonios de especialistas, los archivos pueden contener imprecisiones. Silvia Gomez Benoit Chartrer Traducción Traducción realizada con la valiosa contribución de nuestros traductores, quienes hacen que esta información esté disponible para un público más amplio. Silvia Gomez Interactúa con Fishipedia Para ponerse en contacto con nuestro equipo o participar en nuestro proyecto. Contribuya a esta página Plantilla y contenido © Fishipedia - Reproducción no autorizada sin solicitud previa - ISSN 2270-7247 - Última actualización el 29/11/2023 © Fishipedia.fr 2024",
    "genderDescription": "Syngnathidae",
    "type": "",
    "size": "18 cm",
    "maxSize": "21 cm",
    "mimetism": "",
    "recognize": "",
    "fe/maleDifferences": "Los machos presentan un vientre más voluminoso con una forma redondeada, mientras que en las hembras el vientre termina formando un ángulo de 90º.",
    "diet": "carnívoro",
    "territorial": "No",
    "social": "pareja o en solitario",
    "lifeMode": "dieta",
    "lifeDescription": "",
    "reproductionMode": "<  caballito de mar mediterráneo  Hippocampus guttulatus  Cuvier  1829  (Mundo) DD  Syngnathidae  Hippocampus",
    "migration": "",
    "reproductionDescription": "",
    "poison": "",
    "danger": "",
    "depth": "1 - 20 m",
    "image": "",
    "mapImage": ""
  },
  {
    "name": "Hippocampus hippocampus",
    "sciname": "",
    "IUCN": "",
    "description": "Introducción Hippocampus hippocampus es un hipocampo, también denominado caballito de mar, común de la zona este del océano Atlántico y del mar Mediterráneo. Presente desde las islas británicas hasta el golfo de Guinea. Su presencia se extiende hasta las islas Canarias, Azores y en todo el mar Mediterráneo. Actualmente, está inscrito en el anexo II de CITES. Aunque las poblaciones están dotadas de una resiliencia bastante fuerte, es un animal particularmente sensible a las presiones ejercidas por la actividad humana. En algunas zonas tropicales, las poblaciones de algunos de sus parientes cercanos han prácticamente desaparecido. No hace mucho tiempo que los ejemplares de esta especie eran capturados para ser secados y vendidos como souvenir, e incluso para utilizarlos en la medicina tradicional en algunos países asiáticos, por fortuna estas prácticas han disminuido aunque aún es común capturarlos para venderlos en el mercado acuariófilo. Actualmente no es fácil encontrarlo en el mar Mediterráneo, excepto en algunas lagunas o lagos salobres. ¿Quién es él?  Hippocampus En 2019, el género Hippocampus agrupaba a más de 57 especies censadas. Estos peces son conocidos como \"caballitos de mar\" en referencia a la forma de su cabeza, que recuerda a la cabeza de un caballo. Se desplazan en posición vertical, propulsándose con su aleta dorsal y sus aletas pectorales. La aleta anal es rudimentaria y se encuentra prácticamente ausente. La cola de estos peces ha evolucionado poco a poco, hasta convertirse en un órgano prensil con el cual estos animales se adhieren a la vegetación. La reproducción de los hipocampos es atípica, siendo la hembra quien introduce los huevos en la bolsa ventral del macho. Su alimentación está constituida por microorganismos marinos (crustáceos enanos, larvas, zooplancton, huevos de otros peces...). Para tragarlos, utilizan su boca, situada en el extremo de su hocico, a veces denominado tubo. Cada aspiración produce un ruido seco. La presa es tragada entera ya que estos peces no poseen dientes.  Tipo Hipocampo Tamaño medio 7 cm Tamaño máximo 13 cm Hippocampus hippocampus, caballito de mar común © Benoit Chartrer Hippocampus hippocampus, caballito de mar común © Xavi Salvador Costa Hippocampus hippocampus, caballito de mar común Previous Next Tipo Hipocampo Tamaño medio 7 cm Tamaño máximo 13 cm ¿Cómo reconocer a Este pez ? Este caballito de mar no posee espina dorsal. De adulto suele llegar a medir entre 7 y 13 cm, aunque según algunas fuentes puede llegar a alcanzar hasta 15 cm. Su hocico es pequeño y se encuentra ligeramente curvado hacia arriba, este no supera en ningún caso el tercio de la longitud total de la cabeza. Esto resulta clave para poder diferenciarlo de otros hipocampos. La coloración varía en función del entorno. Pudiendo ser de un marrón uniforme, hasta amarillo, naranja, violeta, negro o incluso verde. Algunos de los ejemplares que viven adheridos a las esponjas pueden presentar una mezcla de colores que van desde el marrón al rojizo. A veces resaltan sobre su cuerpo unos diminutos puntos blancos pero al contrario de lo que ocurre con el H. guttulatus, estos no se fusionan formando líneas horizontales. Diferencias entre machos y hembras Las hembras poseen un cuerpo más fino. Modo de vida y comportamiento dieta planctófago Sociabilidad pareja o en solitario territorial No Modo de vida Diurno Este caballito de mar habita en zonas de densa vegetación. Siendo posible encontrarlo en las praderas de posidonia y en las zonas de algas. A veces, también es posible observarlo adherido a esponjas. No es un gran nadador por lo que suele ser habitual encontrarlo en zonas tranquilas y resguardadas. Imita a la perfección la coloración verde o amarillenta de la vegetación típica del Atlántico Este y del mar Mediterráneo. Esta característica le permite pasar desapercibido para sus depredadores y sorprender a ciertos microorganismos marinos de los que se alimenta, aspirándolos con su trompa. Es un pez generalmente solitario que limita sus movimientos. Evitando, en lo posible, abandonar las zonas de vegetación. En invierno, se traslada a zonas más profundas para volver a emerger en verano. Es común encontrar ejemplares dispersos a grandes distancias, debido principalmente a que durante las tormentas, los adultos se aferran a escombros y se ven transportados a largas distancias. Esta especie suele vivir entre 3 y 5 años. Reproducción Modo de reproducción ovovivíparo Se trata de una especie monógama y ovovivípara. La hembra introduce sus huevos en la bolsa del macho. Durante la época de apareamiento, machos y hembras cambian su coloración y se vuelven más brillantes, en particular durante el cortejo y el acoplamiento. Según algunos estudios, las crías recién nacidas tienen una etapa planctónica que dura al menos ocho semanas. Especies inofensivas Esta especie no supone ningún peligro en particular para el ser humano cuando se encuentra en su entorno natural. Origen y distribución Origen Mar Mediterráneo Océano Atlántico templado oriental Islas Islas Canarias Sicilia Estado de conservación de las poblaciones (UICN) Mundo : DD ¿Dónde observar esta especie? ¿Cuál es su hábitat? Características del entorno natural Temperatura 24 - 28 °C Profundidad 1 - 60 m Corriente Lenta y Estancada Presentación del biotopo Esta especie se encuentra en los pastos marinos y en las algas de las zonas rocosas, así como en las zonas ricas en vegetación de los estanques salobres. Especie del mismo biotopo pez de san Pedro Zeidae dorada Sparidae caballito de mar mediterráneo Syngnathidae pez trompeta del atlántico oriental Aulostomidae doncella común Labridae Previous Next Mantenimiento en cautividad No recomendado Este caballito de mar puede ser mantenido en acuarios, pero las condiciones para lograrlo son particularmente complicadas. Su cuidado solo debe considerarse con una gran experiencia en acuarofilia. Para saber más Especie de la misma familia pez pipa de rayas negras Syngnathidae aguja mula Syngnathidae Dunckerocampus chapmani Syngnathidae Entelurus aequoreus Syngnathidae Syngnathus rostellatus Syngnathidae Microphis retzii Syngnathidae aguja de mar Syngnathidae Dunckerocampus dactyliophorus Syngnathidae Previous Next Para leer en la web Fuentes y realización Participación y validación El equipo de Fishipedia y sus colaboradores especializados se comprometen a proporcionar contenido de alta calidad. Sin embargo, aunque la información proviene de fuentes científicas o testimonios de especialistas, los archivos pueden contener imprecisiones. Benoit Chartrer Traducción Traducción realizada con la valiosa contribución de nuestros traductores, quienes hacen que esta información esté disponible para un público más amplio. Silvia Gomez Interactúa con Fishipedia Para ponerse en contacto con nuestro equipo o participar en nuestro proyecto. Contribuya a esta página Plantilla y contenido © Fishipedia - Reproducción no autorizada sin solicitud previa - ISSN 2270-7247 - Última actualización el 12/11/2023 © Fishipedia.fr 2024",
    "genderDescription": "Syngnathidae",
    "type": "",
    "size": "7 cm",
    "maxSize": "13 cm",
    "mimetism": "",
    "recognize": "",
    "fe/maleDifferences": "Las hembras poseen un cuerpo más fino.",
    "diet": "planctófago",
    "territorial": "No",
    "social": "pareja o en solitario",
    "lifeMode": "dieta",
    "lifeDescription": "",
    "reproductionMode": "<  caballito de mar común  Hippocampus hippocampus  Linnaeus  1758  (Mundo) DD  Syngnathidae  Hippocampus",
    "migration": "",
    "reproductionDescription": "",
    "poison": "",
    "danger": "",
    "depth": "1 - 60 m",
    "image": "",
    "mapImage": ""
  },
  {
    "name": "Isurus oxyrinchus",
    "sciname": "",
    "IUCN": "",
    "description": "Introducción El tiburón mako, Isurus oxyrinchus, es un depredador pelágico con una distribución global que abarca los mares tropicales y templados, pudiendo ser observado en ciertas ocasiones cerca de las costas. Como sucedió en junio de 2023, cuando un ejemplar varó en una playa en Marseillan, en el sur de Francia. El tiburón mako es miembro de la familia Lamnidae, que incluye tres géneros: Carcharodon, Lamna e Isurus. Esta especie es muy cotizada en ciertas regiones debido a su carne, aletas y piel. Debido a su pesca intensiva, fue clasificada como especie en peligro de extinción en 2018. A día de hoy, se tiene constancia de que las poblaciones de esta especie están experimentando un declive preocupante en casi todos los océanos, a excepción del Pacífico Sur. Tradicionalmente, el tiburón mako de aletas cortas se consume de diversas maneras, incluyendo fresco, seco, salado, ahumado y congelado. Además, de esta especie se extrae un aceite rico en vitaminas. Sus aletas son, aún a día de hoy, objeto de deseo, ya que son un ingrediente básico de la famosa sopa de aleta de tiburón. Mientras las mandíbulas y los dientes suelen ser vendidos como ornamentos y trofeos. Esta especie de tiburón es considerada como peligrosa, aunque los ataques son poco frecuentes. Un estudio realizado por Kabasakal y de Maddalena en 2011 informó del registro histórico de un ejemplar de gran tamaño capturado en el mar Mediterráneo frente a Turquía, que medía alrededor de 585 cm. La mayoría de las observaciones señalan ejemplares adultos con una longitud inferior a 3 metros. ¿Quién es él?  Isurus El término Isurus viene del griego isos que significa cola. Este género engloba muy pocas especies, caracterizadas todas ellas por poseer una cola homocerca, al contrario de lo que sucede con la mayor parte del resto de géneros de tiburones, donde la cola es heterocerca.  Tipo tiburón Tamaño medio 270 cm Tamaño máximo 500 cm Longevidad 32 años Forma Rectangular Isurus oxyrinchus, tiburón mako © Fabrice Guérin Tipo tiburón Tamaño medio 270 cm Tamaño máximo 500 cm Longevidad 32 años Forma Rectangular ¿Cómo reconocer a Este pez ? El tiburón mako se distingue por su color uniforme, con un cuerpo principalmente en tonos grises o azulados, y un vientre de color más claro. Gracias a su forma hidrodinámica, esta especie llegar a alcanzar altas velocidades. Su hocico es puntiagudo, su cuerpo esbelto y su primera aleta dorsal presenta una forma redondeada. Las aletas pectorales son largas y triangulares. Los ojos del tiburón mako son grandes y negros, y las hendiduras branquiales son anchas. Sus dientes son delgados, con forma de ganchos curvados hacia el interior de su boca. Diferencias entre machos y hembras Los tiburones macho poseen un par de pterigopodios. Se trata de unos apéndices que aparecen gracias a la modificación de las aletas pélvicas y que permiten la transmisión del esperma hasta la cloaca de la hembra. Los machos pueden utilizar sólo uno de ellos a la vez. Modo de vida y comportamiento dieta carnívoro Sociabilidad solitario territorial No Modo de vida Diurno El tiburón mako es un depredador solitario con un temperamento vivo y nervioso, que ocupa un lugar destacado entre los grandes depredadores de la zona pelágica. Esta especie es capaz de mantener su temperatura corporal 10°C por encima del agua circundante. Gracias a su cuerpo hidrodinámico equipado con unas amplias hendiduras branquiales, puede llegar a realizar unas aceleraciones asombrosas. Alcanzando la impresionante velocidad de 110 km/h, el tiburón mako es uno de los peces más rápidos del mundo, junto con el pez vela. Utilizando esta velocidad para realizar ataques relámpago, generalmente desde abajo. Además, es capaz de realizar espectaculares saltos fuera del agua. Su velocidad promedio se estima en 50 km/h. Los adultos se alimentan principalmente de peces óseos, otros tiburones y cefalópodos. Los ejemplares de gran tamaño también pueden atacar presas de mayor tamaño como marlines y pequeños cetáceos. Esto convierten al tiburón mako en un depredador clave y le otorga un papel crucial en el equilibrio de los ecosistemas marinos en los que habita. Reproducción Modo de reproducción ovovivíparo El tiburón mako es un pez ovovivíparo, dándose en esta especie el conocido canibalismo intrauterino. Después de un período de gestación que va de 15 a 18 meses, la hembra dará a luz entre 4 y 25 crías, cada una de las cuales puede llegar a medir entre 60 y 70 cm. El período entre dos alumbramientos es de 3 años, lo que convierte a este tiburón en una especie particularmente vulnerable. Riesgos para los humanos Venenoso No Mordedor Sí Esta especie puede llegar a atacar si se siente amenazada. Se recomienda permanecer en alerta en su presencia, especialmente durante las inmersiones o las sesiones de pesca. Origen y distribución Origen Golfo de Bengala Golfo de México Golfo Pérsico mar Arábigo Mar de Tasmania Mar del Caribe Mar de Filipinas Mar Mediterráneo Mar Rojo Mares del Sudeste Asiático Mares indonesios Océano Atlántico: costa norte de Brasil Océano Atlántico templado oriental Océano Atlántico noroeste templado frío Océano Atlántico templado cálido del noroeste Sudoeste del Océano Atlántico templado cálido Océano Atlántico tropical oriental Océano Atlántico tropical Sudoeste Océano Índico occidental Galápagos Océano Pacífico tropical oriental Océano Pacífico tropical occidental Islas Islas Canarias La Reunión Polinesia Francesa Cerdeña Sicilia Presencia geográfica y estado de la población La situación de la población mundial del tiburón mako no se conoce con exactitud. Se han realizado estudios en diversas regiones del mundo para evaluar la situación de las distintas poblaciones. En el Atlántico norte, en su momento fue considerado como saludable, sin embargo en la actualidad, el stock se clasifica como sobreexplotado y se encuentra sujeto a la sobrepesca. Aunque las evaluaciones del stock en el Atlántico sur se consideran poco fiables, es probable que la mortalidad debido a la pesca no sea sostenible. En el océano Índico, el stock actualmente no se encuentra sobreexplotado, pero está sujeto a la sobrepesca, y se tienen indicios de trayectorias de biomasa que sugieren una tendencia a la sobreexplotación. Por otro lado, en el Pacífico norte, es probable que el stock no se encuentre sobreexplotado, y tampoco hay signos de sobrepesca. En el Pacífico sur, es el único lugar en el que la población parece estar aumentando. La situación más alarmante se da en el mar Mediterráneo, donde la población habría perdido el 99,9% de su abundancia desde el siglo XIX. El conocimiento sobre las poblaciones de tiburones y su explotación es impreciso. Sin embargo, diversos indicadores, como la disminución de las capturas y los rendimientos, permiten trazar un panorama bastante sombrío del estado de sus stocks, aunque las situaciones varían de una especie a otra. El \"finning\", que consiste en cortar las aletas de los tiburones y arrojar los animales amputados pero aún vivos al mar, sin posibilidad de sobrevivir, es la causa del colapso de varios stocks de tiburones, incluidas algunas especies de tiburones martillo (Sphyrna spp.), zorros (Alopias spp.) o tiburones azules (Isurus spp.)... Estado de conservación de las poblaciones (UICN) Mundo : EN ¿Cuál es su hábitat? Características del entorno natural Temperatura 24 - 28 °C Profundidad 1 - 500 m  Pelágico activo Presentación del biotopo Esta especie puede encontrarse en profundidades inferiores a 500 m. A menudo, puede ser observada nadando en aguas poco profundas o, incluso, en la superficie. Este tiburón es una especie semi-pelágica. Aunque en ciertas ocasiones puede ser avistado cerca de las costas, este tiburón pasa la mayor parte de su tiempo en mar abierto. Especie del mismo biotopo tiburón blanco Lamnidae mero moteado Serranidae Thunnus albacares Scombridae Platax teira Ephippidae raya toro Myliobatidae bacoreta Scombridae Previous Next Para saber más Especie de la misma familia tiburón blanco Lamnidae Para leer en la web Fuentes y realización Participación y validación El equipo de Fishipedia y sus colaboradores especializados se comprometen a proporcionar contenido de alta calidad. Sin embargo, aunque la información proviene de fuentes científicas o testimonios de especialistas, los archivos pueden contener imprecisiones. Adrien Falzon Benoit Chartrer Silvia Gomez Traducción Traducción realizada con la valiosa contribución de nuestros traductores, quienes hacen que esta información esté disponible para un público más amplio. Silvia Gomez Referencias bibliográficas Reproduction and Embryonic Development of the Shortfin Mako, Isurus oxyrinchus Rafinesque, 1810, in the Northwestern Pacific - Shoou-Jeng Joung - Hua-Hsun Hsu - Zoological Studies - 2005. Interactúa con Fishipedia Para ponerse en contacto con nuestro equipo o participar en nuestro proyecto. Contribuya a esta página Plantilla y contenido © Fishipedia - Reproducción no autorizada sin solicitud previa - ISSN 2270-7247 - Última actualización el 12/11/2023 © Fishipedia.fr 2024",
    "genderDescription": "Lamnidae",
    "type": "",
    "size": "270 cm",
    "maxSize": "500 cm",
    "mimetism": "",
    "recognize": "",
    "fe/maleDifferences": "Los tiburones macho poseen un par de pterigopodios. Se trata de unos apéndices que aparecen gracias a la modificación de las aletas pélvicas y que permiten la transmisión del esperma hasta la cloaca de la hembra. Los machos pueden utilizar sólo uno de ellos a la vez.",
    "diet": "carnívoro",
    "territorial": "No",
    "social": "solitario",
    "lifeMode": "dieta",
    "lifeDescription": "",
    "reproductionMode": "<  tiburón mako  Isurus oxyrinchus  Rafinesque  1810  (Mundo) EN  Lamnidae  Isurus",
    "migration": "",
    "reproductionDescription": "",
    "poison": "No",
    "danger": "",
    "depth": "Enciclopedia Explorar Acuariofilia A propósito Prensa Peces Ballestas Barracudas Doradas y sargos Escorpenas Hipocampos Lábridos Morenas Peces cirujano Peces globo Peces payaso Rayas Tiburones Reptiles Cocodrilos Serpientes Tortugas Moluscos Caracoles Nudibranquios Calamares Pulpos Sepias Otros temas Anfibios Cnidarios Crustáceos Amazonas Anaconda gigante Anguila eléctrica Paiche Piraña roja Raya motoro / Raya de rio Tararira Mediterráneo Atún rojo Congrio Dorada real Manta raya Mero Sargo Islas Canarias Ángel de mar Caballito de mar Pez roca de Madeira Pez trompeta atlántico Tiburón Mako Vieja colorada Mar del Caribe Cirujano azul Gran barracuda / Picúa Pez ángel francés pez ángel reina Raya jaspeada Robalo blanco Mar Rojo Mero del Coral Morena gigante Pez león Pez Napoléon Raya de arrecife Vieja florida Especies comunes Betta Splendens Chupa algas Corydoras Discos Escalar Gamba Red Cherry Guppy Pez dorado Pez payaso Grupos temáticos Cíclidos enanos Killis Lochas Luchadores Peces gato Tetras Vivíparos Práctica Peces compatibles 20 L Peces compatibles 40 L Peces compatibles 60 L Peces compatibles 80 L Peces compatibles 100 L El proyecto Fishipedia Nuestra ética Proyecto Yaku Nawi Los fotógrafos colaboradores CONTÁCTANOS Enciclopedia Peces Ballestas Barracudas Doradas y sargos Escorpenas Hipocampos Lábridos Morenas Peces cirujano Peces globo Peces payaso Rayas Tiburones Reptiles Cocodrilos Serpientes Tortugas Moluscos Caracoles Nudibranquios Calamares Pulpos Sepias Otros temas Anfibios Cnidarios Crustáceos Explorar Amazonas Anaconda gigante Anguila eléctrica Paiche Piraña roja Raya motoro / Raya de rio Tararira Mediterráneo Atún rojo Congrio Dorada real Manta raya Mero Sargo Islas Canarias Ángel de mar Caballito de mar Pez roca de Madeira Pez trompeta atlántico Tiburón Mako Vieja colorada Mar del Caribe Cirujano azul Gran barracuda / Picúa Pez ángel francés pez ángel reina Raya jaspeada Robalo blanco Mar Rojo Mero del Coral Morena gigante Pez león Pez Napoléon Raya de arrecife Vieja florida Acuariofilia Especies comunes Betta Splendens Chupa algas Corydoras Discos Escalar Gamba Red Cherry Guppy Pez dorado Pez payaso Grupos temáticos Cíclidos enanos Killis Lochas Luchadores Peces gato Tetras Vivíparos Práctica Peces compatibles 20 L Peces compatibles 40 L Peces compatibles 60 L Peces compatibles 80 L Peces compatibles 100 L A propósito El proyecto Fishipedia Nuestra ética Proyecto Yaku Nawi Los fotógrafos colaboradores CONTÁCTANOS Prensa",
    "image": "",
    "mapImage": ""
  },
  {
    "name": "Kyphosus sectatrix",
    "sciname": "",
    "IUCN": "",
    "description": "Introducción La chopa es una especie de pez marino que se encuentra en las partes tropicales y subtropicales del océano Atlántico. Está presente en el mar Mediterráneo, en las Islas Canarias y también en la costa brasileña. ¿Quién es ella?  Tamaño medio 50 cm Tamaño máximo 76 cm Kyphosus sectatrix, chopa © Kevin Bryant Kyphosus sectatrix, chopa © John Turnbull Kyphosus sectatrix, chopa © François Libert Kyphosus sectatrix, chopa © John Turnbull Kyphosus sectatrix, chopa Previous Next Tamaño medio 50 cm Tamaño máximo 76 cm ¿Cómo reconocer a Este pez ? La chopa mide entre 50 y 76 cm. Los colores de su cuerpo pueden varían según las diferentes poblaciones. En general, este pez es de tono plateado con la presencia de unas líneas horizontales de color amarillo. Una línea amarilla más gruesa aparece en la zona del hocico y una segunda se interrumpe a la altura de los ojos. Los juveniles están cubiertos de manchas de un tono más pálido, y son casi tan grandes como los ojos. Modo de vida y comportamiento dieta omnívoro con tendencia alguívora Sociabilidad bancos territorial No Modo de vida Diurno Estos peces viven en bancos cercanos a las zonas de vegetación. Se alimentan principalmente de algas bentónicas, aunque también pueden cazar pequeños cangrejos y moluscos. Algunas poblaciones son conocidas por alimentarse de las heces de delfines de hocico largo. Reproducción Modo de reproducción ovíparo Se trata de un pez ovíparo. Especies inofensivas Esta especie no representa un peligro particular para los humanos en caso de encuentro en su entorno natural Origen y distribución Origen Golfo de México Mar del Caribe Mar Mediterráneo Mar Negro Océano Atlántico: costa norte de Brasil Océano Atlántico templado oriental Océano Atlántico templado cálido del noroeste Sudoeste del Océano Atlántico templado cálido Océano Atlántico tropical Sudoeste Islas Córcega Islas Canarias Cerdeña Sicilia Presencia geográfica y estado de la población Esta especie se encuentra presente desde las costas tropicales de Brasil hasta el Golfo de México en la fachada oeste del océano Atlántico. En la fachada opuesta, puede ser observada en el Mar Mediterráneo, desde las costas de Portugal hasta las aguas tropicales del sur de África. Estado de conservación de las poblaciones (UICN) Mundo : LC ¿Cuál es su hábitat? Características del entorno natural Temperatura 18 - 26 °C Profundidad 1 - 30 m Presentación del biotopo Esta especie se encuentra con mayor frecuencia a una profundidad que oscila entre 1m y 30m. Habita en diversos biotopos, especialmente en praderas submarinas, zonas arenosas, arrecifes de coral y fondos accidentados. Especie del mismo biotopo raya torpedo Torpedinidae tapaculo Bothidae galán Labridae pez ángel Squatinidae baila Moronidae chopa Sparidae Previous Next Para saber más Especie de la misma familia Microcanthus joyceae Kyphosidae Microcanthus strigatus Kyphosidae Previous Next Para leer en la web Fuentes y realización Participación y validación El equipo de Fishipedia y sus colaboradores especializados se comprometen a proporcionar contenido de alta calidad. Sin embargo, aunque la información proviene de fuentes científicas o testimonios de especialistas, los archivos pueden contener imprecisiones. Benoit Chartrer Traducción Traducción realizada con la valiosa contribución de nuestros traductores, quienes hacen que esta información esté disponible para un público más amplio. Silvia Gomez Interactúa con Fishipedia Para ponerse en contacto con nuestro equipo o participar en nuestro proyecto. Contribuya a esta página Plantilla y contenido © Fishipedia - Reproducción no autorizada sin solicitud previa - ISSN 2270-7247 - Última actualización el 12/11/2023 © Fishipedia.fr 2024",
    "genderDescription": "Kyphosidae",
    "type": "",
    "size": "50 cm",
    "maxSize": "76 cm",
    "mimetism": "",
    "recognize": "",
    "fe/maleDifferences": "",
    "diet": "omnívoro con tendencia alguívora",
    "territorial": "No",
    "social": "bancos",
    "lifeMode": "dieta",
    "lifeDescription": "",
    "reproductionMode": "<  chopa  Kyphosus sectatrix  Linnaeus  1758  (Mundo) LC  Kyphosidae  Kyphosus",
    "migration": "",
    "reproductionDescription": "",
    "poison": "",
    "danger": "",
    "depth": "Enciclopedia Explorar Acuariofilia A propósito Prensa Peces Ballestas Barracudas Doradas y sargos Escorpenas Hipocampos Lábridos Morenas Peces cirujano Peces globo Peces payaso Rayas Tiburones Reptiles Cocodrilos Serpientes Tortugas Moluscos Caracoles Nudibranquios Calamares Pulpos Sepias Otros temas Anfibios Cnidarios Crustáceos Amazonas Anaconda gigante Anguila eléctrica Paiche Piraña roja Raya motoro / Raya de rio Tararira Mediterráneo Atún rojo Congrio Dorada real Manta raya Mero Sargo Islas Canarias Ángel de mar Caballito de mar Pez roca de Madeira Pez trompeta atlántico Tiburón Mako Vieja colorada Mar del Caribe Cirujano azul Gran barracuda / Picúa Pez ángel francés pez ángel reina Raya jaspeada Robalo blanco Mar Rojo Mero del Coral Morena gigante Pez león Pez Napoléon Raya de arrecife Vieja florida Especies comunes Betta Splendens Chupa algas Corydoras Discos Escalar Gamba Red Cherry Guppy Pez dorado Pez payaso Grupos temáticos Cíclidos enanos Killis Lochas Luchadores Peces gato Tetras Vivíparos Práctica Peces compatibles 20 L Peces compatibles 40 L Peces compatibles 60 L Peces compatibles 80 L Peces compatibles 100 L El proyecto Fishipedia Nuestra ética Proyecto Yaku Nawi Los fotógrafos colaboradores CONTÁCTANOS Enciclopedia Peces Ballestas Barracudas Doradas y sargos Escorpenas Hipocampos Lábridos Morenas Peces cirujano Peces globo Peces payaso Rayas Tiburones Reptiles Cocodrilos Serpientes Tortugas Moluscos Caracoles Nudibranquios Calamares Pulpos Sepias Otros temas Anfibios Cnidarios Crustáceos Explorar Amazonas Anaconda gigante Anguila eléctrica Paiche Piraña roja Raya motoro / Raya de rio Tararira Mediterráneo Atún rojo Congrio Dorada real Manta raya Mero Sargo Islas Canarias Ángel de mar Caballito de mar Pez roca de Madeira Pez trompeta atlántico Tiburón Mako Vieja colorada Mar del Caribe Cirujano azul Gran barracuda / Picúa Pez ángel francés pez ángel reina Raya jaspeada Robalo blanco Mar Rojo Mero del Coral Morena gigante Pez león Pez Napoléon Raya de arrecife Vieja florida Acuariofilia Especies comunes Betta Splendens Chupa algas Corydoras Discos Escalar Gamba Red Cherry Guppy Pez dorado Pez payaso Grupos temáticos Cíclidos enanos Killis Lochas Luchadores Peces gato Tetras Vivíparos Práctica Peces compatibles 20 L Peces compatibles 40 L Peces compatibles 60 L Peces compatibles 80 L Peces compatibles 100 L A propósito El proyecto Fishipedia Nuestra ética Proyecto Yaku Nawi Los fotógrafos colaboradores CONTÁCTANOS Prensa",
    "image": "",
    "mapImage": ""
  },
  {
    "name": "Labrus merula",
    "sciname": "",
    "IUCN": "",
    "description": "Introducción Labrus merula, más comúnmente conocido como merlo o pinto, es un pez marino originario del Mar Mediterráneo y de las costas atlánticas de Portugal. Este depredador de tamaño mediano es un especialista en la caza de crustáceos y equinodermos. Poco estudiadas, se cree que sus poblaciones a día de hoy podrían estar amenazadas. Al ser objeto de la pesca recreativa, se está volviendo cada vez más escaso en las costas del Mediterráneo. Según las densidades observadas en áreas protegidas, sin embargo, debería representar una biomasa significativa dentro de la fauna marina. ¿Quién es él?  Labrus Desde 2021, el género Labrus incluye cuatro especies según FishBase. Estos lábridos son particularmente coloridos. Todas las especies son exclusivamente marinas y nativas del Océano Atlántico oriental. Varios taxones se encuentran en el mar Mediterráneo. Los Labrus son especialistas en la caza de crustáceos y moluscos. Se distinguen de otros lábridos por su línea lateral que describe una curva regular. Sus labios son carnosos y la aleta dorsal es larga y única. Estos pequeños parientes de los meros frecuentan las zonas rocosas no muy lejos de la costa. Son hermafroditas, nacen hembras y luego se convierten en machos durante el crecimiento. El macho es solitario y territorial. No tolera la presencia de competidores en su área de vida. Durante la temporada de reproducción, cada macho construye un nido de algas, protegiendo después los huevos hasta que estos eclosionan. Como ocurre con la mayoría de lábridos, las diferencias de color entre machos y hembras suelen ser importantes. La coloración y los patrones evolucionan a lo largo del crecimiento, a veces con transformaciones totales, como en L. mixtus. Cada especie presenta colores diferentes según la región en la que habita, esta característica es aún más marcada en los peces presentes en el Atlántico y el Mar Mediterráneo. Al menos una especie es considerada amenazada por la IUCN. Otras poblaciones parecen haber sido gravemente afectadas en varias regiones y los avistamientos se han vuelto cada vez menos frecuentes con el tiempo. Parece que los estudios sobre el estado de salud de las poblaciones son escasos debido a la falta de interés económico en estas especies. Además de la pesca, estos peces se ven amenazados por el deterioro de las praderas de posidonia. Estos peces son el objetivo particular de la pesca recreativa y los pescadores profesionales los capturan como \"captura incidental\". Sufren de una gestión pesquera inexistente y de la ausencia total de medidas de conservación. Al igual que los meros, los ejemplares grandes son sedentarios y fáciles de capturar. Por lo tanto, recomendamos liberar estos peces en caso de capturas accidentales, especialmente porque contienen muchas espinas, lo que dificulta su consumo.  Tipo Lábrido Tamaño medio 40 cm Tamaño máximo 45 cm Longevidad 20 años Patrón puntuación Labrus merula, merlo © Xavi Salvador Costa Tipo Lábrido Tamaño medio 40 cm Tamaño máximo 45 cm Longevidad 20 años Patrón puntuación ¿Cómo reconocer a Este pez ? El cuerpo, aunque robusto, es relativamente esbelto. Como sucede con sus congéneres, los labios de esta especie destacan por ser carnosos. La característica principal que ayuda a identificar esta especie a primera vista es la presencia de un borde azul en las aletas dorsal, caudal, pélvicas y anal. Los ejemplares jóvenes son de un tono verde con una línea lateral claramente visible, de color más claro. Parece que las hembras presentan tonalidades amarillentas con matices marrones, mientras que los machos son de tonos azules oscuros, beige o verdes. Tanto machos como hembras aparecen recubiertos de pequeños puntos de color turquesa. Diferencias entre machos y hembras Dado que la especie es hermafrodita protógina, por lo general, los machos son más grandes que las hembras. Modo de vida y comportamiento dieta carnívoro Sociabilidad masculina solitario Sociabilidad femenina grupos o en solitario territorial Sí Modo de vida Diurno El merlo reside cerca de rocas y praderas submarinas. Los machos maduros son solitarios, mientras que las hembras y los juveniles a veces se encuentran formando pequeños grupos. Estos peces se alimentan principalmente de crustáceos y otros peces, aunque también pueden cazar erizos de mar, ofiuroideos o gusanos. Reproducción Modo de reproducción ovíparo que desova en sustrato descubierto La temporada de reproducción varía según las áreas en el Mediterráneo, generalmente abarca desde finales del invierno hasta mediados de la primavera. En este período, los grandes machos crean un lecho plano en la vegetación. Posteriormente atraen a las hembras cercanas realizando una ceremonia de cortejo. En este momento, los colores se intensifican y la apariencia del macho se vuelve de un azul oscuro. Aún a día de hoy, existe una falta de estudios que confirmen si el macho de esta especie protege los huevos después del apareamiento, de forma similar a otros Labrus. Especies inofensivas Esta especie no representa un peligro particular para el ser humano en caso de encuentro en su entorno natural. Origen y distribución Origen Mar Mediterráneo Mar Negro Océano Atlántico templado oriental Islas Islas Canarias Cerdeña Sicilia Presencia geográfica y estado de la población El merlo ha sido registrado en toda la región del Mediterráneo, en las costas occidentales de Portugal y en las Azores. A veces, se confunde con la maragota (L. bergylta) y el tordo verde (L. viridis). Estado de conservación de las poblaciones (UICN) Mundo : LC ¿Dónde observar esta especie? ¿Cuál es su hábitat? Características del entorno natural Profundidad 1 - 50 m Presentación del biotopo Esta especie generalmente reside a menos de 50 metros de profundidad. Su entorno se caracteriza por la presencia de numerosas grietas que le proporcionan escondites entre las rocas. La densa vegetación permite que una amplia variedad de crustáceos, presas preferidas de estos peces, se desarrolle. Especie del mismo biotopo gorrión Labridae Symphodus melanocercus Labridae tordo verde Labridae Chelon saliens Mugilidae dorada Sparidae Salaria pavo Blenniidae Previous Next Para saber más Especie de la misma familia Hologymnosus doliatus Labridae Anampses neoguinaicus Labridae tordo picudo Labridae doncella común Labridae Hemigymnus fasciatus Labridae Pteragogus cryptus Labridae Pseudocoris yamashiroi Labridae Macropharyngodon negrosensis Labridae Previous Next Para leer en la web Fuentes y realización Participación y validación El equipo de Fishipedia y sus colaboradores especializados se comprometen a proporcionar contenido de alta calidad. Sin embargo, aunque la información proviene de fuentes científicas o testimonios de especialistas, los archivos pueden contener imprecisiones. Benoit Chartrer Traducción Traducción realizada con la valiosa contribución de nuestros traductores, quienes hacen que esta información esté disponible para un público más amplio. Silvia Gomez Referencias bibliográficas Régime alimentaire de Labrus merula (Labridae) des côtes nord de Tunisie - Saoussen BEN SLAMA - Domia MENIF - Oum Kalthoum BEN HASSINE - Cybium - 2007. Interactúa con Fishipedia Para ponerse en contacto con nuestro equipo o participar en nuestro proyecto. Contribuya a esta página Plantilla y contenido © Fishipedia - Reproducción no autorizada sin solicitud previa - ISSN 2270-7247 - Última actualización el 13/11/2023 © Fishipedia.fr 2024",
    "genderDescription": "Labridae",
    "type": "",
    "size": "40 cm",
    "maxSize": "45 cm",
    "mimetism": "",
    "recognize": "",
    "fe/maleDifferences": "Dado que la especie es hermafrodita protógina, por lo general, los machos son más grandes que las hembras.",
    "diet": "carnívoro",
    "territorial": "Tipo Lábrido Tamaño medio 40 cm Tamaño máximo 45 cm Longevidad 20 años Patrón puntuación Labrus merula, merlo © Xavi Salvador Costa Tipo Lábrido Tamaño medio 40 cm Tamaño máximo 45 cm Longevidad 20 años Patrón puntuación",
    "social": "solitario",
    "lifeMode": "dieta",
    "lifeDescription": "",
    "reproductionMode": "<  merlo  Labrus merula  Linnaeus  1758  (Mundo) LC  Labridae  Labrus",
    "migration": "",
    "reproductionDescription": "",
    "poison": "",
    "danger": "",
    "depth": "Enciclopedia Explorar Acuariofilia A propósito Prensa Peces Ballestas Barracudas Doradas y sargos Escorpenas Hipocampos Lábridos Morenas Peces cirujano Peces globo Peces payaso Rayas Tiburones Reptiles Cocodrilos Serpientes Tortugas Moluscos Caracoles Nudibranquios Calamares Pulpos Sepias Otros temas Anfibios Cnidarios Crustáceos Amazonas Anaconda gigante Anguila eléctrica Paiche Piraña roja Raya motoro / Raya de rio Tararira Mediterráneo Atún rojo Congrio Dorada real Manta raya Mero Sargo Islas Canarias Ángel de mar Caballito de mar Pez roca de Madeira Pez trompeta atlántico Tiburón Mako Vieja colorada Mar del Caribe Cirujano azul Gran barracuda / Picúa Pez ángel francés pez ángel reina Raya jaspeada Robalo blanco Mar Rojo Mero del Coral Morena gigante Pez león Pez Napoléon Raya de arrecife Vieja florida Especies comunes Betta Splendens Chupa algas Corydoras Discos Escalar Gamba Red Cherry Guppy Pez dorado Pez payaso Grupos temáticos Cíclidos enanos Killis Lochas Luchadores Peces gato Tetras Vivíparos Práctica Peces compatibles 20 L Peces compatibles 40 L Peces compatibles 60 L Peces compatibles 80 L Peces compatibles 100 L El proyecto Fishipedia Nuestra ética Proyecto Yaku Nawi Los fotógrafos colaboradores CONTÁCTANOS Enciclopedia Peces Ballestas Barracudas Doradas y sargos Escorpenas Hipocampos Lábridos Morenas Peces cirujano Peces globo Peces payaso Rayas Tiburones Reptiles Cocodrilos Serpientes Tortugas Moluscos Caracoles Nudibranquios Calamares Pulpos Sepias Otros temas Anfibios Cnidarios Crustáceos Explorar Amazonas Anaconda gigante Anguila eléctrica Paiche Piraña roja Raya motoro / Raya de rio Tararira Mediterráneo Atún rojo Congrio Dorada real Manta raya Mero Sargo Islas Canarias Ángel de mar Caballito de mar Pez roca de Madeira Pez trompeta atlántico Tiburón Mako Vieja colorada Mar del Caribe Cirujano azul Gran barracuda / Picúa Pez ángel francés pez ángel reina Raya jaspeada Robalo blanco Mar Rojo Mero del Coral Morena gigante Pez león Pez Napoléon Raya de arrecife Vieja florida Acuariofilia Especies comunes Betta Splendens Chupa algas Corydoras Discos Escalar Gamba Red Cherry Guppy Pez dorado Pez payaso Grupos temáticos Cíclidos enanos Killis Lochas Luchadores Peces gato Tetras Vivíparos Práctica Peces compatibles 20 L Peces compatibles 40 L Peces compatibles 60 L Peces compatibles 80 L Peces compatibles 100 L A propósito El proyecto Fishipedia Nuestra ética Proyecto Yaku Nawi Los fotógrafos colaboradores CONTÁCTANOS Prensa",
    "image": "",
    "mapImage": ""
  },
  {
    "name": "Labrus mixtus",
    "sciname": "",
    "IUCN": "",
    "description": "Introducción Labrus mixtus, conocido de forma común como gorrión, bodión, chiribito o gallito de rey, entre otros, es un pez marino nativo de la costa este del Océano Atlántico y el Mar Mediterráneo. Se trata de una de las especies más coloridas de estas regiones. Desafortunadamente, la especie ha sido, hasta día de hoy, poco estudiada. Actualmente sus poblaciones parecen sufrir las consecuencias tanto de la pesca recreativa como de la industrial, normalmente como captura incidental. Las poblaciones se consideran oficialmente no amenazadas, aunque diversos estudios científicos señalan la falta de investigación sobre su estado en toda su área de distribución. ¿Quién es él?  Labrus Desde 2021, el género Labrus incluye cuatro especies según FishBase. Estos lábridos son particularmente coloridos. Todas las especies son exclusivamente marinas y nativas del Océano Atlántico oriental. Varios taxones se encuentran en el mar Mediterráneo. Los Labrus son especialistas en la caza de crustáceos y moluscos. Se distinguen de otros lábridos por su línea lateral que describe una curva regular. Sus labios son carnosos y la aleta dorsal es larga y única. Estos pequeños parientes de los meros frecuentan las zonas rocosas no muy lejos de la costa. Son hermafroditas, nacen hembras y luego se convierten en machos durante el crecimiento. El macho es solitario y territorial. No tolera la presencia de competidores en su área de vida. Durante la temporada de reproducción, cada macho construye un nido de algas, protegiendo después los huevos hasta que estos eclosionan. Como ocurre con la mayoría de lábridos, las diferencias de color entre machos y hembras suelen ser importantes. La coloración y los patrones evolucionan a lo largo del crecimiento, a veces con transformaciones totales, como en L. mixtus. Cada especie presenta colores diferentes según la región en la que habita, esta característica es aún más marcada en los peces presentes en el Atlántico y el Mar Mediterráneo. Al menos una especie es considerada amenazada por la IUCN. Otras poblaciones parecen haber sido gravemente afectadas en varias regiones y los avistamientos se han vuelto cada vez menos frecuentes con el tiempo. Parece que los estudios sobre el estado de salud de las poblaciones son escasos debido a la falta de interés económico en estas especies. Además de la pesca, estos peces se ven amenazados por el deterioro de las praderas de posidonia. Estos peces son el objetivo particular de la pesca recreativa y los pescadores profesionales los capturan como \"captura incidental\". Sufren de una gestión pesquera inexistente y de la ausencia total de medidas de conservación. Al igual que los meros, los ejemplares grandes son sedentarios y fáciles de capturar. Por lo tanto, recomendamos liberar estos peces en caso de capturas accidentales, especialmente porque contienen muchas espinas, lo que dificulta su consumo.  Tipo Lábrido Tamaño medio 30 cm Tamaño máximo 40 cm Longevidad 20 años Patrón puntuación Labrus mixtus, gorrión © Xavi Salvador Costa Labrus mixtus, gorrión © Xaime Beiro Labrus mixtus, gorrión © Xaime Beiro Previous Next Tipo Lábrido Tamaño medio 30 cm Tamaño máximo 40 cm Longevidad 20 años Patrón puntuación ¿Cómo reconocer a Este pez ? El cuerpo de esta especie es más alargado que el del resto de Labrus. Los juveniles y las hembras son de un color que varía del naranja al rosado, con cuatro puntos blancos y tres puntos negros cercanos a la aleta dorsal. Sus aletas dorsal y anal son de color amarillo y aparecen bordeadas de un margen azul. La coloración de este pez varía a lo largo de su transformación sexual. En el estadio final, los machos de mayor tamaño son bicolores, azul o turquesa por un lado, y rojizo o naranja por el otro. Diferencias entre machos y hembras Aparte de las diferencias existentes en su coloración, los machos son de mayor tamaño que las hembras, pudiendo llegar a alcanzar unos 40 centímetros. Modo de vida y comportamiento dieta carnívoro Sociabilidad masculina grupos o en solitario Sociabilidad femenina pequeños grupos territorial Sí Modo de vida Diurno Esta especie reside en las cercanías de arrecifes cubiertos de algas o en los lechos de pastos marinos. De carácter solitario, especialmente los machos adultos, puede ser observada en ocasiones formando parejas, junto con un grupo de individuos más jóvenes. Este pez no migratorio parece residir toda su vida en el mismo territorio. Al igual que sucede con otros Labrus, este pez caza principalmente crustáceos. Pudiendo llegar a cazar moluscos, pequeños peces o gusanos. Reproducción Modo de reproducción ovíparo que desova en sustrato descubierto El macho construye un nido de algas a principios de la primavera, generalmente en zona mixta, sobre grava o roca. La reproducción tiene lugar en parejas unidas, los machos de esta especie no parecen ser polígamos. El macho protege los huevos y la primera etapa del crecimiento larvario. Siendo estas arrastradas después por las corrientes. En esta especie, la madurez sexual se produce durante el segundo año de vida. El cambio de sexo no parece depender de la edad sino del tamaño y de la necesidad de un macho reproductor en la zona. Especies inofensivas Esta especie no presenta ningún peligro en particular para los humanos en caso de encuentro en su medio natural. Origen y distribución Origen Mar Mediterráneo Mar Negro Océano Atlántico templado oriental Océano Atlántico Oriental Frío Islas Islas Canarias Cerdeña Sicilia Presencia geográfica y estado de la población La especie ha sido registrada desde Senegal hasta Noruega. Diversas poblaciones se encuentran también presentes en las islas del Atlántico oriental, hasta las Azores, y en el mar Mediterráneo. Estado de conservación de las poblaciones (UICN) Mundo : LC ¿Dónde observar esta especie? ¿Cuál es su hábitat? Características del entorno natural Profundidad 2 - 200 m Presentación del biotopo Los ejemplares más jóvenes pueden ser observados en zonas poco profundas mientras que los machos adultos de mayor tamaño se observan más bien a profundidades entre los 40 y 80 metros. Su entorno se caracteriza por una fuerte presencia de algas, plantas y rocas donde estos peces encuentran refugio en caso de peligro. Especie del mismo biotopo tordo verde Labridae merlo Labridae gobio negro Gobiidae dorada Sparidae pez pipa de rayas negras Syngnathidae Chelon saliens Mugilidae Previous Next Para saber más Especie de la misma familia Anampses neoguinaicus Labridae Macropharyngodon ornatus Labridae Macropharyngodon kuiteri Labridae Macropharyngodon meleagris Labridae Symphodus doderleini Labridae Novaculoides macrolepidotus Labridae Bodianus perditio Labridae Bodianus axillaris Labridae Previous Next Para leer en la web Fuentes y realización Participación y validación El equipo de Fishipedia y sus colaboradores especializados se comprometen a proporcionar contenido de alta calidad. Sin embargo, aunque la información proviene de fuentes científicas o testimonios de especialistas, los archivos pueden contener imprecisiones. Benoit Chartrer Traducción Traducción realizada con la valiosa contribución de nuestros traductores, quienes hacen que esta información esté disponible para un público más amplio. Silvia Gomez Referencias bibliográficas The cuckoo wrasse, Labrus mixtus (Pisces: Labridae): biological indices for life history and conservation - Sanja Matić-Skoko - P.Tutman - Armin Pallaoro - DUBRAVKA BOJANIĆ VAREZIĆ - JASNA ŠILJIĆ - Scientia Marina - 2013. Interactúa con Fishipedia Para ponerse en contacto con nuestro equipo o participar en nuestro proyecto. Contribuya a esta página Plantilla y contenido © Fishipedia - Reproducción no autorizada sin solicitud previa - ISSN 2270-7247 - Última actualización el 12/11/2023 © Fishipedia.fr 2024",
    "genderDescription": "Labridae",
    "type": "",
    "size": "30 cm",
    "maxSize": "40 cm",
    "mimetism": "",
    "recognize": "",
    "fe/maleDifferences": "Aparte de las diferencias existentes en su coloración, los machos son de mayor tamaño que las hembras, pudiendo llegar a alcanzar unos 40 centímetros.",
    "diet": "carnívoro",
    "territorial": "Tipo Lábrido Tamaño medio 30 cm Tamaño máximo 40 cm Longevidad 20 años Patrón puntuación Labrus mixtus, gorrión © Xavi Salvador Costa Labrus mixtus, gorrión © Xaime Beiro Labrus mixtus, gorrión © Xaime Beiro Previous Next Tipo Lábrido Tamaño medio 30 cm Tamaño máximo 40 cm Longevidad 20 años Patrón puntuación",
    "social": "grupos o en solitario",
    "lifeMode": "dieta",
    "lifeDescription": "",
    "reproductionMode": "<  gorrión  Labrus mixtus  Linnaeus  1758  (Mundo) LC  Labridae  Labrus",
    "migration": "",
    "reproductionDescription": "",
    "poison": "",
    "danger": "",
    "depth": "Enciclopedia Explorar Acuariofilia A propósito Prensa Peces Ballestas Barracudas Doradas y sargos Escorpenas Hipocampos Lábridos Morenas Peces cirujano Peces globo Peces payaso Rayas Tiburones Reptiles Cocodrilos Serpientes Tortugas Moluscos Caracoles Nudibranquios Calamares Pulpos Sepias Otros temas Anfibios Cnidarios Crustáceos Amazonas Anaconda gigante Anguila eléctrica Paiche Piraña roja Raya motoro / Raya de rio Tararira Mediterráneo Atún rojo Congrio Dorada real Manta raya Mero Sargo Islas Canarias Ángel de mar Caballito de mar Pez roca de Madeira Pez trompeta atlántico Tiburón Mako Vieja colorada Mar del Caribe Cirujano azul Gran barracuda / Picúa Pez ángel francés pez ángel reina Raya jaspeada Robalo blanco Mar Rojo Mero del Coral Morena gigante Pez león Pez Napoléon Raya de arrecife Vieja florida Especies comunes Betta Splendens Chupa algas Corydoras Discos Escalar Gamba Red Cherry Guppy Pez dorado Pez payaso Grupos temáticos Cíclidos enanos Killis Lochas Luchadores Peces gato Tetras Vivíparos Práctica Peces compatibles 20 L Peces compatibles 40 L Peces compatibles 60 L Peces compatibles 80 L Peces compatibles 100 L El proyecto Fishipedia Nuestra ética Proyecto Yaku Nawi Los fotógrafos colaboradores CONTÁCTANOS Enciclopedia Peces Ballestas Barracudas Doradas y sargos Escorpenas Hipocampos Lábridos Morenas Peces cirujano Peces globo Peces payaso Rayas Tiburones Reptiles Cocodrilos Serpientes Tortugas Moluscos Caracoles Nudibranquios Calamares Pulpos Sepias Otros temas Anfibios Cnidarios Crustáceos Explorar Amazonas Anaconda gigante Anguila eléctrica Paiche Piraña roja Raya motoro / Raya de rio Tararira Mediterráneo Atún rojo Congrio Dorada real Manta raya Mero Sargo Islas Canarias Ángel de mar Caballito de mar Pez roca de Madeira Pez trompeta atlántico Tiburón Mako Vieja colorada Mar del Caribe Cirujano azul Gran barracuda / Picúa Pez ángel francés pez ángel reina Raya jaspeada Robalo blanco Mar Rojo Mero del Coral Morena gigante Pez león Pez Napoléon Raya de arrecife Vieja florida Acuariofilia Especies comunes Betta Splendens Chupa algas Corydoras Discos Escalar Gamba Red Cherry Guppy Pez dorado Pez payaso Grupos temáticos Cíclidos enanos Killis Lochas Luchadores Peces gato Tetras Vivíparos Práctica Peces compatibles 20 L Peces compatibles 40 L Peces compatibles 60 L Peces compatibles 80 L Peces compatibles 100 L A propósito El proyecto Fishipedia Nuestra ética Proyecto Yaku Nawi Los fotógrafos colaboradores CONTÁCTANOS Prensa",
    "image": "",
    "mapImage": ""
  },
  {
    "name": "Lithognathus mormyrus",
    "sciname": "",
    "IUCN": "",
    "description": "Introducción Conocido como pez herrera o marbre, Lithognathus mormyrus, es un pez marino que se encuentra en el este del océano Atlántico tropical y templado. También está registrado y es común en el mar Mediterráneo. En España es bastante abundante en el mar Menor, en los meses estivales. Fácilmente identificable por sus rayas verticales de tonos marrones, esta especie frecuenta las zonas poco profundas de arena y lodo en busca de pequeños organismos acuáticos. A veces, es objeto de la pesca recreativa y la pesca profesional. Este pez puede llegar a vivir más de 12 años. ¿Quién es él?  Lithognathus En 2022, el género Lithognathus comprendía 4 especies según Fishbase. Todas ellas se encuentran en el este del océano Atlántico. La más grande, Lithognathus lithognathus, puede medir hasta dos metros y actualmente se encuentra en peligro de extinción debido a la sobrepesca. Estas especies han sido poco estudiadas por el momento, especialmente las de la costa africana, a pesar de su importancia para las pesquerías locales. Todas las especies podrían ser protándricas, naciendo generalmente como machos para transformarse en hembras con la edad. La captura de estos peces a un tamaño demasiado pequeño podría bloquear completamente el proceso de reproducción.  Tamaño medio 30 cm Tamaño máximo 55 cm Longevidad 12 años Mimetismo fondo arenoso Patrón líneas verticales Lithognathus mormyrus, pez herrera © François Libert Lithognathus mormyrus, pez herrera © Xavi Salvador Costa Previous Next Tamaño medio 30 cm Tamaño máximo 55 cm Longevidad 12 años Mimetismo fondo arenoso Patrón líneas verticales ¿Cómo reconocer a Este pez ? Este pez mide entre 30 y 55 cm, no es habitual observar ejemplares de mayor tamaño. Este pez es de color plateado, cubierto de una serie de rayas verticales de color marrón o beige. Las aletas son transparentes. Su apariencia le facilita mimetizarse con los fondos arenosos. Diferencias entre machos y hembras Por lo general, las hembras son más grandes que los machos. Modo de vida y comportamiento dieta carnívoro Sociabilidad bancos territorial No Modo de vida Diurno Se trata de una especie de hábitos gregarios que reside naturalmente cerca del fondo. Carnívora relativamente activa. Para alimentarse, caza gusanos, moluscos y pequeños crustáceos escondidos en el sustrato. Reproducción Modo de reproducción ovíparo que desova en aguas abiertas Hermafrodita Protándrico Es un pez ovíparo que pone sus huevos en el agua libre. Este pez nace siendo macho, para a medida que crecen, cambiar de sexo para convertirse en hembras, en lo que se conoce como hermafroditismo sucesivo de tipo protándrico. El cambio de sexo ocurre entre los 25 y 35 cm, a la edad promedio de 3,5 años. Especies inofensivas Esta especie no representa un peligro particular para el ser humano en caso de encuentro en su entorno natural. Origen y distribución Origen Mar Mediterráneo Mar Negro Mar Rojo Océano Atlántico templado oriental Océano Atlántico tropical oriental Islas Córcega Islas Canarias Cerdeña Sicilia Presencia geográfica y estado de la población Esta especie está registrada desde el golfo de Gascogne hasta el cabo de Buena Esperanza. Parecen existir ciertas poblaciones en el oeste del océano Índico, en el sur de Mozambique. Se encuentra presente igualmente alrededor de las Islas Canarias, Madeira y Cabo Verde, así como en el Mar Mediterráneo, el Mar Negro y el Mar Rojo. En general, la especie no está amenazada, aunque la gestión aleatoria de sus poblaciones podría volverla vulnerable en varias regiones. Este pez no debería ser capturado por debajo de los 35 cm para garantizar el mantenimiento de su ciclo reproductivo. Estado de conservación de las poblaciones (UICN) Mundo : LC ¿Dónde observar esta especie? ¿Cuál es su hábitat? Características del entorno natural Temperatura 14 - 26 °C Profundidad 0 - 150 m Presentación del biotopo Con mayor frecuencia, se encuentra al pez herradura a una profundidad que oscila entre 0 m y 150 m. Siendo más habitual en los primeros 20 metros. Frecuenta principalmente los fondos arenosos o limosos, así como las praderas submarinas, y en ocasiones es común divisarlo en los estuarios. Especie del mismo biotopo pez víbora Trachinidae pez de san Pedro Zeidae raspallón Sparidae gallinita Tetraodontidae lenguado Soleidae pez ángel Squatinidae Previous Next Para saber más Especie de la misma familia boga Sparidae mojarra Sparidae chopa Sparidae chucla Sparidae Pagellus acarne Sparidae raspallón Sparidae sargo común Sparidae oblada Sparidae Previous Next Para leer en la web Fuentes y realización Participación y validación El equipo de Fishipedia y sus colaboradores especializados se comprometen a proporcionar contenido de alta calidad. Sin embargo, aunque la información proviene de fuentes científicas o testimonios de especialistas, los archivos pueden contener imprecisiones. Benoit Chartrer Traducción Traducción realizada con la valiosa contribución de nuestros traductores, quienes hacen que esta información esté disponible para un público más amplio. Silvia Gomez Interactúa con Fishipedia Para ponerse en contacto con nuestro equipo o participar en nuestro proyecto. Contribuya a esta página Plantilla y contenido © Fishipedia - Reproducción no autorizada sin solicitud previa - ISSN 2270-7247 - Última actualización el 28/11/2023 © Fishipedia.fr 2024",
    "genderDescription": "Sparidae",
    "type": "",
    "size": "30 cm",
    "maxSize": "55 cm",
    "mimetism": "fondo arenoso",
    "recognize": "",
    "fe/maleDifferences": "Por lo general, las hembras son más grandes que los machos.",
    "diet": "carnívoro",
    "territorial": "No",
    "social": "bancos",
    "lifeMode": "dieta",
    "lifeDescription": "",
    "reproductionMode": "<  pez herrera  Lithognathus mormyrus  Linné  1758  (Mundo) LC  Sparidae  Lithognathus",
    "migration": "",
    "reproductionDescription": "",
    "poison": "",
    "danger": "",
    "depth": "Enciclopedia Explorar Acuariofilia A propósito Prensa Peces Ballestas Barracudas Doradas y sargos Escorpenas Hipocampos Lábridos Morenas Peces cirujano Peces globo Peces payaso Rayas Tiburones Reptiles Cocodrilos Serpientes Tortugas Moluscos Caracoles Nudibranquios Calamares Pulpos Sepias Otros temas Anfibios Cnidarios Crustáceos Amazonas Anaconda gigante Anguila eléctrica Paiche Piraña roja Raya motoro / Raya de rio Tararira Mediterráneo Atún rojo Congrio Dorada real Manta raya Mero Sargo Islas Canarias Ángel de mar Caballito de mar Pez roca de Madeira Pez trompeta atlántico Tiburón Mako Vieja colorada Mar del Caribe Cirujano azul Gran barracuda / Picúa Pez ángel francés pez ángel reina Raya jaspeada Robalo blanco Mar Rojo Mero del Coral Morena gigante Pez león Pez Napoléon Raya de arrecife Vieja florida Especies comunes Betta Splendens Chupa algas Corydoras Discos Escalar Gamba Red Cherry Guppy Pez dorado Pez payaso Grupos temáticos Cíclidos enanos Killis Lochas Luchadores Peces gato Tetras Vivíparos Práctica Peces compatibles 20 L Peces compatibles 40 L Peces compatibles 60 L Peces compatibles 80 L Peces compatibles 100 L El proyecto Fishipedia Nuestra ética Proyecto Yaku Nawi Los fotógrafos colaboradores CONTÁCTANOS Enciclopedia Peces Ballestas Barracudas Doradas y sargos Escorpenas Hipocampos Lábridos Morenas Peces cirujano Peces globo Peces payaso Rayas Tiburones Reptiles Cocodrilos Serpientes Tortugas Moluscos Caracoles Nudibranquios Calamares Pulpos Sepias Otros temas Anfibios Cnidarios Crustáceos Explorar Amazonas Anaconda gigante Anguila eléctrica Paiche Piraña roja Raya motoro / Raya de rio Tararira Mediterráneo Atún rojo Congrio Dorada real Manta raya Mero Sargo Islas Canarias Ángel de mar Caballito de mar Pez roca de Madeira Pez trompeta atlántico Tiburón Mako Vieja colorada Mar del Caribe Cirujano azul Gran barracuda / Picúa Pez ángel francés pez ángel reina Raya jaspeada Robalo blanco Mar Rojo Mero del Coral Morena gigante Pez león Pez Napoléon Raya de arrecife Vieja florida Acuariofilia Especies comunes Betta Splendens Chupa algas Corydoras Discos Escalar Gamba Red Cherry Guppy Pez dorado Pez payaso Grupos temáticos Cíclidos enanos Killis Lochas Luchadores Peces gato Tetras Vivíparos Práctica Peces compatibles 20 L Peces compatibles 40 L Peces compatibles 60 L Peces compatibles 80 L Peces compatibles 100 L A propósito El proyecto Fishipedia Nuestra ética Proyecto Yaku Nawi Los fotógrafos colaboradores CONTÁCTANOS Prensa",
    "image": "",
    "mapImage": ""
  },
  {
    "name": "Lophius budegassa",
    "sciname": "",
    "IUCN": "",
    "description": "Introducción Lophius budegassa comúnmente conocido como rape rojizo o rape negro. Su distribución se superpone a la del rape común en el océano Atlántico y en el mar Mediterráneo. Al igual que este último, utiliza un cebo para atraer a sus presas. Es uno de los pescados más consumidos en Europa dónde se le encuentra bajo el ambiguo nombre de rape. ¿Quién es él?  Lophius Los peces que pertenecen al género Lophius son comúnmente denominados \"rapes\", bien que este término resulta algo ambiguo. Pertenecen al orden de los Lophiiformes, apodados « peces pescadores », a causa del señuelo ubicado en la primera espina de su aleta dorsal. Especialistas en el arte del camuflaje, utilizan este señuelo para engañar y capturar a sus presas. En 2020, 7 especies aparecen agrupadas dentro de este género según Fishbase. De las cuales la más pequeña mide 60 cm, y la más grande, L. piscatorius, está considerado como un gigante de las profundidades con una talla récord estimada en más de 2m. Se trata de peces bénticos, es decir, que pasan la mayor parte de su tiempo en el fondo, principalmente de arena o de barro. Las aletas pectorales han ido evolucionando progresivamente para permitir su desplazamiento en este entorno. Largas y horizontales, con forma de palmas. Los ejemplares adultos son unos cazadores formidables. Principalmente piscívoros, se encuentran en la zona alta de la cadena alimenticia. Además del señuelo que sacuden vigorosamente, están dotados de una ancha boca provista de una mandíbula superior protráctil que les permite succionar casi instantáneamente a sus presas. Los dientes son largos, afilados y miran hacia adentro para evitar cualquier posible intento de salida de la presa. Los ojos están situados en la parte alta de la cabeza. La forma de su boca seguida de un cuerpo que se estrecha hasta la cola, le da a veces un aspecto deforme y desproporcionado. El color es generalmente uniforme, variando del marrón oscuro al gris según el hábitat. Estos peces se encuentran exclusivamente en el océano Atlántico, a grandes profundidades. Algunas de estas especies son objeto de la pesca de arrastre y varias poblaciones están viendo disminuido su número debido a ello. Actualmente, la captura está autorizada a partir de los 30 cm, antes de que el animal haya alcanzado su tamaño adulto. Sin embargo, debido a su modo de reproducción y a su lento crecimiento, si en un futuro no se toman las medidas adecuadas estos depredadores podrían entrar en riesgo real de desaparición.  Tamaño medio 50 cm Tamaño máximo 100 cm Mimetismo piedra Lophius budegassa, rape negro © Xavi Salvador Costa Tamaño medio 50 cm Tamaño máximo 100 cm Mimetismo piedra ¿Cómo reconocer a Este pez ? Al igual que sucede con otras especies del mismo género, este pez posee un cuerpo aplanado en el que destaca una cabeza de talla desproporcionada. Su prominente mandíbula está recubierta de dientes afilados. El primer radio dorsal precede al señuelo utilizado para atraer a sus presas. Como en el rape común, su coloración varía desde el marrón al negro, con el vientre de color crema. Diferencias entre machos y hembras Los ejemplares de mayor tamaño son generalmente hembras. Excepto por este hecho, es difícil hacer la distinción entre ambos sexos. Modo de vida y comportamiento dieta carnívoro Sociabilidad solitario territorial Sí Modo de vida Diurno De menor tamaño que el rape común, este pez es un cazador formidable de peces pequeños. Vive en solitario, oculto en el substrato, generalmente constituido de barro o arena. Reproducción Modo de reproducción ovíparo que forma ristras de huevos La reproducción parece tener lugar entre los meses de enero y marzo. Las hembras ponen sus huevos en cintas que pueden alcanzar varios metros de largo. La hembra alcanza la madurez sexual en torno a los 50 cm, y el macho alrededor de 40 cm. La edad de madurez para ambos sexos se sitúa aproximadamente entre los 7 y 8 años. Especies inofensivas Esta especie no supone ningún peligro en particular para el ser humano cuando se encuentra en su entorno natural. Origen y distribución Origen Mar Mediterráneo Mar Negro Océano Atlántico templado oriental Islas Islas Canarias Cerdeña Sicilia Presencia geográfica y estado de la población Es una especie de alto valor comercial. Francia es el principal país pescador de este pez en Europa, superando al Reino Unido y siendo responsable de más de un tercio de las capturas. La Unión Europea impone a toda su flota un peso mínimo de desembarque de 500 g por pez entero. Estado de conservación de las poblaciones (UICN) Mundo : DD ¿Cuál es su hábitat? Características del entorno natural Temperatura 16 - 24 °C Profundidad 20 - 1000 m Presentación del biotopo Al rape negro se le suele observar en el fondo, a profundidades de hasta 1000 metros. Un ejemplar ha sido documentado a 1013 m en el mar Jónico oriental. Esta especie parece vivir a mayor profundidad que el rape común. Especie del mismo biotopo galán Labridae pez de san Pedro Zeidae lenguado Soleidae raya látigo común Dasyatidae pez víbora Trachinidae tremielga Torpedinidae Previous Next Para saber más Para leer en la web Fuentes y realización Participación y validación El equipo de Fishipedia y sus colaboradores especializados se comprometen a proporcionar contenido de alta calidad. Sin embargo, aunque la información proviene de fuentes científicas o testimonios de especialistas, los archivos pueden contener imprecisiones. Benoit Chartrer Traducción Traducción realizada con la valiosa contribución de nuestros traductores, quienes hacen que esta información esté disponible para un público más amplio. Silvia Gomez Referencias bibliográficas FAO - Order LOPHIIFORMES - J.H. Caruso - FAO Fisheries Synopsis - 2004. Interactúa con Fishipedia Para ponerse en contacto con nuestro equipo o participar en nuestro proyecto. Contribuya a esta página Plantilla y contenido © Fishipedia - Reproducción no autorizada sin solicitud previa - ISSN 2270-7247 - Última actualización el 13/11/2023 © Fishipedia.fr 2024",
    "genderDescription": "Lophiidae",
    "type": "",
    "size": "50 cm",
    "maxSize": "100 cm",
    "mimetism": "piedra",
    "recognize": "",
    "fe/maleDifferences": "Los ejemplares de mayor tamaño son generalmente hembras. Excepto por este hecho, es difícil hacer la distinción entre ambos sexos.",
    "diet": "carnívoro",
    "territorial": "Sí",
    "social": "solitario",
    "lifeMode": "dieta",
    "lifeDescription": "",
    "reproductionMode": "<  rape negro  Lophius budegassa  Spinola  1807  (Mundo) DD  Lophiidae  Lophius",
    "migration": "",
    "reproductionDescription": "",
    "poison": "",
    "danger": "",
    "depth": "Enciclopedia Explorar Acuariofilia A propósito Prensa Peces Ballestas Barracudas Doradas y sargos Escorpenas Hipocampos Lábridos Morenas Peces cirujano Peces globo Peces payaso Rayas Tiburones Reptiles Cocodrilos Serpientes Tortugas Moluscos Caracoles Nudibranquios Calamares Pulpos Sepias Otros temas Anfibios Cnidarios Crustáceos Amazonas Anaconda gigante Anguila eléctrica Paiche Piraña roja Raya motoro / Raya de rio Tararira Mediterráneo Atún rojo Congrio Dorada real Manta raya Mero Sargo Islas Canarias Ángel de mar Caballito de mar Pez roca de Madeira Pez trompeta atlántico Tiburón Mako Vieja colorada Mar del Caribe Cirujano azul Gran barracuda / Picúa Pez ángel francés pez ángel reina Raya jaspeada Robalo blanco Mar Rojo Mero del Coral Morena gigante Pez león Pez Napoléon Raya de arrecife Vieja florida Especies comunes Betta Splendens Chupa algas Corydoras Discos Escalar Gamba Red Cherry Guppy Pez dorado Pez payaso Grupos temáticos Cíclidos enanos Killis Lochas Luchadores Peces gato Tetras Vivíparos Práctica Peces compatibles 20 L Peces compatibles 40 L Peces compatibles 60 L Peces compatibles 80 L Peces compatibles 100 L El proyecto Fishipedia Nuestra ética Proyecto Yaku Nawi Los fotógrafos colaboradores CONTÁCTANOS Enciclopedia Peces Ballestas Barracudas Doradas y sargos Escorpenas Hipocampos Lábridos Morenas Peces cirujano Peces globo Peces payaso Rayas Tiburones Reptiles Cocodrilos Serpientes Tortugas Moluscos Caracoles Nudibranquios Calamares Pulpos Sepias Otros temas Anfibios Cnidarios Crustáceos Explorar Amazonas Anaconda gigante Anguila eléctrica Paiche Piraña roja Raya motoro / Raya de rio Tararira Mediterráneo Atún rojo Congrio Dorada real Manta raya Mero Sargo Islas Canarias Ángel de mar Caballito de mar Pez roca de Madeira Pez trompeta atlántico Tiburón Mako Vieja colorada Mar del Caribe Cirujano azul Gran barracuda / Picúa Pez ángel francés pez ángel reina Raya jaspeada Robalo blanco Mar Rojo Mero del Coral Morena gigante Pez león Pez Napoléon Raya de arrecife Vieja florida Acuariofilia Especies comunes Betta Splendens Chupa algas Corydoras Discos Escalar Gamba Red Cherry Guppy Pez dorado Pez payaso Grupos temáticos Cíclidos enanos Killis Lochas Luchadores Peces gato Tetras Vivíparos Práctica Peces compatibles 20 L Peces compatibles 40 L Peces compatibles 60 L Peces compatibles 80 L Peces compatibles 100 L A propósito El proyecto Fishipedia Nuestra ética Proyecto Yaku Nawi Los fotógrafos colaboradores CONTÁCTANOS Prensa",
    "image": "",
    "mapImage": ""
  },
  {
    "name": "Lophius piscatorius",
    "sciname": "",
    "IUCN": "",
    "description": "Introducción El rape común, también conocido como rape blanco, se encuentra en una gran parte del océano Atlántico norte. Estando también presente en el mar Mediterráneo y en el mar Negro. Este depredador tiene la particularidad de utilizar un señuelo para cazar a sus presas. En Europa, es uno de los pescados más consumidos. ¿Quién es él?  Lophius Los peces que pertenecen al género Lophius son comúnmente denominados \"rapes\", bien que este término resulta algo ambiguo. Pertenecen al orden de los Lophiiformes, apodados « peces pescadores », a causa del señuelo ubicado en la primera espina de su aleta dorsal. Especialistas en el arte del camuflaje, utilizan este señuelo para engañar y capturar a sus presas. En 2020, 7 especies aparecen agrupadas dentro de este género según Fishbase. De las cuales la más pequeña mide 60 cm, y la más grande, L. piscatorius, está considerado como un gigante de las profundidades con una talla récord estimada en más de 2m. Se trata de peces bénticos, es decir, que pasan la mayor parte de su tiempo en el fondo, principalmente de arena o de barro. Las aletas pectorales han ido evolucionando progresivamente para permitir su desplazamiento en este entorno. Largas y horizontales, con forma de palmas. Los ejemplares adultos son unos cazadores formidables. Principalmente piscívoros, se encuentran en la zona alta de la cadena alimenticia. Además del señuelo que sacuden vigorosamente, están dotados de una ancha boca provista de una mandíbula superior protráctil que les permite succionar casi instantáneamente a sus presas. Los dientes son largos, afilados y miran hacia adentro para evitar cualquier posible intento de salida de la presa. Los ojos están situados en la parte alta de la cabeza. La forma de su boca seguida de un cuerpo que se estrecha hasta la cola, le da a veces un aspecto deforme y desproporcionado. El color es generalmente uniforme, variando del marrón oscuro al gris según el hábitat. Estos peces se encuentran exclusivamente en el océano Atlántico, a grandes profundidades. Algunas de estas especies son objeto de la pesca de arrastre y varias poblaciones están viendo disminuido su número debido a ello. Actualmente, la captura está autorizada a partir de los 30 cm, antes de que el animal haya alcanzado su tamaño adulto. Sin embargo, debido a su modo de reproducción y a su lento crecimiento, si en un futuro no se toman las medidas adecuadas estos depredadores podrían entrar en riesgo real de desaparición.  Tamaño medio 100 cm Tamaño máximo 200 cm Longevidad 24 años Mimetismo piedra Lophius piscatorius, rape común © Xavi Salvador Costa Lophius piscatorius, rape común © Xavi Salvador Costa Lophius piscatorius, rape común © Jim Greenfield Previous Next Tamaño medio 100 cm Tamaño máximo 200 cm Longevidad 24 años Mimetismo piedra ¿Cómo reconocer a Este pez ? Al igual que ocurre con otras especies de rape, la boca es enorme comparada con el resto del cuerpo. Las branquias se extienden por debajo y detrás de la aleta pectoral. Las espinas dorsales son largas y se confunden con las algas de su entorno. El rape común presenta una coloración variable, uniforme o moteada en tonos marrones. La parte superior es más oscura, la zona del vientre es clara. La coloración y el patrón varían en función del entorno, utilizándolo para mimetizarse con los fondos arenosos o de piedra. Es un pez que no posee escamas. Esta especie puede confundirse con el rape negro (o rape rojizo): Lophius budegassa. Sin embargo, este último es más oscuro y mucho más pequeño. Diferencias entre machos y hembras Las hembras alcanzan un tamaño mayor que los machos. Modo de vida y comportamiento dieta carnívoro Sociabilidad solitario territorial Sí Modo de vida Diurno Este rape es uno de los superpredadores de los fondos marinos. Solitario, pasa su tiempo medio enterrado en los sedimentos del fondo mientras espera a sus presas. Al igual que las otras especies de rape, utiliza un cebo para atraer a los peces cercanos hacia su boca. Reproducción Modo de reproducción ovíparo que forma ristras de huevos La reproducción tiene lugar entre los meses de enero y junio. Las hembras ponen sus huevos en cintas que pueden alcanzar varios metros de largo. El macho alcanza la madurez sexual entorno a los 50 cm, con una edad estimada de unos 5 años mientras que la hembra se reproduce después de alcanzar los 14 años con un tamaño de casi un metro. La consecuencia directa de la no diferenciación de especies capturadas por la pesca poco selectiva (principalmente de arrastre) es la captura de muchos individuos jóvenes que aún no han alcanzado la edad para reproducirse. Debido a esto, las poblaciones de esta especie podrían descender rápidamente. Especies inofensivas Esta especie no supone ningún peligro en particular para el ser humano cuando se encuentra en su entorno natural. Origen y distribución Origen Mar Mediterráneo Mar Negro Océano Atlántico templado oriental Islas Islas Canarias Cerdeña Sicilia Presencia geográfica y estado de la población Es una especie de alto valor comercial. Francia es el principal país pescador de este pez en Europa, superando al Reino Unido y siendo responsable de más de un tercio de las capturas. La Unión Europea impone a toda su flota un peso mínimo de desembarque de 500 g por pez entero. Estado de conservación de las poblaciones (UICN) Mundo : LC ¿Dónde observar esta especie? ¿Cuál es su hábitat? Características del entorno natural Temperatura 16 - 24 °C Profundidad 20 - 1000 m Presentación del biotopo Este especie se encuentra en fondos arenosos y fangosos hasta los 1000 metros de profundidad. Especie del mismo biotopo raya boca de rosa Rajidae raya látigo común Dasyatidae chopa Sparidae raya toro Myliobatidae lubina Moronidae raya de clavos Rajidae Previous Next Para saber más Para leer en la web Fuentes y realización Participación y validación El equipo de Fishipedia y sus colaboradores especializados se comprometen a proporcionar contenido de alta calidad. Sin embargo, aunque la información proviene de fuentes científicas o testimonios de especialistas, los archivos pueden contener imprecisiones. Benoit Chartrer Traducción Traducción realizada con la valiosa contribución de nuestros traductores, quienes hacen que esta información esté disponible para un público más amplio. Silvia Gomez Referencias bibliográficas FAO - Order LOPHIIFORMES - J.H. Caruso - FAO Fisheries Synopsis - 2004. Interactúa con Fishipedia Para ponerse en contacto con nuestro equipo o participar en nuestro proyecto. Contribuya a esta página Plantilla y contenido © Fishipedia - Reproducción no autorizada sin solicitud previa - ISSN 2270-7247 - Última actualización el 11/11/2023 © Fishipedia.fr 2024",
    "genderDescription": "Lophiidae",
    "type": "",
    "size": "100 cm",
    "maxSize": "200 cm",
    "mimetism": "piedra",
    "recognize": "",
    "fe/maleDifferences": "Las hembras alcanzan un tamaño mayor que los machos.",
    "diet": "carnívoro",
    "territorial": "Sí",
    "social": "solitario",
    "lifeMode": "dieta",
    "lifeDescription": "",
    "reproductionMode": "<  rape común  Lophius piscatorius  Linnaeus  1758  (Mundo) LC  Lophiidae  Lophius",
    "migration": "",
    "reproductionDescription": "",
    "poison": "",
    "danger": "",
    "depth": "Enciclopedia Explorar Acuariofilia A propósito Prensa Peces Ballestas Barracudas Doradas y sargos Escorpenas Hipocampos Lábridos Morenas Peces cirujano Peces globo Peces payaso Rayas Tiburones Reptiles Cocodrilos Serpientes Tortugas Moluscos Caracoles Nudibranquios Calamares Pulpos Sepias Otros temas Anfibios Cnidarios Crustáceos Amazonas Anaconda gigante Anguila eléctrica Paiche Piraña roja Raya motoro / Raya de rio Tararira Mediterráneo Atún rojo Congrio Dorada real Manta raya Mero Sargo Islas Canarias Ángel de mar Caballito de mar Pez roca de Madeira Pez trompeta atlántico Tiburón Mako Vieja colorada Mar del Caribe Cirujano azul Gran barracuda / Picúa Pez ángel francés pez ángel reina Raya jaspeada Robalo blanco Mar Rojo Mero del Coral Morena gigante Pez león Pez Napoléon Raya de arrecife Vieja florida Especies comunes Betta Splendens Chupa algas Corydoras Discos Escalar Gamba Red Cherry Guppy Pez dorado Pez payaso Grupos temáticos Cíclidos enanos Killis Lochas Luchadores Peces gato Tetras Vivíparos Práctica Peces compatibles 20 L Peces compatibles 40 L Peces compatibles 60 L Peces compatibles 80 L Peces compatibles 100 L El proyecto Fishipedia Nuestra ética Proyecto Yaku Nawi Los fotógrafos colaboradores CONTÁCTANOS Enciclopedia Peces Ballestas Barracudas Doradas y sargos Escorpenas Hipocampos Lábridos Morenas Peces cirujano Peces globo Peces payaso Rayas Tiburones Reptiles Cocodrilos Serpientes Tortugas Moluscos Caracoles Nudibranquios Calamares Pulpos Sepias Otros temas Anfibios Cnidarios Crustáceos Explorar Amazonas Anaconda gigante Anguila eléctrica Paiche Piraña roja Raya motoro / Raya de rio Tararira Mediterráneo Atún rojo Congrio Dorada real Manta raya Mero Sargo Islas Canarias Ángel de mar Caballito de mar Pez roca de Madeira Pez trompeta atlántico Tiburón Mako Vieja colorada Mar del Caribe Cirujano azul Gran barracuda / Picúa Pez ángel francés pez ángel reina Raya jaspeada Robalo blanco Mar Rojo Mero del Coral Morena gigante Pez león Pez Napoléon Raya de arrecife Vieja florida Acuariofilia Especies comunes Betta Splendens Chupa algas Corydoras Discos Escalar Gamba Red Cherry Guppy Pez dorado Pez payaso Grupos temáticos Cíclidos enanos Killis Lochas Luchadores Peces gato Tetras Vivíparos Práctica Peces compatibles 20 L Peces compatibles 40 L Peces compatibles 60 L Peces compatibles 80 L Peces compatibles 100 L A propósito El proyecto Fishipedia Nuestra ética Proyecto Yaku Nawi Los fotógrafos colaboradores CONTÁCTANOS Prensa",
    "image": "",
    "mapImage": ""
  }
]